{
  "type": "Feature",
  "properties": {
    "gn:admin1_code":"8.0",
    "gn:admin2_code":"DC9",
    "gn:admin3_code":"NC092",
    "gn:asciiname":"Windsorton",
    "gn:cc2":"ZA",
    "gn:country_code":"ZA",
    "gn:dem":1122,
    "gn:feature_class":"P",
    "gn:feature_code":"PPL",
    "gn:name":"Windsorton",
    "gn:population":0,
    "gn:timezone":"Africa/Johannesburg",
    "iso:country":"ZA",
    "name:afr_x_preferred":[
        "Windsorton"
    ],
    "name:ceb_x_preferred":[
        "Windsorton"
    ],
    "name:est_x_preferred":[
        "Windsorton"
    ],
    "name:nld_x_preferred":[
        "Windsorton"
    ],
    "name:nso_x_preferred":[
        "Windsorton"
    ],
    "name:ron_x_preferred":[
        "Windsorton"
    ],
    "name:und_x_variant":[
        "Windsorton Dorp",
        "Windsorton Village"
    ],
    "wof:lang_x_official":[
        "eng"
    ],
    "wof:lang_x_spoken":[
        "eng",
        "zul",
        "xho",
        "afr",
        "nso",
        "tsn",
        "sot",
        "tso",
        "ssw",
        "ven",
        "nbl"
    ],
    "wof:name":"Windsorton",
    "wof:placetype":"locality"
},
  "geometry": {"coordinates":[24.71667,-28.33333],"type":"Point"}
}