{
  "type": "Feature",
  "properties": {
    "gn:admin1_code":"8.0",
    "gn:admin2_code":"DC9",
    "gn:admin3_code":"NC092",
    "gn:asciiname":"Windsorton",
    "gn:cc2":"ZA",
    "gn:country_code":"ZA",
    "gn:dem":1122,
    "gn:feature_class":"P",
    "gn:feature_code":"PPL",
    "gn:name":"Windsorton",
    "gn:population":0,
    "gn:timezone":"Africa/Johannesburg",
    "iso:country":"ZA",
    "name:und_x_variant":[
        "Windsorton Dorp",
        "Windsorton Village",
        "Windsorton"
    ],
    "wof:name":"Windsorton",
    "wof:placetype":"locality"
},
  "geometry": {"coordinates":[24.71667,-28.33333],"type":"Point"}
}