{
  "type": "Feature",
  "properties": {
    "gn:admin1_code":"8",
    "gn:admin2_code":"DC7",
    "gn:admin3_code":"NC077",
    "gn:asciiname":"Platsambok",
    "gn:country_code":"ZA",
    "gn:dem":1116,
    "gn:feature_class":"P",
    "gn:feature_code":"PPL",
    "gn:name":"Platsambok",
    "gn:population":0,
    "gn:timezone":"Africa/Johannesburg",
    "iso:country":"ZA",
    "wof:name":"Platsambok",
    "wof:placetype":"locality"
},
  "geometry": {"coordinates":[22.4522,-30.00013],"type":"Point"}
}