{
  "type": "Feature",
  "properties": {
    "gn:admin1_code":"2",
    "gn:admin2_code":"DC26",
    "gn:admin3_code":"KZN265",
    "gn:asciiname":"Njampela",
    "gn:country_code":"ZA",
    "gn:dem":711,
    "gn:feature_class":"P",
    "gn:feature_code":"PPL",
    "gn:name":"Njampela",
    "gn:population":0,
    "gn:timezone":"Africa/Johannesburg",
    "iso:country":"ZA",
    "wof:name":"Njampela",
    "wof:placetype":"locality"
},
  "geometry": {"coordinates":[31.70528,-27.95757],"type":"Point"}
}