{
  "type": "Feature",
  "properties": {
    "gn:admin1_code":"2",
    "gn:admin2_code":"DC26",
    "gn:admin3_code":"KZN265",
    "gn:asciiname":"Ncungu",
    "gn:country_code":"ZA",
    "gn:dem":792,
    "gn:feature_class":"P",
    "gn:feature_code":"PPL",
    "gn:name":"Ncungu",
    "gn:population":0,
    "gn:timezone":"Africa/Johannesburg",
    "iso:country":"ZA",
    "wof:name":"Ncungu",
    "wof:placetype":"locality"
},
  "geometry": {"coordinates":[31.56506,-27.9111],"type":"Point"}
}