{
  "type": "Feature",
  "properties": {
    "gn:admin1_code":"5",
    "gn:admin2_code":"DC13",
    "gn:admin3_code":"EC132",
    "gn:asciiname":"Proceshoek",
    "gn:country_code":"ZA",
    "gn:dem":1104,
    "gn:feature_class":"P",
    "gn:feature_code":"PPL",
    "gn:name":"Proceshoek",
    "gn:population":0,
    "gn:timezone":"Africa/Johannesburg",
    "iso:country":"ZA",
    "wof:name":"Proceshoek",
    "wof:placetype":"locality"
},
  "geometry": {"coordinates":[26.08988,-31.9818],"type":"Point"}
}