{
  "type": "Feature",
  "properties": {
    "gn:admin1_code":"2",
    "gn:admin2_code":"DC23",
    "gn:admin3_code":"KZN234",
    "gn:asciiname":"Nkaseni",
    "gn:cc2":"ZA",
    "gn:country_code":"ZA",
    "gn:dem":692,
    "gn:feature_class":"P",
    "gn:feature_code":"PPL",
    "gn:name":"Nkaseni",
    "gn:population":0,
    "gn:timezone":"Africa/Johannesburg",
    "iso:country":"ZA",
    "name:und_x_variant":[
        "Nkasini Estates",
        "Nkasini",
        "Nkaseni"
    ],
    "wof:lang_x_official":[
        "eng"
    ],
    "wof:lang_x_spoken":[
        "eng",
        "zul",
        "xho",
        "afr",
        "nso",
        "tsn",
        "sot",
        "tso",
        "ssw",
        "ven",
        "nbl"
    ],
    "wof:name":"Nkaseni",
    "wof:placetype":"locality"
},
  "geometry": {"coordinates":[30.16667,-28.76667],"type":"Point"}
}