{
  "type": "Feature",
  "properties": {
    "gn:admin1_code":"9",
    "gn:admin2_code":"DC47",
    "gn:admin3_code":"LIM473",
    "gn:asciiname":"Loopspruit",
    "gn:country_code":"ZA",
    "gn:dem":1140,
    "gn:feature_class":"P",
    "gn:feature_code":"PPL",
    "gn:name":"Loopspruit",
    "gn:population":0,
    "gn:timezone":"Africa/Johannesburg",
    "iso:country":"ZA",
    "name:afr_x_preferred":[
        "Loopspruit"
    ],
    "name:nso_x_preferred":[
        "Loopspruit"
    ],
    "wof:name":"Loopspruit",
    "wof:placetype":"locality"
},
  "geometry": {"coordinates":[29.75,-24.66667],"type":"Point"}
}