{
  "type": "Feature",
  "properties": {
    "gn:admin1_code":"5",
    "gn:admin2_code":"DC44",
    "gn:admin3_code":"EC443",
    "gn:asciiname":"Qasa",
    "gn:country_code":"ZA",
    "gn:dem":879,
    "gn:feature_class":"P",
    "gn:feature_code":"PPL",
    "gn:name":"Qasa",
    "gn:population":0,
    "gn:timezone":"Africa/Johannesburg",
    "iso:country":"ZA",
    "wof:name":"Qasa",
    "wof:placetype":"locality"
},
  "geometry": {"coordinates":[29.61671,-30.97084000000001],"type":"Point"}
}