{
  "type": "Feature",
  "properties": {
    "gn:admin1_code":"9",
    "gn:admin2_code":"DC35",
    "gn:admin3_code":"LIM354",
    "gn:asciiname":"Ga-Kgole",
    "gn:country_code":"ZA",
    "gn:dem":1404,
    "gn:feature_class":"P",
    "gn:feature_code":"PPL",
    "gn:name":"Ga-Kgole",
    "gn:population":0,
    "gn:timezone":"Africa/Johannesburg",
    "iso:country":"ZA",
    "wof:name":"Ga-Kgole",
    "wof:placetype":"locality"
},
  "geometry": {"coordinates":[29.83606,-23.8837],"type":"Point"}
}