{
  "type": "Feature",
  "properties": {
    "gn:admin1_code":"9",
    "gn:admin2_code":"DC36",
    "gn:admin3_code":"LIM366",
    "gn:asciiname":"Codrington",
    "gn:country_code":"ZA",
    "gn:dem":1083,
    "gn:feature_class":"P",
    "gn:feature_code":"PPL",
    "gn:name":"Codrington",
    "gn:population":0,
    "gn:timezone":"Africa/Johannesburg",
    "iso:country":"ZA",
    "name:ceb_x_preferred":[
        "Codrington"
    ],
    "name:deu_x_preferred":[
        "Codrington"
    ],
    "name:fin_x_preferred":[
        "Codrington"
    ],
    "name:fra_x_preferred":[
        "Codrington"
    ],
    "name:ita_x_preferred":[
        "Codrington"
    ],
    "name:nds_x_preferred":[
        "Codrington"
    ],
    "name:nld_x_preferred":[
        "Codrington"
    ],
    "name:pol_x_preferred":[
        "Codrington"
    ],
    "name:swe_x_preferred":[
        "Codrington"
    ],
    "wof:lang_x_official":[
        "eng"
    ],
    "wof:lang_x_spoken":[
        "eng",
        "zul",
        "xho",
        "afr",
        "nso",
        "tsn",
        "sot",
        "tso",
        "ssw",
        "ven",
        "nbl"
    ],
    "wof:name":"Codrington",
    "wof:placetype":"locality"
},
  "geometry": {"coordinates":[28.31361,-25.03583],"type":"Point"}
}