{
  "type": "Feature",
  "properties": {
    "gn:admin1_code":"2.0",
    "gn:admin2_code":"DC28",
    "gn:admin3_code":"KZN281",
    "gn:asciiname":"Teza",
    "gn:country_code":"ZA",
    "gn:dem":56,
    "gn:feature_class":"P",
    "gn:feature_code":"PPL",
    "gn:name":"Teza",
    "gn:population":0,
    "gn:timezone":"Africa/Johannesburg",
    "iso:country":"ZA",
    "name:und_x_variant":[
        "eSitheza",
        "Teza"
    ],
    "wof:name":"Teza",
    "wof:placetype":"locality"
},
  "geometry": {"coordinates":[32.15,-28.51667],"type":"Point"}
}