{
  "type": "Feature",
  "properties": {
    "gn:admin1_code":"2.0",
    "gn:admin2_code":"DC28",
    "gn:admin3_code":"KZN281",
    "gn:asciiname":"Teza",
    "gn:country_code":"ZA",
    "gn:dem":56,
    "gn:feature_class":"P",
    "gn:feature_code":"PPL",
    "gn:name":"Teza",
    "gn:population":0,
    "gn:timezone":"Africa/Johannesburg",
    "iso:country":"ZA",
    "name:ceb_x_preferred":[
        "Teza"
    ],
    "name:deu_x_preferred":[
        "Teza"
    ],
    "name:fra_x_preferred":[
        "Teza"
    ],
    "name:rus_x_preferred":[
        "\u0422\u0435\u0437\u0430"
    ],
    "name:swe_x_preferred":[
        "Teza"
    ],
    "name:und_x_variant":[
        "eSitheza"
    ],
    "wof:lang_x_official":[
        "eng"
    ],
    "wof:lang_x_spoken":[
        "eng",
        "zul",
        "xho",
        "afr",
        "nso",
        "tsn",
        "sot",
        "tso",
        "ssw",
        "ven",
        "nbl"
    ],
    "wof:name":"Teza",
    "wof:placetype":"locality"
},
  "geometry": {"coordinates":[32.15,-28.51667],"type":"Point"}
}