{
  "type": "Feature",
  "properties": {
    "gn:admin1_code":"6",
    "gn:admin2_code":"EKU",
    "gn:admin3_code":"EKU",
    "gn:asciiname":"Casseldale",
    "gn:country_code":"ZA",
    "gn:dem":1597,
    "gn:feature_class":"P",
    "gn:feature_code":"PPL",
    "gn:name":"Casseldale",
    "gn:population":0,
    "gn:timezone":"Africa/Johannesburg",
    "iso:country":"ZA",
    "wof:name":"Casseldale",
    "wof:placetype":"locality"
},
  "geometry": {"coordinates":[28.4679,-26.26296],"type":"Point"}
}