{
  "type": "Feature",
  "properties": {
    "gn:admin1_code":"2",
    "gn:admin2_code":"DC21",
    "gn:admin3_code":"KZN216",
    "gn:asciiname":"eSigodaneni",
    "gn:country_code":"ZA",
    "gn:dem":387,
    "gn:feature_class":"P",
    "gn:feature_code":"PPL",
    "gn:name":"eSigodaneni",
    "gn:population":0,
    "gn:timezone":"Africa/Johannesburg",
    "iso:country":"ZA",
    "wof:name":"eSigodaneni",
    "wof:placetype":"locality"
},
  "geometry": {"coordinates":[30.19469,-30.84863],"type":"Point"}
}