{
  "type": "Feature",
  "properties": {
    "gn:admin1_code":"5",
    "gn:admin2_code":"BUF",
    "gn:admin3_code":"BUF",
    "gn:asciiname":"Fort Grey",
    "gn:country_code":"ZA",
    "gn:dem":191,
    "gn:feature_class":"P",
    "gn:feature_code":"PPL",
    "gn:name":"Fort Grey",
    "gn:population":0,
    "gn:timezone":"Africa/Johannesburg",
    "iso:country":"ZA",
    "name:deu_x_preferred":[
        "Fort Grey"
    ],
    "name:fra_x_preferred":[
        "Ch\u00e2teau du Rocquaine"
    ],
    "wof:lang_x_official":[
        "eng"
    ],
    "wof:lang_x_spoken":[
        "eng",
        "zul",
        "xho",
        "afr",
        "nso",
        "tsn",
        "sot",
        "tso",
        "ssw",
        "ven",
        "nbl"
    ],
    "wof:name":"Fort Grey",
    "wof:placetype":"locality"
},
  "geometry": {"coordinates":[27.77793,-33.03117],"type":"Point"}
}