{
  "type": "Feature",
  "properties": {
    "gn:admin1_code":"5",
    "gn:admin2_code":"DC44",
    "gn:admin3_code":"EC444",
    "gn:asciiname":"KuTela",
    "gn:country_code":"ZA",
    "gn:dem":1454,
    "gn:feature_class":"P",
    "gn:feature_code":"PPL",
    "gn:name":"KuTela",
    "gn:population":0,
    "gn:timezone":"Africa/Johannesburg",
    "iso:country":"ZA",
    "wof:name":"KuTela",
    "wof:placetype":"locality"
},
  "geometry": {"coordinates":[29.46474000000001,-30.73735],"type":"Point"}
}