{
  "type": "Feature",
  "properties": {
    "gn:admin1_code":"5",
    "gn:admin2_code":"DC12",
    "gn:admin3_code":"EC126",
    "gn:asciiname":"Matomelas Location",
    "gn:country_code":"ZA",
    "gn:dem":227,
    "gn:feature_class":"P",
    "gn:feature_code":"PPLL",
    "gn:name":"Matomelas Location",
    "gn:population":0,
    "gn:timezone":"Africa/Johannesburg",
    "iso:country":"ZA",
    "wof:name":"Matomelas Location",
    "wof:placetype":"locality"
},
  "geometry": {"coordinates":[27.11667000000001,-33.28333],"type":"Point"}
}