{
  "type": "Feature",
  "properties": {
    "gn:admin1_code":"5",
    "gn:admin2_code":"DC15",
    "gn:admin3_code":"EC157",
    "gn:asciiname":"Kongeni",
    "gn:country_code":"ZA",
    "gn:dem":831,
    "gn:feature_class":"P",
    "gn:feature_code":"PPL",
    "gn:name":"Kongeni",
    "gn:population":0,
    "gn:timezone":"Africa/Johannesburg",
    "iso:country":"ZA",
    "wof:name":"Kongeni",
    "wof:placetype":"locality"
},
  "geometry": {"coordinates":[28.45,-31.68333],"type":"Point"}
}