{
  "type": "Feature",
  "properties": {
    "gn:admin1_code":"3.0",
    "gn:admin2_code":"DC16",
    "gn:admin3_code":"FS164",
    "gn:asciiname":"Sabella",
    "gn:country_code":"ZA",
    "gn:dem":1488,
    "gn:feature_class":"P",
    "gn:feature_code":"PPL",
    "gn:name":"Sabella",
    "gn:population":0,
    "gn:timezone":"Africa/Johannesburg",
    "iso:country":"ZA",
    "name:deu_x_preferred":[
        "Sabella"
    ],
    "name:fra_x_preferred":[
        "Sabella"
    ],
    "name:ita_x_preferred":[
        "Sabella"
    ],
    "name:nld_x_preferred":[
        "Sabella"
    ],
    "name:spa_x_preferred":[
        "Sabella"
    ],
    "wof:name":"Sabella",
    "wof:placetype":"locality"
},
  "geometry": {"coordinates":[26.9371,-29.68449],"type":"Point"}
}