{
  "type": "Feature",
  "properties": {
    "gn:admin1_code":"2",
    "gn:admin2_code":"DC28",
    "gn:admin3_code":"KZN285",
    "gn:asciiname":"Kortbegrip",
    "gn:country_code":"ZA",
    "gn:dem":924,
    "gn:feature_class":"P",
    "gn:feature_code":"PPL",
    "gn:name":"Kortbegrip",
    "gn:population":0,
    "gn:timezone":"Africa/Johannesburg",
    "iso:country":"ZA",
    "wof:name":"Kortbegrip",
    "wof:placetype":"locality"
},
  "geometry": {"coordinates":[31.29884,-28.65647],"type":"Point"}
}