{
  "type": "Feature",
  "properties": {
    "gn:admin1_code":"7",
    "gn:admin2_code":"DC32",
    "gn:admin3_code":"MP321",
    "gn:asciiname":"Rietfontein",
    "gn:country_code":"ZA",
    "gn:dem":923,
    "gn:feature_class":"P",
    "gn:feature_code":"PPL",
    "gn:name":"Rietfontein",
    "gn:population":0,
    "gn:timezone":"Africa/Johannesburg",
    "iso:country":"ZA",
    "wof:name":"Rietfontein",
    "wof:placetype":"locality"
},
  "geometry": {"coordinates":[30.82754000000001,-25.08259],"type":"Point"}
}