{
  "type": "Feature",
  "properties": {
    "gn:admin1_code":"7",
    "gn:admin2_code":"DC32",
    "gn:admin3_code":"MP322",
    "gn:asciiname":"Daantjielokasie",
    "gn:country_code":"ZA",
    "gn:dem":687,
    "gn:feature_class":"P",
    "gn:feature_code":"PPL",
    "gn:name":"Daantjielokasie",
    "gn:population":0,
    "gn:timezone":"Africa/Johannesburg",
    "iso:country":"ZA",
    "wof:name":"Daantjielokasie",
    "wof:placetype":"locality"
},
  "geometry": {"coordinates":[31.20032,-25.42783],"type":"Point"}
}