{
  "type": "Feature",
  "properties": {
    "gn:admin1_code":"9",
    "gn:admin2_code":"DC35",
    "gn:admin3_code":"LIM351",
    "gn:asciiname":"Ga-Kibi",
    "gn:country_code":"ZA",
    "gn:dem":970,
    "gn:feature_class":"P",
    "gn:feature_code":"PPL",
    "gn:name":"Ga-Kibi",
    "gn:population":0,
    "gn:timezone":"Africa/Johannesburg",
    "iso:country":"ZA",
    "wof:name":"Ga-Kibi",
    "wof:placetype":"locality"
},
  "geometry": {"coordinates":[29.03744,-23.07598],"type":"Point"}
}