{
  "type": "Feature",
  "properties": {
    "gn:admin1_code":"5",
    "gn:admin2_code":"DC13",
    "gn:admin3_code":"EC132",
    "gn:asciiname":"De Kuien",
    "gn:country_code":"ZA",
    "gn:dem":1281,
    "gn:feature_class":"P",
    "gn:feature_code":"PPL",
    "gn:name":"De Kuien",
    "gn:population":0,
    "gn:timezone":"Africa/Johannesburg",
    "iso:country":"ZA",
    "wof:name":"De Kuien",
    "wof:placetype":"locality"
},
  "geometry": {"coordinates":[25.72948,-31.78624000000001],"type":"Point"}
}