{
  "type": "Feature",
  "properties": {
    "gn:admin1_code":"5.0",
    "gn:admin2_code":"DC13",
    "gn:admin3_code":"EC135",
    "gn:asciiname":"Rwantsana",
    "gn:country_code":"ZA",
    "gn:dem":1129,
    "gn:feature_class":"P",
    "gn:feature_code":"PPL",
    "gn:name":"Rwantsana",
    "gn:population":0,
    "gn:timezone":"Africa/Johannesburg",
    "iso:country":"ZA",
    "wof:name":"Rwantsana",
    "wof:placetype":"locality"
},
  "geometry": {"coordinates":[27.44636,-31.74916],"type":"Point"}
}