{
  "type": "Feature",
  "properties": {
    "gn:admin1_code":"5",
    "gn:admin2_code":"DC15",
    "gn:admin3_code":"EC153",
    "gn:asciiname":"Ku-Mate",
    "gn:country_code":"ZA",
    "gn:dem":967,
    "gn:feature_class":"P",
    "gn:feature_code":"PPL",
    "gn:name":"Ku-Mate",
    "gn:population":0,
    "gn:timezone":"Africa/Johannesburg",
    "iso:country":"ZA",
    "wof:name":"Ku-Mate",
    "wof:placetype":"locality"
},
  "geometry": {"coordinates":[29.51933,-31.01272],"type":"Point"}
}