{
  "type": "Feature",
  "properties": {
    "gn:admin1_code":"5",
    "gn:admin2_code":"DC13",
    "gn:admin3_code":"EC136",
    "gn:asciiname":"KwaNcani",
    "gn:country_code":"ZA",
    "gn:dem":1532,
    "gn:feature_class":"P",
    "gn:feature_code":"PPL",
    "gn:name":"KwaNcani",
    "gn:population":0,
    "gn:timezone":"Africa/Johannesburg",
    "iso:country":"ZA",
    "wof:name":"KwaNcani",
    "wof:placetype":"locality"
},
  "geometry": {"coordinates":[26.8016,-31.6625],"type":"Point"}
}