{
  "type": "Feature",
  "properties": {
    "gn:admin1_code":"5",
    "gn:admin2_code":"DC13",
    "gn:admin3_code":"EC137",
    "gn:asciiname":"Ngqokoto",
    "gn:country_code":"ZA",
    "gn:dem":677,
    "gn:feature_class":"P",
    "gn:feature_code":"PPL",
    "gn:name":"Ngqokoto",
    "gn:population":0,
    "gn:timezone":"Africa/Johannesburg",
    "iso:country":"ZA",
    "name:und_x_variant":[
        "Nggokoto",
        "Ngqokoto"
    ],
    "wof:name":"Ngqokoto",
    "wof:placetype":"locality"
},
  "geometry": {"coordinates":[28.14419,-31.76406],"type":"Point"}
}