{
  "type": "Feature",
  "properties": {
    "gn:admin1_code":"5",
    "gn:admin2_code":"DC15",
    "gn:admin3_code":"EC155",
    "gn:asciiname":"Lubanzi",
    "gn:country_code":"ZA",
    "gn:dem":1021,
    "gn:feature_class":"P",
    "gn:feature_code":"PPL",
    "gn:name":"Lubanzi",
    "gn:population":0,
    "gn:timezone":"Africa/Johannesburg",
    "iso:country":"ZA",
    "wof:name":"Lubanzi",
    "wof:placetype":"locality"
},
  "geometry": {"coordinates":[29.06944,-31.43854],"type":"Point"}
}