{
  "type": "Feature",
  "properties": {
    "gn:admin1_code":"5",
    "gn:admin2_code":"DC15",
    "gn:admin3_code":"EC153",
    "gn:asciiname":"Ndindini",
    "gn:country_code":"ZA",
    "gn:dem":346,
    "gn:feature_class":"P",
    "gn:feature_code":"PPL",
    "gn:name":"Ndindini",
    "gn:population":0,
    "gn:timezone":"Africa/Johannesburg",
    "iso:country":"ZA",
    "name:und_x_variant":[
        "Dindini",
        "Ndindini"
    ],
    "wof:name":"Ndindini",
    "wof:placetype":"locality"
},
  "geometry": {"coordinates":[29.8426,-31.32602],"type":"Point"}
}