{
  "type": "Feature",
  "properties": {
    "gn:admin1_code":"5",
    "gn:admin2_code":"DC14",
    "gn:admin3_code":"EC144",
    "gn:asciiname":"Harmonie",
    "gn:country_code":"ZA",
    "gn:dem":1589,
    "gn:feature_class":"P",
    "gn:feature_code":"PPL",
    "gn:name":"Harmonie",
    "gn:population":0,
    "gn:timezone":"Africa/Johannesburg",
    "iso:country":"ZA",
    "name:ces_x_preferred":[
        "Dechov\u00e1 harmonie"
    ],
    "name:deu_x_preferred":[
        "Harmoniemusik"
    ],
    "name:jpn_x_preferred":[
        "\u30cf\u30eb\u30e2\u30cb\u30fc\u30e0\u30b8\u30fc\u30af"
    ],
    "wof:lang_x_official":[
        "eng"
    ],
    "wof:lang_x_spoken":[
        "eng",
        "zul",
        "xho",
        "afr",
        "nso",
        "tsn",
        "sot",
        "tso",
        "ssw",
        "ven",
        "nbl"
    ],
    "wof:name":"Harmonie",
    "wof:placetype":"locality"
},
  "geometry": {"coordinates":[25.78256,-31.2025],"type":"Point"}
}