{
  "type": "Feature",
  "properties": {
    "gn:admin1_code":"5",
    "gn:admin2_code":"DC14",
    "gn:admin3_code":"EC142",
    "gn:asciiname":"Magadla",
    "gn:country_code":"ZA",
    "gn:dem":1779,
    "gn:feature_class":"P",
    "gn:feature_code":"PPL",
    "gn:name":"Magadla",
    "gn:population":0,
    "gn:timezone":"Africa/Johannesburg",
    "iso:country":"ZA",
    "wof:name":"Magadla",
    "wof:placetype":"locality"
},
  "geometry": {"coordinates":[27.31486,-30.6068],"type":"Point"}
}