{
  "type": "Feature",
  "properties": {
    "gn:admin1_code":"5",
    "gn:admin2_code":"DC12",
    "gn:admin3_code":"EC127",
    "gn:asciiname":"Balfour",
    "gn:country_code":"ZA",
    "gn:dem":654,
    "gn:feature_class":"P",
    "gn:feature_code":"PPL",
    "gn:name":"Balfour",
    "gn:population":0,
    "gn:timezone":"Africa/Johannesburg",
    "iso:country":"ZA",
    "name:afr_x_preferred":[
        "Balfour"
    ],
    "name:est_x_preferred":[
        "Balfour"
    ],
    "name:nld_x_preferred":[
        "Balfour"
    ],
    "name:nso_x_preferred":[
        "Balfour"
    ],
    "name:ron_x_preferred":[
        "Balfour"
    ],
    "name:sot_x_preferred":[
        "Balfour"
    ],
    "wof:lang_x_official":[
        "eng"
    ],
    "wof:lang_x_spoken":[
        "eng",
        "zul",
        "xho",
        "afr",
        "nso",
        "tsn",
        "sot",
        "tso",
        "ssw",
        "ven",
        "nbl"
    ],
    "wof:name":"Balfour",
    "wof:placetype":"locality"
},
  "geometry": {"coordinates":[26.67944,-32.5404],"type":"Point"}
}