{
  "type": "Feature",
  "properties": {
    "gn:admin1_code":"6",
    "gn:admin2_code":"TSH",
    "gn:admin3_code":"TSH",
    "gn:asciiname":"Elandsrivier",
    "gn:country_code":"ZA",
    "gn:dem":1471,
    "gn:feature_class":"P",
    "gn:feature_code":"PPL",
    "gn:name":"Elandsrivier",
    "gn:population":0,
    "gn:timezone":"Africa/Johannesburg",
    "iso:country":"ZA",
    "wof:name":"Elandsrivier",
    "wof:placetype":"locality"
},
  "geometry": {"coordinates":[28.57722,-25.76444],"type":"Point"}
}