{
  "type": "Feature",
  "properties": {
    "gn:admin1_code":"9",
    "gn:admin2_code":"DC33",
    "gn:admin3_code":"LIM334",
    "gn:asciiname":"Mhalamhala",
    "gn:country_code":"ZA",
    "gn:dem":332,
    "gn:feature_class":"P",
    "gn:feature_code":"PPL",
    "gn:name":"Mhalamhala",
    "gn:population":0,
    "gn:timezone":"Africa/Johannesburg",
    "iso:country":"ZA",
    "wof:name":"Mhalamhala",
    "wof:placetype":"locality"
},
  "geometry": {"coordinates":[31.75451,-23.85673],"type":"Point"}
}