{
  "type": "Feature",
  "properties": {
    "gn:admin1_code":"5",
    "gn:admin2_code":"DC15",
    "gn:admin3_code":"EC156",
    "gn:asciiname":"Nkamasana",
    "gn:country_code":"ZA",
    "gn:dem":933,
    "gn:feature_class":"P",
    "gn:feature_code":"PPL",
    "gn:name":"Nkamasana",
    "gn:population":0,
    "gn:timezone":"Africa/Johannesburg",
    "iso:country":"ZA",
    "wof:name":"Nkamasana",
    "wof:placetype":"locality"
},
  "geometry": {"coordinates":[28.7199,-31.21844],"type":"Point"}
}