{
  "type": "Feature",
  "properties": {
    "gn:admin1_code":"2",
    "gn:admin2_code":"DC21",
    "gn:admin3_code":"KZN215",
    "gn:asciiname":"Mahlubeni",
    "gn:country_code":"ZA",
    "gn:dem":700,
    "gn:feature_class":"P",
    "gn:feature_code":"PPL",
    "gn:name":"Mahlubeni",
    "gn:population":0,
    "gn:timezone":"Africa/Johannesburg",
    "iso:country":"ZA",
    "wof:name":"Mahlubeni",
    "wof:placetype":"locality"
},
  "geometry": {"coordinates":[30.01362,-30.76876],"type":"Point"}
}