{
  "type": "Feature",
  "properties": {
    "gn:admin1_code":"2",
    "gn:admin2_code":"DC22",
    "gn:admin3_code":"KZN225",
    "gn:asciiname":"iMbali",
    "gn:country_code":"ZA",
    "gn:dem":717,
    "gn:feature_class":"P",
    "gn:feature_code":"PPL",
    "gn:name":"iMbali",
    "gn:population":0,
    "gn:timezone":"Africa/Johannesburg",
    "iso:country":"ZA",
    "wof:name":"iMbali",
    "wof:placetype":"locality"
},
  "geometry": {"coordinates":[30.35063,-29.65453],"type":"Point"}
}