{
  "type": "Feature",
  "properties": {
    "gn:admin1_code":"8.0",
    "gn:admin2_code":"DC6",
    "gn:admin3_code":"NC064",
    "gn:asciiname":"Genoembies",
    "gn:country_code":"ZA",
    "gn:dem":300,
    "gn:feature_class":"P",
    "gn:feature_code":"PPL",
    "gn:name":"Genoembies",
    "gn:population":0,
    "gn:timezone":"Africa/Johannesburg",
    "iso:country":"ZA",
    "wof:name":"Genoembies",
    "wof:placetype":"locality"
},
  "geometry": {"coordinates":[17.66667,-30.35],"type":"Point"}
}