{
  "type": "Feature",
  "properties": {
    "gn:admin1_code":"6.0",
    "gn:admin2_code":"JHB",
    "gn:admin3_code":"JHB",
    "gn:asciiname":"Kyalami Park",
    "gn:country_code":"ZA",
    "gn:dem":1491,
    "gn:feature_class":"P",
    "gn:feature_code":"PPL",
    "gn:name":"Kyalami Park",
    "gn:population":0,
    "gn:timezone":"Africa/Johannesburg",
    "iso:country":"ZA",
    "wof:name":"Kyalami Park",
    "wof:placetype":"locality"
},
  "geometry": {"coordinates":[28.07316,-25.99146],"type":"Point"}
}