{
  "type": "Feature",
  "properties": {
    "gn:gn_country":"ZA",
    "gn:gn_fcode":"PPL",
    "gn:gn_pop":0,
    "iso:country":"ZA",
    "name:afr_x_preferred":[
        "Nieuwoudtville"
    ],
    "name:dut_x_preferred":[
        "Nieuwoudtville"
    ],
    "name:eng_x_preferred":[
        "Nieuwoudtville"
    ],
    "name:fre_x_preferred":[
        "Nieuwoudtville"
    ],
    "name:ger_x_preferred":[
        "Nieuwoudtville"
    ],
    "name:nso_x_preferred":[
        "Nieuwoudtville"
    ],
    "name:rum_x_preferred":[
        "Nieuwoudtville"
    ],
    "qs_pg:aaroncc":"ZA",
    "qs_pg:gn_country":"ZA",
    "qs_pg:gn_fcode":"PPL",
    "qs_pg:gn_pop":0,
    "qs_pg:name":"Nieuwoudtville",
    "qs_pg:name_adm0":"South Africa",
    "qs_pg:name_adm1":"Northern Cape",
    "qs_pg:photos":76,
    "qs_pg:photos_1k":15,
    "qs_pg:photos_9k":1,
    "qs_pg:photos_9r":3,
    "qs_pg:photos_all":140,
    "qs_pg:photos_sr":3,
    "qs_pg:pop_sr":6,
    "qs_pg:qs_pg_placetype":"locality",
    "qs_pg:qs_pg_placetype_gp":"Town",
    "qs_pg:woe_adm0":23424942,
    "woe:adm0_id":23424942,
    "woe:name_adm0":"South Africa",
    "woe:name_adm1":"Northern Cape",
    "woe:placetype":"Town",
    "wof:name":"Nieuwoudtville",
    "wof:placetype":"locality"
},
  "geometry": {"coordinates":[19.1122,-31.37656],"type":"Point"}
}