{
  "type": "Feature",
  "properties": {
    "gn:admin1_code":"10",
    "gn:admin2_code":"DC40",
    "gn:admin3_code":"NW404",
    "gn:asciiname":"Justitia",
    "gn:cc2":"ZA",
    "gn:country_code":"ZA",
    "gn:dem":1352,
    "gn:feature_class":"P",
    "gn:feature_code":"PPL",
    "gn:name":"Justitia",
    "gn:population":0,
    "gn:timezone":"Africa/Johannesburg",
    "iso:country":"ZA",
    "name:und_x_variant":[
        "Justiesia",
        "Justitia"
    ],
    "wof:lang_x_official":[
        "eng"
    ],
    "wof:lang_x_spoken":[
        "eng",
        "zul",
        "xho",
        "afr",
        "nso",
        "tsn",
        "sot",
        "tso",
        "ssw",
        "ven",
        "nbl"
    ],
    "wof:name":"Justitia",
    "wof:placetype":"locality"
},
  "geometry": {"coordinates":[25.71667,-27.21667],"type":"Point"}
}