{
  "type": "Feature",
  "properties": {
    "iso:country":"ZA",
    "name:eng_x_preferred":[
        "Mahlomola"
    ],
    "qs:gn_local":0,
    "qs:local_max":120,
    "qs:local_sum":127,
    "qs:localhoods":2,
    "qs:name":"Mahlomola",
    "qs:name_adm0":"South Africa",
    "qs:name_adm1":"Free State",
    "qs:name_adm2":"Fezile Dabi",
    "qs:name_lau":"Ngwathe",
    "qs:name_local":"Parys",
    "qs:photo_max":7,
    "qs:photo_sum":7,
    "qs:placetype":"Suburb",
    "qs:quad_count":1,
    "qs:woe_adm0":23424942,
    "qs:woe_adm1":2346980,
    "qs:woe_adm2":56189420,
    "qs:woe_lau":56189566,
    "qs:woe_local":1586432,
    "qs:woe_ver":"7.10.0",
    "qs_pg:name":"Mahlomola",
    "qs_pg:name_adm0":"South Africa",
    "qs_pg:name_adm1":"Free State",
    "qs_pg:photos":7,
    "qs_pg:photos_1k":1,
    "qs_pg:photos_9k":1,
    "qs_pg:photos_9r":1,
    "qs_pg:photos_all":7,
    "qs_pg:photos_sr":1,
    "qs_pg:pop_sr":0,
    "qs_pg:qs_pg_placetype":"neighbourhood",
    "qs_pg:qs_pg_placetype_gp":"Suburb",
    "qs_pg:woe_adm0":23424942,
    "woe:adm0_id":23424942,
    "woe:name_adm0":"South Africa",
    "woe:name_adm1":"Free State",
    "woe:placetype":"Suburb",
    "wof:lang_x_official":[
        "eng"
    ],
    "wof:lang_x_spoken":[
        "eng",
        "zul",
        "xho",
        "afr",
        "nso",
        "tsn",
        "sot",
        "tso",
        "ssw",
        "ven",
        "nbl"
    ],
    "wof:name":"Mahlomola",
    "wof:placetype":"neighbourhood"
},
  "geometry": {"coordinates":[27.457581,-26.924519],"type":"Point"}
}