{
  "type": "Feature",
  "properties": {
    "gn:admin1_code":"9.0",
    "gn:admin2_code":"DC35",
    "gn:admin3_code":"LIM352",
    "gn:asciiname":"Seema",
    "gn:country_code":"ZA",
    "gn:dem":1035,
    "gn:feature_class":"P",
    "gn:feature_code":"PPL",
    "gn:name":"Seema",
    "gn:population":0,
    "gn:timezone":"Africa/Johannesburg",
    "iso:country":"ZA",
    "wof:name":"Seema",
    "wof:placetype":"locality"
},
  "geometry": {"coordinates":[28.93333,-23.61667000000001],"type":"Point"}
}