{
  "type": "Feature",
  "properties": {
    "gn:admin1_code":"2",
    "gn:admin2_code":"DC22",
    "gn:admin3_code":"KZN224",
    "gn:asciiname":"KwaThunzi",
    "gn:country_code":"ZA",
    "gn:dem":1239,
    "gn:feature_class":"P",
    "gn:feature_code":"PPL",
    "gn:name":"KwaThunzi",
    "gn:population":0,
    "gn:timezone":"Africa/Johannesburg",
    "iso:country":"ZA",
    "wof:name":"KwaThunzi",
    "wof:placetype":"locality"
},
  "geometry": {"coordinates":[29.64191,-29.62011],"type":"Point"}
}