{
  "type": "Feature",
  "properties": {
    "gn:admin1_code":"10",
    "gn:asciiname":"Mahukubung",
    "gn:country_code":"ZA",
    "gn:dem":1439,
    "gn:feature_class":"P",
    "gn:feature_code":"PPL",
    "gn:name":"Mahukubung",
    "gn:population":0,
    "gn:timezone":"Africa/Johannesburg",
    "iso:country":"ZA",
    "name:und_x_variant":[
        "Mahukubu",
        "Mahukubung"
    ],
    "wof:name":"Mahukubung",
    "wof:placetype":"locality"
},
  "geometry": {"coordinates":[23.73976,-27.46772],"type":"Point"}
}