{
  "type": "Feature",
  "properties": {
    "gn:admin1_code":"5",
    "gn:admin2_code":"DC13",
    "gn:admin3_code":"EC132",
    "gn:asciiname":"Rockdale",
    "gn:country_code":"ZA",
    "gn:dem":1218,
    "gn:feature_class":"P",
    "gn:feature_code":"PPL",
    "gn:name":"Rockdale",
    "gn:population":0,
    "gn:timezone":"Africa/Johannesburg",
    "iso:country":"ZA",
    "name:cat_x_preferred":[
        "Rockdale"
    ],
    "name:ceb_x_preferred":[
        "Rockdale"
    ],
    "name:deu_x_preferred":[
        "Rockdale"
    ],
    "name:fra_x_preferred":[
        "Rockdale"
    ],
    "name:ita_x_preferred":[
        "Rockdale"
    ],
    "name:nld_x_preferred":[
        "Rockdale"
    ],
    "name:pol_x_preferred":[
        "Rockdale"
    ],
    "name:por_x_preferred":[
        "Rockdale"
    ],
    "name:srp_x_preferred":[
        "\u0420\u043e\u043a\u0434\u0435\u0458\u043b"
    ],
    "name:swe_x_preferred":[
        "Rockdale"
    ],
    "name:vol_x_preferred":[
        "Rockdale"
    ],
    "wof:lang_x_official":[
        "eng"
    ],
    "wof:lang_x_spoken":[
        "eng",
        "zul",
        "xho",
        "afr",
        "nso",
        "tsn",
        "sot",
        "tso",
        "ssw",
        "ven",
        "nbl"
    ],
    "wof:name":"Rockdale",
    "wof:placetype":"locality"
},
  "geometry": {"coordinates":[25.65139,-31.89119],"type":"Point"}
}