{
  "type": "Feature",
  "properties": {
    "gn:admin1_code":"5",
    "gn:admin2_code":"DC15",
    "gn:admin3_code":"EC156",
    "gn:asciiname":"Mpumaze",
    "gn:country_code":"ZA",
    "gn:dem":1058,
    "gn:feature_class":"P",
    "gn:feature_code":"PPL",
    "gn:name":"Mpumaze",
    "gn:population":0,
    "gn:timezone":"Africa/Johannesburg",
    "iso:country":"ZA",
    "wof:name":"Mpumaze",
    "wof:placetype":"locality"
},
  "geometry": {"coordinates":[28.87688,-31.13197000000001],"type":"Point"}
}