{
  "type": "Feature",
  "properties": {
    "gn:admin1_code":"5",
    "gn:admin2_code":"DC12",
    "gn:admin3_code":"EC121",
    "gn:asciiname":"Kasa",
    "gn:country_code":"ZA",
    "gn:dem":456,
    "gn:feature_class":"P",
    "gn:feature_code":"PPL",
    "gn:name":"Kasa",
    "gn:population":0,
    "gn:timezone":"Africa/Johannesburg",
    "iso:country":"ZA",
    "name:aze_x_preferred":[
        "Kasa"
    ],
    "name:ceb_x_preferred":[
        "Kasa"
    ],
    "name:deu_x_preferred":[
        "Kasa"
    ],
    "name:fra_x_preferred":[
        "Kasa"
    ],
    "name:ind_x_preferred":[
        "Kasa"
    ],
    "name:ita_x_preferred":[
        "Kasa"
    ],
    "name:pol_x_preferred":[
        "Kasa"
    ],
    "name:que_x_preferred":[
        "Kasa"
    ],
    "name:spa_x_preferred":[
        "Kasa"
    ],
    "name:swe_x_preferred":[
        "Kasa"
    ],
    "name:vie_x_preferred":[
        "Kasa"
    ],
    "wof:name":"Kasa",
    "wof:placetype":"locality"
},
  "geometry": {"coordinates":[28.65,-32.06667],"type":"Point"}
}