{
  "type": "Feature",
  "properties": {
    "gn:admin1_code":"2",
    "gn:admin2_code":"DC43",
    "gn:admin3_code":"KZN431",
    "gn:asciiname":"Epsom",
    "gn:country_code":"ZA",
    "gn:dem":1527,
    "gn:feature_class":"P",
    "gn:feature_code":"PPL",
    "gn:name":"Epsom",
    "gn:population":0,
    "gn:timezone":"Africa/Johannesburg",
    "iso:country":"ZA",
    "name:afr_x_preferred":[
        "Epsom"
    ],
    "name:azb_x_preferred":[
        "\u0627\u067e\u0633\u0645"
    ],
    "name:ceb_x_preferred":[
        "Epsom"
    ],
    "name:ces_x_preferred":[
        "Epsom"
    ],
    "name:cym_x_preferred":[
        "Epsom"
    ],
    "name:dan_x_preferred":[
        "Epsom"
    ],
    "name:deu_x_preferred":[
        "Epsom"
    ],
    "name:fas_x_preferred":[
        "\u0627\u067e\u0633\u0645"
    ],
    "name:fra_x_preferred":[
        "Epsom"
    ],
    "name:gle_x_preferred":[
        "Epsom"
    ],
    "name:ita_x_preferred":[
        "Epsom"
    ],
    "name:jpn_x_preferred":[
        "\u30a8\u30d7\u30bd\u30e0"
    ],
    "name:lao_x_preferred":[
        "\u0ec0\u0ea1\u0eb7\u0ead\u0e87\u0ec0\u0ead\u0eb1\u0e9a\u0e8a\u0eb3"
    ],
    "name:nld_x_preferred":[
        "Epsom"
    ],
    "name:nno_x_preferred":[
        "Epsom"
    ],
    "name:pol_x_preferred":[
        "Epsom"
    ],
    "name:ron_x_preferred":[
        "Epsom"
    ],
    "name:rus_x_preferred":[
        "\u042d\u043f\u0441\u043e\u043c"
    ],
    "name:spa_x_preferred":[
        "Epsom"
    ],
    "name:swe_x_preferred":[
        "Epsom"
    ],
    "name:tur_x_preferred":[
        "Epsom"
    ],
    "name:urd_x_preferred":[
        "\u0627\u067e\u0633\u0648\u0645"
    ],
    "name:zho_x_preferred":[
        "\u57c3\u666e\u7d22\u59c6"
    ],
    "wof:name":"Epsom",
    "wof:placetype":"locality"
},
  "geometry": {"coordinates":[29.75,-29.91667],"type":"Point"}
}