{
  "type": "Feature",
  "properties": {
    "gn:admin1_code":"9.0",
    "gn:asciiname":"Utlha",
    "gn:country_code":"ZA",
    "gn:dem":390,
    "gn:feature_class":"P",
    "gn:feature_code":"PPL",
    "gn:name":"Utlha",
    "gn:population":0,
    "gn:timezone":"Africa/Johannesburg",
    "iso:country":"ZA",
    "wof:name":"Utlha",
    "wof:placetype":"locality"
},
  "geometry": {"coordinates":[31.44154,-24.70231],"type":"Point"}
}