{
  "type": "Feature",
  "properties": {
    "gn:admin1_code":"10.0",
    "gn:admin2_code":"DC39",
    "gn:admin3_code":"NW397",
    "gn:asciiname":"Selobane",
    "gn:country_code":"ZA",
    "gn:dem":1068,
    "gn:feature_class":"P",
    "gn:feature_code":"PPL",
    "gn:name":"Selobane",
    "gn:population":0,
    "gn:timezone":"Africa/Johannesburg",
    "iso:country":"ZA",
    "wof:name":"Selobane",
    "wof:placetype":"locality"
},
  "geometry": {"coordinates":[23.29221,-26.32874],"type":"Point"}
}