{
  "type": "Feature",
  "properties": {
    "gn:admin1_code":"11",
    "gn:admin2_code":"DC4",
    "gn:admin3_code":"WC041",
    "gn:asciiname":"Buffelskloof",
    "gn:country_code":"ZA",
    "gn:dem":405,
    "gn:feature_class":"P",
    "gn:feature_code":"PPL",
    "gn:name":"Buffelskloof",
    "gn:population":0,
    "gn:timezone":"Africa/Johannesburg",
    "iso:country":"ZA",
    "wof:name":"Buffelskloof",
    "wof:placetype":"locality"
},
  "geometry": {"coordinates":[21.87303,-33.50607],"type":"Point"}
}