{
  "type": "Feature",
  "properties": {
    "gn:admin1_code":"5",
    "gn:admin2_code":"DC14",
    "gn:admin3_code":"EC144",
    "gn:asciiname":"Ekron",
    "gn:country_code":"ZA",
    "gn:dem":1593,
    "gn:feature_class":"P",
    "gn:feature_code":"PPL",
    "gn:name":"Ekron",
    "gn:population":0,
    "gn:timezone":"Africa/Johannesburg",
    "iso:country":"ZA",
    "name:ara_x_preferred":[
        "\u0639\u0642\u0631\u0648\u0646"
    ],
    "name:cat_x_preferred":[
        "Ecron"
    ],
    "name:deu_x_preferred":[
        "Ekron"
    ],
    "name:ell_x_preferred":[
        "\u0391\u03ba\u03ba\u03b1\u03c1\u03ce\u03bd"
    ],
    "name:epo_x_preferred":[
        "Ekron"
    ],
    "name:eus_x_preferred":[
        "Ekron"
    ],
    "name:fra_x_preferred":[
        "\u00c9qron"
    ],
    "name:heb_x_preferred":[
        "\u05e2\u05e7\u05e8\u05d5\u05df"
    ],
    "name:hun_x_preferred":[
        "Ekron"
    ],
    "name:ind_x_preferred":[
        "Ekron"
    ],
    "name:ita_x_preferred":[
        "Ekron"
    ],
    "name:jpn_x_preferred":[
        "\u30a8\u30af\u30ed\u30f3"
    ],
    "name:nld_x_preferred":[
        "Ekron"
    ],
    "name:por_x_preferred":[
        "Ecrom"
    ],
    "name:ron_x_preferred":[
        "Ekron"
    ],
    "name:rus_x_preferred":[
        "\u042d\u043a\u0440\u043e\u043d"
    ],
    "name:slv_x_preferred":[
        "Ekron"
    ],
    "name:spa_x_preferred":[
        "Ecr\u00f3n"
    ],
    "name:swe_x_preferred":[
        "Ekron"
    ],
    "name:ukr_x_preferred":[
        "\u0415\u043a\u0440\u043e\u043d"
    ],
    "name:urd_x_preferred":[
        "\u0639\u0642\u0631\u0648\u0646"
    ],
    "name:zho_x_preferred":[
        "\u4ee5\u9769\u4f26"
    ],
    "wof:name":"Ekron",
    "wof:placetype":"locality"
},
  "geometry": {"coordinates":[25.86626,-31.34728],"type":"Point"}
}