{
  "type": "Feature",
  "properties": {
    "gn:admin1_code":"10.0",
    "gn:admin2_code":"DC37",
    "gn:admin3_code":"NW375",
    "gn:asciiname":"Silkaatskop",
    "gn:country_code":"ZA",
    "gn:dem":985,
    "gn:feature_class":"P",
    "gn:feature_code":"PPL",
    "gn:name":"Silkaatskop",
    "gn:population":0,
    "gn:timezone":"Africa/Johannesburg",
    "iso:country":"ZA",
    "name:und_x_variant":[
        "Silakatskop",
        "Silkaatskop"
    ],
    "wof:name":"Silkaatskop",
    "wof:placetype":"locality"
},
  "geometry": {"coordinates":[26.43489000000001,-25.04365],"type":"Point"}
}