{
  "type": "Feature",
  "properties": {
    "gn:admin1_code":"7.0",
    "gn:admin2_code":"DC32",
    "gn:admin3_code":"MP324",
    "gn:asciiname":"Schulzendal",
    "gn:country_code":"ZA",
    "gn:dem":392,
    "gn:feature_class":"P",
    "gn:feature_code":"PPL",
    "gn:name":"Schulzendal",
    "gn:population":0,
    "gn:timezone":"Africa/Johannesburg",
    "iso:country":"ZA",
    "name:nso_x_preferred":[
        "Schulzendal"
    ],
    "wof:lang_x_official":[
        "eng"
    ],
    "wof:lang_x_spoken":[
        "eng",
        "zul",
        "xho",
        "afr",
        "nso",
        "tsn",
        "sot",
        "tso",
        "ssw",
        "ven",
        "nbl"
    ],
    "wof:name":"Schulzendal",
    "wof:placetype":"locality"
},
  "geometry": {"coordinates":[31.53946,-25.75251],"type":"Point"}
}