{
  "type": "Feature",
  "properties": {
    "gn:gn_country":"ZA",
    "gn:gn_fcode":"PPLX",
    "gn:gn_pop":0,
    "iso:country":"ZA",
    "name:cat_x_preferred":[
        "Tempe"
    ],
    "name:ceb_x_preferred":[
        "Tempe"
    ],
    "name:dan_x_preferred":[
        "Tempe"
    ],
    "name:deu_x_preferred":[
        "Tempe"
    ],
    "name:epo_x_preferred":[
        "Tempe"
    ],
    "name:fin_x_preferred":[
        "Tempe"
    ],
    "name:fra_x_preferred":[
        "Tempe"
    ],
    "name:heb_x_preferred":[
        "\u05d8\u05de\u05e4\u05d4"
    ],
    "name:ind_x_preferred":[
        "Tempe"
    ],
    "name:ita_x_preferred":[
        "Tempe"
    ],
    "name:jav_x_preferred":[
        "Tempe"
    ],
    "name:lat_x_preferred":[
        "Tempe"
    ],
    "name:nld_x_preferred":[
        "Tempe"
    ],
    "name:nor_x_preferred":[
        "Tempe"
    ],
    "name:pol_x_preferred":[
        "Tempe"
    ],
    "name:por_x_preferred":[
        "Tempe"
    ],
    "name:ron_x_preferred":[
        "Tempe"
    ],
    "name:rus_x_preferred":[
        "\u0422\u0435\u043c\u043f\u0435"
    ],
    "name:spa_x_preferred":[
        "Tempe"
    ],
    "name:swe_x_preferred":[
        "Tempe"
    ],
    "name:ukr_x_preferred":[
        "\u0422\u0435\u043c\u043f\u0456"
    ],
    "qs_pg:aaroncc":"ZA",
    "qs_pg:gn_country":"ZA",
    "qs_pg:gn_fcode":"PPLX",
    "qs_pg:gn_pop":0,
    "qs_pg:name":"Tempe",
    "qs_pg:name_adm0":"South Africa",
    "qs_pg:name_adm1":"Free State",
    "qs_pg:photos":27,
    "qs_pg:photos_1k":5,
    "qs_pg:photos_9k":1,
    "qs_pg:photos_9r":2,
    "qs_pg:photos_all":27,
    "qs_pg:photos_sr":2,
    "qs_pg:pop_sr":0,
    "qs_pg:qs_pg_placetype":"neighbourhood",
    "qs_pg:qs_pg_placetype_gp":"Suburb",
    "qs_pg:woe_adm0":23424942,
    "woe:adm0_id":23424942,
    "woe:name_adm0":"South Africa",
    "woe:name_adm1":"Free State",
    "woe:placetype":"Suburb",
    "wof:name":"Tempe",
    "wof:placetype":"neighbourhood"
},
  "geometry": {"coordinates":[26.18731,-29.09289],"type":"Point"}
}