{
  "type": "Feature",
  "properties": {
    "iso:country":"ZA",
    "name:afr_x_preferred":[
        "Riversdal"
    ],
    "name:deu_x_preferred":[
        "Riversdale"
    ],
    "name:eng_x_preferred":[
        "Riversdale"
    ],
    "name:fra_x_preferred":[
        "Riversdale"
    ],
    "name:ita_x_preferred":[
        "Riversdale"
    ],
    "name:nld_x_preferred":[
        "Riversdal"
    ],
    "name:nob_x_preferred":[
        "Riversdale"
    ],
    "name:nso_x_preferred":[
        "Riversdale"
    ],
    "name:ron_x_preferred":[
        "Riversdale"
    ],
    "name:ukr_x_preferred":[
        "\u041c\u0456\u0435\u0442\u0434\u0436\u0456\u0435-\u0441\u0435-\u041a\u0440\u0430\u0430\u043b\u044c"
    ],
    "name:zho_x_preferred":[
        "\u91cc\u5f17\u65af\u4ee3\u723e"
    ],
    "qs_pg:aaroncc":"ZA",
    "qs_pg:name":"Riversdale",
    "qs_pg:name_adm0":"South Africa",
    "qs_pg:name_adm1":"Western Cape",
    "qs_pg:photos":50,
    "qs_pg:photos_1k":10,
    "qs_pg:photos_9k":1,
    "qs_pg:photos_9r":2,
    "qs_pg:photos_all":50,
    "qs_pg:photos_sr":2,
    "qs_pg:pop_sr":0,
    "qs_pg:qs_pg_placetype":"locality",
    "qs_pg:qs_pg_placetype_gp":"Town",
    "qs_pg:woe_adm0":23424942,
    "woe:adm0_id":23424942,
    "woe:name_adm0":"South Africa",
    "woe:name_adm1":"Western Cape",
    "woe:placetype":"Town",
    "wof:name":"Riversdale",
    "wof:placetype":"locality"
},
  "geometry": {"coordinates":[21.262166,-34.101667],"type":"Point"}
}