{
  "type": "Feature",
  "properties": {
    "gn:country":"ZA",
    "gn:fcode":"PPL",
    "gn:population":0,
    "iso:country":"ZA",
    "name:afr_x_preferred":[
        "Sutherland"
    ],
    "name:deu_x_preferred":[
        "Sutherland"
    ],
    "name:eng_x_preferred":[
        "Sutherland"
    ],
    "name:est_x_preferred":[
        "Sutherland"
    ],
    "name:fra_x_preferred":[
        "Sutherland"
    ],
    "name:ita_x_preferred":[
        "Sutherland"
    ],
    "name:jpn_x_preferred":[
        "\u30b5\u30b6\u30e9\u30f3\u30c9"
    ],
    "name:nld_x_preferred":[
        "Sutherland"
    ],
    "name:nob_x_preferred":[
        "Sutherland i S\u00f8r-Afrika"
    ],
    "name:nso_x_preferred":[
        "Sutherland"
    ],
    "name:rus_x_preferred":[
        "\u0421\u0430\u0437\u0435\u0440\u043b\u0435\u043d\u0434"
    ],
    "name:spa_x_preferred":[
        "Sutherland"
    ],
    "name:swe_x_preferred":[
        "Sutherland"
    ],
    "name:zho_x_preferred":[
        "\u85a9\u745f\u862d"
    ],
    "qs_pg:aaroncc":"ZA",
    "qs_pg:gn_country":"ZA",
    "qs_pg:gn_fcode":"PPL",
    "qs_pg:gn_pop":0,
    "qs_pg:name":"Sutherland",
    "qs_pg:name_adm0":"South Africa",
    "qs_pg:name_adm1":"Northern Cape",
    "qs_pg:photos":225,
    "qs_pg:photos_1k":46,
    "qs_pg:photos_9k":1,
    "qs_pg:photos_9r":4,
    "qs_pg:photos_all":225,
    "qs_pg:photos_sr":4,
    "qs_pg:pop_sr":6,
    "qs_pg:qs_pg_placetype":"locality",
    "qs_pg:qs_pg_placetype_gp":"Town",
    "qs_pg:woe_adm0":23424942,
    "woe:adm0_id":23424942,
    "woe:name_adm0":"South Africa",
    "woe:name_adm1":"Northern Cape",
    "woe:placetype":"Town",
    "wof:lang_x_official":[
        "eng"
    ],
    "wof:lang_x_spoken":[
        "eng",
        "zul",
        "xho",
        "afr",
        "nso",
        "tsn",
        "sot",
        "tso",
        "ssw",
        "ven",
        "nbl"
    ],
    "wof:name":"Sutherland",
    "wof:placetype":"locality"
},
  "geometry": {"coordinates":[20.66107,-32.39435],"type":"Point"}
}