{
  "type": "Feature",
  "properties": {
    "iso:country":"ZA",
    "name:eng_x_preferred":[
        "Jacarandar"
    ],
    "qs:gn_adm0_cc":"ZA",
    "qs:gn_local":3361077,
    "qs:gn_nam_loc":"de hoek",
    "qs:gn_namadm1":"11",
    "qs:local_max":2440,
    "qs:local_sum":2545,
    "qs:localhoods":3,
    "qs:name":"Jacarandar",
    "qs:name_adm0":"South Africa",
    "qs:name_adm1":"Western Cape",
    "qs:name_adm2":"City of Cape Town",
    "qs:name_lau":"Cape Town",
    "qs:name_local":"Oostenberg",
    "qs:photo_max":19,
    "qs:photo_sum":39,
    "qs:placetype":"Suburb",
    "qs:quad_count":5,
    "qs:woe_adm0":23424942,
    "qs:woe_adm1":2346987,
    "qs:woe_adm2":56189455,
    "qs:woe_lau":56189700,
    "qs:woe_local":55879365,
    "qs:woe_ver":"7.10.0",
    "wof:lang_x_official":[
        "eng"
    ],
    "wof:lang_x_spoken":[
        "eng",
        "zul",
        "xho",
        "afr",
        "nso",
        "tsn",
        "sot",
        "tso",
        "ssw",
        "ven",
        "nbl"
    ],
    "wof:name":"Oostenberg",
    "wof:placetype":"neighbourhood"
},
  "geometry": {"coordinates":[18.721901,-33.933603],"type":"Point"}
}