{
  "type": "Feature",
  "properties": {
    "gn:admin1_code":"3",
    "gn:admin2_code":"MAN",
    "gn:admin3_code":"MAN",
    "gn:asciiname":"Kromspruit",
    "gn:country_code":"ZA",
    "gn:dem":1422,
    "gn:feature_class":"P",
    "gn:feature_code":"PPL",
    "gn:name":"Kromspruit",
    "gn:population":0,
    "gn:timezone":"Africa/Johannesburg",
    "iso:country":"ZA",
    "wof:name":"Kromspruit",
    "wof:placetype":"locality"
},
  "geometry": {"coordinates":[26.40886,-29.25834],"type":"Point"}
}