{
  "type": "Feature",
  "properties": {
    "gn:admin1_code":"3.0",
    "gn:admin2_code":"DC16",
    "gn:admin3_code":"FS162",
    "gn:asciiname":"Vlakfontein",
    "gn:country_code":"ZA",
    "gn:dem":1517,
    "gn:feature_class":"P",
    "gn:feature_code":"PPL",
    "gn:name":"Vlakfontein",
    "gn:population":0,
    "gn:timezone":"Africa/Johannesburg",
    "iso:country":"ZA",
    "wof:name":"Vlakfontein",
    "wof:placetype":"locality"
},
  "geometry": {"coordinates":[26.13337000000001,-30.05009],"type":"Point"}
}