{
  "type": "Feature",
  "properties": {
    "gn:admin1_code":"3.0",
    "gn:admin2_code":"DC16",
    "gn:admin3_code":"FS163",
    "gn:asciiname":"Voorharts",
    "gn:country_code":"ZA",
    "gn:dem":1359,
    "gn:feature_class":"P",
    "gn:feature_code":"PPL",
    "gn:name":"Voorharts",
    "gn:population":0,
    "gn:timezone":"Africa/Johannesburg",
    "iso:country":"ZA",
    "wof:name":"Voorharts",
    "wof:placetype":"locality"
},
  "geometry": {"coordinates":[26.52152,-30.41726],"type":"Point"}
}