{
  "type": "Feature",
  "properties": {
    "gn:gn_country":"ZA",
    "gn:gn_fcode":"ADM3",
    "gn:gn_pop":80121,
    "gn:population":80121,
    "iso:country":"ZA",
    "qs_pg:aaroncc":"ZA",
    "qs_pg:gn_country":"ZA",
    "qs_pg:gn_fcode":"ADM3",
    "qs_pg:gn_pop":80121,
    "qs_pg:name":"Langeberg",
    "qs_pg:photos_9r":0,
    "qs_pg:photos_sr":0,
    "qs_pg:pop_sr":8,
    "qs_pg:qs_pg_placetype":"localadmin",
    "wof:name":"Langeberg",
    "wof:placetype":"localadmin",
    "wof:population":80121
},
  "geometry": {"coordinates":[20.05506,-33.78583],"type":"Point"}
}