{
  "type": "Feature",
  "properties": {
    "gn:country":"ZA",
    "gn:fcode":"ADM3",
    "gn:population":80121,
    "iso:country":"ZA",
    "name:afr_x_preferred":[
        "Langeberg"
    ],
    "name:deu_x_preferred":[
        "Langeberg Mountains"
    ],
    "name:nor_x_preferred":[
        "Langebergfjellene"
    ],
    "name:pol_x_preferred":[
        "G\u00f3ry D\u0142ugie"
    ],
    "name:spa_x_preferred":[
        "Langeberg"
    ],
    "name:zho_x_preferred":[
        "\u6717\u5384\u5c71\u8108"
    ],
    "qs_pg:aaroncc":"ZA",
    "qs_pg:gn_country":"ZA",
    "qs_pg:gn_fcode":"ADM3",
    "qs_pg:gn_pop":80121,
    "qs_pg:name":"Langeberg",
    "qs_pg:photos_9r":0,
    "qs_pg:photos_sr":0,
    "qs_pg:pop_sr":8,
    "qs_pg:qs_pg_placetype":"localadmin",
    "wof:lang_x_official":[
        "eng"
    ],
    "wof:lang_x_spoken":[
        "eng",
        "zul",
        "xho",
        "afr",
        "nso",
        "tsn",
        "sot",
        "tso",
        "ssw",
        "ven",
        "nbl"
    ],
    "wof:name":"Langeberg",
    "wof:placetype":"localadmin",
    "wof:population":80121
},
  "geometry": {"coordinates":[20.05506,-33.78583],"type":"Point"}
}