{
  "type": "Feature",
  "properties": {
    "gn:admin1_code":"8",
    "gn:admin2_code":"DC6",
    "gn:admin3_code":"NC066",
    "gn:asciiname":"Ntshatshongo",
    "gn:country_code":"ZA",
    "gn:dem":1334,
    "gn:feature_class":"P",
    "gn:feature_code":"PPL",
    "gn:name":"Ntshatshongo",
    "gn:population":0,
    "gn:timezone":"Africa/Johannesburg",
    "iso:country":"ZA",
    "wof:name":"Ntshatshongo",
    "wof:placetype":"locality"
},
  "geometry": {"coordinates":[20.66667,-32.21667],"type":"Point"}
}