{
  "type": "Feature",
  "properties": {
    "gn:admin1_code":"8",
    "gn:admin2_code":"DC8",
    "gn:admin3_code":"NC084",
    "gn:asciiname":"Geselskap",
    "gn:country_code":"ZA",
    "gn:dem":963,
    "gn:feature_class":"P",
    "gn:feature_code":"PPL",
    "gn:name":"Geselskap",
    "gn:population":0,
    "gn:timezone":"Africa/Johannesburg",
    "iso:country":"ZA",
    "wof:name":"Geselskap",
    "wof:placetype":"locality"
},
  "geometry": {"coordinates":[21.50608,-29.68786],"type":"Point"}
}