{
  "type": "Feature",
  "properties": {
    "gn:admin1_code":"5",
    "gn:admin2_code":"DC15",
    "gn:admin3_code":"EC156",
    "gn:asciiname":"Mqandanto",
    "gn:country_code":"ZA",
    "gn:dem":878,
    "gn:feature_class":"P",
    "gn:feature_code":"PPL",
    "gn:name":"Mqandanto",
    "gn:population":0,
    "gn:timezone":"Africa/Johannesburg",
    "iso:country":"ZA",
    "wof:name":"Mqandanto",
    "wof:placetype":"locality"
},
  "geometry": {"coordinates":[28.66325,-31.37181],"type":"Point"}
}