{
  "type": "Feature",
  "properties": {
    "gn:admin1_code":"7",
    "gn:admin2_code":"DC30",
    "gn:admin3_code":"MP301",
    "gn:asciiname":"Clarence",
    "gn:country_code":"ZA",
    "gn:dem":1478,
    "gn:feature_class":"P",
    "gn:feature_code":"PPL",
    "gn:name":"Clarence",
    "gn:population":0,
    "gn:timezone":"Africa/Johannesburg",
    "iso:country":"ZA",
    "wof:name":"Clarence",
    "wof:placetype":"locality"
},
  "geometry": {"coordinates":[30.66746,-26.25724],"type":"Point"}
}