{
  "type": "Feature",
  "properties": {
    "gn:admin1_code":"10",
    "gn:asciiname":"Ardath",
    "gn:country_code":"ZA",
    "gn:dem":1109,
    "gn:feature_class":"P",
    "gn:feature_code":"PPL",
    "gn:name":"Ardath",
    "gn:population":0,
    "gn:timezone":"Africa/Johannesburg",
    "iso:country":"ZA",
    "wof:name":"Ardath",
    "wof:placetype":"locality"
},
  "geometry": {"coordinates":[23.16177,-27.09885],"type":"Point"}
}