{
  "type": "Feature",
  "properties": {
    "gn:admin1_code":"5",
    "gn:admin2_code":"DC13",
    "gn:admin3_code":"EC133",
    "gn:asciiname":"Merinowelk",
    "gn:country_code":"ZA",
    "gn:dem":1530,
    "gn:feature_class":"P",
    "gn:feature_code":"PPL",
    "gn:name":"Merinowelk",
    "gn:population":0,
    "gn:timezone":"Africa/Johannesburg",
    "iso:country":"ZA",
    "wof:name":"Merinowelk",
    "wof:placetype":"locality"
},
  "geometry": {"coordinates":[26.79288,-31.56912],"type":"Point"}
}