{
  "type": "Feature",
  "properties": {
    "gn:admin1_code":"9.0",
    "gn:admin2_code":"DC36",
    "gn:admin3_code":"LIM364",
    "gn:asciiname":"Van Alphens Viei",
    "gn:country_code":"ZA",
    "gn:dem":1175,
    "gn:feature_class":"P",
    "gn:feature_code":"PPL",
    "gn:name":"Van Alphens Viei",
    "gn:population":0,
    "gn:timezone":"Africa/Johannesburg",
    "iso:country":"ZA",
    "wof:lang_x_official":[
        "eng"
    ],
    "wof:lang_x_spoken":[
        "eng",
        "zul",
        "xho",
        "afr",
        "nso",
        "tsn",
        "sot",
        "tso",
        "ssw",
        "ven",
        "nbl"
    ],
    "wof:name":"Van Alphens Viei",
    "wof:placetype":"locality"
},
  "geometry": {"coordinates":[28.66667,-24.43333],"type":"Point"}
}