{
  "type": "Feature",
  "properties": {
    "gn:admin1_code":"5",
    "gn:admin2_code":"DC12",
    "gn:admin3_code":"EC126",
    "gn:asciiname":"Hercules",
    "gn:country_code":"ZA",
    "gn:dem":36,
    "gn:feature_class":"P",
    "gn:feature_code":"PPL",
    "gn:name":"Hercules",
    "gn:population":0,
    "gn:timezone":"Africa/Johannesburg",
    "iso:country":"ZA",
    "name:afr_x_preferred":[
        "Hercules"
    ],
    "name:amh_x_preferred":[
        "\u1204\u122d\u12a9\u120c\u1235 \u120a\u1262\u12a9\u1235"
    ],
    "name:ara_x_preferred":[
        "\u0647\u0631\u0642\u0644"
    ],
    "name:arg_x_preferred":[
        "Hercules"
    ],
    "name:ben_x_preferred":[
        "\u09b9\u09be\u09b0\u0995\u09bf\u0989\u09b2\u09bf\u09b8"
    ],
    "name:bos_x_preferred":[
        "Herkules"
    ],
    "name:bre_x_preferred":[
        "Herkules"
    ],
    "name:bul_x_preferred":[
        "\u0425\u0435\u0440\u043a\u0443\u043b\u0435\u0441"
    ],
    "name:cat_x_preferred":[
        "H\u00e8rcules"
    ],
    "name:cos_x_preferred":[
        "Erculu"
    ],
    "name:epo_x_preferred":[
        "Herkulo"
    ],
    "name:eus_x_preferred":[
        "Herkules"
    ],
    "name:glg_x_preferred":[
        "H\u00e9rcules"
    ],
    "name:hrv_x_preferred":[
        "Herkul"
    ],
    "name:hun_x_preferred":[
        "Hercules"
    ],
    "name:ina_x_preferred":[
        "Hercules"
    ],
    "name:ind_x_preferred":[
        "Herkules"
    ],
    "name:ita_x_preferred":[
        "Ercole"
    ],
    "name:lao_x_preferred":[
        "\u0ec1\u0eae\u0e81\u0e81\u0eb9\u0e99"
    ],
    "name:lat_x_preferred":[
        "Hercules"
    ],
    "name:lfn_x_preferred":[
        "Hercule"
    ],
    "name:mal_x_preferred":[
        "\u0d39\u0d46\u0d7c\u0d15\u0d4d\u0d15\u0d41\u0d32\u0d40\u0d38\u0d4d"
    ],
    "name:nep_x_preferred":[
        "\u0939\u0930\u094d\u0915\u0941\u0932\u0938"
    ],
    "name:nld_x_preferred":[
        "Hercules"
    ],
    "name:pan_x_preferred":[
        "\u0a39\u0a30\u0a15\u0a41\u0a32\u0a40\u0a1c\u0a3c"
    ],
    "name:pol_x_preferred":[
        "Herkules"
    ],
    "name:por_x_preferred":[
        "H\u00e9rcules"
    ],
    "name:scn_x_preferred":[
        "Erculi"
    ],
    "name:slv_x_preferred":[
        "Herkul"
    ],
    "name:spa_x_preferred":[
        "H\u00e9rcules"
    ],
    "name:srp_x_preferred":[
        "\u0425\u0435\u0440\u043a\u0443\u043b"
    ],
    "name:swe_x_preferred":[
        "Hercules"
    ],
    "name:tam_x_preferred":[
        "\u0b8e\u0bb0\u0bcd\u0b95\u0bcd\u0b95\u0bc1\u0bb2\u0bbf\u0b9a\u0bc1"
    ],
    "name:tgl_x_preferred":[
        "Herkules"
    ],
    "name:tha_x_preferred":[
        "\u0e40\u0e2e\u0e2d\u0e23\u0e4c\u0e04\u0e34\u0e27\u0e25\u0e35\u0e2a"
    ],
    "name:war_x_preferred":[
        "Hercules"
    ],
    "name:zho_x_preferred":[
        "\u8d6b\u4e18\u5229"
    ],
    "wof:name":"Hercules",
    "wof:placetype":"locality"
},
  "geometry": {"coordinates":[27.42513,-33.31012],"type":"Point"}
}