{
  "type": "Feature",
  "properties": {
    "gn:admin1_code":"5",
    "gn:admin2_code":"DC14",
    "gn:admin3_code":"EC144",
    "gn:asciiname":"El Alamen",
    "gn:country_code":"ZA",
    "gn:dem":1434,
    "gn:feature_class":"P",
    "gn:feature_code":"PPL",
    "gn:name":"El Alamen",
    "gn:population":0,
    "gn:timezone":"Africa/Johannesburg",
    "iso:country":"ZA",
    "wof:name":"El Alamen",
    "wof:placetype":"locality"
},
  "geometry": {"coordinates":[25.95612,-30.89751],"type":"Point"}
}