{
  "type": "Feature",
  "properties": {
    "gn:admin1_code":"11.0",
    "gn:admin2_code":"DC2",
    "gn:admin3_code":"WC024",
    "gn:asciiname":"Jamestown",
    "gn:country_code":"ZA",
    "gn:dem":123,
    "gn:feature_class":"P",
    "gn:feature_code":"PPL",
    "gn:name":"Jamestown",
    "gn:population":0,
    "gn:timezone":"Africa/Johannesburg",
    "iso:country":"ZA",
    "wof:name":"Jamestown",
    "wof:placetype":"locality"
},
  "geometry": {"coordinates":[18.84888,-33.97898],"type":"Point"}
}