{
  "type": "Feature",
  "properties": {
    "gn:admin1_code":"8",
    "gn:admin2_code":"DC45",
    "gn:admin3_code":"NC452",
    "gn:asciiname":"Bretby",
    "gn:country_code":"ZA",
    "gn:dem":1552,
    "gn:feature_class":"P",
    "gn:feature_code":"PPL",
    "gn:name":"Bretby",
    "gn:population":0,
    "gn:timezone":"Africa/Johannesburg",
    "iso:country":"ZA",
    "name:ceb_x_preferred":[
        "Bretby"
    ],
    "name:cym_x_preferred":[
        "Bretby"
    ],
    "name:fas_x_preferred":[
        "\u0628\u0631\u062a\u0628\u06cc"
    ],
    "name:fra_x_preferred":[
        "Bretby"
    ],
    "name:ita_x_preferred":[
        "Bretby"
    ],
    "name:nld_x_preferred":[
        "Bretby"
    ],
    "name:pol_x_preferred":[
        "Bretby"
    ],
    "name:swe_x_preferred":[
        "Bretby"
    ],
    "name:und_x_variant":[
        "Grypoort"
    ],
    "wof:lang_x_official":[
        "eng"
    ],
    "wof:lang_x_spoken":[
        "eng",
        "zul",
        "xho",
        "afr",
        "nso",
        "tsn",
        "sot",
        "tso",
        "ssw",
        "ven",
        "nbl"
    ],
    "wof:name":"Bretby",
    "wof:placetype":"locality"
},
  "geometry": {"coordinates":[23.48859,-27.84816],"type":"Point"}
}