{
  "type": "Feature",
  "properties": {
    "gn:admin1_code":"5",
    "gn:admin2_code":"DC44",
    "gn:admin3_code":"EC441",
    "gn:asciiname":"Ramas Gate",
    "gn:country_code":"ZA",
    "gn:dem":2149,
    "gn:feature_class":"P",
    "gn:feature_code":"PPL",
    "gn:name":"Ramas Gate",
    "gn:population":0,
    "gn:timezone":"Africa/Johannesburg",
    "iso:country":"ZA",
    "wof:name":"Ramas Gate",
    "wof:placetype":"locality"
},
  "geometry": {"coordinates":[28.91667,-30.06667],"type":"Point"}
}