{
  "type": "Feature",
  "properties": {
    "gn:admin1_code":"5",
    "gn:admin2_code":"BUF",
    "gn:admin3_code":"BUF",
    "gn:asciiname":"Bay View",
    "gn:country_code":"ZA",
    "gn:dem":58,
    "gn:feature_class":"P",
    "gn:feature_code":"PPL",
    "gn:name":"Bay View",
    "gn:population":0,
    "gn:timezone":"Africa/Johannesburg",
    "iso:country":"ZA",
    "name:ceb_x_preferred":[
        "Bay View"
    ],
    "name:deu_x_preferred":[
        "Bay View"
    ],
    "name:fra_x_preferred":[
        "Bay View"
    ],
    "name:ita_x_preferred":[
        "Bay View"
    ],
    "name:mlg_x_preferred":[
        "Bay View"
    ],
    "name:nld_x_preferred":[
        "Bay View"
    ],
    "name:pol_x_preferred":[
        "Bay View"
    ],
    "name:por_x_preferred":[
        "Bay View"
    ],
    "name:srp_x_preferred":[
        "\u0411\u0435\u0458 \u0412\u0458\u0443"
    ],
    "name:swe_x_preferred":[
        "Bay View"
    ],
    "name:ukr_x_preferred":[
        "\u0411\u0435\u0439-\u0412'\u044e"
    ],
    "name:vol_x_preferred":[
        "Bay View"
    ],
    "wof:name":"Bay View",
    "wof:placetype":"locality"
},
  "geometry": {"coordinates":[28.03442,-32.9235],"type":"Point"}
}