{
  "type": "Feature",
  "properties": {
    "gn:admin1_code":"5.0",
    "gn:admin2_code":"DC15",
    "gn:admin3_code":"EC154",
    "gn:asciiname":"Umngazi Mouth",
    "gn:country_code":"ZA",
    "gn:dem":11,
    "gn:feature_class":"P",
    "gn:feature_code":"PPL",
    "gn:name":"Umngazi Mouth",
    "gn:population":0,
    "gn:timezone":"Africa/Johannesburg",
    "iso:country":"ZA",
    "wof:name":"Umngazi Mouth",
    "wof:placetype":"locality"
},
  "geometry": {"coordinates":[29.45419,-31.67268],"type":"Point"}
}