{
  "type": "Feature",
  "properties": {
    "gn:admin1_code":"9.0",
    "gn:admin2_code":"DC35",
    "gn:admin3_code":"LIM351",
    "gn:asciiname":"Tonash",
    "gn:country_code":"ZA",
    "gn:dem":774,
    "gn:feature_class":"P",
    "gn:feature_code":"PPL",
    "gn:name":"Tonash",
    "gn:population":0,
    "gn:timezone":"Africa/Johannesburg",
    "iso:country":"ZA",
    "wof:name":"Tonash",
    "wof:placetype":"locality"
},
  "geometry": {"coordinates":[28.74678,-22.78314],"type":"Point"}
}