{
  "type": "Feature",
  "properties": {
    "gn:admin1_code":"11",
    "gn:admin2_code":"DC4",
    "gn:admin3_code":"WC043",
    "gn:asciiname":"Bonnievale",
    "gn:country_code":"ZA",
    "gn:dem":359,
    "gn:feature_class":"P",
    "gn:feature_code":"PPL",
    "gn:name":"Bonnievale",
    "gn:population":0,
    "gn:timezone":"Africa/Johannesburg",
    "iso:country":"ZA",
    "wof:name":"Bonnievale",
    "wof:placetype":"locality"
},
  "geometry": {"coordinates":[22.02977000000001,-33.932],"type":"Point"}
}