{
  "type": "Feature",
  "properties": {
    "gn:admin1_code":"7.0",
    "gn:admin2_code":"DC30",
    "gn:admin3_code":"MP301",
    "gn:asciiname":"Diepdale",
    "gn:country_code":"ZA",
    "gn:dem":1534,
    "gn:feature_class":"P",
    "gn:feature_code":"PPL",
    "gn:name":"Diepdale",
    "gn:population":0,
    "gn:timezone":"Africa/Johannesburg",
    "iso:country":"ZA",
    "name:afr_x_preferred":[
        "Diepdale"
    ],
    "name:nso_x_preferred":[
        "Diepdale"
    ],
    "wof:name":"Diepdale",
    "wof:placetype":"locality"
},
  "geometry": {"coordinates":[30.792,-26.45418],"type":"Point"}
}