{
  "type": "Feature",
  "properties": {
    "gn:admin1_code":"5",
    "gn:admin2_code":"DC14",
    "gn:admin3_code":"EC144",
    "gn:asciiname":"Dagbreek",
    "gn:country_code":"ZA",
    "gn:dem":1608,
    "gn:feature_class":"P",
    "gn:feature_code":"PPL",
    "gn:name":"Dagbreek",
    "gn:population":0,
    "gn:timezone":"Africa/Johannesburg",
    "iso:country":"ZA",
    "wof:name":"Dagbreek",
    "wof:placetype":"locality"
},
  "geometry": {"coordinates":[25.64293,-31.16984],"type":"Point"}
}