{
  "type": "Feature",
  "properties": {
    "gn:admin1_code":"2.0",
    "gn:admin2_code":"DC29",
    "gn:admin3_code":"KZN291",
    "gn:asciiname":"Macambini",
    "gn:country_code":"ZA",
    "gn:dem":76,
    "gn:feature_class":"P",
    "gn:feature_code":"PPL",
    "gn:name":"Macambini",
    "gn:population":0,
    "gn:timezone":"Africa/Johannesburg",
    "iso:country":"ZA",
    "wof:name":"Macambini",
    "wof:placetype":"locality"
},
  "geometry": {"coordinates":[31.53512000000001,-29.11841],"type":"Point"}
}