{
  "type": "Feature",
  "properties": {
    "gn:admin1_code":"5",
    "gn:admin2_code":"DC10",
    "gn:admin3_code":"EC109",
    "gn:asciiname":"Clarkson",
    "gn:country_code":"ZA",
    "gn:dem":249,
    "gn:feature_class":"P",
    "gn:feature_code":"PPL",
    "gn:name":"Clarkson",
    "gn:population":0,
    "gn:timezone":"Africa/Johannesburg",
    "iso:country":"ZA",
    "name:ceb_x_preferred":[
        "Clarkson"
    ],
    "name:deu_x_preferred":[
        "Clarkson"
    ],
    "name:fra_x_preferred":[
        "Clarkson"
    ],
    "name:heb_x_preferred":[
        "\u05e7\u05dc\u05d0\u05e8\u05e7\u05e1\u05d5\u05df"
    ],
    "name:ita_x_preferred":[
        "Clarkson"
    ],
    "name:jpn_x_preferred":[
        "\u30af\u30e9\u30fc\u30af\u30bd\u30f3"
    ],
    "name:lav_x_preferred":[
        "Clarkson"
    ],
    "name:nld_x_preferred":[
        "Clarkson"
    ],
    "name:pol_x_preferred":[
        "Clarkson"
    ],
    "name:por_x_preferred":[
        "Clarkson"
    ],
    "name:rus_x_preferred":[
        "\u041a\u043b\u0430\u0440\u043a\u0441\u043e\u043d"
    ],
    "name:srp_x_preferred":[
        "\u041a\u043b\u0430\u0440\u043a\u0441\u043e\u043d"
    ],
    "name:swe_x_preferred":[
        "Clarkson"
    ],
    "name:ukr_x_preferred":[
        "\u041a\u043b\u0430\u0440\u043a\u0441\u043e\u043d"
    ],
    "name:und_x_variant":[
        "Clarkson Village",
        "Clarkeson"
    ],
    "name:vol_x_preferred":[
        "Clarkson"
    ],
    "wof:name":"Clarkson",
    "wof:placetype":"locality"
},
  "geometry": {"coordinates":[24.34291,-34.01521],"type":"Point"}
}