{
  "type": "Feature",
  "properties": {
    "gn:admin1_code":"5",
    "gn:admin2_code":"DC10",
    "gn:admin3_code":"EC109",
    "gn:asciiname":"Clarkson",
    "gn:country_code":"ZA",
    "gn:dem":249,
    "gn:feature_class":"P",
    "gn:feature_code":"PPL",
    "gn:name":"Clarkson",
    "gn:population":0,
    "gn:timezone":"Africa/Johannesburg",
    "iso:country":"ZA",
    "name:und_x_variant":[
        "Clarkson Village",
        "Clarkeson",
        "Clarkson"
    ],
    "wof:name":"Clarkson",
    "wof:placetype":"locality"
},
  "geometry": {"coordinates":[24.34291,-34.01521],"type":"Point"}
}