{
  "type": "Feature",
  "properties": {
    "gn:admin1_code":"5",
    "gn:admin2_code":"DC13",
    "gn:admin3_code":"EC136",
    "gn:asciiname":"KwaXusha",
    "gn:country_code":"ZA",
    "gn:dem":1276,
    "gn:feature_class":"P",
    "gn:feature_code":"PPL",
    "gn:name":"KwaXusha",
    "gn:population":0,
    "gn:timezone":"Africa/Johannesburg",
    "iso:country":"ZA",
    "wof:name":"KwaXusha",
    "wof:placetype":"locality"
},
  "geometry": {"coordinates":[26.91712,-31.71691],"type":"Point"}
}