{
  "type": "Feature",
  "properties": {
    "gn:admin1_code":"11",
    "gn:admin2_code":"DC1",
    "gn:admin3_code":"WC014",
    "gn:asciiname":"Stompneusbaai",
    "gn:country_code":"ZA",
    "gn:dem":10,
    "gn:feature_class":"P",
    "gn:feature_code":"PPL",
    "gn:name":"Stompneusbaai",
    "gn:population":0,
    "gn:timezone":"Africa/Johannesburg",
    "iso:country":"ZA",
    "name:und_x_variant":[
        "Stompneus Bay",
        "Stompneusbaai"
    ],
    "wof:name":"Stompneusbaai",
    "wof:placetype":"locality"
},
  "geometry": {"coordinates":[17.97544,-32.72419],"type":"Point"}
}