{
  "type": "Feature",
  "properties": {
    "gn:admin1_code":"10",
    "gn:admin2_code":"DC38",
    "gn:admin3_code":"NW385",
    "gn:asciiname":"Nkwedumang",
    "gn:country_code":"ZA",
    "gn:dem":1151,
    "gn:feature_class":"P",
    "gn:feature_code":"PPL",
    "gn:name":"Nkwedumang",
    "gn:population":0,
    "gn:timezone":"Africa/Johannesburg",
    "iso:country":"ZA",
    "wof:name":"Nkwedumang",
    "wof:placetype":"locality"
},
  "geometry": {"coordinates":[25.86276,-25.22987],"type":"Point"}
}