{
  "type": "Feature",
  "properties": {
    "gn:admin1_code":"11",
    "gn:admin2_code":"DC4",
    "gn:admin3_code":"WC048",
    "gn:asciiname":"Diepwalle",
    "gn:country_code":"ZA",
    "gn:dem":496,
    "gn:feature_class":"P",
    "gn:feature_code":"PPL",
    "gn:name":"Diepwalle",
    "gn:population":0,
    "gn:timezone":"Africa/Johannesburg",
    "iso:country":"ZA",
    "name:und_x_variant":[
        "Deepwalls",
        "Diepwalle"
    ],
    "wof:name":"Diepwalle",
    "wof:placetype":"locality"
},
  "geometry": {"coordinates":[23.16064,-33.94673],"type":"Point"}
}