{
  "type": "Feature",
  "properties": {
    "gn:admin1_code":"10",
    "gn:asciiname":"Dawlish",
    "gn:country_code":"ZA",
    "gn:dem":1160,
    "gn:feature_class":"P",
    "gn:feature_code":"PPL",
    "gn:name":"Dawlish",
    "gn:population":0,
    "gn:timezone":"Africa/Johannesburg",
    "iso:country":"ZA",
    "wof:name":"Dawlish",
    "wof:placetype":"locality"
},
  "geometry": {"coordinates":[23.32525,-26.87008],"type":"Point"}
}