{
  "type": "Feature",
  "properties": {
    "gn:admin1_code":"10",
    "gn:asciiname":"Dawlish",
    "gn:country_code":"ZA",
    "gn:dem":1160,
    "gn:feature_class":"P",
    "gn:feature_code":"PPL",
    "gn:name":"Dawlish",
    "gn:population":0,
    "gn:timezone":"Africa/Johannesburg",
    "iso:country":"ZA",
    "name:azb_x_preferred":[
        "\u062f\u0627\u0648\u0644\u06cc\u0634"
    ],
    "name:cym_x_preferred":[
        "Dawlish"
    ],
    "name:deu_x_preferred":[
        "Dawlish"
    ],
    "name:epo_x_preferred":[
        "Dawlish"
    ],
    "name:fas_x_preferred":[
        "\u062f\u0627\u0648\u0644\u06cc\u0634"
    ],
    "name:fra_x_preferred":[
        "Dawlish"
    ],
    "name:gle_x_preferred":[
        "Dawlish"
    ],
    "name:ita_x_preferred":[
        "Dawlish"
    ],
    "name:lat_x_preferred":[
        "Dawlish"
    ],
    "name:nld_x_preferred":[
        "Dawlish"
    ],
    "name:nno_x_preferred":[
        "Dawlish"
    ],
    "name:pol_x_preferred":[
        "Dawlish"
    ],
    "name:por_x_preferred":[
        "Dawlish"
    ],
    "name:ron_x_preferred":[
        "Dawlish"
    ],
    "name:spa_x_preferred":[
        "Dawlish"
    ],
    "name:swe_x_preferred":[
        "Dawlish"
    ],
    "name:vol_x_preferred":[
        "Dawlish"
    ],
    "name:zho_x_preferred":[
        "\u9053\u5229\u4ec0"
    ],
    "wof:name":"Dawlish",
    "wof:placetype":"locality"
},
  "geometry": {"coordinates":[23.32525,-26.87008],"type":"Point"}
}