{
  "type": "Feature",
  "properties": {
    "gn:admin1_code":"3",
    "gn:admin2_code":"DC19",
    "gn:admin3_code":"FS196",
    "gn:asciiname":"Kommissiepoort",
    "gn:country_code":"ZA",
    "gn:dem":1672,
    "gn:feature_class":"P",
    "gn:feature_code":"PPL",
    "gn:name":"Kommissiepoort",
    "gn:population":0,
    "gn:timezone":"Africa/Johannesburg",
    "iso:country":"ZA",
    "name:und_x_variant":[
        "Commissie Poort",
        "Kommissiepoort"
    ],
    "wof:name":"Kommissiepoort",
    "wof:placetype":"locality"
},
  "geometry": {"coordinates":[27.28519,-29.32428],"type":"Point"}
}