{
  "type": "Feature",
  "properties": {
    "gn:admin1_code":"5",
    "gn:admin2_code":"DC15",
    "gn:admin3_code":"EC157",
    "gn:asciiname":"Fama",
    "gn:country_code":"ZA",
    "gn:dem":964,
    "gn:feature_class":"P",
    "gn:feature_code":"PPL",
    "gn:name":"Fama",
    "gn:population":0,
    "gn:timezone":"Africa/Johannesburg",
    "iso:country":"ZA",
    "name:bre_x_preferred":[
        "Fama"
    ],
    "name:cat_x_preferred":[
        "Fama"
    ],
    "name:ceb_x_preferred":[
        "Fama"
    ],
    "name:deu_x_preferred":[
        "Fama"
    ],
    "name:epo_x_preferred":[
        "Fama"
    ],
    "name:eus_x_preferred":[
        "Fama"
    ],
    "name:fra_x_preferred":[
        "Fama"
    ],
    "name:ita_x_preferred":[
        "Fama"
    ],
    "name:lat_x_preferred":[
        "Fama"
    ],
    "name:nld_x_preferred":[
        "Fama"
    ],
    "name:nor_x_preferred":[
        "Fama"
    ],
    "name:por_x_preferred":[
        "Fama"
    ],
    "name:rus_x_preferred":[
        "\u0424\u0430\u043c\u0430"
    ],
    "name:spa_x_preferred":[
        "Fama"
    ],
    "name:swe_x_preferred":[
        "Fama"
    ],
    "wof:name":"Fama",
    "wof:placetype":"locality"
},
  "geometry": {"coordinates":[28.47078,-31.70641],"type":"Point"}
}