{
  "type": "Feature",
  "properties": {
    "gn:admin1_code":"2",
    "gn:admin2_code":"DC25",
    "gn:admin3_code":"KZN253",
    "gn:asciiname":"Groenvlei",
    "gn:country_code":"ZA",
    "gn:dem":1773,
    "gn:feature_class":"P",
    "gn:feature_code":"PPL",
    "gn:name":"Groenvlei",
    "gn:population":0,
    "gn:timezone":"Africa/Johannesburg",
    "iso:country":"ZA",
    "name:ceb_x_preferred":[
        "Groenvlei"
    ],
    "wof:lang_x_official":[
        "eng"
    ],
    "wof:lang_x_spoken":[
        "eng",
        "zul",
        "xho",
        "afr",
        "nso",
        "tsn",
        "sot",
        "tso",
        "ssw",
        "ven",
        "nbl"
    ],
    "wof:name":"Groenvlei",
    "wof:placetype":"locality"
},
  "geometry": {"coordinates":[30.23027,-27.45905],"type":"Point"}
}