{
  "type": "Feature",
  "properties": {
    "gn:admin1_code":"7",
    "gn:admin2_code":"DC30",
    "gn:admin3_code":"MP305",
    "gn:asciiname":"Darling",
    "gn:country_code":"ZA",
    "gn:dem":1577,
    "gn:feature_class":"P",
    "gn:feature_code":"PPL",
    "gn:name":"Darling",
    "gn:population":0,
    "gn:timezone":"Africa/Johannesburg",
    "iso:country":"ZA",
    "name:bel_x_preferred":[
        "\u0414\u0430\u0440\u043b\u0456\u043d\u0433"
    ],
    "name:ceb_x_preferred":[
        "Darling"
    ],
    "name:ces_x_preferred":[
        "Darling"
    ],
    "name:dan_x_preferred":[
        "Darling"
    ],
    "name:deu_x_preferred":[
        "Darling"
    ],
    "name:fin_x_preferred":[
        "Darling"
    ],
    "name:fra_x_preferred":[
        "Darling"
    ],
    "name:heb_x_preferred":[
        "\u05d3\u05e8\u05dc\u05d9\u05e0\u05d2"
    ],
    "name:hun_x_preferred":[
        "Darling"
    ],
    "name:ita_x_preferred":[
        "Darling"
    ],
    "name:jpn_x_preferred":[
        "\u30c0\u30fc\u30ea\u30f3\u30b0"
    ],
    "name:nld_x_preferred":[
        "Darling"
    ],
    "name:nor_x_preferred":[
        "Darling"
    ],
    "name:pol_x_preferred":[
        "Darling"
    ],
    "name:ron_x_preferred":[
        "Darling"
    ],
    "name:rus_x_preferred":[
        "\u0414\u0430\u0440\u043b\u0438\u043d\u0433"
    ],
    "name:slk_x_preferred":[
        "Darling"
    ],
    "name:spa_x_preferred":[
        "Darling"
    ],
    "name:swe_x_preferred":[
        "Darling"
    ],
    "name:tel_x_preferred":[
        "\u0c21\u0c3e\u0c30\u0c4d\u0c32\u0c3f\u0c02\u0c17\u0c4d"
    ],
    "name:tgl_x_preferred":[
        "Irog"
    ],
    "name:ukr_x_preferred":[
        "\u0414\u0430\u0440\u043b\u0456\u043d\u0433"
    ],
    "wof:lang_x_official":[
        "eng"
    ],
    "wof:lang_x_spoken":[
        "eng",
        "zul",
        "xho",
        "afr",
        "nso",
        "tsn",
        "sot",
        "tso",
        "ssw",
        "ven",
        "nbl"
    ],
    "wof:name":"Darling",
    "wof:placetype":"locality"
},
  "geometry": {"coordinates":[29.31892,-27.00349],"type":"Point"}
}