{
  "type": "Feature",
  "properties": {
    "gn:admin1_code":"7",
    "gn:admin2_code":"DC30",
    "gn:admin3_code":"MP305",
    "gn:asciiname":"Darling",
    "gn:country_code":"ZA",
    "gn:dem":1577,
    "gn:feature_class":"P",
    "gn:feature_code":"PPL",
    "gn:name":"Darling",
    "gn:population":0,
    "gn:timezone":"Africa/Johannesburg",
    "iso:country":"ZA",
    "wof:name":"Darling",
    "wof:placetype":"locality"
},
  "geometry": {"coordinates":[29.31892,-27.00349000000001],"type":"Point"}
}