{
  "type": "Feature",
  "properties": {
    "gn:admin1_code":"2",
    "gn:admin2_code":"DC43",
    "gn:admin3_code":"KZN431",
    "gn:asciiname":"Mangwanteni",
    "gn:country_code":"ZA",
    "gn:dem":1113,
    "gn:feature_class":"P",
    "gn:feature_code":"PPL",
    "gn:name":"Mangwanteni",
    "gn:population":0,
    "gn:timezone":"Africa/Johannesburg",
    "iso:country":"ZA",
    "wof:lang_x_official":[
        "eng"
    ],
    "wof:lang_x_spoken":[
        "eng",
        "zul",
        "xho",
        "afr",
        "nso",
        "tsn",
        "sot",
        "tso",
        "ssw",
        "ven",
        "nbl"
    ],
    "wof:name":"Mangwanteni",
    "wof:placetype":"locality"
},
  "geometry": {"coordinates":[29.77043,-29.70886],"type":"Point"}
}