{
  "type": "Feature",
  "properties": {
    "gn:admin1_code":"3.0",
    "gn:admin2_code":"DC16",
    "gn:admin3_code":"FS164",
    "gn:asciiname":"The Cliff",
    "gn:country_code":"ZA",
    "gn:dem":1483,
    "gn:feature_class":"P",
    "gn:feature_code":"PPL",
    "gn:name":"The Cliff",
    "gn:population":0,
    "gn:timezone":"Africa/Johannesburg",
    "iso:country":"ZA",
    "wof:name":"The Cliff",
    "wof:placetype":"locality"
},
  "geometry": {"coordinates":[26.76365,-29.49054000000001],"type":"Point"}
}