{
  "type": "Feature",
  "properties": {
    "gn:admin1_code":"2",
    "gn:admin2_code":"DC21",
    "gn:admin3_code":"KZN214",
    "gn:asciiname":"Lovat",
    "gn:country_code":"ZA",
    "gn:dem":385,
    "gn:feature_class":"P",
    "gn:feature_code":"PPL",
    "gn:name":"Lovat",
    "gn:population":0,
    "gn:timezone":"Africa/Johannesburg",
    "iso:country":"ZA",
    "name:swe_x_preferred":[
        "Lovat"
    ],
    "wof:name":"Lovat",
    "wof:placetype":"locality"
},
  "geometry": {"coordinates":[30.11667000000001,-30.56667],"type":"Point"}
}