{
  "type": "Feature",
  "properties": {
    "gn:admin1_code":"5",
    "gn:admin2_code":"DC44",
    "gn:admin3_code":"EC444",
    "gn:asciiname":"KwaBhala",
    "gn:country_code":"ZA",
    "gn:dem":1015,
    "gn:feature_class":"P",
    "gn:feature_code":"PPL",
    "gn:name":"KwaBhala",
    "gn:population":0,
    "gn:timezone":"Africa/Johannesburg",
    "iso:country":"ZA",
    "wof:name":"KwaBhala",
    "wof:placetype":"locality"
},
  "geometry": {"coordinates":[29.48309,-30.9115],"type":"Point"}
}