{
  "type": "Feature",
  "properties": {
    "gn:admin1_code":"8",
    "gn:admin2_code":"DC8",
    "gn:admin3_code":"NC082",
    "gn:asciiname":"De Bakke (1)",
    "gn:country_code":"ZA",
    "gn:dem":921,
    "gn:feature_class":"P",
    "gn:feature_code":"PPL",
    "gn:name":"De Bakke (1)",
    "gn:population":0,
    "gn:timezone":"Africa/Johannesburg",
    "iso:country":"ZA",
    "wof:name":"De Bakke (1)",
    "wof:placetype":"locality"
},
  "geometry": {"coordinates":[21.00042,-29.51757000000001],"type":"Point"}
}