{
  "type": "Feature",
  "properties": {
    "gn:admin1_code":"2",
    "gn:admin2_code":"DC26",
    "gn:admin3_code":"KZN261",
    "gn:asciiname":"Hildesheim",
    "gn:country_code":"ZA",
    "gn:dem":1300,
    "gn:feature_class":"P",
    "gn:feature_code":"PPL",
    "gn:name":"Hildesheim",
    "gn:population":0,
    "gn:timezone":"Africa/Johannesburg",
    "iso:country":"ZA",
    "wof:name":"Hildesheim",
    "wof:placetype":"locality"
},
  "geometry": {"coordinates":[30.77941,-27.47045],"type":"Point"}
}