{
  "type": "Feature",
  "properties": {
    "gn:country":"ZA",
    "gn:fcode":"PPLA3",
    "gn:population":12126,
    "iso:country":"ZA",
    "name:afr_x_preferred":[
        "Koster"
    ],
    "name:ceb_x_preferred":[
        "Koster"
    ],
    "name:deu_x_preferred":[
        "Koster"
    ],
    "name:eng_x_preferred":[
        "Koster"
    ],
    "name:est_x_preferred":[
        "Koster"
    ],
    "name:nld_x_preferred":[
        "Koster"
    ],
    "name:nso_x_preferred":[
        "Koster"
    ],
    "name:ron_x_preferred":[
        "Koster"
    ],
    "name:rus_x_preferred":[
        "\u041a\u043e\u0441\u0442\u0435\u0440"
    ],
    "name:zho_x_preferred":[
        "\u79d1\u65af\u7279\u723e"
    ],
    "qs_pg:aaroncc":"ZA",
    "qs_pg:gn_country":"ZA",
    "qs_pg:gn_fcode":"PPLA3",
    "qs_pg:gn_pop":12126,
    "qs_pg:name":"Koster",
    "qs_pg:photos_9r":0,
    "qs_pg:photos_sr":0,
    "qs_pg:pop_sr":6,
    "qs_pg:qs_pg_placetype":"locality",
    "wof:lang_x_official":[
        "eng"
    ],
    "wof:lang_x_spoken":[
        "eng",
        "zul",
        "xho",
        "afr",
        "nso",
        "tsn",
        "sot",
        "tso",
        "ssw",
        "ven",
        "nbl"
    ],
    "wof:name":"Koster",
    "wof:placetype":"locality",
    "wof:population":12126
},
  "geometry": {"coordinates":[26.89756,-25.86301],"type":"Point"}
}