{
  "type": "Feature",
  "properties": {
    "gn:admin1_code":"5",
    "gn:admin2_code":"DC15",
    "gn:admin3_code":"EC155",
    "gn:asciiname":"Ngqumani",
    "gn:country_code":"ZA",
    "gn:dem":679,
    "gn:feature_class":"P",
    "gn:feature_code":"PPL",
    "gn:name":"Ngqumani",
    "gn:population":0,
    "gn:timezone":"Africa/Johannesburg",
    "iso:country":"ZA",
    "wof:name":"Ngqumani",
    "wof:placetype":"locality"
},
  "geometry": {"coordinates":[29.19992,-31.59537000000001],"type":"Point"}
}