{
  "type": "Feature",
  "properties": {
    "gn:admin1_code":"10.0",
    "gn:admin2_code":"DC37",
    "gn:admin3_code":"NW372",
    "gn:asciiname":"Melodie",
    "gn:country_code":"ZA",
    "gn:dem":1186,
    "gn:feature_class":"P",
    "gn:feature_code":"PPL",
    "gn:name":"Melodie",
    "gn:population":0,
    "gn:timezone":"Africa/Johannesburg",
    "iso:country":"ZA",
    "wof:name":"Melodie",
    "wof:placetype":"locality"
},
  "geometry": {"coordinates":[27.89094,-25.73342],"type":"Point"}
}