{
  "type": "Feature",
  "properties": {
    "gn:admin1_code":"5.0",
    "gn:admin2_code":"DC13",
    "gn:admin3_code":"EC133",
    "gn:asciiname":"Rondekop",
    "gn:country_code":"ZA",
    "gn:dem":1351,
    "gn:feature_class":"P",
    "gn:feature_code":"PPL",
    "gn:name":"Rondekop",
    "gn:population":0,
    "gn:timezone":"Africa/Johannesburg",
    "iso:country":"ZA",
    "wof:name":"Rondekop",
    "wof:placetype":"locality"
},
  "geometry": {"coordinates":[26.60176,-31.68933],"type":"Point"}
}