{
  "type": "Feature",
  "properties": {
    "gn:country":"ZA",
    "gn:fcode":"ADM3",
    "gn:population":23263,
    "iso:country":"ZA",
    "qs_pg:aaroncc":"ZA",
    "qs_pg:gn_country":"ZA",
    "qs_pg:gn_fcode":"ADM3",
    "qs_pg:gn_pop":23263,
    "qs_pg:name":"Emadlangeni",
    "qs_pg:photos_9r":0,
    "qs_pg:photos_sr":0,
    "qs_pg:pop_sr":7,
    "qs_pg:qs_pg_placetype":"localadmin",
    "wof:name":"Emadlangeni",
    "wof:placetype":"localadmin",
    "wof:population":23263
},
  "geometry": {"coordinates":[30.32123,-27.61791],"type":"Point"}
}