{
  "type": "Feature",
  "properties": {
    "gn:gn_country":"ZA",
    "gn:gn_fcode":"PPL",
    "gn:gn_pop":0,
    "iso:country":"ZA",
    "qs_pg:aaroncc":"ZA",
    "qs_pg:gn_country":"ZA",
    "qs_pg:gn_fcode":"PPL",
    "qs_pg:gn_pop":0,
    "qs_pg:name":"Danville",
    "qs_pg:name_adm0":"South Africa",
    "qs_pg:name_adm1":"Gauteng",
    "qs_pg:photos_9r":0,
    "qs_pg:photos_sr":0,
    "qs_pg:pop_sr":0,
    "qs_pg:qs_pg_placetype":"neighbourhood",
    "qs_pg:qs_pg_placetype_gp":"Suburb",
    "qs_pg:woe_adm0":23424942,
    "woe:adm0_id":23424942,
    "woe:name_adm0":"South Africa",
    "woe:name_adm1":"Gauteng",
    "woe:placetype":"Suburb",
    "wof:name":"Danville",
    "wof:placetype":"neighbourhood"
},
  "geometry": {"coordinates":[28.12747,-25.74047],"type":"Point"}
}