{
  "type": "Feature",
  "properties": {
    "gn:country":"ZA",
    "gn:fcode":"PPL",
    "gn:population":0,
    "iso:country":"ZA",
    "name:cat_x_preferred":[
        "Danville"
    ],
    "name:ceb_x_preferred":[
        "Danville"
    ],
    "name:ces_x_preferred":[
        "Danville"
    ],
    "name:deu_x_preferred":[
        "Danville"
    ],
    "name:fra_x_preferred":[
        "Danville"
    ],
    "name:hun_x_preferred":[
        "Danville"
    ],
    "name:ita_x_preferred":[
        "Danville"
    ],
    "name:jpn_x_preferred":[
        "\u30c0\u30f3\u30d3\u30eb"
    ],
    "name:nld_x_preferred":[
        "Danville"
    ],
    "name:pol_x_preferred":[
        "Danville"
    ],
    "name:por_x_preferred":[
        "Danville"
    ],
    "name:rus_x_preferred":[
        "\u0414\u0430\u043d\u0432\u0438\u043b\u043b"
    ],
    "name:slk_x_preferred":[
        "Danville"
    ],
    "name:spa_x_preferred":[
        "Danville"
    ],
    "name:srp_x_preferred":[
        "\u0414\u0430\u043d\u0432\u0438\u043b"
    ],
    "name:swe_x_preferred":[
        "Danville"
    ],
    "name:ukr_x_preferred":[
        "\u0414\u0430\u043d\u0432\u0456\u043b\u043b"
    ],
    "name:vol_x_preferred":[
        "Danville"
    ],
    "qs_pg:aaroncc":"ZA",
    "qs_pg:gn_country":"ZA",
    "qs_pg:gn_fcode":"PPL",
    "qs_pg:gn_pop":0,
    "qs_pg:name":"Danville",
    "qs_pg:name_adm0":"South Africa",
    "qs_pg:name_adm1":"Gauteng",
    "qs_pg:photos_9r":0,
    "qs_pg:photos_sr":0,
    "qs_pg:pop_sr":0,
    "qs_pg:qs_pg_placetype":"neighbourhood",
    "qs_pg:qs_pg_placetype_gp":"Suburb",
    "qs_pg:woe_adm0":23424942,
    "woe:adm0_id":23424942,
    "woe:name_adm0":"South Africa",
    "woe:name_adm1":"Gauteng",
    "woe:placetype":"Suburb",
    "wof:name":"Danville",
    "wof:placetype":"neighbourhood"
},
  "geometry": {"coordinates":[28.12747,-25.74047],"type":"Point"}
}