{
  "type": "Feature",
  "properties": {
    "gn:admin1_code":"3",
    "gn:admin2_code":"DC19",
    "gn:admin3_code":"FS191",
    "gn:asciiname":"Koornland",
    "gn:country_code":"ZA",
    "gn:dem":1612,
    "gn:feature_class":"P",
    "gn:feature_code":"PPL",
    "gn:name":"Koornland",
    "gn:population":0,
    "gn:timezone":"Africa/Johannesburg",
    "iso:country":"ZA",
    "wof:name":"Koornland",
    "wof:placetype":"locality"
},
  "geometry": {"coordinates":[27.62735,-29.01389],"type":"Point"}
}