{
  "type": "Feature",
  "properties": {
    "gn:admin1_code":"5",
    "gn:admin2_code":"DC44",
    "gn:admin3_code":"EC441",
    "gn:asciiname":"Mampola",
    "gn:country_code":"ZA",
    "gn:dem":1865,
    "gn:feature_class":"P",
    "gn:feature_code":"PPL",
    "gn:name":"Mampola",
    "gn:population":0,
    "gn:timezone":"Africa/Johannesburg",
    "iso:country":"ZA",
    "wof:name":"Mampola",
    "wof:placetype":"locality"
},
  "geometry": {"coordinates":[29.03386,-30.05794],"type":"Point"}
}