{
  "type": "Feature",
  "properties": {
    "gn:gn_country":"ZA",
    "gn:gn_fcode":"ADM3",
    "gn:gn_pop":83086,
    "gn:population":83086,
    "iso:country":"ZA",
    "qs_pg:aaroncc":"ZA",
    "qs_pg:gn_country":"ZA",
    "qs_pg:gn_fcode":"ADM3",
    "qs_pg:gn_pop":83086,
    "qs_pg:name":"Ngqushwa",
    "qs_pg:photos_9r":0,
    "qs_pg:photos_sr":0,
    "qs_pg:pop_sr":8,
    "qs_pg:qs_pg_placetype":"localadmin",
    "wof:name":"Ngqushwa",
    "wof:placetype":"localadmin",
    "wof:population":83086
},
  "geometry": {"coordinates":[27.19866,-33.1865],"type":"Point"}
}