{
  "type": "Feature",
  "properties": {
    "gn:admin1_code":"8.0",
    "gn:admin2_code":"DC7",
    "gn:admin3_code":"NC074",
    "gn:asciiname":"Vleiplaas",
    "gn:country_code":"ZA",
    "gn:dem":939,
    "gn:feature_class":"P",
    "gn:feature_code":"PPL",
    "gn:name":"Vleiplaas",
    "gn:population":0,
    "gn:timezone":"Africa/Johannesburg",
    "iso:country":"ZA",
    "wof:name":"Vleiplaas",
    "wof:placetype":"locality"
},
  "geometry": {"coordinates":[21.91922000000001,-30.16022],"type":"Point"}
}