{
  "type": "Feature",
  "properties": {
    "gn:admin1_code":"3",
    "gn:admin2_code":"DC16",
    "gn:admin3_code":"FS162",
    "gn:asciiname":"Beginsel",
    "gn:country_code":"ZA",
    "gn:dem":1341,
    "gn:feature_class":"P",
    "gn:feature_code":"PPL",
    "gn:name":"Beginsel",
    "gn:population":0,
    "gn:timezone":"Africa/Johannesburg",
    "iso:country":"ZA",
    "wof:name":"Beginsel",
    "wof:placetype":"locality"
},
  "geometry": {"coordinates":[25.96239,-29.31956],"type":"Point"}
}