{
  "type": "Feature",
  "properties": {
    "gn:admin1_code":"9.0",
    "gn:admin2_code":"DC36",
    "gn:admin3_code":"LIM367",
    "gn:asciiname":"Weltevreden",
    "gn:country_code":"ZA",
    "gn:dem":1020,
    "gn:feature_class":"P",
    "gn:feature_code":"PPL",
    "gn:name":"Weltevreden",
    "gn:population":0,
    "gn:timezone":"Africa/Johannesburg",
    "iso:country":"ZA",
    "wof:name":"Weltevreden",
    "wof:placetype":"locality"
},
  "geometry": {"coordinates":[28.8534,-23.62608],"type":"Point"}
}