{
  "type": "Feature",
  "properties": {
    "gn:admin1_code":"5",
    "gn:admin2_code":"DC15",
    "gn:admin3_code":"EC157",
    "gn:asciiname":"Ironstone",
    "gn:country_code":"ZA",
    "gn:dem":817,
    "gn:feature_class":"P",
    "gn:feature_code":"PPL",
    "gn:name":"Ironstone",
    "gn:population":0,
    "gn:timezone":"Africa/Johannesburg",
    "iso:country":"ZA",
    "name:nld_x_preferred":[
        "IJzerzandsteen"
    ],
    "name:pol_x_preferred":[
        "\u017belaziak"
    ],
    "name:swe_x_preferred":[
        "J\u00e4rnsten"
    ],
    "name:tur_x_preferred":[
        "Demirta\u015f\u0131"
    ],
    "name:ukr_x_preferred":[
        "\u0417\u0430\u043b\u0456\u0437\u043d\u044f\u043a"
    ],
    "wof:lang_x_official":[
        "eng"
    ],
    "wof:lang_x_spoken":[
        "eng",
        "zul",
        "xho",
        "afr",
        "nso",
        "tsn",
        "sot",
        "tso",
        "ssw",
        "ven",
        "nbl"
    ],
    "wof:name":"Ironstone",
    "wof:placetype":"locality"
},
  "geometry": {"coordinates":[28.80288,-31.77016],"type":"Point"}
}