{
  "type": "Feature",
  "properties": {
    "gn:admin1_code":"6.0",
    "gn:admin2_code":"JHB",
    "gn:admin3_code":"JHB",
    "gn:asciiname":"Mulbarton",
    "gn:country_code":"ZA",
    "gn:dem":1624,
    "gn:feature_class":"P",
    "gn:feature_code":"PPL",
    "gn:name":"Mulbarton",
    "gn:population":0,
    "gn:timezone":"Africa/Johannesburg",
    "iso:country":"ZA",
    "name:ceb_x_preferred":[
        "Mulbarton"
    ],
    "name:swe_x_preferred":[
        "Mulbarton"
    ],
    "wof:name":"Mulbarton",
    "wof:placetype":"locality"
},
  "geometry": {"coordinates":[28.04921,-26.28962000000001],"type":"Point"}
}