{
  "type": "Feature",
  "properties": {
    "gn:admin1_code":"5",
    "gn:admin2_code":"DC13",
    "gn:admin3_code":"EC136",
    "gn:asciiname":"Milan",
    "gn:country_code":"ZA",
    "gn:dem":1256,
    "gn:feature_class":"P",
    "gn:feature_code":"PPL",
    "gn:name":"Milan",
    "gn:population":0,
    "gn:timezone":"Africa/Johannesburg",
    "iso:country":"ZA",
    "wof:name":"Milan",
    "wof:placetype":"locality"
},
  "geometry": {"coordinates":[27.3288,-31.55149],"type":"Point"}
}