{
  "type": "Feature",
  "properties": {
    "gn:admin1_code":"5",
    "gn:admin2_code":"DC12",
    "gn:admin3_code":"EC123",
    "gn:asciiname":"Lily Vale",
    "gn:country_code":"ZA",
    "gn:dem":240,
    "gn:feature_class":"P",
    "gn:feature_code":"PPL",
    "gn:name":"Lily Vale",
    "gn:population":0,
    "gn:timezone":"Africa/Johannesburg",
    "iso:country":"ZA",
    "wof:name":"Lily Vale",
    "wof:placetype":"locality"
},
  "geometry": {"coordinates":[28.1794,-32.68349],"type":"Point"}
}