{
  "type": "Feature",
  "properties": {
    "gn:admin1_code":"9",
    "gn:admin2_code":"DC35",
    "gn:admin3_code":"LIM352",
    "gn:asciiname":"Ga-Madiba",
    "gn:country_code":"ZA",
    "gn:dem":1431,
    "gn:feature_class":"P",
    "gn:feature_code":"PPL",
    "gn:name":"Ga-Madiba",
    "gn:population":0,
    "gn:timezone":"Africa/Johannesburg",
    "iso:country":"ZA",
    "name:afr_x_preferred":[
        "Ga-Madiba"
    ],
    "name:nso_x_preferred":[
        "Ga-Madiba"
    ],
    "wof:name":"Ga-Madiba",
    "wof:placetype":"locality"
},
  "geometry": {"coordinates":[29.15443,-23.87886],"type":"Point"}
}