{
  "type": "Feature",
  "properties": {
    "gn:admin1_code":"2",
    "gn:asciiname":"Boschfontein",
    "gn:country_code":"ZA",
    "gn:dem":1572,
    "gn:feature_class":"P",
    "gn:feature_code":"PPL",
    "gn:name":"Boschfontein",
    "gn:population":0,
    "gn:timezone":"Africa/Johannesburg",
    "iso:country":"ZA",
    "name:afr_x_preferred":[
        "Boschfontein"
    ],
    "name:est_x_preferred":[
        "Boschfontein"
    ],
    "name:nso_x_preferred":[
        "Boschfontein"
    ],
    "wof:name":"Boschfontein",
    "wof:placetype":"locality"
},
  "geometry": {"coordinates":[29.11667000000001,-30.58333],"type":"Point"}
}