{
  "type": "Feature",
  "properties": {
    "gn:admin1_code":"5.0",
    "gn:admin2_code":"DC15",
    "gn:admin3_code":"EC157",
    "gn:asciiname":"Tafani",
    "gn:country_code":"ZA",
    "gn:dem":945,
    "gn:feature_class":"P",
    "gn:feature_code":"PPL",
    "gn:name":"Tafani",
    "gn:population":0,
    "gn:timezone":"Africa/Johannesburg",
    "iso:country":"ZA",
    "wof:name":"Tafani",
    "wof:placetype":"locality"
},
  "geometry": {"coordinates":[28.68747,-31.76572],"type":"Point"}
}