{
  "type": "Feature",
  "properties": {
    "gn:admin1_code":"7",
    "gn:admin2_code":"DC31",
    "gn:admin3_code":"MP313",
    "gn:asciiname":"Blinkpan",
    "gn:country_code":"ZA",
    "gn:dem":1587,
    "gn:feature_class":"P",
    "gn:feature_code":"PPL",
    "gn:name":"Blinkpan",
    "gn:population":0,
    "gn:timezone":"Africa/Johannesburg",
    "iso:country":"ZA",
    "wof:name":"Blinkpan",
    "wof:placetype":"locality"
},
  "geometry": {"coordinates":[29.43314,-26.08266],"type":"Point"}
}