{
  "type": "Feature",
  "properties": {
    "gn:admin1_code":"7.0",
    "gn:admin2_code":"DC32",
    "gn:admin3_code":"MP324",
    "gn:asciiname":"Tongwe",
    "gn:country_code":"ZA",
    "gn:dem":233,
    "gn:feature_class":"P",
    "gn:feature_code":"PPL",
    "gn:name":"Tongwe",
    "gn:population":0,
    "gn:timezone":"Africa/Johannesburg",
    "iso:country":"ZA",
    "wof:name":"Tongwe",
    "wof:placetype":"locality"
},
  "geometry": {"coordinates":[31.76667,-25.68333],"type":"Point"}
}