{
  "type": "Feature",
  "properties": {
    "gn:admin1_code":"3",
    "gn:admin2_code":"DC16",
    "gn:admin3_code":"FS162",
    "gn:asciiname":"Charleron",
    "gn:country_code":"ZA",
    "gn:dem":1344,
    "gn:feature_class":"P",
    "gn:feature_code":"PPL",
    "gn:name":"Charleron",
    "gn:population":0,
    "gn:timezone":"Africa/Johannesburg",
    "iso:country":"ZA",
    "wof:name":"Charleron",
    "wof:placetype":"locality"
},
  "geometry": {"coordinates":[25.58421,-29.81603],"type":"Point"}
}