{
  "type": "Feature",
  "properties": {
    "gn:admin1_code":"10",
    "gn:asciiname":"Khabetlwane",
    "gn:country_code":"ZA",
    "gn:dem":1264,
    "gn:feature_class":"P",
    "gn:feature_code":"PPL",
    "gn:name":"Khabetlwane",
    "gn:population":0,
    "gn:timezone":"Africa/Johannesburg",
    "iso:country":"ZA",
    "wof:name":"Khabetlwane",
    "wof:placetype":"locality"
},
  "geometry": {"coordinates":[23.54372,-27.24815],"type":"Point"}
}