{
  "type": "Feature",
  "properties": {
    "gn:admin1_code":"6.0",
    "gn:admin2_code":"JHB",
    "gn:admin3_code":"JHB",
    "gn:asciiname":"Cresta",
    "gn:country_code":"ZA",
    "gn:dem":1582,
    "gn:feature_class":"P",
    "gn:feature_code":"PPL",
    "gn:name":"Cresta",
    "gn:population":0,
    "gn:timezone":"Africa/Johannesburg",
    "iso:country":"ZA",
    "name:arg_x_preferred":[
        "Cresta"
    ],
    "name:deu_x_preferred":[
        "Cresta"
    ],
    "name:epo_x_preferred":[
        "Cresta"
    ],
    "name:ita_x_preferred":[
        "Cresta"
    ],
    "name:jpn_x_preferred":[
        "\u30af\u30ec\u30b9\u30bf"
    ],
    "name:spa_x_preferred":[
        "Cresta"
    ],
    "wof:lang_x_official":[
        "eng"
    ],
    "wof:lang_x_spoken":[
        "eng",
        "zul",
        "xho",
        "afr",
        "nso",
        "tsn",
        "sot",
        "tso",
        "ssw",
        "ven",
        "nbl"
    ],
    "wof:name":"Cresta",
    "wof:placetype":"neighbourhood"
},
  "geometry": {"coordinates":[27.9796,-26.12701],"type":"Point"}
}