{
  "type": "Feature",
  "properties": {
    "gn:admin1_code":"5",
    "gn:admin2_code":"DC44",
    "gn:admin3_code":"EC444",
    "gn:asciiname":"Mtukukazi",
    "gn:country_code":"ZA",
    "gn:dem":1089,
    "gn:feature_class":"P",
    "gn:feature_code":"PPL",
    "gn:name":"Mtukukazi",
    "gn:population":0,
    "gn:timezone":"Africa/Johannesburg",
    "iso:country":"ZA",
    "name:und_x_variant":[
        "Mtukazi",
        "Mtukukazi"
    ],
    "wof:name":"Mtukukazi",
    "wof:placetype":"locality"
},
  "geometry": {"coordinates":[29.32203,-31.08448],"type":"Point"}
}