{
  "type": "Feature",
  "properties": {
    "gn:admin1_code":"5",
    "gn:admin2_code":"DC44",
    "gn:admin3_code":"EC444",
    "gn:asciiname":"Mngazana",
    "gn:country_code":"ZA",
    "gn:dem":927,
    "gn:feature_class":"P",
    "gn:feature_code":"PPL",
    "gn:name":"Mngazana",
    "gn:population":0,
    "gn:timezone":"Africa/Johannesburg",
    "iso:country":"ZA",
    "wof:name":"Mngazana",
    "wof:placetype":"locality"
},
  "geometry": {"coordinates":[29.17536,-30.90913],"type":"Point"}
}