{
  "type": "Feature",
  "properties": {
    "gn:admin1_code":"9",
    "gn:admin2_code":"DC33",
    "gn:admin3_code":"LIM333",
    "gn:asciiname":"Mamitwa's Location",
    "gn:country_code":"ZA",
    "gn:dem":542,
    "gn:feature_class":"P",
    "gn:feature_code":"PPLL",
    "gn:name":"Mamitwa\u2019s Location",
    "gn:population":0,
    "gn:timezone":"Africa/Johannesburg",
    "iso:country":"ZA",
    "name:und_x_variant":[
        "Nwamitwaslokasie",
        "Nwamitwalokasie",
        "Mamitwa\u2019s Location"
    ],
    "wof:name":"Mamitwa's Location",
    "wof:placetype":"locality"
},
  "geometry": {"coordinates":[30.38333,-23.73333],"type":"Point"}
}