{
  "type": "Feature",
  "properties": {
    "gn:admin1_code":"8",
    "gn:admin2_code":"DC7",
    "gn:admin3_code":"NC078",
    "gn:asciiname":"Limewell",
    "gn:country_code":"ZA",
    "gn:dem":1062,
    "gn:feature_class":"P",
    "gn:feature_code":"PPL",
    "gn:name":"Limewell",
    "gn:population":0,
    "gn:timezone":"Africa/Johannesburg",
    "iso:country":"ZA",
    "wof:name":"Limewell",
    "wof:placetype":"locality"
},
  "geometry": {"coordinates":[22.50614,-28.84073],"type":"Point"}
}