{
  "type": "Feature",
  "properties": {
    "gn:admin1_code":"8.0",
    "gn:admin2_code":"DC9",
    "gn:admin3_code":"NC092",
    "gn:asciiname":"Smith's Mine",
    "gn:country_code":"ZA",
    "gn:dem":1138,
    "gn:feature_class":"P",
    "gn:feature_code":"PPL",
    "gn:name":"Smith\u2019s Mine",
    "gn:population":0,
    "gn:timezone":"Africa/Johannesburg",
    "iso:country":"ZA",
    "wof:name":"Smith's Mine",
    "wof:placetype":"locality"
},
  "geometry": {"coordinates":[24.51667,-28.25],"type":"Point"}
}