{
  "type": "Feature",
  "properties": {
    "gn:admin1_code":"3",
    "gn:admin2_code":"DC16",
    "gn:admin3_code":"FS164",
    "gn:asciiname":"Bremiker",
    "gn:country_code":"ZA",
    "gn:dem":1489,
    "gn:feature_class":"P",
    "gn:feature_code":"PPL",
    "gn:name":"Bremiker",
    "gn:population":0,
    "gn:timezone":"Africa/Johannesburg",
    "iso:country":"ZA",
    "wof:name":"Bremiker",
    "wof:placetype":"locality"
},
  "geometry": {"coordinates":[26.96816,-30.04629000000001],"type":"Point"}
}