{
  "type": "Feature",
  "properties": {
    "gn:country":"ZA",
    "gn:fcode":"FRMT",
    "gn:population":5,
    "iso:country":"ZA",
    "qs_pg:aaroncc":"ZA",
    "qs_pg:gn_country":"ZA",
    "qs_pg:gn_fcode":"FRMT",
    "qs_pg:gn_pop":5,
    "qs_pg:name":"11 Myl Suid",
    "qs_pg:photos_9r":0,
    "qs_pg:photos_sr":0,
    "qs_pg:pop_sr":1,
    "qs_pg:qs_pg_placetype":"locality",
    "wof:name":"11 Myl Suid",
    "wof:placetype":"locality",
    "wof:population":5
},
  "geometry": {"coordinates":[17.92392,-29.83022],"type":"Point"}
}