{
  "type": "Feature",
  "properties": {
    "gn:admin1_code":"2.0",
    "gn:admin2_code":"DC22",
    "gn:admin3_code":"KZN226",
    "gn:asciiname":"Villa Maria",
    "gn:country_code":"ZA",
    "gn:dem":750,
    "gn:feature_class":"P",
    "gn:feature_code":"PPL",
    "gn:name":"Villa Maria",
    "gn:population":0,
    "gn:timezone":"Africa/Johannesburg",
    "iso:country":"ZA",
    "name:cat_x_preferred":[
        "Villa Maria"
    ],
    "name:deu_x_preferred":[
        "Villa Maria"
    ],
    "name:fra_x_preferred":[
        "Villa-Maria"
    ],
    "name:ita_x_preferred":[
        "Villa Maria"
    ],
    "name:nld_x_preferred":[
        "Villa Maria"
    ],
    "name:por_x_preferred":[
        "Villa Mar\u00eda"
    ],
    "name:spa_x_preferred":[
        "Villa Mar\u00eda"
    ],
    "name:srp_x_preferred":[
        "Vila Marija"
    ],
    "wof:lang_x_official":[
        "eng"
    ],
    "wof:lang_x_spoken":[
        "eng",
        "zul",
        "xho",
        "afr",
        "nso",
        "tsn",
        "sot",
        "tso",
        "ssw",
        "ven",
        "nbl"
    ],
    "wof:name":"Villa Maria",
    "wof:placetype":"locality"
},
  "geometry": {"coordinates":[30.57367,-29.57617],"type":"Point"}
}