{
  "type": "Feature",
  "properties": {
    "gn:admin1_code":"6",
    "gn:admin2_code":"DC42",
    "gn:admin3_code":"GT422",
    "gn:asciiname":"McKay",
    "gn:country_code":"ZA",
    "gn:dem":1441,
    "gn:feature_class":"P",
    "gn:feature_code":"PPL",
    "gn:name":"McKay",
    "gn:population":0,
    "gn:timezone":"Africa/Johannesburg",
    "iso:country":"ZA",
    "name:deu_x_preferred":[
        "McKay"
    ],
    "name:fin_x_preferred":[
        "McKay"
    ],
    "name:fra_x_preferred":[
        "McKay"
    ],
    "name:ita_x_preferred":[
        "McKay"
    ],
    "name:nld_x_preferred":[
        "McKay"
    ],
    "name:por_x_preferred":[
        "McKay"
    ],
    "name:ukr_x_preferred":[
        "\u041c\u0430\u043a\u043a\u0435\u0439"
    ],
    "wof:lang_x_official":[
        "eng"
    ],
    "wof:lang_x_spoken":[
        "eng",
        "zul",
        "xho",
        "afr",
        "nso",
        "tsn",
        "sot",
        "tso",
        "ssw",
        "ven",
        "nbl"
    ],
    "wof:name":"McKay",
    "wof:placetype":"locality"
},
  "geometry": {"coordinates":[27.96667,-26.63333],"type":"Point"}
}