{
  "type": "Feature",
  "properties": {
    "gn:admin1_code":"9",
    "gn:admin2_code":"DC36",
    "gn:admin3_code":"LIM362",
    "gn:asciiname":"Kokstad",
    "gn:country_code":"ZA",
    "gn:dem":844,
    "gn:feature_class":"P",
    "gn:feature_code":"PPL",
    "gn:name":"Kokstad",
    "gn:population":0,
    "gn:timezone":"Africa/Johannesburg",
    "iso:country":"ZA",
    "wof:name":"Kokstad",
    "wof:placetype":"locality"
},
  "geometry": {"coordinates":[27.98037,-23.17389],"type":"Point"}
}