{
  "type": "Feature",
  "properties": {
    "gn:admin1_code":"9",
    "gn:admin2_code":"DC36",
    "gn:admin3_code":"LIM362",
    "gn:asciiname":"Kokstad",
    "gn:country_code":"ZA",
    "gn:dem":844,
    "gn:feature_class":"P",
    "gn:feature_code":"PPL",
    "gn:name":"Kokstad",
    "gn:population":0,
    "gn:timezone":"Africa/Johannesburg",
    "iso:country":"ZA",
    "name:afr_x_preferred":[
        "Kokstad"
    ],
    "name:cat_x_preferred":[
        "Kokstad"
    ],
    "name:ceb_x_preferred":[
        "Kokstad"
    ],
    "name:deu_x_preferred":[
        "Kokstad"
    ],
    "name:est_x_preferred":[
        "Kokstad"
    ],
    "name:fra_x_preferred":[
        "Kokstad"
    ],
    "name:ita_x_preferred":[
        "Kokstad"
    ],
    "name:mlg_x_preferred":[
        "Kokstad"
    ],
    "name:nld_x_preferred":[
        "Kokstad"
    ],
    "name:nso_x_preferred":[
        "Kokstad"
    ],
    "name:pol_x_preferred":[
        "Kokstad"
    ],
    "name:ron_x_preferred":[
        "Kokstad"
    ],
    "name:rus_x_preferred":[
        "\u041a\u043e\u043a\u0441\u0442\u0430\u0434"
    ],
    "name:zho_x_preferred":[
        "\u79d1\u514b\u65af\u5854\u5fb7"
    ],
    "wof:lang_x_official":[
        "eng"
    ],
    "wof:lang_x_spoken":[
        "eng",
        "zul",
        "xho",
        "afr",
        "nso",
        "tsn",
        "sot",
        "tso",
        "ssw",
        "ven",
        "nbl"
    ],
    "wof:name":"Kokstad",
    "wof:placetype":"locality"
},
  "geometry": {"coordinates":[27.98037,-23.17389],"type":"Point"}
}