{
  "type": "Feature",
  "properties": {
    "gn:admin1_code":"5",
    "gn:admin2_code":"DC15",
    "gn:admin3_code":"EC156",
    "gn:asciiname":"Maswabantwana",
    "gn:country_code":"ZA",
    "gn:dem":1067,
    "gn:feature_class":"P",
    "gn:feature_code":"PPL",
    "gn:name":"Maswabantwana",
    "gn:population":0,
    "gn:timezone":"Africa/Johannesburg",
    "iso:country":"ZA",
    "wof:name":"Maswabantwana",
    "wof:placetype":"locality"
},
  "geometry": {"coordinates":[29.06071,-31.03873],"type":"Point"}
}