{
  "type": "Feature",
  "properties": {
    "gn:admin1_code":"9",
    "gn:admin2_code":"DC35",
    "gn:admin3_code":"LIM354",
    "gn:asciiname":"Moria",
    "gn:country_code":"ZA",
    "gn:dem":1263,
    "gn:feature_class":"P",
    "gn:feature_code":"PPL",
    "gn:name":"Moria",
    "gn:population":0,
    "gn:timezone":"Africa/Johannesburg",
    "iso:country":"ZA",
    "wof:name":"Moria",
    "wof:placetype":"locality"
},
  "geometry": {"coordinates":[29.78263,-23.95262],"type":"Point"}
}