{
  "type": "Feature",
  "properties": {
    "gn:admin1_code":"2.0",
    "gn:admin2_code":"DC29",
    "gn:admin3_code":"KZN293",
    "gn:asciiname":"Sanikidge",
    "gn:country_code":"ZA",
    "gn:dem":346,
    "gn:feature_class":"P",
    "gn:feature_code":"PPL",
    "gn:name":"Sanikidge",
    "gn:population":0,
    "gn:timezone":"Africa/Johannesburg",
    "iso:country":"ZA",
    "wof:name":"Sanikidge",
    "wof:placetype":"locality"
},
  "geometry": {"coordinates":[31.13333,-29.36667000000001],"type":"Point"}
}