{
  "type": "Feature",
  "properties": {
    "gn:admin1_code":"5",
    "gn:admin2_code":"DC44",
    "gn:admin3_code":"EC441",
    "gn:asciiname":"Mhlangeni",
    "gn:country_code":"ZA",
    "gn:dem":1744,
    "gn:feature_class":"P",
    "gn:feature_code":"PPL",
    "gn:name":"Mhlangeni",
    "gn:population":0,
    "gn:timezone":"Africa/Johannesburg",
    "iso:country":"ZA",
    "name:afr_x_preferred":[
        "Mhlangeni"
    ],
    "name:nso_x_preferred":[
        "Mhlangeni"
    ],
    "wof:name":"Mhlangeni",
    "wof:placetype":"locality"
},
  "geometry": {"coordinates":[29.00308,-30.13412000000001],"type":"Point"}
}