{
  "type": "Feature",
  "properties": {
    "gn:admin1_code":"8.0",
    "gn:admin2_code":"DC6",
    "gn:admin3_code":"NC065",
    "gn:asciiname":"Vendors Puts",
    "gn:cc2":"ZA",
    "gn:country_code":"ZA",
    "gn:dem":892,
    "gn:feature_class":"P",
    "gn:feature_code":"PPL",
    "gn:name":"Vendors Puts",
    "gn:population":0,
    "gn:timezone":"Africa/Johannesburg",
    "iso:country":"ZA",
    "name:und_x_variant":[
        "Verdors Puts",
        "Vendors Puts"
    ],
    "wof:lang_x_official":[
        "eng"
    ],
    "wof:lang_x_spoken":[
        "eng",
        "zul",
        "xho",
        "afr",
        "nso",
        "tsn",
        "sot",
        "tso",
        "ssw",
        "ven",
        "nbl"
    ],
    "wof:name":"Vendors Puts",
    "wof:placetype":"locality"
},
  "geometry": {"coordinates":[20.43333,-30.05],"type":"Point"}
}