{
  "type": "Feature",
  "properties": {
    "gn:country":"ZA",
    "gn:fcode":"PPLA3",
    "gn:population":13674,
    "iso:country":"ZA",
    "name:afr_x_preferred":[
        "Swellendam"
    ],
    "name:ben_x_preferred":[
        "\u09b8\u09cb\u09df\u09c7\u09b2\u09cd\u09b2\u09c7\u09a8\u09cd\u09a6\u09be\u09ae"
    ],
    "name:bul_x_preferred":[
        "\u0428\u0432\u0435\u043b\u0435\u043d\u0434\u0430\u043c"
    ],
    "name:cat_x_preferred":[
        "Swellendam"
    ],
    "name:dan_x_preferred":[
        "Swellendam"
    ],
    "name:deu_x_preferred":[
        "Swellendam"
    ],
    "name:ell_x_preferred":[
        "\u03a3\u03b2\u03ad\u03bb\u03bb\u03b5\u03bd\u03c4\u03b1\u03bc"
    ],
    "name:est_x_preferred":[
        "Swellendam"
    ],
    "name:fas_x_preferred":[
        "\u0633\u0648\u0644\u0646\u062f\u0627\u0645"
    ],
    "name:fra_x_preferred":[
        "Swellendam"
    ],
    "name:hak_x_preferred":[
        "Swellendam"
    ],
    "name:hin_x_preferred":[
        "\u0938\u094d\u0935\u0947\u0932\u0947\u0928\u0921\u0948\u092e"
    ],
    "name:hun_x_preferred":[
        "Swellendam"
    ],
    "name:ind_x_preferred":[
        "Swellendam"
    ],
    "name:ita_x_preferred":[
        "Swellendam"
    ],
    "name:kor_x_preferred":[
        "\uc2a4\uc6f0\ub80c\ub2f4"
    ],
    "name:nld_x_preferred":[
        "Swellendam"
    ],
    "name:nor_x_preferred":[
        "Swellendam"
    ],
    "name:nso_x_preferred":[
        "Swellendam"
    ],
    "name:pol_x_preferred":[
        "Swellendam"
    ],
    "name:por_x_preferred":[
        "Swellendam"
    ],
    "name:ron_x_preferred":[
        "Swellendam"
    ],
    "name:rus_x_preferred":[
        "\u0421\u0432\u0435\u043b\u043b\u0435\u043d\u0434\u0430\u043c"
    ],
    "name:spa_x_preferred":[
        "Swellendam"
    ],
    "name:swa_x_preferred":[
        "Swellendam"
    ],
    "name:swe_x_preferred":[
        "Republiken Swellendam"
    ],
    "name:tur_x_preferred":[
        "Swellendam"
    ],
    "name:ukr_x_preferred":[
        "\u0421\u0432\u0435\u043b\u043b\u0435\u043d\u0434\u0430\u043c"
    ],
    "name:urd_x_preferred":[
        "\u0633\u0648\u06cc\u0644\u06cc\u0646\u062f\u0627\u0645"
    ],
    "name:vie_x_preferred":[
        "Swellendam"
    ],
    "name:zho_x_preferred":[
        "\u65af\u97cb\u502b\u4e39"
    ],
    "qs_pg:aaroncc":"ZA",
    "qs_pg:gn_country":"ZA",
    "qs_pg:gn_fcode":"PPLA3",
    "qs_pg:gn_pop":13674,
    "qs_pg:name":"Swellendam",
    "qs_pg:name_adm0":"South Africa",
    "qs_pg:name_adm1":"Western Cape",
    "qs_pg:photos_9k":5,
    "qs_pg:photos_9r":7,
    "qs_pg:photos_all":1086,
    "qs_pg:photos_sr":0,
    "qs_pg:pop_sr":6,
    "qs_pg:qs_pg_placetype":"localadmin",
    "qs_pg:qs_pg_placetype_gp":"LocalAdmin",
    "qs_pg:woe_adm0":23424942,
    "woe:adm0_id":23424942,
    "woe:name_adm0":"South Africa",
    "woe:name_adm1":"Western Cape",
    "woe:placetype":"LocalAdmin",
    "wof:lang_x_official":[
        "eng"
    ],
    "wof:lang_x_spoken":[
        "eng",
        "zul",
        "xho",
        "afr",
        "nso",
        "tsn",
        "sot",
        "tso",
        "ssw",
        "ven",
        "nbl"
    ],
    "wof:name":"Swellendam",
    "wof:placetype":"localadmin",
    "wof:population":13674
},
  "geometry": {"coordinates":[20.44171,-34.02262],"type":"Point"}
}