{
  "type": "Feature",
  "properties": {
    "gn:gn_country":"ZA",
    "gn:gn_fcode":"PPLA3",
    "gn:gn_pop":13674,
    "gn:population":13674,
    "iso:country":"ZA",
    "name:bul_x_preferred":[
        "\u0428\u0432\u0435\u043b\u0435\u043d\u0434\u0430\u043c"
    ],
    "name:rus_x_preferred":[
        "\u0421\u0432\u0435\u043b\u043b\u0435\u043d\u0434\u0430\u043c"
    ],
    "name:swe_x_preferred":[
        "Republiken Swellendam"
    ],
    "name:zho_x_preferred":[
        "\u65af\u97cb\u502b\u4e39"
    ],
    "qs_pg:aaroncc":"ZA",
    "qs_pg:gn_country":"ZA",
    "qs_pg:gn_fcode":"PPLA3",
    "qs_pg:gn_pop":13674,
    "qs_pg:name":"Swellendam",
    "qs_pg:name_adm0":"South Africa",
    "qs_pg:name_adm1":"Western Cape",
    "qs_pg:photos_9k":5,
    "qs_pg:photos_9r":7,
    "qs_pg:photos_all":1086,
    "qs_pg:photos_sr":0,
    "qs_pg:pop_sr":6,
    "qs_pg:qs_pg_placetype":"localadmin",
    "qs_pg:qs_pg_placetype_gp":"LocalAdmin",
    "qs_pg:woe_adm0":23424942,
    "woe:adm0_id":23424942,
    "woe:name_adm0":"South Africa",
    "woe:name_adm1":"Western Cape",
    "woe:placetype":"LocalAdmin",
    "wof:name":"Swellendam",
    "wof:placetype":"localadmin",
    "wof:population":13674
},
  "geometry": {"coordinates":[20.44171,-34.02262],"type":"Point"}
}