{
  "type": "Feature",
  "properties": {
    "gn:admin1_code":"9",
    "gn:admin2_code":"DC35",
    "gn:admin3_code":"LIM354",
    "gn:asciiname":"Ga-Molepo",
    "gn:country_code":"ZA",
    "gn:dem":1374,
    "gn:feature_class":"P",
    "gn:feature_code":"PPL",
    "gn:name":"Ga-Molepo",
    "gn:population":0,
    "gn:timezone":"Africa/Johannesburg",
    "iso:country":"ZA",
    "name:afr_x_preferred":[
        "Ga-Molepo"
    ],
    "name:nso_x_preferred":[
        "Ga-Molepo"
    ],
    "wof:name":"Ga-Molepo",
    "wof:placetype":"locality"
},
  "geometry": {"coordinates":[29.67787,-23.9771],"type":"Point"}
}