{
  "type": "Feature",
  "properties": {
    "gn:admin1_code":"6",
    "gn:admin2_code":"DC42",
    "gn:admin3_code":"GT422",
    "gn:asciiname":"Ophir",
    "gn:country_code":"ZA",
    "gn:dem":1526,
    "gn:feature_class":"P",
    "gn:feature_code":"PPL",
    "gn:name":"Ophir",
    "gn:population":0,
    "gn:timezone":"Africa/Johannesburg",
    "iso:country":"ZA",
    "name:amh_x_preferred":[
        "\u12a6\u134a\u122d"
    ],
    "name:bul_x_preferred":[
        "\u041e\u0444\u0438\u0440"
    ],
    "name:cat_x_preferred":[
        "Ofir"
    ],
    "name:deu_x_preferred":[
        "Ophir"
    ],
    "name:fra_x_preferred":[
        "Ophir"
    ],
    "name:heb_x_preferred":[
        "\u05d0\u05d5\u05e4\u05d9\u05e8"
    ],
    "name:hun_x_preferred":[
        "Of\u00edr"
    ],
    "name:ind_x_preferred":[
        "Ofir"
    ],
    "name:ita_x_preferred":[
        "Ofir"
    ],
    "name:lat_x_preferred":[
        "Ophir"
    ],
    "name:mlg_x_preferred":[
        "Ofira"
    ],
    "name:nld_x_preferred":[
        "Ofir"
    ],
    "name:pol_x_preferred":[
        "Ofir"
    ],
    "name:por_x_preferred":[
        "Ofir"
    ],
    "name:rus_x_preferred":[
        "\u041e\u0444\u0438\u0440"
    ],
    "name:spa_x_preferred":[
        "Ofir"
    ],
    "name:swe_x_preferred":[
        "Ofir"
    ],
    "name:ukr_x_preferred":[
        "\u041e\u0444\u0456\u0440"
    ],
    "wof:lang_x_official":[
        "eng"
    ],
    "wof:lang_x_spoken":[
        "eng",
        "zul",
        "xho",
        "afr",
        "nso",
        "tsn",
        "sot",
        "tso",
        "ssw",
        "ven",
        "nbl"
    ],
    "wof:name":"Ophir",
    "wof:placetype":"locality"
},
  "geometry": {"coordinates":[27.98163,-26.5392],"type":"Point"}
}