{
  "type": "Feature",
  "properties": {
    "gn:admin1_code":"9",
    "gn:admin2_code":"DC33",
    "gn:admin3_code":"LIM335",
    "gn:asciiname":"Finale",
    "gn:country_code":"ZA",
    "gn:dem":487,
    "gn:feature_class":"P",
    "gn:feature_code":"PPL",
    "gn:name":"Finale",
    "gn:population":0,
    "gn:timezone":"Africa/Johannesburg",
    "iso:country":"ZA",
    "name:ceb_x_preferred":[
        "Finale"
    ],
    "name:ces_x_preferred":[
        "Fin\u00e1le"
    ],
    "name:dan_x_preferred":[
        "Finale"
    ],
    "name:deu_x_preferred":[
        "Finale"
    ],
    "name:est_x_preferred":[
        "Finale"
    ],
    "name:fin_x_preferred":[
        "Finaali"
    ],
    "name:fra_x_preferred":[
        "Finale"
    ],
    "name:ita_x_preferred":[
        "Finale"
    ],
    "name:jpn_x_preferred":[
        "\u30d5\u30a3\u30ca\u30fc\u30ec"
    ],
    "name:kor_x_preferred":[
        "\ud53c\ub0a0\ub808"
    ],
    "name:nld_x_preferred":[
        "Finale"
    ],
    "name:srp_x_preferred":[
        "Finale"
    ],
    "name:swe_x_preferred":[
        "Finale"
    ],
    "wof:lang_x_official":[
        "eng"
    ],
    "wof:lang_x_spoken":[
        "eng",
        "zul",
        "xho",
        "afr",
        "nso",
        "tsn",
        "sot",
        "tso",
        "ssw",
        "ven",
        "nbl"
    ],
    "wof:name":"Finale",
    "wof:placetype":"locality"
},
  "geometry": {"coordinates":[30.70528,-24.33059],"type":"Point"}
}