{
  "type": "Feature",
  "properties": {
    "gn:admin1_code":"5",
    "gn:admin2_code":"DC12",
    "gn:admin3_code":"EC124",
    "gn:asciiname":"Mnyameni",
    "gn:country_code":"ZA",
    "gn:dem":896,
    "gn:feature_class":"P",
    "gn:feature_code":"PPL",
    "gn:name":"Mnyameni",
    "gn:population":0,
    "gn:timezone":"Africa/Johannesburg",
    "iso:country":"ZA",
    "name:afr_x_preferred":[
        "Mnyameni"
    ],
    "name:nso_x_preferred":[
        "Mnyameni"
    ],
    "name:und_x_variant":[
        "Nyameni"
    ],
    "wof:lang_x_official":[
        "eng"
    ],
    "wof:lang_x_spoken":[
        "eng",
        "zul",
        "xho",
        "afr",
        "nso",
        "tsn",
        "sot",
        "tso",
        "ssw",
        "ven",
        "nbl"
    ],
    "wof:name":"Mnyameni",
    "wof:placetype":"locality"
},
  "geometry": {"coordinates":[27.07321,-32.61568],"type":"Point"}
}