{
  "type": "Feature",
  "properties": {
    "gn:admin1_code":"5",
    "gn:admin2_code":"DC13",
    "gn:admin3_code":"EC133",
    "gn:asciiname":"Carnarvon",
    "gn:country_code":"ZA",
    "gn:dem":1554,
    "gn:feature_class":"P",
    "gn:feature_code":"PPL",
    "gn:name":"Carnarvon",
    "gn:population":0,
    "gn:timezone":"Africa/Johannesburg",
    "iso:country":"ZA",
    "name:ceb_x_preferred":[
        "Carnarvon"
    ],
    "name:ces_x_preferred":[
        "Carnarvon"
    ],
    "name:cym_x_preferred":[
        "Caernarfon"
    ],
    "name:deu_x_preferred":[
        "Carnarvon"
    ],
    "name:fra_x_preferred":[
        "Carnarvon"
    ],
    "name:ind_x_preferred":[
        "Caernarvon"
    ],
    "name:ita_x_preferred":[
        "Caernarvon"
    ],
    "name:jav_x_preferred":[
        "Caernarvon"
    ],
    "name:mlg_x_preferred":[
        "Carnarvon"
    ],
    "name:nld_x_preferred":[
        "Carnarvon"
    ],
    "name:pol_x_preferred":[
        "Caernarvon"
    ],
    "name:swe_x_preferred":[
        "Carnarvon"
    ],
    "name:ukr_x_preferred":[
        "\u041a\u0430\u0440\u043d\u0430\u0440\u0432\u043e\u043d"
    ],
    "name:ukr_x_variant":[
        "\u041a\u0435\u0440\u043d\u0430\u0440\u0432\u043e\u043d"
    ],
    "name:urd_x_preferred":[
        "\u06a9\u06cc\u0631\u0646\u0627\u0631\u0648\u0646"
    ],
    "name:vie_x_preferred":[
        "Carnarvon"
    ],
    "wof:lang_x_official":[
        "eng"
    ],
    "wof:lang_x_spoken":[
        "eng",
        "zul",
        "xho",
        "afr",
        "nso",
        "tsn",
        "sot",
        "tso",
        "ssw",
        "ven",
        "nbl"
    ],
    "wof:name":"Carnarvon",
    "wof:placetype":"locality"
},
  "geometry": {"coordinates":[26.73707,-31.58571],"type":"Point"}
}