{
  "type": "Feature",
  "properties": {
    "gn:admin1_code":"7",
    "gn:admin2_code":"DC30",
    "gn:admin3_code":"MP302",
    "gn:asciiname":"Lothair",
    "gn:country_code":"ZA",
    "gn:dem":1721,
    "gn:feature_class":"P",
    "gn:feature_code":"PPL",
    "gn:name":"Lothair",
    "gn:population":0,
    "gn:timezone":"Africa/Johannesburg",
    "iso:country":"ZA",
    "name:afr_x_preferred":[
        "Lothair"
    ],
    "name:deu_x_preferred":[
        "Lothair"
    ],
    "name:nld_x_preferred":[
        "Lothair"
    ],
    "name:nso_x_preferred":[
        "Lothair"
    ],
    "name:ron_x_preferred":[
        "Lothair"
    ],
    "wof:name":"Lothair",
    "wof:placetype":"locality"
},
  "geometry": {"coordinates":[30.43526,-26.38939],"type":"Point"}
}