{
  "type": "Feature",
  "properties": {
    "gn:admin1_code":"2.0",
    "gn:admin2_code":"DC43",
    "gn:admin3_code":"KZN431",
    "gn:asciiname":"Winters",
    "gn:country_code":"ZA",
    "gn:dem":1008,
    "gn:feature_class":"P",
    "gn:feature_code":"PPL",
    "gn:name":"Winters",
    "gn:population":0,
    "gn:timezone":"Africa/Johannesburg",
    "iso:country":"ZA",
    "name:ceb_x_preferred":[
        "Winters"
    ],
    "name:deu_x_preferred":[
        "Winters"
    ],
    "name:fra_x_preferred":[
        "Winters"
    ],
    "name:heb_x_preferred":[
        "\u05d5\u05d9\u05e0\u05d8\u05e8\u05e1"
    ],
    "name:ita_x_preferred":[
        "Winters"
    ],
    "name:jpn_x_preferred":[
        "\u30a6\u30a3\u30f3\u30bf\u30fc\u30b9"
    ],
    "name:nds_x_preferred":[
        "Winters"
    ],
    "name:nld_x_preferred":[
        "Winters"
    ],
    "name:pol_x_preferred":[
        "Winters"
    ],
    "name:por_x_preferred":[
        "Winters"
    ],
    "name:rus_x_preferred":[
        "\u0423\u0438\u043d\u0442\u0435\u0440\u0441"
    ],
    "name:srp_x_preferred":[
        "\u0412\u0438\u043d\u0442\u0435\u0440\u0441"
    ],
    "name:ukr_x_preferred":[
        "\u0412\u0456\u043d\u0442\u0435\u0440\u0441"
    ],
    "name:vol_x_preferred":[
        "Winters"
    ],
    "wof:name":"Winters",
    "wof:placetype":"locality"
},
  "geometry": {"coordinates":[29.96667,-29.85],"type":"Point"}
}