{
  "type": "Feature",
  "properties": {
    "gn:admin1_code":"2.0",
    "gn:admin2_code":"DC43",
    "gn:admin3_code":"KZN431",
    "gn:asciiname":"Winters",
    "gn:country_code":"ZA",
    "gn:dem":1008,
    "gn:feature_class":"P",
    "gn:feature_code":"PPL",
    "gn:name":"Winters",
    "gn:population":0,
    "gn:timezone":"Africa/Johannesburg",
    "iso:country":"ZA",
    "wof:name":"Winters",
    "wof:placetype":"locality"
},
  "geometry": {"coordinates":[29.96667,-29.85],"type":"Point"}
}