{
  "type": "Feature",
  "properties": {
    "gn:admin1_code":"5.0",
    "gn:admin2_code":"DC13",
    "gn:admin3_code":"EC133",
    "gn:asciiname":"Vrede",
    "gn:country_code":"ZA",
    "gn:dem":1717,
    "gn:feature_class":"P",
    "gn:feature_code":"PPL",
    "gn:name":"Vrede",
    "gn:population":0,
    "gn:timezone":"Africa/Johannesburg",
    "iso:country":"ZA",
    "name:afr_x_preferred":[
        "Vrede"
    ],
    "name:bar_x_preferred":[
        "Vrede"
    ],
    "name:ceb_x_preferred":[
        "Vrede"
    ],
    "name:deu_x_preferred":[
        "Vrede"
    ],
    "name:est_x_preferred":[
        "Vrede"
    ],
    "name:fra_x_preferred":[
        "Vrede"
    ],
    "name:ita_x_preferred":[
        "Vrede"
    ],
    "name:nld_x_preferred":[
        "Vrede"
    ],
    "name:nso_x_preferred":[
        "Vrede"
    ],
    "name:pol_x_preferred":[
        "Vrede"
    ],
    "name:ron_x_preferred":[
        "Vrede"
    ],
    "name:swe_x_preferred":[
        "Vrede"
    ],
    "name:zho_x_preferred":[
        "\u5f17\u96f7\u5fb7"
    ],
    "wof:name":"Vrede",
    "wof:placetype":"locality"
},
  "geometry": {"coordinates":[26.42847,-31.50335],"type":"Point"}
}