{
  "type": "Feature",
  "properties": {
    "gn:admin1_code":"7.0",
    "gn:admin2_code":"DC31",
    "gn:admin3_code":"MP314",
    "gn:asciiname":"Torburnlea",
    "gn:country_code":"ZA",
    "gn:dem":1841,
    "gn:feature_class":"P",
    "gn:feature_code":"PPL",
    "gn:name":"Torburnlea",
    "gn:population":0,
    "gn:timezone":"Africa/Johannesburg",
    "iso:country":"ZA",
    "wof:name":"Torburnlea",
    "wof:placetype":"locality"
},
  "geometry": {"coordinates":[30.34799000000001,-25.72592],"type":"Point"}
}