{
  "type": "Feature",
  "properties": {
    "gn:admin1_code":"5.0",
    "gn:admin2_code":"DC14",
    "gn:admin3_code":"EC142",
    "gn:asciiname":"Telle Falls",
    "gn:country_code":"ZA",
    "gn:dem":1917,
    "gn:feature_class":"P",
    "gn:feature_code":"PPL",
    "gn:name":"Telle Falls",
    "gn:population":0,
    "gn:timezone":"Africa/Johannesburg",
    "iso:country":"ZA",
    "wof:name":"Telle Falls",
    "wof:placetype":"locality"
},
  "geometry": {"coordinates":[27.82932000000001,-30.62815],"type":"Point"}
}