{
  "type": "Feature",
  "properties": {
    "gn:admin1_code":"9.0",
    "gn:admin2_code":"DC34",
    "gn:admin3_code":"LIM344",
    "gn:asciiname":"Uitsig",
    "gn:country_code":"ZA",
    "gn:dem":944,
    "gn:feature_class":"P",
    "gn:feature_code":"PPL",
    "gn:name":"Uitsig",
    "gn:population":0,
    "gn:timezone":"Africa/Johannesburg",
    "iso:country":"ZA",
    "wof:name":"Uitsig",
    "wof:placetype":"locality"
},
  "geometry": {"coordinates":[29.8839,-23.13485],"type":"Point"}
}