{
  "type": "Feature",
  "properties": {
    "gn:admin1_code":"9",
    "gn:admin2_code":"DC35",
    "gn:admin3_code":"LIM355",
    "gn:asciiname":"Mphahlele 2",
    "gn:country_code":"ZA",
    "gn:dem":904,
    "gn:feature_class":"P",
    "gn:feature_code":"PPL",
    "gn:name":"Mphahlele 2",
    "gn:population":0,
    "gn:timezone":"Africa/Johannesburg",
    "iso:country":"ZA",
    "name:und_x_variant":[
        "Ga-Mphahlele"
    ],
    "wof:name":"Mphahlele 2",
    "wof:placetype":"locality"
},
  "geometry": {"coordinates":[29.62202000000001,-24.30971],"type":"Point"}
}