{
  "type": "Feature",
  "properties": {
    "gn:gn_country":"ZA",
    "gn:gn_fcode":"PPLX",
    "gn:gn_pop":0,
    "iso:country":"ZA",
    "name:cat_x_preferred":[
        "Norwood"
    ],
    "name:ceb_x_preferred":[
        "Norwood"
    ],
    "name:ces_x_preferred":[
        "Norwood"
    ],
    "name:deu_x_preferred":[
        "Norwood"
    ],
    "name:fas_x_preferred":[
        "\u0646\u0648\u0631\u0648\u0648\u062f"
    ],
    "name:fra_x_preferred":[
        "Norwood"
    ],
    "name:ita_x_preferred":[
        "Norwood"
    ],
    "name:nld_x_preferred":[
        "Norwood"
    ],
    "name:pol_x_preferred":[
        "Norwood"
    ],
    "name:por_x_preferred":[
        "Norwood"
    ],
    "name:rus_x_preferred":[
        "\u041d\u043e\u0440\u0432\u0443\u0434"
    ],
    "name:srp_x_preferred":[
        "\u041d\u043e\u0440\u0432\u0443\u0434"
    ],
    "name:swa_x_preferred":[
        "Norwood"
    ],
    "name:swe_x_preferred":[
        "Norwood"
    ],
    "qs_pg:aaroncc":"ZA",
    "qs_pg:gn_country":"ZA",
    "qs_pg:gn_fcode":"PPLX",
    "qs_pg:gn_pop":0,
    "qs_pg:name":"Norwood",
    "qs_pg:name_adm0":"South Africa",
    "qs_pg:name_adm1":"Western Cape",
    "qs_pg:photos_9r":0,
    "qs_pg:photos_sr":0,
    "qs_pg:pop_sr":0,
    "qs_pg:qs_pg_placetype":"neighbourhood",
    "qs_pg:qs_pg_placetype_gp":"Suburb",
    "qs_pg:woe_adm0":23424942,
    "woe:adm0_id":23424942,
    "woe:name_adm0":"South Africa",
    "woe:name_adm1":"Western Cape",
    "woe:placetype":"Suburb",
    "wof:name":"Norwood",
    "wof:placetype":"neighbourhood"
},
  "geometry": {"coordinates":[18.57808,-33.92644],"type":"Point"}
}