{
  "type": "Feature",
  "properties": {
    "gn:admin1_code":"9.0",
    "gn:admin2_code":"DC34",
    "gn:admin3_code":"LIM343",
    "gn:asciiname":"Vhutandabos",
    "gn:country_code":"ZA",
    "gn:dem":914,
    "gn:feature_class":"P",
    "gn:feature_code":"PPL",
    "gn:name":"Vhutandabos",
    "gn:population":0,
    "gn:timezone":"Africa/Johannesburg",
    "iso:country":"ZA",
    "wof:name":"Vhutandabos",
    "wof:placetype":"locality"
},
  "geometry": {"coordinates":[30.33333,-22.93333],"type":"Point"}
}