{
  "type": "Feature",
  "properties": {
    "gn:country":"ZA",
    "gn:fcode":"ADM3",
    "gn:population":60475,
    "iso:country":"ZA",
    "qs_pg:aaroncc":"ZA",
    "qs_pg:gn_country":"ZA",
    "qs_pg:gn_fcode":"ADM3",
    "qs_pg:gn_pop":60475,
    "qs_pg:name":"Umjindi",
    "qs_pg:name_adm0":"South Africa",
    "qs_pg:name_adm1":"Mpumalanga",
    "qs_pg:photos_9k":1,
    "qs_pg:photos_9r":2,
    "qs_pg:photos_all":53,
    "qs_pg:photos_sr":0,
    "qs_pg:pop_sr":8,
    "qs_pg:qs_pg_placetype":"localadmin",
    "qs_pg:qs_pg_placetype_gp":"LocalAdmin",
    "qs_pg:woe_adm0":23424942,
    "woe:adm0_id":23424942,
    "woe:name_adm0":"South Africa",
    "woe:name_adm1":"Mpumalanga",
    "woe:placetype":"LocalAdmin",
    "wof:lang_x_official":[
        "eng"
    ],
    "wof:lang_x_spoken":[
        "eng",
        "zul",
        "xho",
        "afr",
        "nso",
        "tsn",
        "sot",
        "tso",
        "ssw",
        "ven",
        "nbl"
    ],
    "wof:name":"Umjindi",
    "wof:placetype":"localadmin",
    "wof:population":60475
},
  "geometry": {"coordinates":[31.00102,-25.74873],"type":"Point"}
}