{
  "type": "Feature",
  "properties": {
    "gn:admin1_code":"11.0",
    "gn:admin2_code":"CPT",
    "gn:admin3_code":"CPT",
    "gn:asciiname":"Sir Lowry's Pass",
    "gn:country_code":"ZA",
    "gn:dem":93,
    "gn:feature_class":"P",
    "gn:feature_code":"PPL",
    "gn:name":"Sir Lowry's Pass",
    "gn:population":0,
    "gn:timezone":"Africa/Johannesburg",
    "iso:country":"ZA",
    "name:afr_x_preferred":[
        "Sir Lowryspas"
    ],
    "name:ceb_x_preferred":[
        "Sir Lowry's Pass"
    ],
    "name:ron_x_preferred":[
        "Sir Lowry's Pass"
    ],
    "wof:lang_x_official":[
        "eng"
    ],
    "wof:lang_x_spoken":[
        "eng",
        "zul",
        "xho",
        "afr",
        "nso",
        "tsn",
        "sot",
        "tso",
        "ssw",
        "ven",
        "nbl"
    ],
    "wof:name":"Sir Lowry's Pass",
    "wof:placetype":"neighbourhood"
},
  "geometry": {"coordinates":[18.90996,-34.12054],"type":"Point"}
}