{
  "type": "Feature",
  "properties": {
    "gn:admin1_code":"11.0",
    "gn:admin2_code":"DC4",
    "gn:admin3_code":"WC042",
    "gn:asciiname":"Vermaaklikheid",
    "gn:country_code":"ZA",
    "gn:dem":33,
    "gn:feature_class":"P",
    "gn:feature_code":"PPL",
    "gn:name":"Vermaaklikheid",
    "gn:population":0,
    "gn:timezone":"Africa/Johannesburg",
    "iso:country":"ZA",
    "name:afr_x_preferred":[
        "Vermaaklikheid"
    ],
    "name:fas_x_preferred":[
        "\u0648\u0631\u0645\u0627\u06a9\u0644\u06cc\u062e\u06cc\u062f"
    ],
    "wof:name":"Vermaaklikheid",
    "wof:placetype":"locality"
},
  "geometry": {"coordinates":[21.02969,-34.31172],"type":"Point"}
}