{
  "type": "Feature",
  "properties": {
    "gn:admin1_code":"3",
    "gn:admin2_code":"DC20",
    "gn:admin3_code":"FS205",
    "gn:asciiname":"Belmont",
    "gn:country_code":"ZA",
    "gn:dem":1562,
    "gn:feature_class":"P",
    "gn:feature_code":"PPL",
    "gn:name":"Belmont",
    "gn:population":0,
    "gn:timezone":"Africa/Johannesburg",
    "iso:country":"ZA",
    "wof:name":"Belmont",
    "wof:placetype":"locality"
},
  "geometry": {"coordinates":[28.73956,-27.46378],"type":"Point"}
}