{
  "type": "Feature",
  "properties": {
    "gn:admin1_code":"2",
    "gn:admin2_code":"DC21",
    "gn:admin3_code":"KZN216",
    "gn:asciiname":"KwaNonhlanga",
    "gn:country_code":"ZA",
    "gn:dem":559,
    "gn:feature_class":"P",
    "gn:feature_code":"PPL",
    "gn:name":"KwaNonhlanga",
    "gn:population":0,
    "gn:timezone":"Africa/Johannesburg",
    "iso:country":"ZA",
    "wof:name":"KwaNonhlanga",
    "wof:placetype":"locality"
},
  "geometry": {"coordinates":[30.15294,-30.81175],"type":"Point"}
}