{
  "type": "Feature",
  "properties": {
    "gn:admin1_code":"3",
    "gn:admin2_code":"DC16",
    "gn:admin3_code":"FS163",
    "gn:asciiname":"Moreson",
    "gn:country_code":"ZA",
    "gn:dem":1474,
    "gn:feature_class":"P",
    "gn:feature_code":"PPL",
    "gn:name":"M\u00f4reson",
    "gn:population":0,
    "gn:timezone":"Africa/Johannesburg",
    "iso:country":"ZA",
    "wof:name":"Moreson",
    "wof:placetype":"locality"
},
  "geometry": {"coordinates":[26.62416,-30.10638],"type":"Point"}
}