{
  "type": "Feature",
  "properties": {
    "gn:admin1_code":"5",
    "gn:admin2_code":"DC15",
    "gn:admin3_code":"EC153",
    "gn:asciiname":"Mgume",
    "gn:country_code":"ZA",
    "gn:dem":623,
    "gn:feature_class":"P",
    "gn:feature_code":"PPL",
    "gn:name":"Mgume",
    "gn:population":0,
    "gn:timezone":"Africa/Johannesburg",
    "iso:country":"ZA",
    "name:und_x_variant":[
        "Mqume",
        "Mgume"
    ],
    "wof:name":"Mgume",
    "wof:placetype":"locality"
},
  "geometry": {"coordinates":[29.65687,-31.17999],"type":"Point"}
}