{
  "type": "Feature",
  "properties": {
    "gn:admin1_code":"9",
    "gn:admin2_code":"DC47",
    "gn:admin3_code":"LIM474",
    "gn:asciiname":"Radingwane",
    "gn:country_code":"ZA",
    "gn:dem":1059,
    "gn:feature_class":"P",
    "gn:feature_code":"PPL",
    "gn:name":"Radingwane",
    "gn:population":0,
    "gn:timezone":"Africa/Johannesburg",
    "iso:country":"ZA",
    "wof:name":"Radingwane",
    "wof:placetype":"locality"
},
  "geometry": {"coordinates":[29.86667000000001,-24.56667],"type":"Point"}
}