{
  "type": "Feature",
  "properties": {
    "gn:admin1_code":"5",
    "gn:admin2_code":"DC15",
    "gn:admin3_code":"EC154",
    "gn:asciiname":"Gxokoza",
    "gn:country_code":"ZA",
    "gn:dem":281,
    "gn:feature_class":"P",
    "gn:feature_code":"PPL",
    "gn:name":"Gxokoza",
    "gn:population":0,
    "gn:timezone":"Africa/Johannesburg",
    "iso:country":"ZA",
    "wof:name":"Gxokoza",
    "wof:placetype":"locality"
},
  "geometry": {"coordinates":[29.26823,-31.58786],"type":"Point"}
}