{
  "type": "Feature",
  "properties": {
    "gn:admin1_code":"3",
    "gn:admin2_code":"MAN",
    "gn:admin3_code":"MAN",
    "gn:asciiname":"Lockshoek",
    "gn:country_code":"ZA",
    "gn:dem":1401,
    "gn:feature_class":"P",
    "gn:feature_code":"PPL",
    "gn:name":"Lockshoek",
    "gn:population":0,
    "gn:timezone":"Africa/Johannesburg",
    "iso:country":"ZA",
    "wof:name":"Lockshoek",
    "wof:placetype":"locality"
},
  "geometry": {"coordinates":[26.03134,-29.16247000000001],"type":"Point"}
}