{
  "type": "Feature",
  "properties": {
    "gn:admin1_code":"10.0",
    "gn:admin2_code":"DC37",
    "gn:admin3_code":"NW374",
    "gn:asciiname":"Schoongezicht",
    "gn:country_code":"ZA",
    "gn:dem":1122,
    "gn:feature_class":"P",
    "gn:feature_code":"PPL",
    "gn:name":"Schoongezicht",
    "gn:population":0,
    "gn:timezone":"Africa/Johannesburg",
    "iso:country":"ZA",
    "name:und_x_variant":[
        "Shoongezicht",
        "Schoongezicht"
    ],
    "wof:name":"Schoongezicht",
    "wof:placetype":"locality"
},
  "geometry": {"coordinates":[26.76238,-25.46022],"type":"Point"}
}