{
  "type": "Feature",
  "properties": {
    "gn:admin1_code":"2",
    "gn:asciiname":"Conningarth",
    "gn:country_code":"ZA",
    "gn:dem":1495,
    "gn:feature_class":"P",
    "gn:feature_code":"PPL",
    "gn:name":"Conningarth",
    "gn:population":0,
    "gn:timezone":"Africa/Johannesburg",
    "iso:country":"ZA",
    "name:und_x_variant":[
        "Gonningarth",
        "Conningarth"
    ],
    "wof:name":"Conningarth",
    "wof:placetype":"locality"
},
  "geometry": {"coordinates":[29.01504000000001,-30.28089000000001],"type":"Point"}
}