{
  "type": "Feature",
  "properties": {
    "gn:gn_country":"ZA",
    "gn:gn_fcode":"ADM3",
    "gn:gn_pop":244501,
    "gn:population":244501,
    "iso:country":"ZA",
    "name:afr_x_preferred":[
        "Nongoma"
    ],
    "name:deu_x_preferred":[
        "Nongoma"
    ],
    "name:est_x_preferred":[
        "Nongoma"
    ],
    "name:fra_x_preferred":[
        "Nongoma"
    ],
    "name:ita_x_preferred":[
        "Nongoma"
    ],
    "name:nso_x_preferred":[
        "Nongoma"
    ],
    "name:ron_x_preferred":[
        "Nongoma"
    ],
    "name:spa_x_preferred":[
        "Nongoma"
    ],
    "name:swe_x_preferred":[
        "Nongoma"
    ],
    "name:war_x_preferred":[
        "Nongoma"
    ],
    "name:zho_x_preferred":[
        "\u8fb2\u6208\u99ac"
    ],
    "qs_pg:aaroncc":"ZA",
    "qs_pg:gn_country":"ZA",
    "qs_pg:gn_fcode":"ADM3",
    "qs_pg:gn_pop":244501,
    "qs_pg:name":"Nongoma",
    "qs_pg:photos_9r":0,
    "qs_pg:photos_sr":0,
    "qs_pg:pop_sr":10,
    "qs_pg:qs_pg_placetype":"localadmin",
    "wof:name":"Nongoma",
    "wof:placetype":"localadmin",
    "wof:population":244501
},
  "geometry": {"coordinates":[31.74556,-27.91178],"type":"Point"}
}