{
  "type": "Feature",
  "properties": {
    "gn:admin1_code":"5",
    "gn:admin2_code":"DC12",
    "gn:admin3_code":"EC121",
    "gn:asciiname":"Hobeni",
    "gn:country_code":"ZA",
    "gn:dem":241,
    "gn:feature_class":"P",
    "gn:feature_code":"PPL",
    "gn:name":"Hobeni",
    "gn:population":0,
    "gn:timezone":"Africa/Johannesburg",
    "iso:country":"ZA",
    "name:afr_x_preferred":[
        "Hobeni"
    ],
    "name:est_x_preferred":[
        "Hobeni"
    ],
    "name:nso_x_preferred":[
        "Hobeni"
    ],
    "wof:name":"Hobeni",
    "wof:placetype":"locality"
},
  "geometry": {"coordinates":[28.88333,-32.16667],"type":"Point"}
}