{
  "type": "Feature",
  "properties": {
    "gn:admin1_code":"2",
    "gn:admin2_code":"DC22",
    "gn:admin3_code":"KZN227",
    "gn:asciiname":"Baynesfield",
    "gn:country_code":"ZA",
    "gn:dem":803,
    "gn:feature_class":"P",
    "gn:feature_code":"PPL",
    "gn:name":"Baynesfield",
    "gn:population":0,
    "gn:timezone":"Africa/Johannesburg",
    "iso:country":"ZA",
    "name:und_x_variant":[
        "Baynesfield Estate",
        "Baynesfield"
    ],
    "wof:name":"Baynesfield",
    "wof:placetype":"locality"
},
  "geometry": {"coordinates":[30.35316,-29.75748],"type":"Point"}
}