{
  "type": "Feature",
  "properties": {
    "gn:admin1_code":"9.0",
    "gn:admin2_code":"DC34",
    "gn:admin3_code":"LIM343",
    "gn:asciiname":"Upper Shingwidzi",
    "gn:country_code":"ZA",
    "gn:dem":366,
    "gn:feature_class":"P",
    "gn:feature_code":"PPL",
    "gn:name":"Upper Shingwidzi",
    "gn:population":0,
    "gn:timezone":"Africa/Johannesburg",
    "iso:country":"ZA",
    "wof:lang_x_official":[
        "eng"
    ],
    "wof:lang_x_spoken":[
        "eng",
        "zul",
        "xho",
        "afr",
        "nso",
        "tsn",
        "sot",
        "tso",
        "ssw",
        "ven",
        "nbl"
    ],
    "wof:name":"Upper Shingwidzi",
    "wof:placetype":"locality"
},
  "geometry": {"coordinates":[31.15,-23.18333],"type":"Point"}
}