{
  "type": "Feature",
  "properties": {
    "gn:admin1_code":"5.0",
    "gn:admin2_code":"DC14",
    "gn:admin3_code":"EC144",
    "gn:asciiname":"Rooipoort",
    "gn:country_code":"ZA",
    "gn:dem":1596,
    "gn:feature_class":"P",
    "gn:feature_code":"PPL",
    "gn:name":"Rooipoort",
    "gn:population":0,
    "gn:timezone":"Africa/Johannesburg",
    "iso:country":"ZA",
    "wof:name":"Rooipoort",
    "wof:placetype":"locality"
},
  "geometry": {"coordinates":[25.82766,-31.16809000000001],"type":"Point"}
}