{
  "type": "Feature",
  "properties": {
    "gn:admin1_code":"5",
    "gn:admin2_code":"DC13",
    "gn:admin3_code":"EC131",
    "gn:asciiname":"Glen Alfa",
    "gn:country_code":"ZA",
    "gn:dem":977,
    "gn:feature_class":"P",
    "gn:feature_code":"PPL",
    "gn:name":"Glen Alfa",
    "gn:population":0,
    "gn:timezone":"Africa/Johannesburg",
    "iso:country":"ZA",
    "wof:name":"Glen Alfa",
    "wof:placetype":"locality"
},
  "geometry": {"coordinates":[25.51314,-31.91194],"type":"Point"}
}