{
  "type": "Feature",
  "properties": {
    "gn:admin1_code":"2.0",
    "gn:admin2_code":"DC23",
    "gn:admin3_code":"KZN234",
    "gn:asciiname":"Stendal",
    "gn:country_code":"ZA",
    "gn:dem":671,
    "gn:feature_class":"P",
    "gn:feature_code":"PPL",
    "gn:name":"Stendal",
    "gn:population":0,
    "gn:timezone":"Africa/Johannesburg",
    "iso:country":"ZA",
    "wof:name":"Stendal",
    "wof:placetype":"locality"
},
  "geometry": {"coordinates":[30.11372,-28.77126],"type":"Point"}
}