{
  "type": "Feature",
  "properties": {
    "gn:admin1_code":"2.0",
    "gn:admin2_code":"DC23",
    "gn:admin3_code":"KZN234",
    "gn:asciiname":"Stendal",
    "gn:country_code":"ZA",
    "gn:dem":671,
    "gn:feature_class":"P",
    "gn:feature_code":"PPL",
    "gn:name":"Stendal",
    "gn:population":0,
    "gn:timezone":"Africa/Johannesburg",
    "iso:country":"ZA",
    "name:ara_x_preferred":[
        "\u0634\u062a\u0646\u062f\u0627\u0644"
    ],
    "name:azb_x_preferred":[
        "\u0627\u0634\u062a\u0646\u062f\u0644"
    ],
    "name:cat_x_preferred":[
        "Stendal"
    ],
    "name:ceb_x_preferred":[
        "Stendal"
    ],
    "name:ces_x_preferred":[
        "Stendal"
    ],
    "name:dan_x_preferred":[
        "Stendal"
    ],
    "name:deu_x_preferred":[
        "Stendal"
    ],
    "name:epo_x_preferred":[
        "Stendal"
    ],
    "name:est_x_preferred":[
        "Stendal"
    ],
    "name:eus_x_preferred":[
        "Stendal"
    ],
    "name:fas_x_preferred":[
        "\u0627\u0634\u062a\u0646\u062f\u0644"
    ],
    "name:fin_x_preferred":[
        "Stendal"
    ],
    "name:fra_x_preferred":[
        "Stendal"
    ],
    "name:gla_x_preferred":[
        "Stendal"
    ],
    "name:heb_x_preferred":[
        "\u05e9\u05d8\u05e0\u05d3\u05d0\u05dc"
    ],
    "name:hun_x_preferred":[
        "Stendal"
    ],
    "name:ita_x_preferred":[
        "Stendal"
    ],
    "name:kaz_x_preferred":[
        "\u0428\u0442\u0435\u043d\u0434\u0430\u043b\u044c"
    ],
    "name:kir_x_preferred":[
        "\u0428\u0442\u0435\u043d\u0434\u0430\u043b\u044c"
    ],
    "name:kor_x_preferred":[
        "\uc288\ud150\ub2ec"
    ],
    "name:lat_x_preferred":[
        "Stendalia"
    ],
    "name:lit_x_preferred":[
        "\u0160tendalis"
    ],
    "name:mkd_x_preferred":[
        "\u0428\u0442\u0435\u043d\u0434\u0430\u043b"
    ],
    "name:msa_x_preferred":[
        "Stendal"
    ],
    "name:nds_x_preferred":[
        "Stendal"
    ],
    "name:nld_x_preferred":[
        "Stendal"
    ],
    "name:nor_x_preferred":[
        "Stendal"
    ],
    "name:oci_x_preferred":[
        "Stendal"
    ],
    "name:pol_x_preferred":[
        "Stendal"
    ],
    "name:por_x_preferred":[
        "Stendal"
    ],
    "name:ron_x_preferred":[
        "Stendal"
    ],
    "name:rus_x_preferred":[
        "\u0428\u0442\u0435\u043d\u0434\u0430\u043b\u044c"
    ],
    "name:slk_x_preferred":[
        "Stendal"
    ],
    "name:spa_x_preferred":[
        "Stendal"
    ],
    "name:srp_x_preferred":[
        "\u0428\u0442\u0435\u043d\u0434\u0430\u043b"
    ],
    "name:swe_x_preferred":[
        "Stendal"
    ],
    "name:tat_x_preferred":[
        "\u0428\u0442\u0435\u043d\u0434\u0430\u043b\u044c"
    ],
    "name:tur_x_preferred":[
        "Stendal"
    ],
    "name:ukr_x_preferred":[
        "\u0428\u0442\u0435\u043d\u0434\u0430\u043b\u044c"
    ],
    "name:vol_x_preferred":[
        "Stendal"
    ],
    "name:war_x_preferred":[
        "Stendal"
    ],
    "name:zho_x_preferred":[
        "\u65bd\u6ed5\u8fbe\u5c14"
    ],
    "wof:lang_x_official":[
        "eng"
    ],
    "wof:lang_x_spoken":[
        "eng",
        "zul",
        "xho",
        "afr",
        "nso",
        "tsn",
        "sot",
        "tso",
        "ssw",
        "ven",
        "nbl"
    ],
    "wof:name":"Stendal",
    "wof:placetype":"locality"
},
  "geometry": {"coordinates":[30.11372,-28.77126],"type":"Point"}
}