{
  "type": "Feature",
  "properties": {
    "gn:admin1_code":"2.0",
    "gn:admin2_code":"DC22",
    "gn:admin3_code":"KZN223",
    "gn:asciiname":"Windy",
    "gn:country_code":"ZA",
    "gn:dem":1502,
    "gn:feature_class":"P",
    "gn:feature_code":"PPL",
    "gn:name":"Windy",
    "gn:population":0,
    "gn:timezone":"Africa/Johannesburg",
    "iso:country":"ZA",
    "wof:name":"Windy",
    "wof:placetype":"locality"
},
  "geometry": {"coordinates":[29.95,-29.16667],"type":"Point"}
}