{
  "type": "Feature",
  "properties": {
    "gn:admin1_code":"9",
    "gn:admin2_code":"DC34",
    "gn:admin3_code":"LIM343",
    "gn:asciiname":"Ka-Matsakeli",
    "gn:country_code":"ZA",
    "gn:dem":520,
    "gn:feature_class":"P",
    "gn:feature_code":"PPL",
    "gn:name":"Ka-Matsakeli",
    "gn:population":0,
    "gn:timezone":"Africa/Johannesburg",
    "iso:country":"ZA",
    "wof:lang_x_official":[
        "eng"
    ],
    "wof:lang_x_spoken":[
        "eng",
        "zul",
        "xho",
        "afr",
        "nso",
        "tsn",
        "sot",
        "tso",
        "ssw",
        "ven",
        "nbl"
    ],
    "wof:name":"Ka-Matsakeli",
    "wof:placetype":"locality"
},
  "geometry": {"coordinates":[30.76136,-23.05085],"type":"Point"}
}