{
  "type": "Feature",
  "properties": {
    "gn:country":"ZA",
    "gn:fcode":"PPL",
    "gn:population":0,
    "iso:country":"ZA",
    "name:afr_x_preferred":[
        "Goedverwacht"
    ],
    "name:ast_x_preferred":[
        "Goedverwacht"
    ],
    "name:eng_x_preferred":[
        "Goedverwacht"
    ],
    "name:est_x_preferred":[
        "Goedverwacht"
    ],
    "name:ita_x_preferred":[
        "Goedverwacht"
    ],
    "name:nld_x_preferred":[
        "Goedverwacht"
    ],
    "name:nso_x_preferred":[
        "Goedverwacht"
    ],
    "name:zul_x_preferred":[
        "IGoedverwacht"
    ],
    "qs_pg:aaroncc":"ZA",
    "qs_pg:gn_country":"ZA",
    "qs_pg:gn_fcode":"PPL",
    "qs_pg:gn_pop":0,
    "qs_pg:name":"Goedverwag",
    "qs_pg:name_adm0":"South Africa",
    "qs_pg:name_adm1":"Western Cape",
    "qs_pg:photos_9r":0,
    "qs_pg:photos_sr":0,
    "qs_pg:pop_sr":0,
    "qs_pg:qs_pg_placetype":"locality",
    "qs_pg:qs_pg_placetype_gp":"Town",
    "qs_pg:woe_adm0":23424942,
    "woe:adm0_id":23424942,
    "woe:name_adm0":"South Africa",
    "woe:name_adm1":"Western Cape",
    "woe:placetype":"Town",
    "wof:lang_x_official":[
        "eng"
    ],
    "wof:lang_x_spoken":[
        "eng",
        "zul",
        "xho",
        "afr",
        "nso",
        "tsn",
        "sot",
        "tso",
        "ssw",
        "ven",
        "nbl"
    ],
    "wof:name":"Goedverwag",
    "wof:placetype":"locality"
},
  "geometry": {"coordinates":[18.69433,-32.86752],"type":"Point"}
}