{
  "type": "Feature",
  "properties": {
    "gn:admin1_code":"5",
    "gn:admin2_code":"DC13",
    "gn:admin3_code":"EC137",
    "gn:asciiname":"langdon",
    "gn:country_code":"ZA",
    "gn:dem":864,
    "gn:feature_class":"P",
    "gn:feature_code":"PPL",
    "gn:name":"langdon",
    "gn:population":0,
    "gn:timezone":"Africa/Johannesburg",
    "iso:country":"ZA",
    "name:cat_x_preferred":[
        "Langdon"
    ],
    "name:ceb_x_preferred":[
        "Langdon"
    ],
    "name:deu_x_preferred":[
        "Langdon"
    ],
    "name:fra_x_preferred":[
        "Langdon"
    ],
    "name:heb_x_preferred":[
        "\u05dc\u05e0\u05d2\u05d3\u05d5\u05df"
    ],
    "name:ita_x_preferred":[
        "Langdon"
    ],
    "name:jpn_x_preferred":[
        "\u30e9\u30f3\u30b0\u30c9\u30f3"
    ],
    "name:nld_x_preferred":[
        "Langdon"
    ],
    "name:pol_x_preferred":[
        "Langdon"
    ],
    "name:por_x_preferred":[
        "Langdon"
    ],
    "name:rus_x_preferred":[
        "\u041b\u044d\u043d\u0433\u0434\u043e\u043d"
    ],
    "name:spa_x_preferred":[
        "Langdon"
    ],
    "name:srp_x_preferred":[
        "\u041b\u0430\u043d\u0433\u0434\u0430\u043d"
    ],
    "name:swe_x_preferred":[
        "Langdon"
    ],
    "name:ukr_x_preferred":[
        "\u041b\u0430\u043d\u0433\u0434\u043e\u043d"
    ],
    "name:urd_x_preferred":[
        "\u0644\u06cc\u0646\u06af\u0688\u0646"
    ],
    "name:vol_x_preferred":[
        "Langdon"
    ],
    "wof:name":"langdon",
    "wof:placetype":"locality"
},
  "geometry": {"coordinates":[28.15,-31.65],"type":"Point"}
}