{
  "type": "Feature",
  "properties": {
    "gn:admin1_code":"5",
    "gn:admin2_code":"DC14",
    "gn:admin3_code":"EC144",
    "gn:asciiname":"Haaspoort",
    "gn:country_code":"ZA",
    "gn:dem":1557,
    "gn:feature_class":"P",
    "gn:feature_code":"PPL",
    "gn:name":"Haaspoort",
    "gn:population":0,
    "gn:timezone":"Africa/Johannesburg",
    "iso:country":"ZA",
    "wof:name":"Haaspoort",
    "wof:placetype":"locality"
},
  "geometry": {"coordinates":[26.11293,-31.15764],"type":"Point"}
}