{
  "type": "Feature",
  "properties": {
    "gn:gn_country":"ZA",
    "gn:gn_fcode":"PPL",
    "gn:gn_pop":9788,
    "gn:population":9788,
    "iso:country":"ZA",
    "name:afr_x_preferred":[
        "Alice"
    ],
    "name:dut_x_preferred":[
        "Alice"
    ],
    "name:eng_x_preferred":[
        "Alice"
    ],
    "name:fas_x_preferred":[
        "\u0627\u0644\u06cc\u0633\u060c \u06a9\u06cc\u067e \u0634\u0631\u0642\u06cc"
    ],
    "name:fre_x_preferred":[
        "Alice"
    ],
    "name:ger_x_preferred":[
        "Alice"
    ],
    "name:ita_x_preferred":[
        "Alice"
    ],
    "name:jpn_x_preferred":[
        "\u30a2\u30ea\u30b9"
    ],
    "name:nso_x_preferred":[
        "Alice"
    ],
    "name:per_x_preferred":[
        "\u0627\u0644\u06cc\u0633\u060c \u06a9\u06cc\u067e \u0634\u0631\u0642\u06cc"
    ],
    "name:pol_x_preferred":[
        "Alice"
    ],
    "name:rum_x_preferred":[
        "Alice"
    ],
    "name:rus_x_preferred":[
        "\u042d\u043b\u0438\u0441"
    ],
    "name:spa_x_preferred":[
        "Alice"
    ],
    "name:ven_x_preferred":[
        "Alice"
    ],
    "qs_pg:aaroncc":"ZA",
    "qs_pg:gn_country":"ZA",
    "qs_pg:gn_fcode":"PPL",
    "qs_pg:gn_pop":9788,
    "qs_pg:name":"Alice",
    "qs_pg:name_adm0":"South Africa",
    "qs_pg:name_adm1":"Eastern Cape",
    "qs_pg:photos":12,
    "qs_pg:photos_1k":2,
    "qs_pg:photos_9k":1,
    "qs_pg:photos_9r":2,
    "qs_pg:photos_all":56,
    "qs_pg:photos_sr":1,
    "qs_pg:pop_sr":5,
    "qs_pg:qs_pg_placetype":"locality",
    "qs_pg:qs_pg_placetype_gp":"Town",
    "qs_pg:woe_adm0":23424942,
    "woe:adm0_id":23424942,
    "woe:name_adm0":"South Africa",
    "woe:name_adm1":"Eastern Cape",
    "woe:placetype":"Town",
    "wof:name":"Alice",
    "wof:placetype":"locality",
    "wof:population":9788
},
  "geometry": {"coordinates":[26.8344,-32.78749],"type":"Point"}
}