{
  "type": "Feature",
  "properties": {
    "iso:country":"ZA",
    "name:eng_x_preferred":[
        "Rynfield"
    ],
    "name:unk_x_variant":[
        "Rynfield"
    ],
    "qs:gn_adm0_cc":"ZA",
    "qs:gn_local":1020098,
    "qs:gn_nam_loc":"Benoni, Ekurhuleni, Ekurhuleni, Gauteng, ZA",
    "qs:gn_namadm1":"06",
    "qs:local_max":15,
    "qs:local_sum":17,
    "qs:localhoods":2,
    "qs:name":"Rynfield",
    "qs:name_adm0":"South Africa",
    "qs:name_adm1":"Gauteng",
    "qs:name_adm2":"Ekurhuleni",
    "qs:name_lau":"Ekurhuleni",
    "qs:name_local":"Benoni",
    "qs:photo_max":8,
    "qs:photo_sum":15,
    "qs:placetype":"Suburb",
    "qs:quad_count":6,
    "qs:woe_adm0":23424942,
    "qs:woe_adm1":2346981,
    "qs:woe_adm2":56189451,
    "qs:woe_lau":56189689,
    "qs:woe_local":1579744,
    "qs:woe_ver":"7.10.0",
    "wof:lang":[
        "eng"
    ],
    "wof:name":"Rynfield",
    "wof:placetype":"neighbourhood"
},
  "geometry": {"coordinates":[28.33905,-26.156917],"type":"Point"}
}