{
  "type": "Feature",
  "properties": {
    "gn:admin1_code":"5",
    "gn:admin2_code":"DC13",
    "gn:admin3_code":"EC134",
    "gn:asciiname":"KuZingqutu",
    "gn:country_code":"ZA",
    "gn:dem":1396,
    "gn:feature_class":"P",
    "gn:feature_code":"PPL",
    "gn:name":"KuZingqutu",
    "gn:population":0,
    "gn:timezone":"Africa/Johannesburg",
    "iso:country":"ZA",
    "wof:name":"KuZingqutu",
    "wof:placetype":"locality"
},
  "geometry": {"coordinates":[26.85653,-31.76304],"type":"Point"}
}