{
  "type": "Feature",
  "properties": {
    "gn:admin1_code":"5",
    "gn:admin2_code":"DC13",
    "gn:admin3_code":"EC134",
    "gn:asciiname":"Enqobokeni",
    "gn:country_code":"ZA",
    "gn:dem":1206,
    "gn:feature_class":"P",
    "gn:feature_code":"PPLL",
    "gn:name":"Enqobokeni",
    "gn:population":0,
    "gn:timezone":"Africa/Johannesburg",
    "iso:country":"ZA",
    "wof:name":"Enqobokeni",
    "wof:placetype":"locality"
},
  "geometry": {"coordinates":[26.72207,-32.16451],"type":"Point"}
}