{
  "type": "Feature",
  "properties": {
    "gn:admin1_code":"9",
    "gn:admin2_code":"DC35",
    "gn:admin3_code":"LIM351",
    "gn:asciiname":"Lebu",
    "gn:country_code":"ZA",
    "gn:dem":852,
    "gn:feature_class":"P",
    "gn:feature_code":"PPL",
    "gn:name":"Lebu",
    "gn:population":0,
    "gn:timezone":"Africa/Johannesburg",
    "iso:country":"ZA",
    "name:ceb_x_preferred":[
        "Lebu"
    ],
    "name:spa_x_preferred":[
        "Lebu"
    ],
    "name:swe_x_preferred":[
        "Lebu"
    ],
    "wof:name":"Lebu",
    "wof:placetype":"locality"
},
  "geometry": {"coordinates":[28.74547,-23.10616],"type":"Point"}
}