{
  "type": "Feature",
  "properties": {
    "gn:admin1_code":"3",
    "gn:admin2_code":"DC19",
    "gn:admin3_code":"FS195",
    "gn:asciiname":"Kafferstad",
    "gn:country_code":"ZA",
    "gn:dem":1608,
    "gn:feature_class":"P",
    "gn:feature_code":"PPL",
    "gn:name":"Kafferstad",
    "gn:population":0,
    "gn:timezone":"Africa/Johannesburg",
    "iso:country":"ZA",
    "wof:name":"Kafferstad",
    "wof:placetype":"locality"
},
  "geometry": {"coordinates":[28.99563,-28.02278],"type":"Point"}
}