{
  "type": "Feature",
  "properties": {
    "gn:admin1_code":"5",
    "gn:admin2_code":"DC12",
    "gn:admin3_code":"EC123",
    "gn:asciiname":"Harefield",
    "gn:country_code":"ZA",
    "gn:dem":476,
    "gn:feature_class":"P",
    "gn:feature_code":"PPL",
    "gn:name":"Harefield",
    "gn:population":0,
    "gn:timezone":"Africa/Johannesburg",
    "iso:country":"ZA",
    "name:ceb_x_preferred":[
        "Harefield"
    ],
    "name:cym_x_preferred":[
        "Harefield"
    ],
    "name:fas_x_preferred":[
        "\u0647\u06cc\u0631\u0641\u06cc\u0644\u062f"
    ],
    "name:gle_x_preferred":[
        "Harefield"
    ],
    "name:hin_x_preferred":[
        "\u0939\u0947\u0930\u092b\u093c\u0940\u0932\u094d\u0921"
    ],
    "name:nld_x_preferred":[
        "Harefield"
    ],
    "name:pol_x_preferred":[
        "Harefield"
    ],
    "name:swe_x_preferred":[
        "Harefield"
    ],
    "wof:lang_x_official":[
        "eng"
    ],
    "wof:lang_x_spoken":[
        "eng",
        "zul",
        "xho",
        "afr",
        "nso",
        "tsn",
        "sot",
        "tso",
        "ssw",
        "ven",
        "nbl"
    ],
    "wof:name":"Harefield",
    "wof:placetype":"locality"
},
  "geometry": {"coordinates":[28.00567,-32.67888],"type":"Point"}
}