{
  "type": "Feature",
  "properties": {
    "gn:admin1_code":"5",
    "gn:admin2_code":"DC13",
    "gn:admin3_code":"EC132",
    "gn:asciiname":"Knowsley",
    "gn:country_code":"ZA",
    "gn:dem":1416,
    "gn:feature_class":"P",
    "gn:feature_code":"PPL",
    "gn:name":"Knowsley",
    "gn:population":0,
    "gn:timezone":"Africa/Johannesburg",
    "iso:country":"ZA",
    "name:ceb_x_preferred":[
        "Knowsley"
    ],
    "name:deu_x_preferred":[
        "Knowsley"
    ],
    "name:fra_x_preferred":[
        "Knowsley"
    ],
    "name:nld_x_preferred":[
        "Knowsley"
    ],
    "name:pol_x_preferred":[
        "Knowsley"
    ],
    "name:swe_x_preferred":[
        "Knowsley"
    ],
    "wof:lang_x_official":[
        "eng"
    ],
    "wof:lang_x_spoken":[
        "eng",
        "zul",
        "xho",
        "afr",
        "nso",
        "tsn",
        "sot",
        "tso",
        "ssw",
        "ven",
        "nbl"
    ],
    "wof:name":"Knowsley",
    "wof:placetype":"locality"
},
  "geometry": {"coordinates":[26.32591,-32.13779],"type":"Point"}
}