{
  "type": "Feature",
  "properties": {
    "gn:admin1_code":"5",
    "gn:admin2_code":"DC13",
    "gn:admin3_code":"EC132",
    "gn:asciiname":"Knowsley",
    "gn:country_code":"ZA",
    "gn:dem":1416,
    "gn:feature_class":"P",
    "gn:feature_code":"PPL",
    "gn:name":"Knowsley",
    "gn:population":0,
    "gn:timezone":"Africa/Johannesburg",
    "iso:country":"ZA",
    "name:ara_x_preferred":[
        "\u0646\u0648\u0633\u0644\u064a"
    ],
    "name:ceb_x_preferred":[
        "Knowsley"
    ],
    "name:deu_x_preferred":[
        "Knowsley"
    ],
    "name:ell_x_preferred":[
        "\u039d\u03cc\u03bf\u03c5\u03c3\u03bb\u03b9"
    ],
    "name:fra_x_preferred":[
        "Knowsley"
    ],
    "name:heb_x_preferred":[
        "\u05e0\u05d5\u05e1\u05dc\u05d9\u05d9"
    ],
    "name:hin_x_preferred":[
        "\u0928\u094b\u091c\u093c\u094d\u0932\u0947"
    ],
    "name:ind_x_preferred":[
        "Knowsley"
    ],
    "name:nld_x_preferred":[
        "Knowsley"
    ],
    "name:pol_x_preferred":[
        "Knowsley"
    ],
    "name:swe_x_preferred":[
        "Knowsley"
    ],
    "name:tur_x_preferred":[
        "Knowsley"
    ],
    "name:vie_x_preferred":[
        "Knowsley"
    ],
    "wof:lang_x_official":[
        "eng"
    ],
    "wof:lang_x_spoken":[
        "eng",
        "zul",
        "xho",
        "afr",
        "nso",
        "tsn",
        "sot",
        "tso",
        "ssw",
        "ven",
        "nbl"
    ],
    "wof:name":"Knowsley",
    "wof:placetype":"locality"
},
  "geometry": {"coordinates":[26.32591,-32.13779],"type":"Point"}
}