{
  "type": "Feature",
  "properties": {
    "gn:admin1_code":"5",
    "gn:admin2_code":"DC13",
    "gn:admin3_code":"EC132",
    "gn:asciiname":"Damanskraal",
    "gn:country_code":"ZA",
    "gn:dem":1290,
    "gn:feature_class":"P",
    "gn:feature_code":"PPL",
    "gn:name":"Damanskraal",
    "gn:population":0,
    "gn:timezone":"Africa/Johannesburg",
    "iso:country":"ZA",
    "wof:name":"Damanskraal",
    "wof:placetype":"locality"
},
  "geometry": {"coordinates":[25.85881,-31.50538],"type":"Point"}
}