{
  "type": "Feature",
  "properties": {
    "gn:admin1_code":"2",
    "gn:admin2_code":"DC27",
    "gn:admin3_code":"KZN272",
    "gn:asciiname":"KwaJobe",
    "gn:country_code":"ZA",
    "gn:dem":67,
    "gn:feature_class":"P",
    "gn:feature_code":"PPL",
    "gn:name":"KwaJobe",
    "gn:population":0,
    "gn:timezone":"Africa/Johannesburg",
    "iso:country":"ZA",
    "wof:name":"KwaJobe",
    "wof:placetype":"locality"
},
  "geometry": {"coordinates":[32.32464,-27.60292],"type":"Point"}
}