{
  "type": "Feature",
  "properties": {
    "gn:admin1_code":"5.0",
    "gn:admin2_code":"DC14",
    "gn:admin3_code":"EC141",
    "gn:asciiname":"Upper Tsitsana",
    "gn:country_code":"ZA",
    "gn:dem":1361,
    "gn:feature_class":"P",
    "gn:feature_code":"PPL",
    "gn:name":"Upper Tsitsana",
    "gn:population":0,
    "gn:timezone":"Africa/Johannesburg",
    "iso:country":"ZA",
    "name:und_x_variant":[
        "Upper Tsitana",
        "Upper Tsitsana"
    ],
    "wof:name":"Upper Tsitsana",
    "wof:placetype":"locality"
},
  "geometry": {"coordinates":[28.30184,-30.83216],"type":"Point"}
}