{
  "type": "Feature",
  "properties": {
    "gn:admin1_code":"7",
    "gn:admin2_code":"DC30",
    "gn:admin3_code":"MP303",
    "gn:asciiname":"Commondale",
    "gn:country_code":"ZA",
    "gn:dem":1026,
    "gn:feature_class":"P",
    "gn:feature_code":"PPL",
    "gn:name":"Commondale",
    "gn:population":0,
    "gn:timezone":"Africa/Johannesburg",
    "iso:country":"ZA",
    "name:ceb_x_preferred":[
        "Commondale"
    ],
    "name:nld_x_preferred":[
        "Commondale"
    ],
    "name:pol_x_preferred":[
        "Commondale"
    ],
    "name:swe_x_preferred":[
        "Commondale"
    ],
    "wof:lang_x_official":[
        "eng"
    ],
    "wof:lang_x_spoken":[
        "eng",
        "zul",
        "xho",
        "afr",
        "nso",
        "tsn",
        "sot",
        "tso",
        "ssw",
        "ven",
        "nbl"
    ],
    "wof:name":"Commondale",
    "wof:placetype":"locality"
},
  "geometry": {"coordinates":[30.89885,-27.2941],"type":"Point"}
}