{
  "type": "Feature",
  "properties": {
    "gn:admin1_code":"11",
    "gn:admin2_code":"DC4",
    "gn:admin3_code":"WC042",
    "gn:asciiname":"Port Beaufort",
    "gn:country_code":"ZA",
    "gn:dem":16,
    "gn:feature_class":"P",
    "gn:feature_code":"PPL",
    "gn:name":"Port Beaufort",
    "gn:population":0,
    "gn:timezone":"Africa/Johannesburg",
    "iso:country":"ZA",
    "wof:name":"Port Beaufort",
    "wof:placetype":"locality"
},
  "geometry": {"coordinates":[20.82183,-34.39718],"type":"Point"}
}