{
  "type": "Feature",
  "properties": {
    "gn:admin1_code":"11",
    "gn:admin2_code":"DC4",
    "gn:admin3_code":"WC042",
    "gn:asciiname":"Port Beaufort",
    "gn:country_code":"ZA",
    "gn:dem":16,
    "gn:feature_class":"P",
    "gn:feature_code":"PPL",
    "gn:name":"Port Beaufort",
    "gn:population":0,
    "gn:timezone":"Africa/Johannesburg",
    "iso:country":"ZA",
    "name:afr_x_preferred":[
        "Port Beaufort"
    ],
    "name:est_x_preferred":[
        "Port Beaufort"
    ],
    "name:nld_x_preferred":[
        "Port Beaufort"
    ],
    "name:nso_x_preferred":[
        "Port Beaufort"
    ],
    "name:rus_x_preferred":[
        "\u041f\u043e\u0440\u0442-\u0411\u043e\u0444\u043e\u0440\u0442"
    ],
    "name:ukr_x_preferred":[
        "\u041f\u043e\u0440\u0442-\u0411\u043e\u0444\u043e\u0440\u0442"
    ],
    "name:urd_x_preferred":[
        "\u067e\u0648\u0631\u0679 \u0628\u06cc\u0648\u0641\u0648\u0631\u0679"
    ],
    "wof:lang_x_official":[
        "eng"
    ],
    "wof:lang_x_spoken":[
        "eng",
        "zul",
        "xho",
        "afr",
        "nso",
        "tsn",
        "sot",
        "tso",
        "ssw",
        "ven",
        "nbl"
    ],
    "wof:name":"Port Beaufort",
    "wof:placetype":"locality"
},
  "geometry": {"coordinates":[20.82183,-34.39718],"type":"Point"}
}