{
  "type": "Feature",
  "properties": {
    "gn:country":"ZA",
    "gn:fcode":"ADM3",
    "gn:population":246969,
    "iso:country":"ZA",
    "qs_pg:aaroncc":"ZA",
    "qs_pg:gn_country":"ZA",
    "qs_pg:gn_fcode":"ADM3",
    "qs_pg:gn_pop":246969,
    "qs_pg:name":"Dr JS Moroka",
    "qs_pg:photos_9r":0,
    "qs_pg:photos_sr":0,
    "qs_pg:pop_sr":10,
    "qs_pg:qs_pg_placetype":"localadmin",
    "wof:name":"Dr JS Moroka",
    "wof:placetype":"localadmin",
    "wof:population":246969
},
  "geometry": {"coordinates":[28.80147,-25.10388],"type":"Point"}
}