{
  "type": "Feature",
  "properties": {
    "gn:admin1_code":"10",
    "gn:admin2_code":"DC37",
    "gn:admin3_code":"NW373",
    "gn:asciiname":"Maumong",
    "gn:country_code":"ZA",
    "gn:dem":1133,
    "gn:feature_class":"P",
    "gn:feature_code":"PPL",
    "gn:name":"Maumong",
    "gn:population":0,
    "gn:timezone":"Africa/Johannesburg",
    "iso:country":"ZA",
    "wof:name":"Maumong",
    "wof:placetype":"locality"
},
  "geometry": {"coordinates":[27.44786,-25.58399],"type":"Point"}
}