{
  "type": "Feature",
  "properties": {
    "gn:admin1_code":"3.0",
    "gn:admin2_code":"MAN",
    "gn:admin3_code":"MAN",
    "gn:asciiname":"Yoxford",
    "gn:country_code":"ZA",
    "gn:dem":1532,
    "gn:feature_class":"P",
    "gn:feature_code":"PPL",
    "gn:name":"Yoxford",
    "gn:population":0,
    "gn:timezone":"Africa/Johannesburg",
    "iso:country":"ZA",
    "name:ceb_x_preferred":[
        "Yoxford"
    ],
    "name:fas_x_preferred":[
        "\u06cc\u0648\u06a9\u0633\u0641\u0648\u0631\u062f"
    ],
    "name:nld_x_preferred":[
        "Yoxford"
    ],
    "name:pol_x_preferred":[
        "Yoxford"
    ],
    "name:spa_x_preferred":[
        "Yoxford"
    ],
    "name:swe_x_preferred":[
        "Yoxford"
    ],
    "wof:name":"Yoxford",
    "wof:placetype":"locality"
},
  "geometry": {"coordinates":[26.84787,-29.41338],"type":"Point"}
}