{
  "type": "Feature",
  "properties": {
    "gn:admin1_code":"5.0",
    "gn:admin2_code":"DC10",
    "gn:admin3_code":"EC104",
    "gn:asciiname":"Salem",
    "gn:country_code":"ZA",
    "gn:dem":225,
    "gn:feature_class":"P",
    "gn:feature_code":"PPL",
    "gn:name":"Salem",
    "gn:population":0,
    "gn:timezone":"Africa/Johannesburg",
    "iso:country":"ZA",
    "name:afr_x_preferred":[
        "Salem"
    ],
    "name:bre_x_preferred":[
        "Salem"
    ],
    "name:cat_x_preferred":[
        "Salem"
    ],
    "name:ceb_x_preferred":[
        "Salem"
    ],
    "name:ces_x_preferred":[
        "Salem"
    ],
    "name:cym_x_preferred":[
        "Salem"
    ],
    "name:dan_x_preferred":[
        "Salem"
    ],
    "name:deu_x_preferred":[
        "Salem"
    ],
    "name:epo_x_preferred":[
        "Salem"
    ],
    "name:est_x_preferred":[
        "Salem"
    ],
    "name:eus_x_preferred":[
        "Salem"
    ],
    "name:fas_x_preferred":[
        "\u0633\u06cc\u0644\u0645"
    ],
    "name:fin_x_preferred":[
        "Salem"
    ],
    "name:fra_x_preferred":[
        "Salem"
    ],
    "name:heb_x_preferred":[
        "\u05e1\u05d0\u05dc\u05dd"
    ],
    "name:hun_x_preferred":[
        "Salem"
    ],
    "name:ind_x_preferred":[
        "Salem"
    ],
    "name:ita_x_preferred":[
        "Salem"
    ],
    "name:jpn_x_preferred":[
        "\u30bb\u30a4\u30e9\u30e0"
    ],
    "name:kor_x_preferred":[
        "\uc138\uc77c\ub7fc"
    ],
    "name:lat_x_preferred":[
        "Salem"
    ],
    "name:lim_x_preferred":[
        "Salem"
    ],
    "name:nld_x_preferred":[
        "Salem"
    ],
    "name:nno_x_preferred":[
        "Salem"
    ],
    "name:nor_x_preferred":[
        "Salem"
    ],
    "name:pol_x_preferred":[
        "Salem"
    ],
    "name:por_x_preferred":[
        "Sal\u00e9m"
    ],
    "name:ron_x_preferred":[
        "Salem"
    ],
    "name:rus_x_preferred":[
        "\u0421\u0435\u0439\u043b\u0435\u043c"
    ],
    "name:slk_x_preferred":[
        "Salem"
    ],
    "name:spa_x_preferred":[
        "Salem"
    ],
    "name:srp_x_preferred":[
        "\u0421\u0435\u0458\u043b\u0435\u043c"
    ],
    "name:swa_x_preferred":[
        "Salem"
    ],
    "name:swe_x_preferred":[
        "Salem"
    ],
    "name:tur_x_preferred":[
        "Salem"
    ],
    "name:ukr_x_preferred":[
        "\u0421\u0435\u0439\u043b\u0435\u043c"
    ],
    "name:urd_x_preferred":[
        "\u0633\u06cc\u0644\u0645"
    ],
    "name:vie_x_preferred":[
        "Salem"
    ],
    "name:vol_x_preferred":[
        "Salem"
    ],
    "name:war_x_preferred":[
        "Salem"
    ],
    "name:zho_x_preferred":[
        "\u585e\u52d2\u59c6"
    ],
    "wof:name":"Salem",
    "wof:placetype":"locality"
},
  "geometry": {"coordinates":[26.48028,-33.46828],"type":"Point"}
}