{
  "type": "Feature",
  "properties": {
    "gn:admin1_code":"5.0",
    "gn:admin2_code":"DC10",
    "gn:admin3_code":"EC104",
    "gn:asciiname":"Salem",
    "gn:country_code":"ZA",
    "gn:dem":225,
    "gn:feature_class":"P",
    "gn:feature_code":"PPL",
    "gn:name":"Salem",
    "gn:population":0,
    "gn:timezone":"Africa/Johannesburg",
    "iso:country":"ZA",
    "wof:name":"Salem",
    "wof:placetype":"locality"
},
  "geometry": {"coordinates":[26.48028,-33.46828],"type":"Point"}
}