{
  "type": "Feature",
  "properties": {
    "gn:admin1_code":"5.0",
    "gn:admin2_code":"DC10",
    "gn:admin3_code":"EC101",
    "gn:asciiname":"Spandau",
    "gn:country_code":"ZA",
    "gn:dem":784,
    "gn:feature_class":"P",
    "gn:feature_code":"PPL",
    "gn:name":"Spandau",
    "gn:population":0,
    "gn:timezone":"Africa/Johannesburg",
    "iso:country":"ZA",
    "name:bre_x_preferred":[
        "Spandau"
    ],
    "name:dan_x_preferred":[
        "Spandau"
    ],
    "name:deu_x_preferred":[
        "Bezirk Spandau"
    ],
    "name:ell_x_preferred":[
        "\u03a3\u03c0\u03ac\u03bd\u03c4\u03b1\u03bf\u03c5"
    ],
    "name:epo_x_preferred":[
        "Spandau"
    ],
    "name:est_x_preferred":[
        "Spandau"
    ],
    "name:eus_x_preferred":[
        "Spandau"
    ],
    "name:fas_x_preferred":[
        "\u0634\u067e\u0627\u0646\u062f\u0627\u0648"
    ],
    "name:fin_x_preferred":[
        "Spandau"
    ],
    "name:heb_x_preferred":[
        "\u05e9\u05e4\u05e0\u05d3\u05d0\u05d5"
    ],
    "name:hrv_x_preferred":[
        "Spandau"
    ],
    "name:hsb_x_preferred":[
        "Spandawa"
    ],
    "name:ile_x_preferred":[
        "District Spandau"
    ],
    "name:ind_x_preferred":[
        "Spandau"
    ],
    "name:isl_x_preferred":[
        "Spandau"
    ],
    "name:jpn_x_preferred":[
        "\u30b7\u30e5\u30d1\u30f3\u30c0\u30a6\u533a"
    ],
    "name:kor_x_preferred":[
        "\uc288\ud310\ub2e4\uc6b0\uad6c"
    ],
    "name:lat_x_preferred":[
        "Spandavia"
    ],
    "name:mkd_x_preferred":[
        "\u0428\u043f\u0430\u043d\u0434\u0430\u0443"
    ],
    "name:nld_x_preferred":[
        "Spandau"
    ],
    "name:nno_x_preferred":[
        "Spandau"
    ],
    "name:nor_x_preferred":[
        "Spandau"
    ],
    "name:pol_x_preferred":[
        "Spandau"
    ],
    "name:por_x_preferred":[
        "Spandau"
    ],
    "name:ron_x_preferred":[
        "Sector Spandau"
    ],
    "name:rus_x_preferred":[
        "\u0428\u043f\u0430\u043d\u0434\u0430\u0443"
    ],
    "name:spa_x_preferred":[
        "Spandau"
    ],
    "name:srp_x_preferred":[
        "\u0428\u043f\u0430\u043d\u0434\u0430\u0443"
    ],
    "name:swe_x_preferred":[
        "Spandau"
    ],
    "name:tur_x_preferred":[
        "Spandau"
    ],
    "name:ukr_x_preferred":[
        "\u0428\u043f\u0430\u043d\u0434\u0430\u0443"
    ],
    "name:und_x_variant":[
        "Spandauville"
    ],
    "name:zho_x_preferred":[
        "\u65bd\u6f58\u9053"
    ],
    "wof:lang_x_official":[
        "eng"
    ],
    "wof:lang_x_spoken":[
        "eng",
        "zul",
        "xho",
        "afr",
        "nso",
        "tsn",
        "sot",
        "tso",
        "ssw",
        "ven",
        "nbl"
    ],
    "wof:name":"Spandau",
    "wof:placetype":"locality"
},
  "geometry": {"coordinates":[24.53157,-32.26681],"type":"Point"}
}