{
  "type": "Feature",
  "properties": {
    "gn:admin1_code":"5.0",
    "gn:admin2_code":"DC10",
    "gn:admin3_code":"EC101",
    "gn:asciiname":"Spandau",
    "gn:country_code":"ZA",
    "gn:dem":784,
    "gn:feature_class":"P",
    "gn:feature_code":"PPL",
    "gn:name":"Spandau",
    "gn:population":0,
    "gn:timezone":"Africa/Johannesburg",
    "iso:country":"ZA",
    "name:und_x_variant":[
        "Spandauville",
        "Spandau"
    ],
    "wof:name":"Spandau",
    "wof:placetype":"locality"
},
  "geometry": {"coordinates":[24.53157,-32.26681],"type":"Point"}
}