{
  "type": "Feature",
  "properties": {
    "gn:admin1_code":"10",
    "gn:asciiname":"Colston",
    "gn:country_code":"ZA",
    "gn:dem":1397,
    "gn:feature_class":"P",
    "gn:feature_code":"PPL",
    "gn:name":"Colston",
    "gn:population":0,
    "gn:timezone":"Africa/Johannesburg",
    "iso:country":"ZA",
    "name:eus_x_preferred":[
        "Colston"
    ],
    "wof:name":"Colston",
    "wof:placetype":"locality"
},
  "geometry": {"coordinates":[23.84648,-27.25958],"type":"Point"}
}