{
  "type": "Feature",
  "properties": {
    "gn:admin1_code":"2",
    "gn:admin2_code":"DC43",
    "gn:admin3_code":"KZN433",
    "gn:asciiname":"Nolangeni",
    "gn:country_code":"ZA",
    "gn:dem":1374,
    "gn:feature_class":"P",
    "gn:feature_code":"PPL",
    "gn:name":"Nolangeni",
    "gn:population":0,
    "gn:timezone":"Africa/Johannesburg",
    "iso:country":"ZA",
    "name:und_x_variant":[
        "Nolengeni",
        "Nolangeni"
    ],
    "wof:name":"Nolangeni",
    "wof:placetype":"locality"
},
  "geometry": {"coordinates":[29.41845,-30.62035],"type":"Point"}
}