{
  "type": "Feature",
  "properties": {
    "gn:admin1_code":"5",
    "gn:admin2_code":"DC12",
    "gn:admin3_code":"EC127",
    "gn:asciiname":"Argyle",
    "gn:country_code":"ZA",
    "gn:dem":595,
    "gn:feature_class":"P",
    "gn:feature_code":"PPL",
    "gn:name":"Argyle",
    "gn:population":0,
    "gn:timezone":"Africa/Johannesburg",
    "iso:country":"ZA",
    "name:bre_x_preferred":[
        "Argyle"
    ],
    "name:cat_x_preferred":[
        "Argyle"
    ],
    "name:ceb_x_preferred":[
        "Argyle"
    ],
    "name:ces_x_preferred":[
        "Argyle"
    ],
    "name:deu_x_preferred":[
        "Argyle"
    ],
    "name:fra_x_preferred":[
        "Argyle"
    ],
    "name:ita_x_preferred":[
        "Argyle"
    ],
    "name:jpn_x_preferred":[
        "\u30a2\u30fc\u30ac\u30a4\u30eb"
    ],
    "name:nld_x_preferred":[
        "Argyle"
    ],
    "name:pol_x_preferred":[
        "Argyle"
    ],
    "name:por_x_preferred":[
        "Argyle"
    ],
    "name:spa_x_preferred":[
        "Argyle"
    ],
    "name:srp_x_preferred":[
        "\u0410\u0440\u0433\u0430\u0458\u043b"
    ],
    "name:swe_x_preferred":[
        "Argyle"
    ],
    "name:vol_x_preferred":[
        "Argyle"
    ],
    "wof:name":"Argyle",
    "wof:placetype":"locality"
},
  "geometry": {"coordinates":[26.86667000000001,-32.71667],"type":"Point"}
}