{
  "type": "Feature",
  "properties": {
    "gn:admin1_code":"5",
    "gn:admin2_code":"DC12",
    "gn:admin3_code":"EC127",
    "gn:asciiname":"Argyle",
    "gn:country_code":"ZA",
    "gn:dem":595,
    "gn:feature_class":"P",
    "gn:feature_code":"PPL",
    "gn:name":"Argyle",
    "gn:population":0,
    "gn:timezone":"Africa/Johannesburg",
    "iso:country":"ZA",
    "wof:name":"Argyle",
    "wof:placetype":"locality"
},
  "geometry": {"coordinates":[26.86667000000001,-32.71667],"type":"Point"}
}