{
  "type": "Feature",
  "properties": {
    "gn:gn_country":"ZA",
    "gn:gn_fcode":"ADM3",
    "gn:gn_pop":82462,
    "gn:population":82462,
    "iso:country":"ZA",
    "qs_pg:aaroncc":"ZA",
    "qs_pg:gn_country":"ZA",
    "qs_pg:gn_fcode":"ADM3",
    "qs_pg:gn_pop":82462,
    "qs_pg:name":"Kagisano/Molopo",
    "qs_pg:photos_9r":0,
    "qs_pg:photos_sr":0,
    "qs_pg:pop_sr":8,
    "qs_pg:qs_pg_placetype":"localadmin",
    "wof:name":"Kagisano/Molopo",
    "wof:placetype":"localadmin",
    "wof:population":82462
},
  "geometry": {"coordinates":[23.76503,-26.11805],"type":"Point"}
}