{
  "type": "Feature",
  "properties": {
    "gn:admin1_code":"2",
    "gn:admin2_code":"DC29",
    "gn:admin3_code":"KZN293",
    "gn:asciiname":"eNgedleni",
    "gn:country_code":"ZA",
    "gn:dem":104,
    "gn:feature_class":"P",
    "gn:feature_code":"PPL",
    "gn:name":"eNgedleni",
    "gn:population":0,
    "gn:timezone":"Africa/Johannesburg",
    "iso:country":"ZA",
    "wof:name":"eNgedleni",
    "wof:placetype":"locality"
},
  "geometry": {"coordinates":[31.08652,-29.53334000000001],"type":"Point"}
}