{
  "type": "Feature",
  "properties": {
    "gn:admin1_code":"3.0",
    "gn:admin2_code":"DC16",
    "gn:admin3_code":"FS164",
    "gn:asciiname":"Stilfontein",
    "gn:country_code":"ZA",
    "gn:dem":1484,
    "gn:feature_class":"P",
    "gn:feature_code":"PPL",
    "gn:name":"Stilfontein",
    "gn:population":0,
    "gn:timezone":"Africa/Johannesburg",
    "iso:country":"ZA",
    "name:afr_x_preferred":[
        "Stilfontein"
    ],
    "name:ceb_x_preferred":[
        "Stilfontein"
    ],
    "name:deu_x_preferred":[
        "Stilfontein"
    ],
    "name:epo_x_preferred":[
        "Stilfontein"
    ],
    "name:est_x_preferred":[
        "Stilfontein"
    ],
    "name:fra_x_preferred":[
        "Stilfontein"
    ],
    "name:mlg_x_preferred":[
        "Stilfontein"
    ],
    "name:nld_x_preferred":[
        "Stilfontein"
    ],
    "name:nso_x_preferred":[
        "Stilfontein"
    ],
    "name:pol_x_preferred":[
        "Stilfontein"
    ],
    "name:ron_x_preferred":[
        "Stilfontein"
    ],
    "name:rus_x_preferred":[
        "\u0421\u0442\u0438\u043b\u0444\u043e\u043d\u0442\u0435\u0439\u043d"
    ],
    "name:tsn_x_preferred":[
        "Stilfontein"
    ],
    "wof:name":"Stilfontein",
    "wof:placetype":"locality"
},
  "geometry": {"coordinates":[26.59714,-29.49323],"type":"Point"}
}