{
  "type": "Feature",
  "properties": {
    "gn:admin1_code":"9.0",
    "gn:admin2_code":"DC35",
    "gn:admin3_code":"LIM355",
    "gn:asciiname":"Thabaneng",
    "gn:country_code":"ZA",
    "gn:dem":906,
    "gn:feature_class":"P",
    "gn:feature_code":"PPL",
    "gn:name":"Thabaneng",
    "gn:population":0,
    "gn:timezone":"Africa/Johannesburg",
    "iso:country":"ZA",
    "wof:name":"Thabaneng",
    "wof:placetype":"locality"
},
  "geometry": {"coordinates":[29.49049,-24.45609],"type":"Point"}
}