{
  "type": "Feature",
  "properties": {
    "iso:country":"ZA",
    "name:afr_x_preferred":[
        "Laingsburg"
    ],
    "name:ast_x_preferred":[
        "Laingsburg"
    ],
    "name:ceb_x_preferred":[
        "Laingsburg"
    ],
    "name:deu_x_preferred":[
        "Laingsburg"
    ],
    "name:eng_x_preferred":[
        "Laingsburg"
    ],
    "name:est_x_preferred":[
        "Laingsburg"
    ],
    "name:fra_x_preferred":[
        "Laingsburg"
    ],
    "name:ibo_x_preferred":[
        "Laingsburg"
    ],
    "name:ita_x_preferred":[
        "Laingsburg"
    ],
    "name:nld_x_preferred":[
        "Laingsburg"
    ],
    "name:nso_x_preferred":[
        "Laingsburg"
    ],
    "name:ron_x_preferred":[
        "Laingsburg"
    ],
    "name:rus_x_preferred":[
        "\u041b\u0430\u0439\u043d\u0433\u0441\u0431\u0443\u0440\u0433"
    ],
    "name:ven_x_preferred":[
        "Laingsburg"
    ],
    "name:zho_x_preferred":[
        "\u862d\u65af\u5821"
    ],
    "name:zul_x_preferred":[
        "ILaingsburg"
    ],
    "qs_pg:aaroncc":"ZA",
    "qs_pg:name":"Laingsburg",
    "qs_pg:name_adm0":"South Africa",
    "qs_pg:name_adm1":"Western Cape",
    "qs_pg:photos":9,
    "qs_pg:photos_1k":2,
    "qs_pg:photos_9k":1,
    "qs_pg:photos_9r":1,
    "qs_pg:photos_all":15,
    "qs_pg:photos_sr":1,
    "qs_pg:pop_sr":0,
    "qs_pg:qs_pg_placetype":"locality",
    "qs_pg:qs_pg_placetype_gp":"Town",
    "qs_pg:woe_adm0":23424942,
    "woe:adm0_id":23424942,
    "woe:name_adm0":"South Africa",
    "woe:name_adm1":"Western Cape",
    "woe:placetype":"Town",
    "wof:lang_x_official":[
        "eng"
    ],
    "wof:lang_x_spoken":[
        "eng",
        "zul",
        "xho",
        "afr",
        "nso",
        "tsn",
        "sot",
        "tso",
        "ssw",
        "ven",
        "nbl"
    ],
    "wof:name":"Laingsburg",
    "wof:placetype":"locality"
},
  "geometry": {"coordinates":[20.85326,-33.204222],"type":"Point"}
}