{
  "type": "Feature",
  "properties": {
    "gn:admin1_code":"11.0",
    "gn:admin2_code":"DC4",
    "gn:admin3_code":"WC043",
    "gn:asciiname":"Ruitersbos",
    "gn:country_code":"ZA",
    "gn:dem":316,
    "gn:feature_class":"P",
    "gn:feature_code":"PPL",
    "gn:name":"Ruitersbos",
    "gn:population":0,
    "gn:timezone":"Africa/Johannesburg",
    "iso:country":"ZA",
    "name:und_x_variant":[
        "Ruytersbosch",
        "Ruiterbosch",
        "Ruitersbos"
    ],
    "wof:lang_x_official":[
        "eng"
    ],
    "wof:lang_x_spoken":[
        "eng",
        "zul",
        "xho",
        "afr",
        "nso",
        "tsn",
        "sot",
        "tso",
        "ssw",
        "ven",
        "nbl"
    ],
    "wof:name":"Ruitersbos",
    "wof:placetype":"locality"
},
  "geometry": {"coordinates":[22.03486,-33.94591],"type":"Point"}
}