{
  "type": "Feature",
  "properties": {
    "gn:admin1_code":"10",
    "gn:admin2_code":"DC38",
    "gn:admin3_code":"NW385",
    "gn:asciiname":"Maphephane",
    "gn:country_code":"ZA",
    "gn:dem":1134,
    "gn:feature_class":"P",
    "gn:feature_code":"PPL",
    "gn:name":"Maphephane",
    "gn:population":0,
    "gn:timezone":"Africa/Johannesburg",
    "iso:country":"ZA",
    "wof:name":"Maphephane",
    "wof:placetype":"locality"
},
  "geometry": {"coordinates":[25.80082,-25.22735],"type":"Point"}
}