{
  "type": "Feature",
  "properties": {
    "gn:admin1_code":"9",
    "gn:admin2_code":"DC33",
    "gn:admin3_code":"LIM335",
    "gn:asciiname":"Mdlazi",
    "gn:country_code":"ZA",
    "gn:dem":493,
    "gn:feature_class":"P",
    "gn:feature_code":"PPL",
    "gn:name":"Mdlazi",
    "gn:population":0,
    "gn:timezone":"Africa/Johannesburg",
    "iso:country":"ZA",
    "wof:name":"Mdlazi",
    "wof:placetype":"locality"
},
  "geometry": {"coordinates":[30.90557,-24.3679],"type":"Point"}
}