{
  "type": "Feature",
  "properties": {
    "gn:admin1_code":"5",
    "gn:admin2_code":"DC12",
    "gn:admin3_code":"EC127",
    "gn:asciiname":"Kwa-Nomadola",
    "gn:country_code":"ZA",
    "gn:dem":747,
    "gn:feature_class":"P",
    "gn:feature_code":"PPL",
    "gn:name":"Kwa-Nomadola",
    "gn:population":0,
    "gn:timezone":"Africa/Johannesburg",
    "iso:country":"ZA",
    "wof:name":"Kwa-Nomadola",
    "wof:placetype":"locality"
},
  "geometry": {"coordinates":[26.94475,-32.66465],"type":"Point"}
}