{
  "type": "Feature",
  "properties": {
    "gn:admin1_code":"5",
    "gn:admin2_code":"DC14",
    "gn:admin3_code":"EC143",
    "gn:asciiname":"Goedehoop",
    "gn:country_code":"ZA",
    "gn:dem":1355,
    "gn:feature_class":"P",
    "gn:feature_code":"PPL",
    "gn:name":"Goedehoop",
    "gn:population":0,
    "gn:timezone":"Africa/Johannesburg",
    "iso:country":"ZA",
    "name:afr_x_preferred":[
        "Goedehoop"
    ],
    "name:est_x_preferred":[
        "Goedehoop"
    ],
    "name:nso_x_preferred":[
        "Goedehoop"
    ],
    "wof:name":"Goedehoop",
    "wof:placetype":"locality"
},
  "geometry": {"coordinates":[26.90589000000001,-30.82228],"type":"Point"}
}