{
  "type": "Feature",
  "properties": {
    "gn:admin1_code":"8.0",
    "gn:admin2_code":"DC9",
    "gn:admin3_code":"NC091",
    "gn:asciiname":"Rooipan",
    "gn:country_code":"ZA",
    "gn:dem":1113,
    "gn:feature_class":"P",
    "gn:feature_code":"PPL",
    "gn:name":"Rooipan",
    "gn:population":0,
    "gn:timezone":"Africa/Johannesburg",
    "iso:country":"ZA",
    "wof:name":"Rooipan",
    "wof:placetype":"locality"
},
  "geometry": {"coordinates":[24.34389,-28.77752000000001],"type":"Point"}
}