{
  "type": "Feature",
  "properties": {
    "gn:admin1_code":"3.0",
    "gn:admin2_code":"DC16",
    "gn:admin3_code":"FS163",
    "gn:asciiname":"Skaapkraal",
    "gn:country_code":"ZA",
    "gn:dem":1459,
    "gn:feature_class":"P",
    "gn:feature_code":"PPL",
    "gn:name":"Skaapkraal",
    "gn:population":0,
    "gn:timezone":"Africa/Johannesburg",
    "iso:country":"ZA",
    "wof:name":"Skaapkraal",
    "wof:placetype":"locality"
},
  "geometry": {"coordinates":[26.67018,-30.0849],"type":"Point"}
}