{
  "type": "Feature",
  "properties": {
    "gn:admin1_code":"5",
    "gn:admin2_code":"DC15",
    "gn:admin3_code":"EC155",
    "gn:asciiname":"Mgwenyana",
    "gn:country_code":"ZA",
    "gn:dem":307,
    "gn:feature_class":"P",
    "gn:feature_code":"PPL",
    "gn:name":"Mgwenyana",
    "gn:population":0,
    "gn:timezone":"Africa/Johannesburg",
    "iso:country":"ZA",
    "name:und_x_variant":[
        "Nkwanyana",
        "Mgwenjana",
        "Mgwenyana"
    ],
    "wof:name":"Mgwenyana",
    "wof:placetype":"locality"
},
  "geometry": {"coordinates":[29.23334,-31.55544],"type":"Point"}
}