{
  "type": "Feature",
  "properties": {
    "gn:admin1_code":"11.0",
    "gn:admin2_code":"DC2",
    "gn:admin3_code":"WC023",
    "gn:asciiname":"Test",
    "gn:country_code":"ZA",
    "gn:dem":124,
    "gn:feature_class":"P",
    "gn:feature_code":"PPL",
    "gn:name":"Test",
    "gn:population":0,
    "gn:timezone":"Africa/Johannesburg",
    "iso:country":"ZA",
    "wof:name":"Test",
    "wof:placetype":"locality"
},
  "geometry": {"coordinates":[18.98163,-33.73576],"type":"Point"}
}