{
  "type": "Feature",
  "properties": {
    "gn:admin1_code":"11.0",
    "gn:admin2_code":"DC2",
    "gn:admin3_code":"WC023",
    "gn:asciiname":"Test",
    "gn:country_code":"ZA",
    "gn:dem":124,
    "gn:feature_class":"P",
    "gn:feature_code":"PPL",
    "gn:name":"Test",
    "gn:population":0,
    "gn:timezone":"Africa/Johannesburg",
    "iso:country":"ZA",
    "name:ara_x_preferred":[
        "\u0627\u062e\u062a\u0628\u0627\u0631"
    ],
    "name:aze_x_preferred":[
        "Test"
    ],
    "name:bul_x_preferred":[
        "\u0422\u0435\u0441\u0442"
    ],
    "name:cat_x_preferred":[
        "Test"
    ],
    "name:ces_x_preferred":[
        "Testov\u00e1n\u00ed"
    ],
    "name:dan_x_preferred":[
        "Test"
    ],
    "name:deu_x_preferred":[
        "Test"
    ],
    "name:eus_x_preferred":[
        "Test"
    ],
    "name:fas_x_preferred":[
        "\u062a\u0633\u062a"
    ],
    "name:fra_x_preferred":[
        "Test"
    ],
    "name:hun_x_preferred":[
        "Test"
    ],
    "name:ita_x_preferred":[
        "Test"
    ],
    "name:jpn_x_preferred":[
        "\u30c6\u30b9\u30c8"
    ],
    "name:kir_x_preferred":[
        "\u0422\u0435\u0441\u0442"
    ],
    "name:kor_x_preferred":[
        "\ud14c\uc2a4\ud2b8"
    ],
    "name:nld_x_preferred":[
        "Test"
    ],
    "name:nor_x_preferred":[
        "Test"
    ],
    "name:pol_x_preferred":[
        "Test"
    ],
    "name:ron_x_preferred":[
        "Test"
    ],
    "name:rus_x_preferred":[
        "\u0422\u0435\u0441\u0442"
    ],
    "name:slk_x_preferred":[
        "Test"
    ],
    "name:spa_x_preferred":[
        "Test"
    ],
    "name:swe_x_preferred":[
        "Test"
    ],
    "name:tha_x_preferred":[
        "Test"
    ],
    "name:tur_x_preferred":[
        "Test"
    ],
    "name:ukr_x_preferred":[
        "\u0422\u0435\u0441\u0442"
    ],
    "wof:lang_x_official":[
        "eng"
    ],
    "wof:lang_x_spoken":[
        "eng",
        "zul",
        "xho",
        "afr",
        "nso",
        "tsn",
        "sot",
        "tso",
        "ssw",
        "ven",
        "nbl"
    ],
    "wof:name":"Test",
    "wof:placetype":"locality"
},
  "geometry": {"coordinates":[18.98163,-33.73576],"type":"Point"}
}