{
  "type": "Feature",
  "properties": {
    "gn:admin1_code":"2",
    "gn:admin2_code":"DC28",
    "gn:admin3_code":"KZN281",
    "gn:asciiname":"Mfolozi",
    "gn:country_code":"ZA",
    "gn:dem":51,
    "gn:feature_class":"P",
    "gn:feature_code":"PPL",
    "gn:name":"Mfolozi",
    "gn:population":0,
    "gn:timezone":"Africa/Johannesburg",
    "iso:country":"ZA",
    "wof:name":"Mfolozi",
    "wof:placetype":"locality"
},
  "geometry": {"coordinates":[32.16919,-28.48805],"type":"Point"}
}