{
  "type": "Feature",
  "properties": {
    "gn:admin1_code":"11.0",
    "gn:admin2_code":"DC1",
    "gn:admin3_code":"WC014",
    "gn:asciiname":"Jacobs Bay",
    "gn:country_code":"ZA",
    "gn:dem":18,
    "gn:feature_class":"P",
    "gn:feature_code":"PPL",
    "gn:name":"Jacobs Bay",
    "gn:population":0,
    "gn:timezone":"Africa/Johannesburg",
    "iso:country":"ZA",
    "wof:name":"Jacobs Bay",
    "wof:placetype":"locality"
},
  "geometry": {"coordinates":[17.89398,-32.97209],"type":"Point"}
}