{
  "type": "Feature",
  "properties": {
    "gn:admin1_code":"2",
    "gn:admin2_code":"DC21",
    "gn:admin3_code":"KZN214",
    "gn:asciiname":"Brookland",
    "gn:country_code":"ZA",
    "gn:dem":1098,
    "gn:feature_class":"P",
    "gn:feature_code":"PPL",
    "gn:name":"Brookland",
    "gn:population":0,
    "gn:timezone":"Africa/Johannesburg",
    "iso:country":"ZA",
    "name:ceb_x_preferred":[
        "Brookland"
    ],
    "name:deu_x_preferred":[
        "Brookland"
    ],
    "name:fra_x_preferred":[
        "Brookland"
    ],
    "name:ita_x_preferred":[
        "Brookland"
    ],
    "name:nld_x_preferred":[
        "Brookland"
    ],
    "name:pol_x_preferred":[
        "Brookland"
    ],
    "name:spa_x_preferred":[
        "Brookland"
    ],
    "name:swe_x_preferred":[
        "Brookland"
    ],
    "name:und_x_variant":[
        "Middlebrook"
    ],
    "wof:lang_x_official":[
        "eng"
    ],
    "wof:lang_x_spoken":[
        "eng",
        "zul",
        "xho",
        "afr",
        "nso",
        "tsn",
        "sot",
        "tso",
        "ssw",
        "ven",
        "nbl"
    ],
    "wof:name":"Brookland",
    "wof:placetype":"locality"
},
  "geometry": {"coordinates":[29.7845,-30.55886],"type":"Point"}
}