{
  "type": "Feature",
  "properties": {
    "gn:admin1_code":"2",
    "gn:admin2_code":"DC21",
    "gn:admin3_code":"KZN214",
    "gn:asciiname":"Brookland",
    "gn:country_code":"ZA",
    "gn:dem":1098,
    "gn:feature_class":"P",
    "gn:feature_code":"PPL",
    "gn:name":"Brookland",
    "gn:population":0,
    "gn:timezone":"Africa/Johannesburg",
    "iso:country":"ZA",
    "name:und_x_variant":[
        "Middlebrook",
        "Brookland"
    ],
    "wof:name":"Brookland",
    "wof:placetype":"locality"
},
  "geometry": {"coordinates":[29.7845,-30.55886],"type":"Point"}
}