{
  "type": "Feature",
  "properties": {
    "gn:admin1_code":"9",
    "gn:asciiname":"Orinoco",
    "gn:country_code":"ZA",
    "gn:dem":613,
    "gn:feature_class":"P",
    "gn:feature_code":"PPL",
    "gn:name":"Orinoco",
    "gn:population":0,
    "gn:timezone":"Africa/Johannesburg",
    "iso:country":"ZA",
    "wof:name":"Orinoco",
    "wof:placetype":"locality"
},
  "geometry": {"coordinates":[31.07919,-24.76913],"type":"Point"}
}