{
  "type": "Feature",
  "properties": {
    "gn:admin1_code":"7",
    "gn:admin2_code":"DC31",
    "gn:admin3_code":"MP311",
    "gn:asciiname":"Rietkol",
    "gn:country_code":"ZA",
    "gn:dem":1600,
    "gn:feature_class":"P",
    "gn:feature_code":"PPL",
    "gn:name":"Rietkol",
    "gn:population":0,
    "gn:timezone":"Africa/Johannesburg",
    "iso:country":"ZA",
    "name:afr_x_preferred":[
        "Rietkol"
    ],
    "name:est_x_preferred":[
        "Rietkol"
    ],
    "name:nso_x_preferred":[
        "Rietkol"
    ],
    "name:pol_x_preferred":[
        "Rietkol"
    ],
    "wof:lang_x_official":[
        "eng"
    ],
    "wof:lang_x_spoken":[
        "eng",
        "zul",
        "xho",
        "afr",
        "nso",
        "tsn",
        "sot",
        "tso",
        "ssw",
        "ven",
        "nbl"
    ],
    "wof:name":"Rietkol",
    "wof:placetype":"locality"
},
  "geometry": {"coordinates":[28.58745,-26.15841],"type":"Point"}
}