{
  "type": "Feature",
  "properties": {
    "gn:admin1_code":"3",
    "gn:admin2_code":"DC18",
    "gn:admin3_code":"FS182",
    "gn:asciiname":"Kromkuilplaas",
    "gn:country_code":"ZA",
    "gn:dem":1223,
    "gn:feature_class":"P",
    "gn:feature_code":"PPL",
    "gn:name":"Kromkuilplaas",
    "gn:population":0,
    "gn:timezone":"Africa/Johannesburg",
    "iso:country":"ZA",
    "wof:name":"Kromkuilplaas",
    "wof:placetype":"locality"
},
  "geometry": {"coordinates":[25.53333,-28.76667],"type":"Point"}
}