{
  "type": "Feature",
  "properties": {
    "iso:country":"ZA",
    "name:eng_x_preferred":[
        "Monument"
    ],
    "name:unk_x_variant":[
        "Monument"
    ],
    "qs:gn_local":0,
    "qs:local_max":135,
    "qs:local_sum":151,
    "qs:localhoods":2,
    "qs:name":"Monument",
    "qs:name_adm0":"South Africa",
    "qs:name_adm1":"Gauteng",
    "qs:name_adm2":"West Rand",
    "qs:name_lau":"Mogale City",
    "qs:name_local":"Krugersdorp",
    "qs:photo_max":115,
    "qs:photo_sum":135,
    "qs:placetype":"Suburb",
    "qs:quad_count":8,
    "qs:woe_adm0":23424942,
    "qs:woe_adm1":2346981,
    "qs:woe_adm2":56189447,
    "qs:woe_lau":56189544,
    "qs:woe_local":1583081,
    "qs:woe_ver":"7.10.0",
    "wof:lang":[
        "eng"
    ],
    "wof:name":"Monument",
    "wof:placetype":"neighbourhood"
},
  "geometry": {"coordinates":[27.802053,-26.086544],"type":"Point"}
}