{
  "type": "Feature",
  "properties": {
    "gn:admin1_code":"9",
    "gn:admin2_code":"DC35",
    "gn:admin3_code":"LIM355",
    "gn:asciiname":"Good-Hope",
    "gn:country_code":"ZA",
    "gn:dem":1202,
    "gn:feature_class":"P",
    "gn:feature_code":"PPL",
    "gn:name":"Good-Hope",
    "gn:population":0,
    "gn:timezone":"Africa/Johannesburg",
    "iso:country":"ZA",
    "wof:name":"Good-Hope",
    "wof:placetype":"locality"
},
  "geometry": {"coordinates":[29.8233,-24.00908],"type":"Point"}
}