{
  "type": "Feature",
  "properties": {
    "gn:admin1_code":"2",
    "gn:admin2_code":"DC29",
    "gn:admin3_code":"KZN293",
    "gn:asciiname":"Kruisfontein",
    "gn:country_code":"ZA",
    "gn:dem":248,
    "gn:feature_class":"P",
    "gn:feature_code":"PPL",
    "gn:name":"Kruisfontein",
    "gn:population":0,
    "gn:timezone":"Africa/Johannesburg",
    "iso:country":"ZA",
    "name:afr_x_preferred":[
        "Kruisfontein"
    ],
    "name:nld_x_preferred":[
        "Kruisfontein"
    ],
    "name:nso_x_preferred":[
        "Kruisfontein"
    ],
    "name:ron_x_preferred":[
        "Kruisfontein"
    ],
    "name:sot_x_preferred":[
        "Kruisfontein"
    ],
    "wof:name":"Kruisfontein",
    "wof:placetype":"locality"
},
  "geometry": {"coordinates":[31.03333,-29.46667],"type":"Point"}
}