{
  "type": "Feature",
  "properties": {
    "gn:admin1_code":"10",
    "gn:asciiname":"Morpeth",
    "gn:country_code":"ZA",
    "gn:dem":1223,
    "gn:feature_class":"P",
    "gn:feature_code":"PPL",
    "gn:name":"Morpeth",
    "gn:population":0,
    "gn:timezone":"Africa/Johannesburg",
    "iso:country":"ZA",
    "name:ceb_x_preferred":[
        "Morpeth"
    ],
    "name:deu_x_preferred":[
        "Morpeth"
    ],
    "name:fra_x_preferred":[
        "Morpeth"
    ],
    "name:swe_x_preferred":[
        "Morpeth"
    ],
    "name:vol_x_preferred":[
        "Morpeth"
    ],
    "wof:lang_x_official":[
        "eng"
    ],
    "wof:lang_x_spoken":[
        "eng",
        "zul",
        "xho",
        "afr",
        "nso",
        "tsn",
        "sot",
        "tso",
        "ssw",
        "ven",
        "nbl"
    ],
    "wof:name":"Morpeth",
    "wof:placetype":"locality"
},
  "geometry": {"coordinates":[23.48197,-26.9425],"type":"Point"}
}