{
  "type": "Feature",
  "properties": {
    "gn:admin1_code":"10",
    "gn:asciiname":"Morpeth",
    "gn:country_code":"ZA",
    "gn:dem":1223,
    "gn:feature_class":"P",
    "gn:feature_code":"PPL",
    "gn:name":"Morpeth",
    "gn:population":0,
    "gn:timezone":"Africa/Johannesburg",
    "iso:country":"ZA",
    "wof:name":"Morpeth",
    "wof:placetype":"locality"
},
  "geometry": {"coordinates":[23.48197,-26.9425],"type":"Point"}
}