{
  "type": "Feature",
  "properties": {
    "gn:admin1_code":"6",
    "gn:admin2_code":"DC42",
    "gn:admin3_code":"GT422",
    "gn:asciiname":"Kliprivier",
    "gn:country_code":"ZA",
    "gn:dem":1468,
    "gn:feature_class":"P",
    "gn:feature_code":"PPL",
    "gn:name":"Kliprivier",
    "gn:population":0,
    "gn:timezone":"Africa/Johannesburg",
    "iso:country":"ZA",
    "name:afr_x_preferred":[
        "Kliprivier"
    ],
    "name:nso_x_preferred":[
        "Kliprivier"
    ],
    "name:und_x_variant":[
        "Klip River",
        "Kliprivier"
    ],
    "wof:name":"Kliprivier",
    "wof:placetype":"locality"
},
  "geometry": {"coordinates":[28.00501,-26.5777],"type":"Point"}
}