{
  "type": "Feature",
  "properties": {
    "gn:admin1_code":"10",
    "gn:asciiname":"Lotlhakane",
    "gn:country_code":"ZA",
    "gn:dem":1346,
    "gn:feature_class":"P",
    "gn:feature_code":"PPL",
    "gn:name":"Lotlhakane",
    "gn:population":0,
    "gn:timezone":"Africa/Johannesburg",
    "iso:country":"ZA",
    "name:fra_x_preferred":[
        "Lotlhakane"
    ],
    "name:ita_x_preferred":[
        "Lotlhakane"
    ],
    "name:mlg_x_preferred":[
        "Lotlhakane"
    ],
    "name:nld_x_preferred":[
        "Lotlhakane"
    ],
    "name:pol_x_preferred":[
        "Lotlhakane"
    ],
    "name:spa_x_preferred":[
        "Lotlhakane"
    ],
    "name:swa_x_preferred":[
        "Lotlhakane"
    ],
    "name:swe_x_preferred":[
        "Lotlhakane"
    ],
    "wof:lang_x_official":[
        "eng"
    ],
    "wof:lang_x_spoken":[
        "eng",
        "zul",
        "xho",
        "afr",
        "nso",
        "tsn",
        "sot",
        "tso",
        "ssw",
        "ven",
        "nbl"
    ],
    "wof:name":"Lotlhakane",
    "wof:placetype":"locality"
},
  "geometry": {"coordinates":[23.81023,-27.14965],"type":"Point"}
}