{
  "type": "Feature",
  "properties": {
    "gn:admin1_code":"5",
    "gn:admin2_code":"DC13",
    "gn:admin3_code":"EC133",
    "gn:asciiname":"Penryn",
    "gn:country_code":"ZA",
    "gn:dem":1729,
    "gn:feature_class":"P",
    "gn:feature_code":"PPL",
    "gn:name":"Penryn",
    "gn:population":0,
    "gn:timezone":"Africa/Johannesburg",
    "iso:country":"ZA",
    "name:ceb_x_preferred":[
        "Penryn"
    ],
    "name:deu_x_preferred":[
        "Penryn"
    ],
    "name:fra_x_preferred":[
        "Penryn"
    ],
    "name:ita_x_preferred":[
        "Penryn"
    ],
    "name:nor_x_preferred":[
        "Penryn"
    ],
    "name:pol_x_preferred":[
        "Penryn"
    ],
    "name:srp_x_preferred":[
        "\u041f\u0435\u043d\u0440\u0435\u043d"
    ],
    "wof:name":"Penryn",
    "wof:placetype":"locality"
},
  "geometry": {"coordinates":[26.45173,-31.42247],"type":"Point"}
}