{
  "type": "Feature",
  "properties": {
    "gn:admin1_code":"2.0",
    "gn:admin2_code":"DC23",
    "gn:admin3_code":"KZN235",
    "gn:asciiname":"Shambles",
    "gn:country_code":"ZA",
    "gn:dem":1213,
    "gn:feature_class":"P",
    "gn:feature_code":"PPL",
    "gn:name":"Shambles",
    "gn:population":0,
    "gn:timezone":"Africa/Johannesburg",
    "iso:country":"ZA",
    "name:ita_x_preferred":[
        "Shambles"
    ],
    "wof:lang_x_official":[
        "eng"
    ],
    "wof:lang_x_spoken":[
        "eng",
        "zul",
        "xho",
        "afr",
        "nso",
        "tsn",
        "sot",
        "tso",
        "ssw",
        "ven",
        "nbl"
    ],
    "wof:name":"Shambles",
    "wof:placetype":"locality"
},
  "geometry": {"coordinates":[29.08333,-28.66667],"type":"Point"}
}