{
  "type": "Feature",
  "properties": {
    "gn:admin1_code":"9.0",
    "gn:admin2_code":"DC47",
    "gn:admin3_code":"LIM475",
    "gn:asciiname":"Taung",
    "gn:country_code":"ZA",
    "gn:dem":609,
    "gn:feature_class":"P",
    "gn:feature_code":"PPL",
    "gn:name":"Taung",
    "gn:population":0,
    "gn:timezone":"Africa/Johannesburg",
    "iso:country":"ZA",
    "name:afr_x_preferred":[
        "Taung"
    ],
    "name:ast_x_preferred":[
        "Taung"
    ],
    "name:deu_x_preferred":[
        "Taung"
    ],
    "name:est_x_preferred":[
        "Taung"
    ],
    "name:fra_x_preferred":[
        "Taung"
    ],
    "name:hye_x_preferred":[
        "\u0539\u0561\u0578\u0582\u0576\u0563"
    ],
    "name:ita_x_preferred":[
        "Taung"
    ],
    "name:nor_x_preferred":[
        "Taung"
    ],
    "name:nso_x_preferred":[
        "Taung"
    ],
    "name:pol_x_preferred":[
        "Taung"
    ],
    "name:ron_x_preferred":[
        "Taung"
    ],
    "name:rus_x_preferred":[
        "\u0422\u0430\u0443\u043d\u0433"
    ],
    "name:spa_x_preferred":[
        "Taung"
    ],
    "name:srp_x_preferred":[
        "\u0422\u0430\u0443\u043d\u0433"
    ],
    "name:tsn_x_preferred":[
        "Taung"
    ],
    "name:tur_x_preferred":[
        "Taung"
    ],
    "wof:lang_x_official":[
        "eng"
    ],
    "wof:lang_x_spoken":[
        "eng",
        "zul",
        "xho",
        "afr",
        "nso",
        "tsn",
        "sot",
        "tso",
        "ssw",
        "ven",
        "nbl"
    ],
    "wof:name":"Taung",
    "wof:placetype":"locality"
},
  "geometry": {"coordinates":[30.41667,-24.48333],"type":"Point"}
}