{
  "type": "Feature",
  "properties": {
    "gn:admin1_code":"3.0",
    "gn:admin2_code":"MAN",
    "gn:admin3_code":"MAN",
    "gn:asciiname":"Wilhelmshohe",
    "gn:country_code":"ZA",
    "gn:dem":1392,
    "gn:feature_class":"P",
    "gn:feature_code":"PPL",
    "gn:name":"Wilhelmsh\u00f6he",
    "gn:population":0,
    "gn:timezone":"Africa/Johannesburg",
    "iso:country":"ZA",
    "wof:name":"Wilhelmshohe",
    "wof:placetype":"locality"
},
  "geometry": {"coordinates":[26.08165,-29.38371],"type":"Point"}
}