{
  "type": "Feature",
  "properties": {
    "gn:admin1_code":"9",
    "gn:admin2_code":"DC35",
    "gn:admin3_code":"LIM355",
    "gn:asciiname":"Ramorake",
    "gn:country_code":"ZA",
    "gn:dem":850,
    "gn:feature_class":"P",
    "gn:feature_code":"PPL",
    "gn:name":"Ramorake",
    "gn:population":0,
    "gn:timezone":"Africa/Johannesburg",
    "iso:country":"ZA",
    "wof:name":"Ramorake",
    "wof:placetype":"locality"
},
  "geometry": {"coordinates":[29.67938,-24.31667],"type":"Point"}
}