{
  "type": "Feature",
  "properties": {
    "gn:admin1_code":"9.0",
    "gn:admin2_code":"DC34",
    "gn:admin3_code":"LIM343",
    "gn:asciiname":"Shingwidzi",
    "gn:country_code":"ZA",
    "gn:dem":481,
    "gn:feature_class":"P",
    "gn:feature_code":"PPL",
    "gn:name":"Shingwidzi",
    "gn:population":0,
    "gn:timezone":"Africa/Johannesburg",
    "iso:country":"ZA",
    "wof:name":"Shingwidzi",
    "wof:placetype":"locality"
},
  "geometry": {"coordinates":[30.78333,-22.86667000000001],"type":"Point"}
}