{
  "type": "Feature",
  "properties": {
    "gn:admin1_code":"2",
    "gn:admin2_code":"DC23",
    "gn:admin3_code":"KZN235",
    "gn:asciiname":"Kruisfontein",
    "gn:country_code":"ZA",
    "gn:dem":1268,
    "gn:feature_class":"P",
    "gn:feature_code":"PPL",
    "gn:name":"Kruisfontein",
    "gn:population":0,
    "gn:timezone":"Africa/Johannesburg",
    "iso:country":"ZA",
    "wof:name":"Kruisfontein",
    "wof:placetype":"locality"
},
  "geometry": {"coordinates":[29.10357,-28.62587000000001],"type":"Point"}
}