{
  "type": "Feature",
  "properties": {
    "gn:admin1_code":"5",
    "gn:admin2_code":"DC15",
    "gn:admin3_code":"EC155",
    "gn:asciiname":"Bidiza",
    "gn:country_code":"ZA",
    "gn:dem":769,
    "gn:feature_class":"P",
    "gn:feature_code":"PPL",
    "gn:name":"Bidiza",
    "gn:population":0,
    "gn:timezone":"Africa/Johannesburg",
    "iso:country":"ZA",
    "wof:name":"Bidiza",
    "wof:placetype":"locality"
},
  "geometry": {"coordinates":[28.85221,-31.62172],"type":"Point"}
}