{
  "type": "Feature",
  "properties": {
    "gn:admin1_code":"7",
    "gn:admin2_code":"DC31",
    "gn:admin3_code":"MP316",
    "gn:asciiname":"Dikgwale",
    "gn:cc2":"ZA",
    "gn:country_code":"ZA",
    "gn:dem":1005,
    "gn:feature_class":"P",
    "gn:feature_code":"PPL",
    "gn:name":"Dikgwale",
    "gn:population":0,
    "gn:timezone":"Africa/Johannesburg",
    "iso:country":"ZA",
    "name:und_x_variant":[
        "Dikgale",
        "Dikgwale"
    ],
    "wof:lang_x_official":[
        "eng"
    ],
    "wof:lang_x_spoken":[
        "eng",
        "zul",
        "xho",
        "afr",
        "nso",
        "tsn",
        "sot",
        "tso",
        "ssw",
        "ven",
        "nbl"
    ],
    "wof:name":"Dikgwale",
    "wof:placetype":"locality"
},
  "geometry": {"coordinates":[28.91861,-25.205],"type":"Point"}
}