{
  "type": "Feature",
  "properties": {
    "gn:admin1_code":"5",
    "gn:admin2_code":"DC12",
    "gn:admin3_code":"EC126",
    "gn:asciiname":"KwaMvemve",
    "gn:country_code":"ZA",
    "gn:dem":267,
    "gn:feature_class":"P",
    "gn:feature_code":"PPL",
    "gn:name":"KwaMvemve",
    "gn:population":0,
    "gn:timezone":"Africa/Johannesburg",
    "iso:country":"ZA",
    "wof:name":"KwaMvemve",
    "wof:placetype":"locality"
},
  "geometry": {"coordinates":[27.17557,-33.2078],"type":"Point"}
}