{
  "type": "Feature",
  "properties": {
    "gn:admin1_code":"5",
    "gn:admin2_code":"DC14",
    "gn:admin3_code":"EC143",
    "gn:asciiname":"Korenhof",
    "gn:country_code":"ZA",
    "gn:dem":1398,
    "gn:feature_class":"P",
    "gn:feature_code":"PPL",
    "gn:name":"Korenhof",
    "gn:population":0,
    "gn:timezone":"Africa/Johannesburg",
    "iso:country":"ZA",
    "wof:name":"Korenhof",
    "wof:placetype":"locality"
},
  "geometry": {"coordinates":[26.51667,-30.76667],"type":"Point"}
}