{
  "type": "Feature",
  "properties": {
    "gn:admin1_code":"7",
    "gn:admin2_code":"DC30",
    "gn:admin3_code":"MP306",
    "gn:asciiname":"Ellisdale",
    "gn:country_code":"ZA",
    "gn:dem":1573,
    "gn:feature_class":"P",
    "gn:feature_code":"PPL",
    "gn:name":"Ellisdale",
    "gn:population":0,
    "gn:timezone":"Africa/Johannesburg",
    "iso:country":"ZA",
    "wof:name":"Ellisdale",
    "wof:placetype":"locality"
},
  "geometry": {"coordinates":[28.82875,-26.76807],"type":"Point"}
}