{
  "type": "Feature",
  "properties": {
    "gn:admin1_code":"5",
    "gn:admin2_code":"DC12",
    "gn:admin3_code":"EC121",
    "gn:asciiname":"Ebufumbu",
    "gn:country_code":"ZA",
    "gn:dem":408,
    "gn:feature_class":"P",
    "gn:feature_code":"PPL",
    "gn:name":"Ebufumbu",
    "gn:population":0,
    "gn:timezone":"Africa/Johannesburg",
    "iso:country":"ZA",
    "name:und_x_variant":[
        "Ebufumbe",
        "Ebufumbu"
    ],
    "wof:name":"Ebufumbu",
    "wof:placetype":"locality"
},
  "geometry": {"coordinates":[28.93525,-31.97557],"type":"Point"}
}