{
  "type": "Feature",
  "properties": {
    "gn:admin1_code":"10",
    "gn:admin2_code":"DC38",
    "gn:admin3_code":"NW383",
    "gn:asciiname":"Heathview",
    "gn:country_code":"ZA",
    "gn:dem":1241,
    "gn:feature_class":"P",
    "gn:feature_code":"PPL",
    "gn:name":"Heathview",
    "gn:population":0,
    "gn:timezone":"Africa/Johannesburg",
    "iso:country":"ZA",
    "wof:name":"Heathview",
    "wof:placetype":"locality"
},
  "geometry": {"coordinates":[25.39108,-25.94467],"type":"Point"}
}