{
  "type": "Feature",
  "properties": {
    "gn:admin1_code":"5",
    "gn:admin2_code":"DC14",
    "gn:admin3_code":"EC142",
    "gn:asciiname":"Dulcies Nek",
    "gn:country_code":"ZA",
    "gn:dem":1648,
    "gn:feature_class":"P",
    "gn:feature_code":"PPL",
    "gn:name":"Dulcies Nek",
    "gn:population":0,
    "gn:timezone":"Africa/Johannesburg",
    "iso:country":"ZA",
    "wof:name":"Dulcies Nek",
    "wof:placetype":"locality"
},
  "geometry": {"coordinates":[27.45,-30.48333],"type":"Point"}
}