{
  "type": "Feature",
  "properties": {
    "gn:admin1_code":"5",
    "gn:admin2_code":"DC14",
    "gn:admin3_code":"EC144",
    "gn:asciiname":"Aylesby",
    "gn:country_code":"ZA",
    "gn:dem":1352,
    "gn:feature_class":"P",
    "gn:feature_code":"PPL",
    "gn:name":"Aylesby",
    "gn:population":0,
    "gn:timezone":"Africa/Johannesburg",
    "iso:country":"ZA",
    "name:ceb_x_preferred":[
        "Aylesby"
    ],
    "name:cym_x_preferred":[
        "Aylesby"
    ],
    "name:pol_x_preferred":[
        "Aylesby"
    ],
    "name:swe_x_preferred":[
        "Aylesby"
    ],
    "wof:name":"Aylesby",
    "wof:placetype":"locality"
},
  "geometry": {"coordinates":[26.33088,-30.66104],"type":"Point"}
}