{
  "type": "Feature",
  "properties": {
    "gn:admin1_code":"2",
    "gn:admin2_code":"DC21",
    "gn:admin3_code":"KZN211",
    "gn:asciiname":"Fairfield",
    "gn:country_code":"ZA",
    "gn:dem":702,
    "gn:feature_class":"P",
    "gn:feature_code":"PPL",
    "gn:name":"Fairfield",
    "gn:population":0,
    "gn:timezone":"Africa/Johannesburg",
    "iso:country":"ZA",
    "wof:name":"Fairfield",
    "wof:placetype":"locality"
},
  "geometry": {"coordinates":[30.41012000000001,-30.31565],"type":"Point"}
}