{
  "type": "Feature",
  "properties": {
    "gn:admin1_code":"2",
    "gn:admin2_code":"DC21",
    "gn:admin3_code":"KZN211",
    "gn:asciiname":"Fairfield",
    "gn:country_code":"ZA",
    "gn:dem":702,
    "gn:feature_class":"P",
    "gn:feature_code":"PPL",
    "gn:name":"Fairfield",
    "gn:population":0,
    "gn:timezone":"Africa/Johannesburg",
    "iso:country":"ZA",
    "name:cat_x_preferred":[
        "Fairfield"
    ],
    "name:ceb_x_preferred":[
        "Fairfield"
    ],
    "name:dan_x_preferred":[
        "Fairfield"
    ],
    "name:deu_x_preferred":[
        "Fairfield"
    ],
    "name:fas_x_preferred":[
        "\u0641\u06cc\u0631\u0641\u06cc\u0644\u062f"
    ],
    "name:fin_x_preferred":[
        "Fairfield"
    ],
    "name:fra_x_preferred":[
        "Fairfield"
    ],
    "name:ido_x_preferred":[
        "Fairfield"
    ],
    "name:ita_x_preferred":[
        "Fairfield"
    ],
    "name:jpn_x_preferred":[
        "\u30d5\u30a7\u30a2\u30d5\u30a3\u30fc\u30eb\u30c9"
    ],
    "name:kor_x_preferred":[
        "\ud398\uc5b4\ud544\ub4dc"
    ],
    "name:mlg_x_preferred":[
        "Fairfield"
    ],
    "name:nld_x_preferred":[
        "Fairfield"
    ],
    "name:pol_x_preferred":[
        "Fairfield"
    ],
    "name:por_x_preferred":[
        "Fairfield"
    ],
    "name:rus_x_preferred":[
        "\u0424\u044d\u0440\u0444\u0438\u043b\u0434"
    ],
    "name:sco_x_preferred":[
        "Fairfield"
    ],
    "name:spa_x_preferred":[
        "Fairfield"
    ],
    "name:srp_x_preferred":[
        "\u0424\u0435\u0440\u0444\u0438\u043b\u0434"
    ],
    "name:swa_x_preferred":[
        "Fairfield"
    ],
    "name:swe_x_preferred":[
        "Fairfield"
    ],
    "name:tur_x_preferred":[
        "Farfield"
    ],
    "name:ukr_x_preferred":[
        "\u0424\u0435\u0439\u0440\u0444\u0456\u043b\u0434"
    ],
    "name:urd_x_preferred":[
        "\u0641\u06cc\u0626\u0631\u0641\u06cc\u0644\u0688"
    ],
    "name:vol_x_preferred":[
        "Fairfield"
    ],
    "name:war_x_preferred":[
        "Fairfield"
    ],
    "wof:name":"Fairfield",
    "wof:placetype":"locality"
},
  "geometry": {"coordinates":[30.41012000000001,-30.31565],"type":"Point"}
}