{
  "type": "Feature",
  "properties": {
    "gn:admin1_code":"2.0",
    "gn:asciiname":"Taleni",
    "gn:country_code":"ZA",
    "gn:dem":904,
    "gn:feature_class":"P",
    "gn:feature_code":"PPL",
    "gn:name":"Taleni",
    "gn:population":0,
    "gn:timezone":"Africa/Johannesburg",
    "iso:country":"ZA",
    "wof:name":"Taleni",
    "wof:placetype":"locality"
},
  "geometry": {"coordinates":[29.68677000000001,-30.69402],"type":"Point"}
}