{
  "type": "Feature",
  "properties": {
    "gn:admin1_code":"3.0",
    "gn:admin2_code":"DC16",
    "gn:admin3_code":"FS163",
    "gn:asciiname":"Swartlaagte",
    "gn:country_code":"ZA",
    "gn:dem":1533,
    "gn:feature_class":"P",
    "gn:feature_code":"PPL",
    "gn:name":"Swartlaagte",
    "gn:population":0,
    "gn:timezone":"Africa/Johannesburg",
    "iso:country":"ZA",
    "wof:name":"Swartlaagte",
    "wof:placetype":"locality"
},
  "geometry": {"coordinates":[26.52063,-30.04774],"type":"Point"}
}