{
  "type": "Feature",
  "properties": {
    "gn:admin1_code":"2",
    "gn:admin2_code":"DC24",
    "gn:admin3_code":"KZN244",
    "gn:asciiname":"Nocomboshe",
    "gn:country_code":"ZA",
    "gn:dem":1336,
    "gn:feature_class":"P",
    "gn:feature_code":"PPL",
    "gn:name":"Nocomboshe",
    "gn:population":0,
    "gn:timezone":"Africa/Johannesburg",
    "iso:country":"ZA",
    "name:und_x_variant":[
        "Ncamboshe",
        "Nocomboshe"
    ],
    "wof:lang_x_official":[
        "eng"
    ],
    "wof:lang_x_spoken":[
        "eng",
        "zul",
        "xho",
        "afr",
        "nso",
        "tsn",
        "sot",
        "tso",
        "ssw",
        "ven",
        "nbl"
    ],
    "wof:name":"Nocomboshe",
    "wof:placetype":"locality"
},
  "geometry": {"coordinates":[30.6093,-28.66827],"type":"Point"}
}