{
  "type": "Feature",
  "properties": {
    "gn:admin1_code":"8",
    "gn:admin2_code":"DC7",
    "gn:admin3_code":"NC077",
    "gn:asciiname":"Grassmoor",
    "gn:country_code":"ZA",
    "gn:dem":1055,
    "gn:feature_class":"P",
    "gn:feature_code":"PPL",
    "gn:name":"Grassmoor",
    "gn:population":0,
    "gn:timezone":"Africa/Johannesburg",
    "iso:country":"ZA",
    "name:cym_x_preferred":[
        "Grassmoor"
    ],
    "name:fas_x_preferred":[
        "\u06af\u0631\u0633\u0645\u0648\u0648\u0631"
    ],
    "name:ita_x_preferred":[
        "Grassmoor"
    ],
    "name:pol_x_preferred":[
        "Grassmoor"
    ],
    "name:por_x_preferred":[
        "Grassmoor"
    ],
    "name:spa_x_preferred":[
        "Grassmoor"
    ],
    "name:swe_x_preferred":[
        "Grassmoor"
    ],
    "wof:lang_x_official":[
        "eng"
    ],
    "wof:lang_x_spoken":[
        "eng",
        "zul",
        "xho",
        "afr",
        "nso",
        "tsn",
        "sot",
        "tso",
        "ssw",
        "ven",
        "nbl"
    ],
    "wof:name":"Grassmoor",
    "wof:placetype":"locality"
},
  "geometry": {"coordinates":[22.19131,-29.92664],"type":"Point"}
}