{
  "type": "Feature",
  "properties": {
    "gn:admin1_code":"11",
    "gn:admin2_code":"DC3",
    "gn:admin3_code":"WC032",
    "gn:asciiname":"Strandskloof",
    "gn:country_code":"ZA",
    "gn:dem":59,
    "gn:feature_class":"P",
    "gn:feature_code":"PPL",
    "gn:name":"Strandskloof",
    "gn:population":0,
    "gn:timezone":"Africa/Johannesburg",
    "iso:country":"ZA",
    "wof:name":"Strandskloof",
    "wof:placetype":"locality"
},
  "geometry": {"coordinates":[19.44257,-34.57814],"type":"Point"}
}