{
  "type": "Feature",
  "properties": {
    "gn:admin1_code":"5",
    "gn:admin2_code":"DC13",
    "gn:admin3_code":"EC134",
    "gn:asciiname":"Mceula",
    "gn:country_code":"ZA",
    "gn:dem":1199,
    "gn:feature_class":"P",
    "gn:feature_code":"PPLL",
    "gn:name":"Mceula",
    "gn:population":0,
    "gn:timezone":"Africa/Johannesburg",
    "iso:country":"ZA",
    "wof:name":"Mceula",
    "wof:placetype":"locality"
},
  "geometry": {"coordinates":[26.69238,-32.09996],"type":"Point"}
}