{
  "type": "Feature",
  "properties": {
    "gn:admin1_code":"9.0",
    "gn:admin2_code":"DC34",
    "gn:admin3_code":"LIM344",
    "gn:asciiname":"Tshikhwani",
    "gn:country_code":"ZA",
    "gn:dem":934,
    "gn:feature_class":"P",
    "gn:feature_code":"PPL",
    "gn:name":"Tshikhwani",
    "gn:population":0,
    "gn:timezone":"Africa/Johannesburg",
    "iso:country":"ZA",
    "wof:name":"Tshikhwani",
    "wof:placetype":"locality"
},
  "geometry": {"coordinates":[29.79307,-23.13535],"type":"Point"}
}