{
  "type": "Feature",
  "properties": {
    "gn:admin1_code":"5",
    "gn:admin2_code":"DC13",
    "gn:admin3_code":"EC135",
    "gn:asciiname":"Ncuncuzo",
    "gn:country_code":"ZA",
    "gn:dem":1092,
    "gn:feature_class":"P",
    "gn:feature_code":"PPL",
    "gn:name":"Ncuncuzo",
    "gn:population":0,
    "gn:timezone":"Africa/Johannesburg",
    "iso:country":"ZA",
    "wof:name":"Ncuncuzo",
    "wof:placetype":"locality"
},
  "geometry": {"coordinates":[27.61667000000001,-31.88333],"type":"Point"}
}