{
  "type": "Feature",
  "properties": {
    "gn:country":"ZA",
    "gn:fcode":"PPL",
    "gn:population":0,
    "iso:country":"ZA",
    "name:afr_x_preferred":[
        "Qoloramond"
    ],
    "name:ast_x_preferred":[
        "Qolora Mouth"
    ],
    "name:eng_x_preferred":[
        "Qolora Mouth"
    ],
    "name:est_x_preferred":[
        "Qolora Mouth"
    ],
    "name:nld_x_preferred":[
        "Qolora Mouth"
    ],
    "name:nso_x_preferred":[
        "Qolora Mouth"
    ],
    "name:sot_x_preferred":[
        "Qolora Mouth"
    ],
    "name:zul_x_preferred":[
        "IQolora Mouth"
    ],
    "qs_pg:aaroncc":"ZA",
    "qs_pg:gn_country":"ZA",
    "qs_pg:gn_fcode":"PPL",
    "qs_pg:gn_pop":0,
    "qs_pg:name":"Qolora Mouth",
    "qs_pg:name_adm0":"South Africa",
    "qs_pg:name_adm1":"Eastern Cape",
    "qs_pg:photos":113,
    "qs_pg:photos_1k":23,
    "qs_pg:photos_9k":1,
    "qs_pg:photos_9r":3,
    "qs_pg:photos_all":113,
    "qs_pg:photos_sr":3,
    "qs_pg:pop_sr":0,
    "qs_pg:qs_pg_placetype":"locality",
    "qs_pg:qs_pg_placetype_gp":"Town",
    "qs_pg:woe_adm0":23424942,
    "woe:adm0_id":23424942,
    "woe:name_adm0":"South Africa",
    "woe:name_adm1":"Eastern Cape",
    "woe:placetype":"Town",
    "wof:lang_x_official":[
        "eng"
    ],
    "wof:lang_x_spoken":[
        "eng",
        "zul",
        "xho",
        "afr",
        "nso",
        "tsn",
        "sot",
        "tso",
        "ssw",
        "ven",
        "nbl"
    ],
    "wof:name":"Qolora Mouth",
    "wof:placetype":"locality"
},
  "geometry": {"coordinates":[28.41798,-32.63333],"type":"Point"}
}