{
  "type": "Feature",
  "properties": {
    "gn:admin1_code":"5",
    "gn:admin2_code":"DC44",
    "gn:admin3_code":"EC443",
    "gn:asciiname":"KuCitwayo",
    "gn:country_code":"ZA",
    "gn:dem":652,
    "gn:feature_class":"P",
    "gn:feature_code":"PPL",
    "gn:name":"KuCitwayo",
    "gn:population":0,
    "gn:timezone":"Africa/Johannesburg",
    "iso:country":"ZA",
    "name:und_x_variant":[
        "Kwa-Citwayo",
        "KuCitwayo"
    ],
    "wof:name":"KuCitwayo",
    "wof:placetype":"locality"
},
  "geometry": {"coordinates":[29.75558,-31.09267],"type":"Point"}
}