{
  "type": "Feature",
  "properties": {
    "gn:country":"ZA",
    "gn:fcode":"PPL",
    "gn:population":0,
    "iso:country":"ZA",
    "name:afr_x_preferred":[
        "Ocean View"
    ],
    "name:ceb_x_preferred":[
        "Ocean View"
    ],
    "name:eng_x_preferred":[
        "Ocean View"
    ],
    "name:fra_x_preferred":[
        "Ocean View"
    ],
    "name:nld_x_preferred":[
        "Ocean View"
    ],
    "name:sot_x_preferred":[
        "Ocean View"
    ],
    "qs_pg:aaroncc":"ZA",
    "qs_pg:gn_country":"ZA",
    "qs_pg:gn_fcode":"PPL",
    "qs_pg:gn_pop":0,
    "qs_pg:name":"Ocean View",
    "qs_pg:name_adm0":"South Africa",
    "qs_pg:name_adm1":"Western Cape",
    "qs_pg:photos":148,
    "qs_pg:photos_1k":30,
    "qs_pg:photos_9k":1,
    "qs_pg:photos_9r":3,
    "qs_pg:photos_all":148,
    "qs_pg:photos_sr":3,
    "qs_pg:pop_sr":0,
    "qs_pg:qs_pg_placetype":"locality",
    "qs_pg:qs_pg_placetype_gp":"Town",
    "qs_pg:woe_adm0":23424942,
    "woe:adm0_id":23424942,
    "woe:name_adm0":"South Africa",
    "woe:name_adm1":"Western Cape",
    "woe:placetype":"Town",
    "wof:lang_x_official":[
        "eng"
    ],
    "wof:lang_x_spoken":[
        "eng",
        "zul",
        "xho",
        "afr",
        "nso",
        "tsn",
        "sot",
        "tso",
        "ssw",
        "ven",
        "nbl"
    ],
    "wof:name":"Ocean View",
    "wof:placetype":"neighbourhood"
},
  "geometry": {"coordinates":[18.35365,-34.14861],"type":"Point"}
}