{
  "type": "Feature",
  "properties": {
    "gn:admin1_code":"5",
    "gn:asciiname":"Gugwini",
    "gn:country_code":"ZA",
    "gn:dem":849,
    "gn:feature_class":"P",
    "gn:feature_code":"PPL",
    "gn:name":"Gugwini",
    "gn:population":0,
    "gn:timezone":"Africa/Johannesburg",
    "iso:country":"ZA",
    "wof:name":"Gugwini",
    "wof:placetype":"locality"
},
  "geometry": {"coordinates":[29.94045,-30.50152000000001],"type":"Point"}
}