{
  "type": "Feature",
  "properties": {
    "gn:admin1_code":"9",
    "gn:admin2_code":"DC33",
    "gn:admin3_code":"LIM333",
    "gn:asciiname":"Hekpoort",
    "gn:country_code":"ZA",
    "gn:dem":1632,
    "gn:feature_class":"P",
    "gn:feature_code":"PPL",
    "gn:name":"Hekpoort",
    "gn:population":0,
    "gn:timezone":"Africa/Johannesburg",
    "iso:country":"ZA",
    "wof:name":"Hekpoort",
    "wof:placetype":"locality"
},
  "geometry": {"coordinates":[29.97444,-23.77811],"type":"Point"}
}