{
  "type": "Feature",
  "properties": {
    "gn:admin1_code":"3",
    "gn:admin2_code":"DC19",
    "gn:admin3_code":"FS195",
    "gn:asciiname":"Arcadia",
    "gn:country_code":"ZA",
    "gn:dem":1679,
    "gn:feature_class":"P",
    "gn:feature_code":"PPL",
    "gn:name":"Arcadia",
    "gn:population":0,
    "gn:timezone":"Africa/Johannesburg",
    "iso:country":"ZA",
    "wof:name":"Arcadia",
    "wof:placetype":"locality"
},
  "geometry": {"coordinates":[29.28333,-27.31667],"type":"Point"}
}