{
  "type": "Feature",
  "properties": {
    "gn:admin1_code":"11",
    "gn:admin2_code":"DC4",
    "gn:admin3_code":"WC044",
    "gn:asciiname":"Mike",
    "gn:cc2":"ZA",
    "gn:country_code":"ZA",
    "gn:dem":623,
    "gn:feature_class":"P",
    "gn:feature_code":"PPL",
    "gn:name":"Mike",
    "gn:population":0,
    "gn:timezone":"Africa/Johannesburg",
    "iso:country":"ZA",
    "name:fin_x_preferred":[
        "Mike"
    ],
    "name:swe_x_preferred":[
        "Mike"
    ],
    "name:und_x_variant":[
        "Mikes"
    ],
    "wof:name":"Mike",
    "wof:placetype":"locality"
},
  "geometry": {"coordinates":[22.91667,-33.76667],"type":"Point"}
}