{
  "type": "Feature",
  "properties": {
    "gn:admin1_code":"3.0",
    "gn:admin2_code":"DC16",
    "gn:admin3_code":"FS162",
    "gn:asciiname":"Twyfelfontein",
    "gn:country_code":"ZA",
    "gn:dem":1335,
    "gn:feature_class":"P",
    "gn:feature_code":"PPL",
    "gn:name":"Twyfelfontein",
    "gn:population":0,
    "gn:timezone":"Africa/Johannesburg",
    "iso:country":"ZA",
    "name:afr_x_preferred":[
        "Twyfelfontein"
    ],
    "name:ara_x_preferred":[
        "\u062a\u0648\u064a\u0641\u0644\u0641\u0648\u0646\u062a\u064a\u0646"
    ],
    "name:ast_x_preferred":[
        "Twyfelfontein"
    ],
    "name:cat_x_preferred":[
        "Twyfelfontein"
    ],
    "name:ces_x_preferred":[
        "Twyfelfontein"
    ],
    "name:deu_x_preferred":[
        "Twyfelfontein"
    ],
    "name:epo_x_preferred":[
        "Twyfelfontein"
    ],
    "name:fin_x_preferred":[
        "Twyfelfontein"
    ],
    "name:fra_x_preferred":[
        "Twyfelfontein"
    ],
    "name:heb_x_preferred":[
        "\u05d8\u05d5\u05d5\u05d0\u05d9\u05e4\u05dc\u05e4\u05d5\u05e0\u05d8\u05d9\u05d9\u05df"
    ],
    "name:hin_x_preferred":[
        "\u0924\u094d\u0935\u092f\u094d\u092b\u0947\u0932\u094d\u092b\u094b\u0902\u0924\u0948\u0928"
    ],
    "name:hrv_x_preferred":[
        "Twyfelfontein"
    ],
    "name:hun_x_preferred":[
        "Twyfelfontein"
    ],
    "name:ita_x_preferred":[
        "Twyfelfontein"
    ],
    "name:jpn_x_preferred":[
        "\u30c8\u30a5\u30a6\u30a7\u30a4\u30d5\u30eb\u30d5\u30a9\u30f3\u30c6\u30fc\u30f3"
    ],
    "name:kat_x_preferred":[
        "\u10e2\u10d5\u10d8\u10e4\u10d4\u10da\u10e4\u10dd\u10dc\u10e2\u10d4\u10d8\u10dc\u10d8"
    ],
    "name:lit_x_preferred":[
        "Tveifelfonteinas"
    ],
    "name:nep_x_preferred":[
        "\u091f\u094d\u0935\u093e\u092b\u0947\u0932\u092b\u094b\u0928\u094d\u091f\u0947\u0928"
    ],
    "name:nld_x_preferred":[
        "Twyfelfontein"
    ],
    "name:nor_x_preferred":[
        "Twyfelfontein"
    ],
    "name:pol_x_preferred":[
        "Twyfelfontein"
    ],
    "name:por_x_preferred":[
        "Twyfelfontein"
    ],
    "name:rus_x_preferred":[
        "\u0422\u0432\u0438\u0444\u0435\u043b\u0444\u043e\u043d\u0442\u0435\u0439\u043d"
    ],
    "name:slv_x_preferred":[
        "Twyfelfontein"
    ],
    "name:spa_x_preferred":[
        "Twyfelfontein"
    ],
    "name:swe_x_preferred":[
        "Twyfelfontein"
    ],
    "name:tur_x_preferred":[
        "Twyfelfontein"
    ],
    "name:war_x_preferred":[
        "Twyfelfontein"
    ],
    "name:zho_x_preferred":[
        "\u7279\u97e6\u5f17\u5c14\u6cc9"
    ],
    "wof:name":"Twyfelfontein",
    "wof:placetype":"locality"
},
  "geometry": {"coordinates":[25.80151,-29.46194],"type":"Point"}
}