{
  "type": "Feature",
  "properties": {
    "gn:admin1_code":"3.0",
    "gn:admin2_code":"DC16",
    "gn:admin3_code":"FS162",
    "gn:asciiname":"Twyfelfontein",
    "gn:country_code":"ZA",
    "gn:dem":1335,
    "gn:feature_class":"P",
    "gn:feature_code":"PPL",
    "gn:name":"Twyfelfontein",
    "gn:population":0,
    "gn:timezone":"Africa/Johannesburg",
    "iso:country":"ZA",
    "wof:name":"Twyfelfontein",
    "wof:placetype":"locality"
},
  "geometry": {"coordinates":[25.80151,-29.46194],"type":"Point"}
}