{
  "type": "Feature",
  "properties": {
    "iso:country":"ZA",
    "name:afr_x_preferred":[
        "Steenbrasdam"
    ],
    "name:eng_x_preferred":[
        "Steenbras"
    ],
    "name:unk_x_variant":[
        "Steenbras"
    ],
    "qs:gn_adm0_cc":"ZA",
    "qs:gn_fcode":"PPL",
    "qs:gn_local":3367513,
    "qs:gn_nam_loc":"grabouw",
    "qs:gn_namadm1":"11",
    "qs:gn_name":"Steenbras",
    "qs:local_max":18,
    "qs:local_sum":18,
    "qs:localhoods":1,
    "qs:name":"Steenbras",
    "qs:name_adm0":"South Africa",
    "qs:name_adm1":"Western Cape",
    "qs:name_adm2":"Overberg",
    "qs:name_lau":"Theewaterskloof",
    "qs:name_local":"Grabouw",
    "qs:photo_max":16,
    "qs:photo_sum":18,
    "qs:placetype":"Suburb",
    "qs:quad_count":2,
    "qs:woe_adm0":23424942,
    "qs:woe_adm1":2346987,
    "qs:woe_adm2":56189456,
    "qs:woe_lau":56189681,
    "qs:woe_local":1581911,
    "qs:woe_ver":"7.10.0",
    "wd:wordcount":215,
    "wof:lang":[
        "eng"
    ],
    "wof:name":"Steenbras",
    "wof:placetype":"neighbourhood"
},
  "geometry": {"coordinates":[18.997498,-34.140352],"type":"Point"}
}