{
  "type": "Feature",
  "properties": {
    "gn:admin1_code":"5",
    "gn:admin2_code":"DC12",
    "gn:admin3_code":"EC124",
    "gn:asciiname":"Cenyu",
    "gn:country_code":"ZA",
    "gn:dem":924,
    "gn:feature_class":"P",
    "gn:feature_code":"PPL",
    "gn:name":"Cenyu",
    "gn:population":0,
    "gn:timezone":"Africa/Johannesburg",
    "iso:country":"ZA",
    "wof:name":"Cenyu",
    "wof:placetype":"locality"
},
  "geometry": {"coordinates":[27.44951,-32.55183],"type":"Point"}
}