{
  "type": "Feature",
  "properties": {
    "gn:admin1_code":"9",
    "gn:admin2_code":"DC47",
    "gn:admin3_code":"LIM474",
    "gn:asciiname":"Mooiklip",
    "gn:country_code":"ZA",
    "gn:dem":767,
    "gn:feature_class":"P",
    "gn:feature_code":"PPL",
    "gn:name":"Mooiklip",
    "gn:population":0,
    "gn:timezone":"Africa/Johannesburg",
    "iso:country":"ZA",
    "wof:name":"Mooiklip",
    "wof:placetype":"locality"
},
  "geometry": {"coordinates":[29.73809,-24.44743],"type":"Point"}
}