{
  "type": "Feature",
  "properties": {
    "gn:admin1_code":"5.0",
    "gn:admin2_code":"DC13",
    "gn:admin3_code":"EC136",
    "gn:asciiname":"Tafeni",
    "gn:country_code":"ZA",
    "gn:dem":1123,
    "gn:feature_class":"P",
    "gn:feature_code":"PPL",
    "gn:name":"Tafeni",
    "gn:population":0,
    "gn:timezone":"Africa/Johannesburg",
    "iso:country":"ZA",
    "wof:name":"Tafeni",
    "wof:placetype":"locality"
},
  "geometry": {"coordinates":[27.32478,-31.82893],"type":"Point"}
}