{
  "type": "Feature",
  "properties": {
    "gn:admin1_code":"3",
    "gn:admin2_code":"DC16",
    "gn:admin3_code":"FS163",
    "gn:asciiname":"Rifle",
    "gn:country_code":"ZA",
    "gn:dem":1423,
    "gn:feature_class":"P",
    "gn:feature_code":"PPL",
    "gn:name":"Rifle",
    "gn:population":0,
    "gn:timezone":"Africa/Johannesburg",
    "iso:country":"ZA",
    "wof:name":"Rifle",
    "wof:placetype":"locality"
},
  "geometry": {"coordinates":[26.78288,-30.36305],"type":"Point"}
}