{
  "type": "Feature",
  "properties": {
    "gn:admin1_code":"5",
    "gn:admin2_code":"BUF",
    "gn:admin3_code":"BUF",
    "gn:asciiname":"Amalinda",
    "gn:country_code":"ZA",
    "gn:dem":124,
    "gn:feature_class":"P",
    "gn:feature_code":"PPL",
    "gn:name":"Amalinda",
    "gn:population":0,
    "gn:timezone":"Africa/Johannesburg",
    "iso:country":"ZA",
    "wof:name":"Amalinda",
    "wof:placetype":"locality"
},
  "geometry": {"coordinates":[27.85,-32.98333],"type":"Point"}
}