{
  "type": "Feature",
  "properties": {
    "gn:admin1_code":"9",
    "gn:admin2_code":"DC33",
    "gn:admin3_code":"LIM333",
    "gn:asciiname":"Mawa",
    "gn:country_code":"ZA",
    "gn:dem":501,
    "gn:feature_class":"P",
    "gn:feature_code":"PPL",
    "gn:name":"Mawa",
    "gn:population":0,
    "gn:timezone":"Africa/Johannesburg",
    "iso:country":"ZA",
    "name:ceb_x_preferred":[
        "Mawa"
    ],
    "name:fra_x_preferred":[
        "Mawa"
    ],
    "name:swe_x_preferred":[
        "Mawa"
    ],
    "wof:lang_x_official":[
        "eng"
    ],
    "wof:lang_x_spoken":[
        "eng",
        "zul",
        "xho",
        "afr",
        "nso",
        "tsn",
        "sot",
        "tso",
        "ssw",
        "ven",
        "nbl"
    ],
    "wof:name":"Mawa",
    "wof:placetype":"locality"
},
  "geometry": {"coordinates":[30.54327,-23.56395],"type":"Point"}
}