{
  "type": "Feature",
  "properties": {
    "gn:country":"ZA",
    "gn:fcode":"PPLX",
    "gn:population":0,
    "iso:country":"ZA",
    "name:afr_x_preferred":[
        "Dan Pienaar"
    ],
    "name:fra_x_preferred":[
        "Dan Pienaar"
    ],
    "name:ita_x_preferred":[
        "Daniel Hermanus Pienaar"
    ],
    "name:slv_x_preferred":[
        "Daniel Hermanus Pienaar"
    ],
    "qs_pg:aaroncc":"ZA",
    "qs_pg:gn_country":"ZA",
    "qs_pg:gn_fcode":"PPLX",
    "qs_pg:gn_pop":0,
    "qs_pg:name":"Dan Pienaar",
    "qs_pg:name_adm0":"South Africa",
    "qs_pg:name_adm1":"Free State",
    "qs_pg:photos":21,
    "qs_pg:photos_1k":4,
    "qs_pg:photos_9k":1,
    "qs_pg:photos_9r":1,
    "qs_pg:photos_all":21,
    "qs_pg:photos_sr":1,
    "qs_pg:pop_sr":0,
    "qs_pg:qs_pg_placetype":"neighbourhood",
    "qs_pg:qs_pg_placetype_gp":"Suburb",
    "qs_pg:woe_adm0":23424942,
    "woe:adm0_id":23424942,
    "woe:name_adm0":"South Africa",
    "woe:name_adm1":"Free State",
    "woe:placetype":"Suburb",
    "wof:lang_x_official":[
        "eng"
    ],
    "wof:lang_x_spoken":[
        "eng",
        "zul",
        "xho",
        "afr",
        "nso",
        "tsn",
        "sot",
        "tso",
        "ssw",
        "ven",
        "nbl"
    ],
    "wof:name":"Dan Pienaar",
    "wof:placetype":"neighbourhood"
},
  "geometry": {"coordinates":[26.21509,-29.08512],"type":"Point"}
}