{
  "type": "Feature",
  "properties": {
    "gn:admin1_code":"5",
    "gn:admin2_code":"DC13",
    "gn:admin3_code":"EC137",
    "gn:asciiname":"Gqutyini",
    "gn:country_code":"ZA",
    "gn:dem":955,
    "gn:feature_class":"P",
    "gn:feature_code":"PPL",
    "gn:name":"Gqutyini",
    "gn:population":0,
    "gn:timezone":"Africa/Johannesburg",
    "iso:country":"ZA",
    "wof:name":"Gqutyini",
    "wof:placetype":"locality"
},
  "geometry": {"coordinates":[27.8815,-31.62662000000001],"type":"Point"}
}