{
  "type": "Feature",
  "properties": {
    "gn:admin1_code":"3",
    "gn:admin2_code":"DC16",
    "gn:admin3_code":"FS163",
    "gn:asciiname":"La Rochelle",
    "gn:country_code":"ZA",
    "gn:dem":1491,
    "gn:feature_class":"P",
    "gn:feature_code":"PPL",
    "gn:name":"La Rochelle",
    "gn:population":0,
    "gn:timezone":"Africa/Johannesburg",
    "iso:country":"ZA",
    "wof:name":"La Rochelle",
    "wof:placetype":"locality"
},
  "geometry": {"coordinates":[26.70745,-29.99035],"type":"Point"}
}