{
  "type": "Feature",
  "properties": {
    "gn:admin1_code":"6",
    "gn:admin2_code":"DC42",
    "gn:admin3_code":"GT422",
    "gn:asciiname":"Homestead Apple Orchards",
    "gn:country_code":"ZA",
    "gn:dem":1595,
    "gn:feature_class":"P",
    "gn:feature_code":"PPL",
    "gn:name":"Homestead Apple Orchards",
    "gn:population":0,
    "gn:timezone":"Africa/Johannesburg",
    "iso:country":"ZA",
    "wof:lang_x_official":[
        "eng"
    ],
    "wof:lang_x_spoken":[
        "eng",
        "zul",
        "xho",
        "afr",
        "nso",
        "tsn",
        "sot",
        "tso",
        "ssw",
        "ven",
        "nbl"
    ],
    "wof:name":"Homestead Apple Orchards",
    "wof:placetype":"locality"
},
  "geometry": {"coordinates":[27.93619,-26.46141],"type":"Point"}
}