{
  "type": "Feature",
  "properties": {
    "gn:admin1_code":"2",
    "gn:admin2_code":"DC43",
    "gn:admin3_code":"KZN433",
    "gn:asciiname":"Oatlands",
    "gn:country_code":"ZA",
    "gn:dem":1372,
    "gn:feature_class":"P",
    "gn:feature_code":"PPL",
    "gn:name":"Oatlands",
    "gn:population":0,
    "gn:timezone":"Africa/Johannesburg",
    "iso:country":"ZA",
    "name:ben_x_preferred":[
        "\u0993\u099f\u09b2\u09cd\u09af\u09be\u09a8\u09cd\u09a1\u09b8"
    ],
    "name:deu_x_preferred":[
        "Oatlands"
    ],
    "name:ell_x_preferred":[
        "\u038c\u03b1\u03c4\u03bb\u03b1\u03bd\u03c4\u03c2"
    ],
    "name:fas_x_preferred":[
        "\u0627\u0648\u062a\u0644\u0646\u062f\u0632"
    ],
    "name:heb_x_preferred":[
        "\u05d0\u05d5\u05d8\u05dc\u05e0\u05d3\u05e1"
    ],
    "name:hin_x_preferred":[
        "\u0913\u091f\u094d\u0938\u0932\u0948\u0902\u0921"
    ],
    "name:hun_x_preferred":[
        "Oatlands"
    ],
    "name:ind_x_preferred":[
        "Oatlands"
    ],
    "name:jpn_x_preferred":[
        "\u30aa\u30fc\u30c8\u30e9\u30f3\u30ba"
    ],
    "name:kor_x_preferred":[
        "\uc624\ud2c0\ub79c\uc988"
    ],
    "name:pol_x_preferred":[
        "Oatlands"
    ],
    "name:rus_x_preferred":[
        "\u041e\u0442\u043b\u0435\u043d\u0434\u0441"
    ],
    "name:swe_x_preferred":[
        "Oatlands"
    ],
    "name:tur_x_preferred":[
        "Oatlands"
    ],
    "name:ukr_x_preferred":[
        "\u041e\u0443\u0442\u043b\u0435\u043d\u0434\u0441"
    ],
    "name:urd_x_preferred":[
        "\u0627\u0648\u0679\u0633\u0644\u06cc\u0646\u0688"
    ],
    "name:vie_x_preferred":[
        "Oatlands"
    ],
    "name:zho_cn_x_preferred":[
        "\u5965\u7279\u5170\u5179"
    ],
    "name:zho_tw_x_preferred":[
        "\u5967\u7279\u862d\u8332"
    ],
    "wof:lang_x_official":[
        "eng"
    ],
    "wof:lang_x_spoken":[
        "eng",
        "zul",
        "xho",
        "afr",
        "nso",
        "tsn",
        "sot",
        "tso",
        "ssw",
        "ven",
        "nbl"
    ],
    "wof:name":"Oatlands",
    "wof:placetype":"locality"
},
  "geometry": {"coordinates":[29.32321,-30.55286],"type":"Point"}
}