{
  "type": "Feature",
  "properties": {
    "gn:admin1_code":"2",
    "gn:admin2_code":"DC43",
    "gn:admin3_code":"KZN433",
    "gn:asciiname":"Oatlands",
    "gn:country_code":"ZA",
    "gn:dem":1372,
    "gn:feature_class":"P",
    "gn:feature_code":"PPL",
    "gn:name":"Oatlands",
    "gn:population":0,
    "gn:timezone":"Africa/Johannesburg",
    "iso:country":"ZA",
    "name:deu_x_preferred":[
        "Oatlands"
    ],
    "name:pol_x_preferred":[
        "Oatlands"
    ],
    "name:swe_x_preferred":[
        "Oatlands"
    ],
    "wof:name":"Oatlands",
    "wof:placetype":"locality"
},
  "geometry": {"coordinates":[29.32321,-30.55286],"type":"Point"}
}