{
  "type": "Feature",
  "properties": {
    "gn:admin1_code":"11.0",
    "gn:admin2_code":"DC1",
    "gn:admin3_code":"WC011",
    "gn:asciiname":"Klawer",
    "gn:country_code":"ZA",
    "gn:dem":51,
    "gn:feature_class":"P",
    "gn:feature_code":"PPL",
    "gn:name":"Klawer",
    "gn:population":0,
    "gn:timezone":"Africa/Johannesburg",
    "iso:country":"ZA",
    "name:und_x_variant":[
        "Klaver",
        "Klarer",
        "Klawer"
    ],
    "wof:name":"Klawer",
    "wof:placetype":"locality"
},
  "geometry": {"coordinates":[18.62497,-31.77593],"type":"Point"}
}