{
  "type": "Feature",
  "properties": {
    "gn:admin1_code":"5",
    "gn:admin2_code":"DC15",
    "gn:admin3_code":"EC156",
    "gn:asciiname":"Ngwemnyama",
    "gn:country_code":"ZA",
    "gn:dem":813,
    "gn:feature_class":"P",
    "gn:feature_code":"PPL",
    "gn:name":"Ngwemnyama",
    "gn:population":0,
    "gn:timezone":"Africa/Johannesburg",
    "iso:country":"ZA",
    "wof:name":"Ngwemnyama",
    "wof:placetype":"locality"
},
  "geometry": {"coordinates":[29.02184,-31.25746],"type":"Point"}
}