{
  "type": "Feature",
  "properties": {
    "gn:country":"ZA",
    "gn:fcode":"PPL",
    "gn:population":11445,
    "iso:country":"ZA",
    "name:und_x_variant":[
        "Kopjes"
    ],
    "qs_pg:aaroncc":"ZA",
    "qs_pg:gn_country":"ZA",
    "qs_pg:gn_fcode":"PPL",
    "qs_pg:gn_pop":11445,
    "qs_pg:name":"Koppies Sh",
    "qs_pg:name_adm0":"South Africa",
    "qs_pg:name_adm1":"Free State",
    "qs_pg:photos_9r":0,
    "qs_pg:photos_sr":0,
    "qs_pg:pop_sr":6,
    "qs_pg:qs_pg_placetype":"neighbourhood",
    "qs_pg:qs_pg_placetype_gp":"Suburb",
    "qs_pg:woe_adm0":23424942,
    "woe:adm0_id":23424942,
    "woe:name_adm0":"South Africa",
    "woe:name_adm1":"Free State",
    "woe:placetype":"Suburb",
    "wof:lang_x_official":[
        "eng"
    ],
    "wof:lang_x_spoken":[
        "eng",
        "zul",
        "xho",
        "afr",
        "nso",
        "tsn",
        "sot",
        "tso",
        "ssw",
        "ven",
        "nbl"
    ],
    "wof:name":"Koppies Sh",
    "wof:placetype":"neighbourhood",
    "wof:population":11445
},
  "geometry": {"coordinates":[27.57422,-27.24179],"type":"Point"}
}