{
  "type": "Feature",
  "properties": {
    "gn:admin1_code":"10",
    "gn:asciiname":"Ganap",
    "gn:country_code":"ZA",
    "gn:dem":1087,
    "gn:feature_class":"P",
    "gn:feature_code":"PPL",
    "gn:name":"Ganap",
    "gn:population":0,
    "gn:timezone":"Africa/Johannesburg",
    "iso:country":"ZA",
    "wof:name":"Ganap",
    "wof:placetype":"locality"
},
  "geometry": {"coordinates":[23.24908,-26.69644000000001],"type":"Point"}
}