{
  "type": "Feature",
  "properties": {
    "gn:admin1_code":"5.0",
    "gn:admin2_code":"DC13",
    "gn:admin3_code":"EC138",
    "gn:asciiname":"Siginqini",
    "gn:country_code":"ZA",
    "gn:dem":1475,
    "gn:feature_class":"P",
    "gn:feature_code":"PPL",
    "gn:name":"Siginqini",
    "gn:population":0,
    "gn:timezone":"Africa/Johannesburg",
    "iso:country":"ZA",
    "wof:name":"Siginqini",
    "wof:placetype":"locality"
},
  "geometry": {"coordinates":[27.72084000000001,-31.46991],"type":"Point"}
}