{
  "type": "Feature",
  "properties": {
    "gn:gn_country":"ZA",
    "gn:gn_fcode":"ADM3",
    "gn:gn_pop":161894,
    "gn:population":161894,
    "iso:country":"ZA",
    "qs_pg:aaroncc":"ZA",
    "qs_pg:gn_country":"ZA",
    "qs_pg:gn_fcode":"ADM3",
    "qs_pg:gn_pop":161894,
    "qs_pg:name":"Msinga",
    "qs_pg:photos_9r":0,
    "qs_pg:photos_sr":0,
    "qs_pg:pop_sr":9,
    "qs_pg:qs_pg_placetype":"localadmin",
    "wof:name":"Msinga",
    "wof:placetype":"localadmin",
    "wof:population":161894
},
  "geometry": {"coordinates":[30.46023,-28.61807],"type":"Point"}
}