{
  "type": "Feature",
  "properties": {
    "gn:admin1_code":"11.0",
    "gn:admin2_code":"DC3",
    "gn:admin3_code":"WC031",
    "gn:asciiname":"Klipkraal",
    "gn:country_code":"ZA",
    "gn:dem":224,
    "gn:feature_class":"P",
    "gn:feature_code":"PPL",
    "gn:name":"Klipkraal",
    "gn:population":0,
    "gn:timezone":"Africa/Johannesburg",
    "iso:country":"ZA",
    "name:afr_x_preferred":[
        "Klipkraal"
    ],
    "name:nso_x_preferred":[
        "Klipkraal"
    ],
    "wof:name":"Klipkraal",
    "wof:placetype":"locality"
},
  "geometry": {"coordinates":[19.19765,-34.0901],"type":"Point"}
}