{
  "type": "Feature",
  "properties": {
    "gn:admin1_code":"10",
    "gn:admin2_code":"DC38",
    "gn:admin3_code":"NW382",
    "gn:asciiname":"Bahurutshe",
    "gn:country_code":"ZA",
    "gn:dem":1390,
    "gn:feature_class":"P",
    "gn:feature_code":"PPL",
    "gn:name":"Bahurutshe",
    "gn:population":0,
    "gn:timezone":"Africa/Johannesburg",
    "iso:country":"ZA",
    "wof:name":"Bahurutshe",
    "wof:placetype":"locality"
},
  "geometry": {"coordinates":[25.46393,-26.45809],"type":"Point"}
}