{
  "type": "Feature",
  "properties": {
    "gn:admin1_code":"11.0",
    "gn:admin2_code":"DC1",
    "gn:admin3_code":"WC011",
    "gn:asciiname":"Nuwerus",
    "gn:country_code":"ZA",
    "gn:dem":363,
    "gn:feature_class":"P",
    "gn:feature_code":"PPL",
    "gn:name":"Nuwerus",
    "gn:population":0,
    "gn:timezone":"Africa/Johannesburg",
    "iso:country":"ZA",
    "name:afr_x_preferred":[
        "Nuwerus"
    ],
    "name:est_x_preferred":[
        "Nuwerus"
    ],
    "name:nso_x_preferred":[
        "Nuwerus"
    ],
    "name:und_x_variant":[
        "Nieuwerust"
    ],
    "wof:lang_x_official":[
        "eng"
    ],
    "wof:lang_x_spoken":[
        "eng",
        "zul",
        "xho",
        "afr",
        "nso",
        "tsn",
        "sot",
        "tso",
        "ssw",
        "ven",
        "nbl"
    ],
    "wof:name":"Nuwerus",
    "wof:placetype":"locality"
},
  "geometry": {"coordinates":[18.35827,-31.1494],"type":"Point"}
}