{
  "type": "Feature",
  "properties": {
    "gn:admin1_code":"7",
    "gn:admin2_code":"DC32",
    "gn:admin3_code":"MP324",
    "gn:asciiname":"Ka-Sibhejane",
    "gn:country_code":"ZA",
    "gn:dem":225,
    "gn:feature_class":"P",
    "gn:feature_code":"PPL",
    "gn:name":"Ka-Sibhejane",
    "gn:population":0,
    "gn:timezone":"Africa/Johannesburg",
    "iso:country":"ZA",
    "wof:lang_x_official":[
        "eng"
    ],
    "wof:lang_x_spoken":[
        "eng",
        "zul",
        "xho",
        "afr",
        "nso",
        "tsn",
        "sot",
        "tso",
        "ssw",
        "ven",
        "nbl"
    ],
    "wof:name":"Ka-Sibhejane",
    "wof:placetype":"locality"
},
  "geometry": {"coordinates":[31.80662,-25.65215],"type":"Point"}
}