{
  "type": "Feature",
  "properties": {
    "gn:admin1_code":"3",
    "gn:admin2_code":"MAN",
    "gn:admin3_code":"MAN",
    "gn:asciiname":"Olga",
    "gn:country_code":"ZA",
    "gn:dem":1453,
    "gn:feature_class":"P",
    "gn:feature_code":"PPL",
    "gn:name":"Olga",
    "gn:population":0,
    "gn:timezone":"Africa/Johannesburg",
    "iso:country":"ZA",
    "name:bul_x_preferred":[
        "\u041e\u043b\u0433\u0430"
    ],
    "name:ceb_x_preferred":[
        "Olga"
    ],
    "name:deu_x_preferred":[
        "Olga"
    ],
    "name:est_x_preferred":[
        "Olga"
    ],
    "name:fra_x_preferred":[
        "Olga"
    ],
    "name:heb_x_preferred":[
        "\u05d0\u05d5\u05dc\u05d2\u05d4"
    ],
    "name:ita_x_preferred":[
        "Olga"
    ],
    "name:jpn_x_preferred":[
        "\u30aa\u30ea\u30ac"
    ],
    "name:lav_x_preferred":[
        "Olga"
    ],
    "name:nld_x_preferred":[
        "Olga"
    ],
    "name:por_x_preferred":[
        "Olga"
    ],
    "name:ron_x_preferred":[
        "Olga"
    ],
    "name:rus_x_preferred":[
        "\u041e\u043b\u044c\u0433\u0430"
    ],
    "name:swe_x_preferred":[
        "Olga"
    ],
    "name:tat_x_preferred":[
        "\u041e\u043b\u044c\u0433\u0430"
    ],
    "name:ukr_x_preferred":[
        "\u041e\u043b\u044c\u0433\u0430"
    ],
    "name:vol_x_preferred":[
        "Olga"
    ],
    "wof:name":"Olga",
    "wof:placetype":"locality"
},
  "geometry": {"coordinates":[26.22122,-29.33675],"type":"Point"}
}