{
  "type": "Feature",
  "properties": {
    "gn:admin1_code":"9",
    "gn:admin2_code":"DC47",
    "gn:admin3_code":"LIM475",
    "gn:asciiname":"Melau",
    "gn:country_code":"ZA",
    "gn:dem":857,
    "gn:feature_class":"P",
    "gn:feature_code":"PPL",
    "gn:name":"Melau",
    "gn:population":0,
    "gn:timezone":"Africa/Johannesburg",
    "iso:country":"ZA",
    "wof:name":"Melau",
    "wof:placetype":"locality"
},
  "geometry": {"coordinates":[30.05,-24.46667],"type":"Point"}
}