{
  "type": "Feature",
  "properties": {
    "gn:admin1_code":"6.0",
    "gn:admin2_code":"DC48",
    "gn:admin3_code":"GT484",
    "gn:asciiname":"The Village",
    "gn:country_code":"ZA",
    "gn:dem":1625,
    "gn:feature_class":"P",
    "gn:feature_code":"PPL",
    "gn:name":"The Village",
    "gn:population":0,
    "gn:timezone":"Africa/Johannesburg",
    "iso:country":"ZA",
    "name:deu_x_preferred":[
        "The Village"
    ],
    "name:fas_x_preferred":[
        "\u0631\u0648\u0633\u062a\u0627"
    ],
    "name:fra_x_preferred":[
        "The Village"
    ],
    "name:ita_x_preferred":[
        "The Village"
    ],
    "name:kor_x_preferred":[
        "\ube4c\ub9ac\uc9c0"
    ],
    "name:nld_x_preferred":[
        "The Village"
    ],
    "wof:lang_x_official":[
        "eng"
    ],
    "wof:lang_x_spoken":[
        "eng",
        "zul",
        "xho",
        "afr",
        "nso",
        "tsn",
        "sot",
        "tso",
        "ssw",
        "ven",
        "nbl"
    ],
    "wof:name":"The Village",
    "wof:placetype":"locality"
},
  "geometry": {"coordinates":[27.38482,-26.4001],"type":"Point"}
}