{
  "type": "Feature",
  "properties": {
    "gn:admin1_code":"5",
    "gn:admin2_code":"DC15",
    "gn:admin3_code":"EC156",
    "gn:asciiname":"Noziyongwana",
    "gn:country_code":"ZA",
    "gn:dem":974,
    "gn:feature_class":"P",
    "gn:feature_code":"PPL",
    "gn:name":"Noziyongwana",
    "gn:population":0,
    "gn:timezone":"Africa/Johannesburg",
    "iso:country":"ZA",
    "wof:name":"Noziyongwana",
    "wof:placetype":"locality"
},
  "geometry": {"coordinates":[28.70667000000001,-31.24524000000001],"type":"Point"}
}