{
  "type": "Feature",
  "properties": {
    "gn:admin1_code":"10.0",
    "gn:admin2_code":"DC38",
    "gn:admin3_code":"NW382",
    "gn:asciiname":"Saleng",
    "gn:country_code":"ZA",
    "gn:dem":1373,
    "gn:feature_class":"P",
    "gn:feature_code":"PPL",
    "gn:name":"Saleng",
    "gn:population":0,
    "gn:timezone":"Africa/Johannesburg",
    "iso:country":"ZA",
    "wof:name":"Saleng",
    "wof:placetype":"locality"
},
  "geometry": {"coordinates":[25.33988,-26.42896],"type":"Point"}
}