{
  "type": "Feature",
  "properties": {
    "gn:admin1_code":"9",
    "gn:admin2_code":"DC35",
    "gn:admin3_code":"LIM353",
    "gn:asciiname":"Ga-Manthata",
    "gn:country_code":"ZA",
    "gn:dem":1045,
    "gn:feature_class":"P",
    "gn:feature_code":"PPL",
    "gn:name":"Ga-Manthata",
    "gn:population":0,
    "gn:timezone":"Africa/Johannesburg",
    "iso:country":"ZA",
    "wof:name":"Ga-Manthata",
    "wof:placetype":"locality"
},
  "geometry": {"coordinates":[29.12425,-23.37979],"type":"Point"}
}