{
  "type": "Feature",
  "properties": {
    "gn:admin1_code":"3.0",
    "gn:asciiname":"Ha Mathata",
    "gn:country_code":"ZA",
    "gn:dem":1564,
    "gn:feature_class":"P",
    "gn:feature_code":"PPL",
    "gn:name":"Ha Mathata",
    "gn:population":0,
    "gn:timezone":"Africa/Johannesburg",
    "iso:country":"ZA",
    "wof:name":"Ha Mathata",
    "wof:placetype":"locality"
},
  "geometry": {"coordinates":[27.8923,-28.88579],"type":"Point"}
}