{
  "type": "Feature",
  "properties": {
    "gn:admin1_code":"9",
    "gn:admin2_code":"DC35",
    "gn:admin3_code":"LIM354",
    "gn:asciiname":"Maripathekong",
    "gn:country_code":"ZA",
    "gn:dem":1242,
    "gn:feature_class":"P",
    "gn:feature_code":"PPL",
    "gn:name":"Maripathekong",
    "gn:population":0,
    "gn:timezone":"Africa/Johannesburg",
    "iso:country":"ZA",
    "wof:name":"Maripathekong",
    "wof:placetype":"locality"
},
  "geometry": {"coordinates":[29.80653,-24.03236],"type":"Point"}
}