{
  "type": "Feature",
  "properties": {
    "gn:admin1_code":"10",
    "gn:asciiname":"Maputsane",
    "gn:country_code":"ZA",
    "gn:dem":1324,
    "gn:feature_class":"P",
    "gn:feature_code":"PPL",
    "gn:name":"Maputsane",
    "gn:population":0,
    "gn:timezone":"Africa/Johannesburg",
    "iso:country":"ZA",
    "wof:name":"Maputsane",
    "wof:placetype":"locality"
},
  "geometry": {"coordinates":[23.82037,-27.12266],"type":"Point"}
}