{
  "type": "Feature",
  "properties": {
    "gn:admin1_code":"8",
    "gn:admin2_code":"DC45",
    "gn:admin3_code":"NC451",
    "gn:asciiname":"Grootdrink",
    "gn:country_code":"ZA",
    "gn:dem":971,
    "gn:feature_class":"P",
    "gn:feature_code":"PPL",
    "gn:name":"Grootdrink",
    "gn:population":0,
    "gn:timezone":"Africa/Johannesburg",
    "iso:country":"ZA",
    "name:afr_x_preferred":[
        "Grootdrink"
    ],
    "name:est_x_preferred":[
        "Grootdrink"
    ],
    "name:nld_x_preferred":[
        "Grootdrink"
    ],
    "name:nso_x_preferred":[
        "Grootdrink"
    ],
    "wof:lang_x_official":[
        "eng"
    ],
    "wof:lang_x_spoken":[
        "eng",
        "zul",
        "xho",
        "afr",
        "nso",
        "tsn",
        "sot",
        "tso",
        "ssw",
        "ven",
        "nbl"
    ],
    "wof:name":"Grootdrink",
    "wof:placetype":"locality"
},
  "geometry": {"coordinates":[22.27877,-26.49494],"type":"Point"}
}