{
  "type": "Feature",
  "properties": {
    "gn:admin1_code":"5",
    "gn:admin2_code":"DC12",
    "gn:admin3_code":"EC124",
    "gn:asciiname":"Mfula",
    "gn:country_code":"ZA",
    "gn:dem":743,
    "gn:feature_class":"P",
    "gn:feature_code":"PPL",
    "gn:name":"Mfula",
    "gn:population":0,
    "gn:timezone":"Africa/Johannesburg",
    "iso:country":"ZA",
    "wof:name":"Mfula",
    "wof:placetype":"locality"
},
  "geometry": {"coordinates":[27.74485,-32.24925],"type":"Point"}
}