{
  "type": "Feature",
  "properties": {
    "gn:admin1_code":"5",
    "gn:admin2_code":"DC12",
    "gn:admin3_code":"EC121",
    "gn:asciiname":"Mpuku",
    "gn:country_code":"ZA",
    "gn:dem":734,
    "gn:feature_class":"P",
    "gn:feature_code":"PPL",
    "gn:name":"Mpuku",
    "gn:population":0,
    "gn:timezone":"Africa/Johannesburg",
    "iso:country":"ZA",
    "wof:name":"Mpuku",
    "wof:placetype":"locality"
},
  "geometry": {"coordinates":[28.45703,-32.02269],"type":"Point"}
}