{
  "type": "Feature",
  "properties": {
    "gn:admin1_code":"5.0",
    "gn:admin2_code":"DC12",
    "gn:admin3_code":"EC122",
    "gn:asciiname":"Trennerys",
    "gn:country_code":"ZA",
    "gn:dem":28,
    "gn:feature_class":"P",
    "gn:feature_code":"PPL",
    "gn:name":"Trennerys",
    "gn:population":0,
    "gn:timezone":"Africa/Johannesburg",
    "iso:country":"ZA",
    "name:und_x_variant":[
        "Trennerys Hotel",
        "Trennerys"
    ],
    "wof:lang_x_official":[
        "eng"
    ],
    "wof:lang_x_spoken":[
        "eng",
        "zul",
        "xho",
        "afr",
        "nso",
        "tsn",
        "sot",
        "tso",
        "ssw",
        "ven",
        "nbl"
    ],
    "wof:name":"Trennerys",
    "wof:placetype":"locality"
},
  "geometry": {"coordinates":[28.4267,-32.63473],"type":"Point"}
}