{
  "type": "Feature",
  "properties": {
    "gn:country":"ZA",
    "gn:fcode":"PPLX",
    "gn:population":0,
    "iso:country":"ZA",
    "name:ceb_x_preferred":[
        "Inanda"
    ],
    "name:deu_x_preferred":[
        "Inanda"
    ],
    "name:ita_x_preferred":[
        "Inanda"
    ],
    "qs_pg:aaroncc":"ZA",
    "qs_pg:gn_country":"ZA",
    "qs_pg:gn_fcode":"PPLX",
    "qs_pg:gn_pop":0,
    "qs_pg:name":"Inanda",
    "qs_pg:name_adm0":"South Africa",
    "qs_pg:name_adm1":"Gauteng",
    "qs_pg:photos":146,
    "qs_pg:photos_1k":30,
    "qs_pg:photos_9k":1,
    "qs_pg:photos_9r":3,
    "qs_pg:photos_all":146,
    "qs_pg:photos_sr":3,
    "qs_pg:pop_sr":0,
    "qs_pg:qs_pg_placetype":"neighbourhood",
    "qs_pg:qs_pg_placetype_gp":"Suburb",
    "qs_pg:woe_adm0":23424942,
    "woe:adm0_id":23424942,
    "woe:name_adm0":"South Africa",
    "woe:name_adm1":"Gauteng",
    "woe:placetype":"Suburb",
    "wof:lang_x_official":[
        "eng"
    ],
    "wof:lang_x_spoken":[
        "eng",
        "zul",
        "xho",
        "afr",
        "nso",
        "tsn",
        "sot",
        "tso",
        "ssw",
        "ven",
        "nbl"
    ],
    "wof:name":"Inanda",
    "wof:placetype":"neighbourhood"
},
  "geometry": {"coordinates":[28.05453,-26.12015],"type":"Point"}
}