{
  "type": "Feature",
  "properties": {
    "gn:admin1_code":"10",
    "gn:admin2_code":"DC38",
    "gn:admin3_code":"NW383",
    "gn:asciiname":"Malmanie Oog",
    "gn:country_code":"ZA",
    "gn:dem":1467,
    "gn:feature_class":"P",
    "gn:feature_code":"PPL",
    "gn:name":"Malmanie Oog",
    "gn:population":0,
    "gn:timezone":"Africa/Johannesburg",
    "iso:country":"ZA",
    "name:und_x_variant":[
        "Malmanie",
        "Malani Oog",
        "Malmanioog",
        "Malmanie Oog"
    ],
    "wof:name":"Malmanie Oog",
    "wof:placetype":"locality"
},
  "geometry": {"coordinates":[26.04983,-25.81356],"type":"Point"}
}