{
  "type": "Feature",
  "properties": {
    "gn:admin1_code":"2",
    "gn:admin2_code":"ETH",
    "gn:admin3_code":"ETH",
    "gn:asciiname":"Bedat",
    "gn:cc2":"ZA",
    "gn:country_code":"ZA",
    "gn:dem":704,
    "gn:feature_class":"P",
    "gn:feature_code":"PPL",
    "gn:name":"Bedat",
    "gn:population":0,
    "gn:timezone":"Africa/Johannesburg",
    "iso:country":"ZA",
    "name:und_x_variant":[
        "Bedat Store",
        "Bedat"
    ],
    "wof:name":"Bedat",
    "wof:placetype":"locality"
},
  "geometry": {"coordinates":[30.63333,-29.68333],"type":"Point"}
}