{
  "type": "Feature",
  "properties": {
    "gn:country":"ZA",
    "gn:fcode":"PPLX",
    "gn:population":0,
    "iso:country":"ZA",
    "name:bar_x_preferred":[
        "Sunnyside"
    ],
    "name:ceb_x_preferred":[
        "Sunnyside"
    ],
    "name:deu_x_preferred":[
        "Sunnyside"
    ],
    "name:fra_x_preferred":[
        "Sunnyside"
    ],
    "name:ita_x_preferred":[
        "Sunnyside"
    ],
    "name:kor_x_preferred":[
        "\uc11c\ub2c8\uc0ac\uc774\ub4dc"
    ],
    "name:nld_x_preferred":[
        "Sunnyside"
    ],
    "name:pol_x_preferred":[
        "Sunnyside"
    ],
    "name:por_x_preferred":[
        "Sunnyside"
    ],
    "name:rus_x_preferred":[
        "\u0421\u0430\u043d\u043d\u0438\u0441\u0430\u0439\u0434"
    ],
    "name:spa_x_preferred":[
        "Sunnyside"
    ],
    "name:srp_x_preferred":[
        "\u0421\u0430\u043d\u0438\u0441\u0430\u0458\u0434"
    ],
    "name:swe_x_preferred":[
        "Sunnyside"
    ],
    "name:vol_x_preferred":[
        "Sunnyside"
    ],
    "qs_pg:aaroncc":"ZA",
    "qs_pg:gn_country":"ZA",
    "qs_pg:gn_fcode":"PPLX",
    "qs_pg:gn_pop":0,
    "qs_pg:name":"Sunnyside",
    "qs_pg:name_adm0":"South Africa",
    "qs_pg:name_adm1":"Western Cape",
    "qs_pg:photos":61,
    "qs_pg:photos_1k":12,
    "qs_pg:photos_9k":1,
    "qs_pg:photos_9r":2,
    "qs_pg:photos_all":61,
    "qs_pg:photos_sr":2,
    "qs_pg:pop_sr":0,
    "qs_pg:qs_pg_placetype":"neighbourhood",
    "qs_pg:qs_pg_placetype_gp":"Suburb",
    "qs_pg:woe_adm0":23424942,
    "woe:adm0_id":23424942,
    "woe:name_adm0":"South Africa",
    "woe:name_adm1":"Western Cape",
    "woe:placetype":"Suburb",
    "wof:name":"Sunnyside",
    "wof:placetype":"neighbourhood"
},
  "geometry": {"coordinates":[18.51751,-33.96999],"type":"Point"}
}