{
  "type": "Feature",
  "properties": {
    "gn:admin1_code":"2",
    "gn:asciiname":"Cibini",
    "gn:country_code":"ZA",
    "gn:dem":1725,
    "gn:feature_class":"P",
    "gn:feature_code":"PPL",
    "gn:name":"Cibini",
    "gn:population":0,
    "gn:timezone":"Africa/Johannesburg",
    "iso:country":"ZA",
    "wof:name":"Cibini",
    "wof:placetype":"locality"
},
  "geometry": {"coordinates":[29.06538,-30.17201],"type":"Point"}
}