{
  "type": "Feature",
  "properties": {
    "gn:admin1_code":"5",
    "gn:admin2_code":"DC44",
    "gn:admin3_code":"EC442",
    "gn:asciiname":"Butsheni",
    "gn:country_code":"ZA",
    "gn:dem":937,
    "gn:feature_class":"P",
    "gn:feature_code":"PPL",
    "gn:name":"Butsheni",
    "gn:population":0,
    "gn:timezone":"Africa/Johannesburg",
    "iso:country":"ZA",
    "wof:name":"Butsheni",
    "wof:placetype":"locality"
},
  "geometry": {"coordinates":[29.05403,-30.84066],"type":"Point"}
}