{
  "type": "Feature",
  "properties": {
    "gn:admin1_code":"2.0",
    "gn:admin2_code":"DC28",
    "gn:admin3_code":"KZN286",
    "gn:asciiname":"Tandanani",
    "gn:country_code":"ZA",
    "gn:dem":1116,
    "gn:feature_class":"P",
    "gn:feature_code":"PPL",
    "gn:name":"Tandanani",
    "gn:population":0,
    "gn:timezone":"Africa/Johannesburg",
    "iso:country":"ZA",
    "wof:name":"Tandanani",
    "wof:placetype":"locality"
},
  "geometry": {"coordinates":[31.05597,-28.55482],"type":"Point"}
}