{
  "type": "Feature",
  "properties": {
    "gn:admin1_code":"10.0",
    "gn:asciiname":"Whitby",
    "gn:country_code":"ZA",
    "gn:dem":1062,
    "gn:feature_class":"P",
    "gn:feature_code":"PPL",
    "gn:name":"Whitby",
    "gn:population":0,
    "gn:timezone":"Africa/Johannesburg",
    "iso:country":"ZA",
    "name:ang_x_preferred":[
        "Str\u0113oneshalh"
    ],
    "name:azb_x_preferred":[
        "\u0648\u06cc\u062a\u0628\u06cc"
    ],
    "name:bre_x_preferred":[
        "Whitby"
    ],
    "name:cat_x_preferred":[
        "Whitby"
    ],
    "name:cym_x_preferred":[
        "Whitby"
    ],
    "name:dan_x_preferred":[
        "Whitby"
    ],
    "name:deu_x_preferred":[
        "Whitby"
    ],
    "name:epo_x_preferred":[
        "Whitby"
    ],
    "name:est_x_preferred":[
        "Whitby"
    ],
    "name:fas_x_preferred":[
        "\u0648\u06cc\u062a\u0628\u06cc"
    ],
    "name:fra_x_preferred":[
        "Whitby"
    ],
    "name:gle_x_preferred":[
        "Whitby"
    ],
    "name:ita_x_preferred":[
        "Whitby"
    ],
    "name:jpn_x_preferred":[
        "\u30a6\u30a3\u30c3\u30c8\u30d3\u30fc"
    ],
    "name:kor_x_preferred":[
        "\ud718\ud2b8\ube44"
    ],
    "name:lit_x_preferred":[
        "Vitbis"
    ],
    "name:nld_x_preferred":[
        "Whitby"
    ],
    "name:nno_x_preferred":[
        "Whitby"
    ],
    "name:nor_x_preferred":[
        "Whitby"
    ],
    "name:pol_x_preferred":[
        "Whitby"
    ],
    "name:ron_x_preferred":[
        "Whitby"
    ],
    "name:rus_x_preferred":[
        "\u0423\u0438\u0442\u0431\u0438"
    ],
    "name:spa_x_preferred":[
        "Whitby"
    ],
    "name:swe_x_preferred":[
        "Whitby"
    ],
    "name:vol_x_preferred":[
        "Whitby"
    ],
    "name:zho_x_preferred":[
        "\u60e0\u7279\u6bd4"
    ],
    "wof:lang_x_official":[
        "eng"
    ],
    "wof:lang_x_spoken":[
        "eng",
        "zul",
        "xho",
        "afr",
        "nso",
        "tsn",
        "sot",
        "tso",
        "ssw",
        "ven",
        "nbl"
    ],
    "wof:name":"Whitby",
    "wof:placetype":"locality"
},
  "geometry": {"coordinates":[23.10067,-26.57227],"type":"Point"}
}