{
  "type": "Feature",
  "properties": {
    "gn:admin1_code":"10.0",
    "gn:asciiname":"Whitby",
    "gn:country_code":"ZA",
    "gn:dem":1062,
    "gn:feature_class":"P",
    "gn:feature_code":"PPL",
    "gn:name":"Whitby",
    "gn:population":0,
    "gn:timezone":"Africa/Johannesburg",
    "iso:country":"ZA",
    "wof:name":"Whitby",
    "wof:placetype":"locality"
},
  "geometry": {"coordinates":[23.10067,-26.57227],"type":"Point"}
}