{
  "type": "Feature",
  "properties": {
    "gn:admin1_code":"9.0",
    "gn:admin2_code":"DC35",
    "gn:admin3_code":"LIM352",
    "gn:asciiname":"Sandfontein",
    "gn:country_code":"ZA",
    "gn:dem":1271,
    "gn:feature_class":"P",
    "gn:feature_code":"PPL",
    "gn:name":"Sandfontein",
    "gn:population":0,
    "gn:timezone":"Africa/Johannesburg",
    "iso:country":"ZA",
    "name:afr_x_preferred":[
        "Sandfontein"
    ],
    "name:est_x_preferred":[
        "Sandfontein"
    ],
    "name:nso_x_preferred":[
        "Sandfontein"
    ],
    "name:und_x_variant":[
        "Zandfontein"
    ],
    "wof:name":"Sandfontein",
    "wof:placetype":"locality"
},
  "geometry": {"coordinates":[29.12195,-23.72827],"type":"Point"}
}