{
  "type": "Feature",
  "properties": {
    "gn:admin1_code":"9",
    "gn:admin2_code":"DC33",
    "gn:admin3_code":"LIM334",
    "gn:asciiname":"Mashisimali Location",
    "gn:cc2":"ZA",
    "gn:country_code":"ZA",
    "gn:dem":415,
    "gn:feature_class":"P",
    "gn:feature_code":"PPLL",
    "gn:name":"Mashisimali Location",
    "gn:population":0,
    "gn:timezone":"Africa/Johannesburg",
    "iso:country":"ZA",
    "name:und_x_variant":[
        "Mashishimaleslokasie",
        "Mashisimalislokasie",
        "Mashisimali Location"
    ],
    "wof:name":"Mashisimali Location",
    "wof:placetype":"locality"
},
  "geometry": {"coordinates":[30.98333,-23.93333],"type":"Point"}
}