{
  "type": "Feature",
  "properties": {
    "gn:country":"ZA",
    "gn:fcode":"ADM3",
    "gn:population":136542,
    "iso:country":"ZA",
    "name:als_x_preferred":[
        "George"
    ],
    "name:ara_x_preferred":[
        "\u062c\u0648\u0631\u062c"
    ],
    "name:bre_x_preferred":[
        "George"
    ],
    "name:bul_x_preferred":[
        "\u0414\u0436\u043e\u0440\u0434\u0436"
    ],
    "name:cat_x_preferred":[
        "George"
    ],
    "name:ceb_x_preferred":[
        "George"
    ],
    "name:ces_x_preferred":[
        "George"
    ],
    "name:deu_x_preferred":[
        "George"
    ],
    "name:est_x_preferred":[
        "George"
    ],
    "name:fas_x_preferred":[
        "\u062c\u0631\u062c"
    ],
    "name:fin_x_preferred":[
        "George"
    ],
    "name:fra_x_preferred":[
        "George"
    ],
    "name:heb_x_preferred":[
        "\u05d2'\u05d5\u05e8\u05d2'"
    ],
    "name:hrv_x_preferred":[
        "George"
    ],
    "name:ita_x_preferred":[
        "George"
    ],
    "name:jpn_x_preferred":[
        "\u30b8\u30e7\u30fc\u30b8"
    ],
    "name:kaz_x_preferred":[
        "\u0414\u0436\u043e\u0440\u0434\u0436"
    ],
    "name:lav_x_preferred":[
        "George"
    ],
    "name:nep_x_preferred":[
        "\u091c\u0930\u094d\u091c"
    ],
    "name:nld_x_preferred":[
        "George"
    ],
    "name:pol_x_preferred":[
        "George"
    ],
    "name:por_x_preferred":[
        "George"
    ],
    "name:rus_x_preferred":[
        "\u0414\u0436\u043e\u0440\u0434\u0436"
    ],
    "name:slv_x_preferred":[
        "George"
    ],
    "name:spa_x_preferred":[
        "George"
    ],
    "name:srp_x_preferred":[
        "\u040f\u043e\u0440\u045f"
    ],
    "name:tam_x_preferred":[
        "\u0b9c\u0bbe\u0bb0\u0bcd\u0b9c\u0bcd"
    ],
    "name:tur_x_preferred":[
        "George"
    ],
    "name:ukr_x_preferred":[
        "\u0414\u0436\u043e\u0440\u0434\u0436"
    ],
    "name:vie_x_preferred":[
        "George"
    ],
    "name:vol_x_preferred":[
        "George"
    ],
    "qs_pg:aaroncc":"ZA",
    "qs_pg:gn_country":"ZA",
    "qs_pg:gn_fcode":"ADM3",
    "qs_pg:gn_pop":136542,
    "qs_pg:name":"George",
    "qs_pg:photos_9r":0,
    "qs_pg:photos_sr":0,
    "qs_pg:pop_sr":9,
    "qs_pg:qs_pg_placetype":"localadmin",
    "wof:lang_x_official":[
        "eng"
    ],
    "wof:lang_x_spoken":[
        "eng",
        "zul",
        "xho",
        "afr",
        "nso",
        "tsn",
        "sot",
        "tso",
        "ssw",
        "ven",
        "nbl"
    ],
    "wof:name":"George",
    "wof:placetype":"localadmin",
    "wof:population":136542
},
  "geometry": {"coordinates":[22.93003,-33.69528],"type":"Point"}
}