{
  "type": "Feature",
  "properties": {
    "gn:admin1_code":"5",
    "gn:admin2_code":"DC13",
    "gn:admin3_code":"EC132",
    "gn:asciiname":"Quaggafontein",
    "gn:country_code":"ZA",
    "gn:dem":1170,
    "gn:feature_class":"P",
    "gn:feature_code":"PPL",
    "gn:name":"Quaggafontein",
    "gn:population":0,
    "gn:timezone":"Africa/Johannesburg",
    "iso:country":"ZA",
    "wof:name":"Quaggafontein",
    "wof:placetype":"locality"
},
  "geometry": {"coordinates":[26.55165,-31.85552],"type":"Point"}
}