{
  "type": "Feature",
  "properties": {
    "gn:admin1_code":"8.0",
    "gn:admin2_code":"DC6",
    "gn:admin3_code":"NC065",
    "gn:asciiname":"O'Grabie West",
    "gn:country_code":"ZA",
    "gn:dem":946,
    "gn:feature_class":"P",
    "gn:feature_code":"PPL",
    "gn:name":"O\u2019Grabie West",
    "gn:population":0,
    "gn:timezone":"Africa/Johannesburg",
    "iso:country":"ZA",
    "wof:name":"O'Grabie West",
    "wof:placetype":"locality"
},
  "geometry": {"coordinates":[19.93333,-30.58333],"type":"Point"}
}