{
  "type": "Feature",
  "properties": {
    "gn:admin1_code":"11.0",
    "gn:admin2_code":"DC2",
    "gn:admin3_code":"WC024",
    "gn:asciiname":"Vlottenburg",
    "gn:country_code":"ZA",
    "gn:dem":55,
    "gn:feature_class":"P",
    "gn:feature_code":"PPL",
    "gn:name":"Vlottenburg",
    "gn:population":0,
    "gn:timezone":"Africa/Johannesburg",
    "iso:country":"ZA",
    "wof:name":"Vlottenburg",
    "wof:placetype":"locality"
},
  "geometry": {"coordinates":[18.79834,-33.95952],"type":"Point"}
}