{
  "type": "Feature",
  "properties": {
    "gn:admin1_code":"5",
    "gn:admin2_code":"DC15",
    "gn:admin3_code":"EC157",
    "gn:asciiname":"Ku-Nyokinala",
    "gn:country_code":"ZA",
    "gn:dem":966,
    "gn:feature_class":"P",
    "gn:feature_code":"PPL",
    "gn:name":"Ku-Nyokinala",
    "gn:population":0,
    "gn:timezone":"Africa/Johannesburg",
    "iso:country":"ZA",
    "wof:name":"Ku-Nyokinala",
    "wof:placetype":"locality"
},
  "geometry": {"coordinates":[28.47178,-31.64949],"type":"Point"}
}