{
  "type": "Feature",
  "properties": {
    "gn:country":"ZA",
    "gn:fcode":"PPLX",
    "gn:population":0,
    "iso:country":"ZA",
    "name:afr_x_preferred":[
        "Kloofsig"
    ],
    "name:eng_x_preferred":[
        "Kloofsig"
    ],
    "name:nld_x_preferred":[
        "Kloofsig"
    ],
    "qs_pg:aaroncc":"ZA",
    "qs_pg:gn_country":"ZA",
    "qs_pg:gn_fcode":"PPLX",
    "qs_pg:gn_pop":0,
    "qs_pg:name":"Kloofsig",
    "qs_pg:name_adm0":"South Africa",
    "qs_pg:name_adm1":"Gauteng",
    "qs_pg:photos_9k":1,
    "qs_pg:photos_9r":4,
    "qs_pg:photos_all":184,
    "qs_pg:photos_sr":0,
    "qs_pg:pop_sr":0,
    "qs_pg:qs_pg_placetype":"locality_gp_neighbourhood_gn",
    "qs_pg:qs_pg_placetype_gp":"Town",
    "qs_pg:woe_adm0":23424942,
    "woe:adm0_id":23424942,
    "woe:name_adm0":"South Africa",
    "woe:name_adm1":"Gauteng",
    "woe:placetype":"Town",
    "wof:lang_x_official":[
        "eng"
    ],
    "wof:lang_x_spoken":[
        "eng",
        "zul",
        "xho",
        "afr",
        "nso",
        "tsn",
        "sot",
        "tso",
        "ssw",
        "ven",
        "nbl"
    ],
    "wof:name":"Kloofsig",
    "wof:placetype":"locality"
},
  "geometry": {"coordinates":[28.20552,-25.81298],"type":"Point"}
}