{
  "type": "Feature",
  "properties": {
    "gn:admin1_code":"2.0",
    "gn:admin2_code":"DC21",
    "gn:admin3_code":"KZN213",
    "gn:asciiname":"Turton",
    "gn:country_code":"ZA",
    "gn:dem":46,
    "gn:feature_class":"P",
    "gn:feature_code":"PPL",
    "gn:name":"Turton",
    "gn:population":0,
    "gn:timezone":"Africa/Johannesburg",
    "iso:country":"ZA",
    "name:deu_x_preferred":[
        "Turton"
    ],
    "name:ita_x_preferred":[
        "Turton"
    ],
    "name:nds_x_preferred":[
        "Turton"
    ],
    "name:pol_x_preferred":[
        "Turton"
    ],
    "name:por_x_preferred":[
        "Turton"
    ],
    "name:rus_x_preferred":[
        "\u0422\u0435\u0440\u0442\u043e\u043d"
    ],
    "wof:lang_x_official":[
        "eng"
    ],
    "wof:lang_x_spoken":[
        "eng",
        "zul",
        "xho",
        "afr",
        "nso",
        "tsn",
        "sot",
        "tso",
        "ssw",
        "ven",
        "nbl"
    ],
    "wof:name":"Turton",
    "wof:placetype":"locality"
},
  "geometry": {"coordinates":[30.60756,-30.51701],"type":"Point"}
}