{
  "type": "Feature",
  "properties": {
    "gn:admin1_code":"6",
    "gn:admin2_code":"DC48",
    "gn:admin3_code":"GT481",
    "gn:asciiname":"Kromdraai",
    "gn:country_code":"ZA",
    "gn:dem":1440,
    "gn:feature_class":"P",
    "gn:feature_code":"PPL",
    "gn:name":"Kromdraai",
    "gn:population":0,
    "gn:timezone":"Africa/Johannesburg",
    "iso:country":"ZA",
    "name:afr_x_preferred":[
        "Kromdraai-fossielterrein"
    ],
    "name:fra_x_preferred":[
        "Kromdraai"
    ],
    "name:ita_x_preferred":[
        "Kromdraai"
    ],
    "wof:name":"Kromdraai",
    "wof:placetype":"locality"
},
  "geometry": {"coordinates":[27.78186,-25.99454],"type":"Point"}
}