{
  "type": "Feature",
  "properties": {
    "gn:admin1_code":"9.0",
    "gn:admin2_code":"DC35",
    "gn:admin3_code":"LIM351",
    "gn:asciiname":"Setlaole",
    "gn:country_code":"ZA",
    "gn:dem":1050,
    "gn:feature_class":"P",
    "gn:feature_code":"PPL",
    "gn:name":"Setlaole",
    "gn:population":0,
    "gn:timezone":"Africa/Johannesburg",
    "iso:country":"ZA",
    "wof:name":"Setlaole",
    "wof:placetype":"locality"
},
  "geometry": {"coordinates":[28.9562,-23.38696],"type":"Point"}
}