{
  "type": "Feature",
  "properties": {
    "gn:admin1_code":"5.0",
    "gn:admin2_code":"DC12",
    "gn:admin3_code":"EC123",
    "gn:asciiname":"Towerhill",
    "gn:country_code":"ZA",
    "gn:dem":289,
    "gn:feature_class":"P",
    "gn:feature_code":"PPL",
    "gn:name":"Towerhill",
    "gn:population":0,
    "gn:timezone":"Africa/Johannesburg",
    "iso:country":"ZA",
    "wof:name":"Towerhill",
    "wof:placetype":"locality"
},
  "geometry": {"coordinates":[28.02328,-32.79638],"type":"Point"}
}