{
  "type": "Feature",
  "properties": {
    "gn:admin1_code":"5",
    "gn:admin2_code":"DC15",
    "gn:admin3_code":"EC155",
    "gn:asciiname":"Kwa-Nolokoza",
    "gn:country_code":"ZA",
    "gn:dem":805,
    "gn:feature_class":"P",
    "gn:feature_code":"PPL",
    "gn:name":"Kwa-Nolokoza",
    "gn:population":0,
    "gn:timezone":"Africa/Johannesburg",
    "iso:country":"ZA",
    "wof:name":"Kwa-Nolokoza",
    "wof:placetype":"locality"
},
  "geometry": {"coordinates":[29.11667000000001,-31.35],"type":"Point"}
}