{
  "type": "Feature",
  "properties": {
    "gn:admin1_code":"11.0",
    "gn:admin2_code":"CPT",
    "gn:admin3_code":"CPT",
    "gn:asciiname":"Three Anchor Bay",
    "gn:country_code":"ZA",
    "gn:dem":6,
    "gn:feature_class":"P",
    "gn:feature_code":"PPL",
    "gn:name":"Three Anchor Bay",
    "gn:population":0,
    "gn:timezone":"Africa/Johannesburg",
    "iso:country":"ZA",
    "wof:name":"Three Anchor Bay",
    "wof:placetype":"locality"
},
  "geometry": {"coordinates":[18.40055,-33.90535999999999],"type":"Point"}
}