{
  "type": "Feature",
  "properties": {
    "gn:admin1_code":"2.0",
    "gn:admin2_code":"ETH",
    "gn:admin3_code":"ETH",
    "gn:asciiname":"Park Hill",
    "gn:country_code":"ZA",
    "gn:dem":88,
    "gn:feature_class":"P",
    "gn:feature_code":"PPL",
    "gn:name":"Park Hill",
    "gn:population":0,
    "gn:timezone":"Africa/Johannesburg",
    "iso:country":"ZA",
    "name:ceb_x_preferred":[
        "Park Hill"
    ],
    "name:deu_x_preferred":[
        "Park Hill"
    ],
    "name:ita_x_preferred":[
        "Park Hills"
    ],
    "name:nld_x_preferred":[
        "Park Hills"
    ],
    "name:pol_x_preferred":[
        "Park Hills"
    ],
    "name:por_x_preferred":[
        "Park Hill"
    ],
    "name:urd_x_preferred":[
        "\u067e\u0627\u0631\u06a9 \u06c1\u0644"
    ],
    "name:vol_x_preferred":[
        "Park Hills"
    ],
    "wof:name":"Park Hill",
    "wof:placetype":"locality"
},
  "geometry": {"coordinates":[31.0235,-29.78618],"type":"Point"}
}