{
  "type": "Feature",
  "properties": {
    "gn:admin1_code":"3",
    "gn:admin2_code":"DC16",
    "gn:admin3_code":"FS163",
    "gn:asciiname":"Boesmanskop",
    "gn:country_code":"ZA",
    "gn:dem":1521,
    "gn:feature_class":"P",
    "gn:feature_code":"PPL",
    "gn:name":"Boesmanskop",
    "gn:population":0,
    "gn:timezone":"Africa/Johannesburg",
    "iso:country":"ZA",
    "wof:name":"Boesmanskop",
    "wof:placetype":"locality"
},
  "geometry": {"coordinates":[27.11667000000001,-30.03333],"type":"Point"}
}