{
  "type": "Feature",
  "properties": {
    "gn:admin1_code":"2",
    "gn:admin2_code":"DC22",
    "gn:admin3_code":"KZN225",
    "gn:asciiname":"KwaMgwagwa",
    "gn:country_code":"ZA",
    "gn:dem":1297,
    "gn:feature_class":"P",
    "gn:feature_code":"PPL",
    "gn:name":"KwaMgwagwa",
    "gn:population":0,
    "gn:timezone":"Africa/Johannesburg",
    "iso:country":"ZA",
    "wof:name":"KwaMgwagwa",
    "wof:placetype":"locality"
},
  "geometry": {"coordinates":[30.17315,-29.62367],"type":"Point"}
}