{
  "type": "Feature",
  "properties": {
    "gn:admin1_code":"5.0",
    "gn:admin2_code":"DC13",
    "gn:admin3_code":"EC132",
    "gn:asciiname":"Rondezvous",
    "gn:country_code":"ZA",
    "gn:dem":1328,
    "gn:feature_class":"P",
    "gn:feature_code":"PPL",
    "gn:name":"Rondezvous",
    "gn:population":0,
    "gn:timezone":"Africa/Johannesburg",
    "iso:country":"ZA",
    "wof:name":"Rondezvous",
    "wof:placetype":"locality"
},
  "geometry": {"coordinates":[26.16062,-31.76439],"type":"Point"}
}