{
  "type": "Feature",
  "properties": {
    "iso:country":"ZA",
    "qs_pg:aaroncc":"ZA",
    "qs_pg:name":"Nompumelelo",
    "qs_pg:name_adm0":"South Africa",
    "qs_pg:name_adm1":"Eastern Cape",
    "qs_pg:photos":86,
    "qs_pg:photos_1k":17,
    "qs_pg:photos_9k":1,
    "qs_pg:photos_9r":3,
    "qs_pg:photos_all":86,
    "qs_pg:photos_sr":3,
    "qs_pg:pop_sr":0,
    "qs_pg:qs_pg_placetype":"locality",
    "qs_pg:qs_pg_placetype_gp":"Town",
    "qs_pg:woe_adm0":23424942,
    "woe:adm0_id":23424942,
    "woe:name_adm0":"South Africa",
    "woe:name_adm1":"Eastern Cape",
    "woe:placetype":"Town",
    "wof:name":"Nompumelelo",
    "wof:placetype":"locality"
},
  "geometry": {"coordinates":[23.9329735,-33.967569],"type":"Point"}
}