{
  "type": "Feature",
  "properties": {
    "gn:admin1_code":"2",
    "gn:admin2_code":"DC28",
    "gn:admin3_code":"KZN282",
    "gn:asciiname":"Ongoye",
    "gn:country_code":"ZA",
    "gn:dem":102,
    "gn:feature_class":"P",
    "gn:feature_code":"PPL",
    "gn:name":"Ongoye",
    "gn:population":0,
    "gn:timezone":"Africa/Johannesburg",
    "iso:country":"ZA",
    "wof:name":"Ongoye",
    "wof:placetype":"locality"
},
  "geometry": {"coordinates":[31.73871,-28.89162],"type":"Point"}
}