{
  "type": "Feature",
  "properties": {
    "gn:admin1_code":"2",
    "gn:admin2_code":"DC27",
    "gn:admin3_code":"KZN272",
    "gn:asciiname":"KwaNonjinjikazi",
    "gn:country_code":"ZA",
    "gn:dem":113,
    "gn:feature_class":"P",
    "gn:feature_code":"PPL",
    "gn:name":"KwaNonjinjikazi",
    "gn:population":0,
    "gn:timezone":"Africa/Johannesburg",
    "iso:country":"ZA",
    "name:und_x_variant":[
        "Nonjingigazi",
        "Nonjinjakazi",
        "KwaNonjinjikazi"
    ],
    "wof:name":"KwaNonjinjikazi",
    "wof:placetype":"locality"
},
  "geometry": {"coordinates":[32.13485,-27.06253],"type":"Point"}
}