{
  "type": "Feature",
  "properties": {
    "gn:admin1_code":"5",
    "gn:admin2_code":"DC12",
    "gn:admin3_code":"EC121",
    "gn:asciiname":"Mqonci",
    "gn:country_code":"ZA",
    "gn:dem":822,
    "gn:feature_class":"P",
    "gn:feature_code":"PPL",
    "gn:name":"Mqonci",
    "gn:population":0,
    "gn:timezone":"Africa/Johannesburg",
    "iso:country":"ZA",
    "name:und_x_variant":[
        "Thornville",
        "Mgonci",
        "Mqonce",
        "Mqonci"
    ],
    "wof:name":"Mqonci",
    "wof:placetype":"locality"
},
  "geometry": {"coordinates":[28.17754,-31.97656],"type":"Point"}
}