{
  "type": "Feature",
  "properties": {
    "gn:admin1_code":"5.0",
    "gn:admin2_code":"DC12",
    "gn:admin3_code":"EC126",
    "gn:asciiname":"Zalara",
    "gn:country_code":"ZA",
    "gn:dem":389,
    "gn:feature_class":"P",
    "gn:feature_code":"PPLL",
    "gn:name":"Zalara",
    "gn:population":0,
    "gn:timezone":"Africa/Johannesburg",
    "iso:country":"ZA",
    "wof:name":"Zalara",
    "wof:placetype":"locality"
},
  "geometry": {"coordinates":[27.17135,-32.99732],"type":"Point"}
}