{
  "type": "Feature",
  "properties": {
    "gn:admin1_code":"3",
    "gn:admin2_code":"DC16",
    "gn:admin3_code":"FS162",
    "gn:asciiname":"Kommetjesfontein",
    "gn:country_code":"ZA",
    "gn:dem":1515,
    "gn:feature_class":"P",
    "gn:feature_code":"PPL",
    "gn:name":"Kommetjesfontein",
    "gn:population":0,
    "gn:timezone":"Africa/Johannesburg",
    "iso:country":"ZA",
    "wof:name":"Kommetjesfontein",
    "wof:placetype":"locality"
},
  "geometry": {"coordinates":[25.63173,-30.1909],"type":"Point"}
}