{
  "type": "Feature",
  "properties": {
    "gn:admin1_code":"10",
    "gn:admin2_code":"DC38",
    "gn:admin3_code":"NW385",
    "gn:asciiname":"Liversedge",
    "gn:country_code":"ZA",
    "gn:dem":1132,
    "gn:feature_class":"P",
    "gn:feature_code":"PPL",
    "gn:name":"Liversedge",
    "gn:population":0,
    "gn:timezone":"Africa/Johannesburg",
    "iso:country":"ZA",
    "wof:name":"Liversedge",
    "wof:placetype":"locality"
},
  "geometry": {"coordinates":[26.23333,-25.43333],"type":"Point"}
}