{
  "type": "Feature",
  "properties": {
    "gn:admin1_code":"5",
    "gn:admin2_code":"DC10",
    "gn:admin3_code":"EC108",
    "gn:asciiname":"Otterford",
    "gn:country_code":"ZA",
    "gn:dem":462,
    "gn:feature_class":"P",
    "gn:feature_code":"PPL",
    "gn:name":"Otterford",
    "gn:population":0,
    "gn:timezone":"Africa/Johannesburg",
    "iso:country":"ZA",
    "name:bre_x_preferred":[
        "Otterford"
    ],
    "name:ceb_x_preferred":[
        "Otterford"
    ],
    "name:fas_x_preferred":[
        "\u0622\u062a\u0631\u0641\u0648\u0631\u062f"
    ],
    "name:ita_x_preferred":[
        "Otterford"
    ],
    "name:nld_x_preferred":[
        "Otterford"
    ],
    "name:pol_x_preferred":[
        "Otterford"
    ],
    "name:swe_x_preferred":[
        "Otterford"
    ],
    "wof:name":"Otterford",
    "wof:placetype":"locality"
},
  "geometry": {"coordinates":[25.01944,-33.78389],"type":"Point"}
}