{
  "type": "Feature",
  "properties": {
    "gn:admin1_code":"5",
    "gn:admin2_code":"DC10",
    "gn:admin3_code":"EC108",
    "gn:asciiname":"Otterford",
    "gn:country_code":"ZA",
    "gn:dem":462,
    "gn:feature_class":"P",
    "gn:feature_code":"PPL",
    "gn:name":"Otterford",
    "gn:population":0,
    "gn:timezone":"Africa/Johannesburg",
    "iso:country":"ZA",
    "wof:name":"Otterford",
    "wof:placetype":"locality"
},
  "geometry": {"coordinates":[25.01944,-33.78389],"type":"Point"}
}