{
  "type": "Feature",
  "properties": {
    "gn:admin1_code":"5",
    "gn:admin2_code":"DC15",
    "gn:admin3_code":"EC157",
    "gn:asciiname":"Ngcwanguba",
    "gn:country_code":"ZA",
    "gn:dem":485,
    "gn:feature_class":"P",
    "gn:feature_code":"PPL",
    "gn:name":"Ngcwanguba",
    "gn:population":0,
    "gn:timezone":"Africa/Johannesburg",
    "iso:country":"ZA",
    "name:und_x_variant":[
        "Ncwanguba",
        "Ngcwanguba"
    ],
    "wof:name":"Ngcwanguba",
    "wof:placetype":"locality"
},
  "geometry": {"coordinates":[29.03214,-31.91889],"type":"Point"}
}