{
  "type": "Feature",
  "properties": {
    "gn:admin1_code":"9",
    "gn:admin2_code":"DC36",
    "gn:admin3_code":"LIM366",
    "gn:asciiname":"Pienaarsrivier",
    "gn:cc2":"ZA",
    "gn:country_code":"ZA",
    "gn:dem":1048,
    "gn:feature_class":"P",
    "gn:feature_code":"PPL",
    "gn:name":"Pienaarsrivier",
    "gn:population":0,
    "gn:timezone":"Africa/Johannesburg",
    "iso:country":"ZA",
    "name:afr_x_preferred":[
        "Pienaarsrivier"
    ],
    "name:nso_x_preferred":[
        "Pienaarsrivier"
    ],
    "name:und_x_variant":[
        "Pienaar\u2019s River"
    ],
    "wof:name":"Pienaarsrivier",
    "wof:placetype":"locality"
},
  "geometry": {"coordinates":[28.30111,-25.20417],"type":"Point"}
}