{
  "type": "Feature",
  "properties": {
    "gn:admin1_code":"5",
    "gn:admin2_code":"DC14",
    "gn:admin3_code":"EC144",
    "gn:asciiname":"Dalmanutha",
    "gn:country_code":"ZA",
    "gn:dem":1381,
    "gn:feature_class":"P",
    "gn:feature_code":"PPL",
    "gn:name":"Dalmanutha",
    "gn:population":0,
    "gn:timezone":"Africa/Johannesburg",
    "iso:country":"ZA",
    "name:deu_x_preferred":[
        "Dalmanutha"
    ],
    "name:ind_x_preferred":[
        "Dalmanuta"
    ],
    "name:pol_x_preferred":[
        "Dalmanuta"
    ],
    "name:por_x_preferred":[
        "Dalmanuta"
    ],
    "name:rus_x_preferred":[
        "\u0414\u0430\u043b\u043c\u0430\u043d\u0443\u0444\u0430"
    ],
    "name:srp_x_preferred":[
        "\u0414\u0430\u043b\u043c\u0430\u043d\u0443\u0442\u0430"
    ],
    "name:swe_x_preferred":[
        "Dalmanuta"
    ],
    "name:tgl_x_preferred":[
        "Dalmanuta"
    ],
    "name:wol_x_preferred":[
        "Dalmanuta"
    ],
    "wof:name":"Dalmanutha",
    "wof:placetype":"locality"
},
  "geometry": {"coordinates":[26.49396,-30.89927],"type":"Point"}
}