{
  "type": "Feature",
  "properties": {
    "gn:admin1_code":"11",
    "gn:admin2_code":"DC4",
    "gn:admin3_code":"WC048",
    "gn:asciiname":"Kleinrivier",
    "gn:country_code":"ZA",
    "gn:dem":512,
    "gn:feature_class":"P",
    "gn:feature_code":"PPL",
    "gn:name":"Kleinrivier",
    "gn:population":0,
    "gn:timezone":"Africa/Johannesburg",
    "iso:country":"ZA",
    "wof:name":"Kleinrivier",
    "wof:placetype":"locality"
},
  "geometry": {"coordinates":[23.18333,-33.88333],"type":"Point"}
}