{
  "type": "Feature",
  "properties": {
    "gn:admin1_code":"3",
    "gn:asciiname":"Paardelaagte",
    "gn:country_code":"ZA",
    "gn:dem":1303,
    "gn:feature_class":"P",
    "gn:feature_code":"PPL",
    "gn:name":"Paardelaagte",
    "gn:population":0,
    "gn:timezone":"Africa/Johannesburg",
    "iso:country":"ZA",
    "wof:name":"Paardelaagte",
    "wof:placetype":"locality"
},
  "geometry": {"coordinates":[26.40406,-30.58147],"type":"Point"}
}