{
  "type": "Feature",
  "properties": {
    "gn:admin1_code":"10",
    "gn:asciiname":"Geelboom",
    "gn:country_code":"ZA",
    "gn:dem":1138,
    "gn:feature_class":"P",
    "gn:feature_code":"PPL",
    "gn:name":"Geelboom",
    "gn:population":0,
    "gn:timezone":"Africa/Johannesburg",
    "iso:country":"ZA",
    "wof:name":"Geelboom",
    "wof:placetype":"locality"
},
  "geometry": {"coordinates":[23.18173,-27.17339],"type":"Point"}
}