{
  "type": "Feature",
  "properties": {
    "gn:admin1_code":"7.0",
    "gn:asciiname":"Uitvlugt",
    "gn:country_code":"ZA",
    "gn:dem":909,
    "gn:feature_class":"P",
    "gn:feature_code":"PPL",
    "gn:name":"Uitvlugt",
    "gn:population":0,
    "gn:timezone":"Africa/Johannesburg",
    "iso:country":"ZA",
    "name:nld_x_preferred":[
        "Uitvlugt"
    ],
    "wof:name":"Uitvlugt",
    "wof:placetype":"locality"
},
  "geometry": {"coordinates":[29.92571,-24.98745],"type":"Point"}
}