{
  "type": "Feature",
  "properties": {
    "gn:admin1_code":"5",
    "gn:admin2_code":"DC14",
    "gn:admin3_code":"EC142",
    "gn:asciiname":"Makhumsha",
    "gn:country_code":"ZA",
    "gn:dem":1760,
    "gn:feature_class":"P",
    "gn:feature_code":"PPL",
    "gn:name":"Makhumsha",
    "gn:population":0,
    "gn:timezone":"Africa/Johannesburg",
    "iso:country":"ZA",
    "wof:name":"Makhumsha",
    "wof:placetype":"locality"
},
  "geometry": {"coordinates":[27.67007000000001,-30.55215],"type":"Point"}
}