{
  "type": "Feature",
  "properties": {
    "gn:admin1_code":"5.0",
    "gn:admin2_code":"DC14",
    "gn:admin3_code":"EC141",
    "gn:asciiname":"Thabaputsoa",
    "gn:country_code":"ZA",
    "gn:dem":1470,
    "gn:feature_class":"P",
    "gn:feature_code":"PPL",
    "gn:name":"Thabaputsoa",
    "gn:population":0,
    "gn:timezone":"Africa/Johannesburg",
    "iso:country":"ZA",
    "wof:name":"Thabaputsoa",
    "wof:placetype":"locality"
},
  "geometry": {"coordinates":[28.44431,-30.69165],"type":"Point"}
}