{
  "type": "Feature",
  "properties": {
    "gn:admin1_code":"5",
    "gn:admin2_code":"DC44",
    "gn:admin3_code":"EC442",
    "gn:asciiname":"Cabase",
    "gn:country_code":"ZA",
    "gn:dem":1038,
    "gn:feature_class":"P",
    "gn:feature_code":"PPL",
    "gn:name":"Cabase",
    "gn:population":0,
    "gn:timezone":"Africa/Johannesburg",
    "iso:country":"ZA",
    "wof:name":"Cabase",
    "wof:placetype":"locality"
},
  "geometry": {"coordinates":[28.9981,-30.835],"type":"Point"}
}