{
  "type": "Feature",
  "properties": {
    "gn:admin1_code":"10.0",
    "gn:admin2_code":"DC38",
    "gn:admin3_code":"NW385",
    "gn:asciiname":"Madikwe Game Reserve",
    "gn:country_code":"ZA",
    "gn:dem":1071,
    "gn:feature_class":"P",
    "gn:feature_code":"PPL",
    "gn:name":"Madikwe Game Reserve",
    "gn:population":0,
    "gn:timezone":"Africa/Johannesburg",
    "iso:country":"ZA",
    "name:afr_x_preferred":[
        "Madikwe-wildreservaat"
    ],
    "wof:name":"Madikwe Game Reserve",
    "wof:placetype":"locality"
},
  "geometry": {"coordinates":[26.25732,-24.74351],"type":"Point"}
}