{
  "type": "Feature",
  "properties": {
    "gn:admin1_code":"5.0",
    "gn:admin2_code":"BUF",
    "gn:admin3_code":"BUF",
    "gn:asciiname":"Sandile",
    "gn:country_code":"ZA",
    "gn:dem":65,
    "gn:feature_class":"P",
    "gn:feature_code":"PPL",
    "gn:name":"Sandile",
    "gn:population":0,
    "gn:timezone":"Africa/Johannesburg",
    "iso:country":"ZA",
    "wof:name":"Sandile",
    "wof:placetype":"locality"
},
  "geometry": {"coordinates":[27.5465,-33.15159],"type":"Point"}
}