{
  "type": "Feature",
  "properties": {
    "gn:admin1_code":"11",
    "gn:admin2_code":"DC4",
    "gn:admin3_code":"WC047",
    "gn:asciiname":"Nature's Valley",
    "gn:country_code":"ZA",
    "gn:dem":12,
    "gn:feature_class":"P",
    "gn:feature_code":"PPL",
    "gn:name":"Nature\u2019s Valley",
    "gn:population":0,
    "gn:timezone":"Africa/Johannesburg",
    "iso:country":"ZA",
    "name:und_x_variant":[
        "Nature\u2019s Valley"
    ],
    "wof:name":"Nature's Valley",
    "wof:placetype":"locality"
},
  "geometry": {"coordinates":[23.55735,-33.98054],"type":"Point"}
}