{
  "type": "Feature",
  "properties": {
    "gn:admin1_code":"11",
    "gn:admin2_code":"DC4",
    "gn:admin3_code":"WC047",
    "gn:asciiname":"Nature's Valley",
    "gn:country_code":"ZA",
    "gn:dem":12,
    "gn:feature_class":"P",
    "gn:feature_code":"PPL",
    "gn:name":"Nature\u2019s Valley",
    "gn:population":0,
    "gn:timezone":"Africa/Johannesburg",
    "iso:country":"ZA",
    "name:afr_x_preferred":[
        "Nature's Valley"
    ],
    "name:est_x_preferred":[
        "Nature's Valley"
    ],
    "name:hye_x_preferred":[
        "\u0546\u0565\u0575\u0579\u0580\u057d \u054e\u0561\u056c\u056c\u056b"
    ],
    "name:nld_x_preferred":[
        "Nature's Valley"
    ],
    "name:nso_x_preferred":[
        "Nature's Valley"
    ],
    "name:por_x_preferred":[
        "Nature's Valley"
    ],
    "name:ron_x_preferred":[
        "Nature's Valley"
    ],
    "name:rus_x_preferred":[
        "\u041d\u0435\u0439\u0447\u0435\u0440\u0441-\u0412\u0430\u043b\u043b\u0438"
    ],
    "name:swa_x_preferred":[
        "Nature's Valley"
    ],
    "name:ukr_x_preferred":[
        "\u041d\u0435\u0439\u0447\u0435\u0440\u0441-\u0412\u0435\u043b\u043b\u0456"
    ],
    "name:und_x_variant":[
        "Nature\u2019s Valley"
    ],
    "wof:name":"Nature's Valley",
    "wof:placetype":"locality"
},
  "geometry": {"coordinates":[23.55735,-33.98054],"type":"Point"}
}