{
  "type": "Feature",
  "properties": {
    "gn:admin1_code":"5.0",
    "gn:admin2_code":"DC12",
    "gn:admin3_code":"EC127",
    "gn:asciiname":"Thorndale",
    "gn:country_code":"ZA",
    "gn:dem":613,
    "gn:feature_class":"P",
    "gn:feature_code":"PPL",
    "gn:name":"Thorndale",
    "gn:population":0,
    "gn:timezone":"Africa/Johannesburg",
    "iso:country":"ZA",
    "name:ceb_x_preferred":[
        "Thorndale"
    ],
    "name:deu_x_preferred":[
        "Thorndale"
    ],
    "name:ita_x_preferred":[
        "Thorndale"
    ],
    "name:nld_x_preferred":[
        "Thorndale"
    ],
    "name:pol_x_preferred":[
        "Thorndale"
    ],
    "name:por_x_preferred":[
        "Thorndale"
    ],
    "name:srp_x_preferred":[
        "\u0422\u043e\u0440\u043d\u0434\u0435\u0458\u043b"
    ],
    "wof:lang_x_official":[
        "eng"
    ],
    "wof:lang_x_spoken":[
        "eng",
        "zul",
        "xho",
        "afr",
        "nso",
        "tsn",
        "sot",
        "tso",
        "ssw",
        "ven",
        "nbl"
    ],
    "wof:name":"Thorndale",
    "wof:placetype":"locality"
},
  "geometry": {"coordinates":[26.86222,-32.71535],"type":"Point"}
}