{
  "type": "Feature",
  "properties": {
    "gn:admin1_code":"11.0",
    "gn:admin2_code":"DC3",
    "gn:admin3_code":"WC032",
    "gn:asciiname":"Hawston",
    "gn:country_code":"ZA",
    "gn:dem":21,
    "gn:feature_class":"P",
    "gn:feature_code":"PPL",
    "gn:name":"Hawston",
    "gn:population":0,
    "gn:timezone":"Africa/Johannesburg",
    "iso:country":"ZA",
    "name:afr_x_preferred":[
        "Hawston"
    ],
    "name:est_x_preferred":[
        "Hawston"
    ],
    "name:ita_x_preferred":[
        "Hawston"
    ],
    "name:nld_x_preferred":[
        "Hawston"
    ],
    "name:ron_x_preferred":[
        "Hawston"
    ],
    "name:rus_x_preferred":[
        "\u0425\u043e\u0441\u0442\u043e\u043d"
    ],
    "wof:name":"Hawston",
    "wof:placetype":"locality"
},
  "geometry": {"coordinates":[19.13099,-34.38634],"type":"Point"}
}