{
  "type": "Feature",
  "properties": {
    "iso:country":"ZA",
    "name:afr_x_preferred":[
        "Jeppestown"
    ],
    "name:ast_x_preferred":[
        "Jeppestown"
    ],
    "name:deu_x_preferred":[
        "Jeppestown"
    ],
    "name:eng_x_preferred":[
        "Jeppestown"
    ],
    "name:fas_x_preferred":[
        "\u0698\u067e\u0633\u062a\u0627\u0648\u0646"
    ],
    "name:nld_x_preferred":[
        "Jeppestown"
    ],
    "name:nso_x_preferred":[
        "Jeppestown"
    ],
    "qs:gn_adm0_cc":"ZA",
    "qs:gn_local":993800,
    "qs:gn_nam_loc":"Johannesburg, Johannesburg, City of Johannesburg, Gauteng, ZA",
    "qs:gn_namadm1":"06",
    "qs:local_max":2766,
    "qs:local_sum":31655,
    "qs:localhoods":69,
    "qs:name":"Jeppestown",
    "qs:name_adm0":"South Africa",
    "qs:name_adm1":"Gauteng",
    "qs:name_adm2":"City of Johannesburg",
    "qs:name_lau":"Johannesburg",
    "qs:name_local":"Johannesburg",
    "qs:photo_max":33,
    "qs:photo_sum":115,
    "qs:placetype":"Suburb",
    "qs:quad_count":12,
    "qs:woe_adm0":23424942,
    "qs:woe_adm1":2346981,
    "qs:woe_adm2":56189422,
    "qs:woe_lau":56189710,
    "qs:woe_local":1582504,
    "qs:woe_ver":"7.10.0",
    "wd:wordcount":208,
    "wof:lang_x_official":[
        "eng"
    ],
    "wof:lang_x_spoken":[
        "eng",
        "zul",
        "xho",
        "afr",
        "nso",
        "tsn",
        "sot",
        "tso",
        "ssw",
        "ven",
        "nbl"
    ],
    "wof:name":"Jeppestown",
    "wof:placetype":"neighbourhood"
},
  "geometry": {"coordinates":[28.072129,-26.203953],"type":"Point"}
}