{
  "type": "Feature",
  "properties": {
    "gn:admin1_code":"2",
    "gn:admin2_code":"DC22",
    "gn:admin3_code":"KZN227",
    "gn:asciiname":"eMgadleteni",
    "gn:country_code":"ZA",
    "gn:dem":694,
    "gn:feature_class":"P",
    "gn:feature_code":"PPL",
    "gn:name":"eMgadleteni",
    "gn:population":0,
    "gn:timezone":"Africa/Johannesburg",
    "iso:country":"ZA",
    "wof:lang_x_official":[
        "eng"
    ],
    "wof:lang_x_spoken":[
        "eng",
        "zul",
        "xho",
        "afr",
        "nso",
        "tsn",
        "sot",
        "tso",
        "ssw",
        "ven",
        "nbl"
    ],
    "wof:name":"eMgadleteni",
    "wof:placetype":"locality"
},
  "geometry": {"coordinates":[30.21053,-29.94846],"type":"Point"}
}