{
  "type": "Feature",
  "properties": {
    "gn:admin1_code":"5.0",
    "gn:admin2_code":"DC14",
    "gn:admin3_code":"EC144",
    "gn:asciiname":"Verstersfontein",
    "gn:country_code":"ZA",
    "gn:dem":1587,
    "gn:feature_class":"P",
    "gn:feature_code":"PPL",
    "gn:name":"Verstersfontein",
    "gn:population":0,
    "gn:timezone":"Africa/Johannesburg",
    "iso:country":"ZA",
    "wof:name":"Verstersfontein",
    "wof:placetype":"locality"
},
  "geometry": {"coordinates":[25.66394,-31.06335],"type":"Point"}
}