{
  "type": "Feature",
  "properties": {
    "gn:admin1_code":"8",
    "gn:admin2_code":"DC8",
    "gn:admin3_code":"NC081",
    "gn:asciiname":"Mooirivier",
    "gn:country_code":"ZA",
    "gn:dem":825,
    "gn:feature_class":"P",
    "gn:feature_code":"PPL",
    "gn:name":"Mooirivier",
    "gn:population":0,
    "gn:timezone":"Africa/Johannesburg",
    "iso:country":"ZA",
    "name:und_x_variant":[
        "Klipkolk",
        "Mooirivier"
    ],
    "wof:name":"Mooirivier",
    "wof:placetype":"locality"
},
  "geometry": {"coordinates":[20.09263,-26.87531],"type":"Point"}
}