{
  "type": "Feature",
  "properties": {
    "gn:admin1_code":"2.0",
    "gn:admin2_code":"ETH",
    "gn:admin3_code":"ETH",
    "gn:asciiname":"Shallcross",
    "gn:country_code":"ZA",
    "gn:dem":223,
    "gn:feature_class":"P",
    "gn:feature_code":"PPL",
    "gn:name":"Shallcross",
    "gn:population":0,
    "gn:timezone":"Africa/Johannesburg",
    "iso:country":"ZA",
    "wof:name":"Shallcross",
    "wof:placetype":"locality"
},
  "geometry": {"coordinates":[30.88037000000001,-29.88887],"type":"Point"}
}