{
  "type": "Feature",
  "properties": {
    "gn:admin1_code":"8",
    "gn:admin2_code":"DC7",
    "gn:admin3_code":"NC078",
    "gn:asciiname":"Higgs' Hope",
    "gn:country_code":"ZA",
    "gn:dem":996,
    "gn:feature_class":"P",
    "gn:feature_code":"PPL",
    "gn:name":"Higgs\u2019 Hope",
    "gn:population":0,
    "gn:timezone":"Africa/Johannesburg",
    "iso:country":"ZA",
    "wof:lang_x_official":[
        "eng"
    ],
    "wof:lang_x_spoken":[
        "eng",
        "zul",
        "xho",
        "afr",
        "nso",
        "tsn",
        "sot",
        "tso",
        "ssw",
        "ven",
        "nbl"
    ],
    "wof:name":"Higgs' Hope",
    "wof:placetype":"locality"
},
  "geometry": {"coordinates":[23.26667,-29.31667],"type":"Point"}
}