{
  "type": "Feature",
  "properties": {
    "gn:country":"ZA",
    "gn:fcode":"PPL",
    "gn:population":0,
    "iso:country":"ZA",
    "name:afr_x_preferred":[
        "Reebok"
    ],
    "name:eng_x_preferred":[
        "Klein Brak Rivier"
    ],
    "name:fra_x_preferred":[
        "Klein Brakrivier"
    ],
    "name:nld_x_preferred":[
        "Klein Brakrivier"
    ],
    "name:nso_x_preferred":[
        "Little Brak River"
    ],
    "name:ukr_x_preferred":[
        "\u041a\u043b\u0435\u0456\u043d-\u0411\u0440\u0430\u043a-\u0420\u0456\u0432'\u0454\u0440"
    ],
    "name:zho_x_preferred":[
        "\u5c0f\u5e03\u62c9\u514b\u6cb3"
    ],
    "qs_pg:aaroncc":"ZA",
    "qs_pg:gn_country":"ZA",
    "qs_pg:gn_fcode":"PPL",
    "qs_pg:gn_pop":0,
    "qs_pg:name":"Klein-Brakrivier",
    "qs_pg:name_adm0":"South Africa",
    "qs_pg:name_adm1":"Western Cape",
    "qs_pg:photos":191,
    "qs_pg:photos_1k":39,
    "qs_pg:photos_9k":1,
    "qs_pg:photos_9r":4,
    "qs_pg:photos_all":191,
    "qs_pg:photos_sr":4,
    "qs_pg:pop_sr":0,
    "qs_pg:qs_pg_placetype":"locality",
    "qs_pg:qs_pg_placetype_gp":"Town",
    "qs_pg:woe_adm0":23424942,
    "woe:adm0_id":23424942,
    "woe:name_adm0":"South Africa",
    "woe:name_adm1":"Western Cape",
    "woe:placetype":"Town",
    "wof:lang_x_official":[
        "eng"
    ],
    "wof:lang_x_spoken":[
        "eng",
        "zul",
        "xho",
        "afr",
        "nso",
        "tsn",
        "sot",
        "tso",
        "ssw",
        "ven",
        "nbl"
    ],
    "wof:name":"Klein-Brakrivier",
    "wof:placetype":"locality"
},
  "geometry": {"coordinates":[22.14763,-34.08286],"type":"Point"}
}