{
  "type": "Feature",
  "properties": {
    "gn:admin1_code":"3.0",
    "gn:asciiname":"The Junction",
    "gn:country_code":"ZA",
    "gn:dem":1305,
    "gn:feature_class":"P",
    "gn:feature_code":"PPL",
    "gn:name":"The Junction",
    "gn:population":0,
    "gn:timezone":"Africa/Johannesburg",
    "iso:country":"ZA",
    "wof:name":"The Junction",
    "wof:placetype":"locality"
},
  "geometry": {"coordinates":[26.76664,-30.65736],"type":"Point"}
}