{
  "type": "Feature",
  "properties": {
    "gn:admin1_code":"10.0",
    "gn:admin2_code":"DC40",
    "gn:admin3_code":"NW403",
    "gn:asciiname":"Syferkuil",
    "gn:country_code":"ZA",
    "gn:dem":1449,
    "gn:feature_class":"P",
    "gn:feature_code":"PPL",
    "gn:name":"Syferkuil",
    "gn:population":0,
    "gn:timezone":"Africa/Johannesburg",
    "iso:country":"ZA",
    "wof:name":"Syferkuil",
    "wof:placetype":"locality"
},
  "geometry": {"coordinates":[26.41667,-26.51667],"type":"Point"}
}