{
  "type": "Feature",
  "properties": {
    "gn:admin1_code":"10",
    "gn:admin2_code":"DC38",
    "gn:admin3_code":"NW384",
    "gn:asciiname":"Hakboslaagte",
    "gn:country_code":"ZA",
    "gn:dem":1509,
    "gn:feature_class":"P",
    "gn:feature_code":"PPL",
    "gn:name":"Hakboslaagte",
    "gn:population":0,
    "gn:timezone":"Africa/Johannesburg",
    "iso:country":"ZA",
    "wof:name":"Hakboslaagte",
    "wof:placetype":"locality"
},
  "geometry": {"coordinates":[26.15298,-26.32711],"type":"Point"}
}