{
  "type": "Feature",
  "properties": {
    "gn:admin1_code":"8.0",
    "gn:admin2_code":"DC8",
    "gn:admin3_code":"NC084",
    "gn:asciiname":"Varsput",
    "gn:country_code":"ZA",
    "gn:dem":898,
    "gn:feature_class":"P",
    "gn:feature_code":"PPL",
    "gn:name":"Varsput",
    "gn:population":0,
    "gn:timezone":"Africa/Johannesburg",
    "iso:country":"ZA",
    "wof:name":"Varsput",
    "wof:placetype":"locality"
},
  "geometry": {"coordinates":[21.36654,-29.2901],"type":"Point"}
}