{
  "type": "Feature",
  "properties": {
    "gn:admin1_code":"2",
    "gn:admin2_code":"DC26",
    "gn:admin3_code":"KZN266",
    "gn:asciiname":"Bululwane",
    "gn:country_code":"ZA",
    "gn:dem":432,
    "gn:feature_class":"P",
    "gn:feature_code":"PPL",
    "gn:name":"Bululwane",
    "gn:population":0,
    "gn:timezone":"Africa/Johannesburg",
    "iso:country":"ZA",
    "wof:name":"Bululwane",
    "wof:placetype":"locality"
},
  "geometry": {"coordinates":[31.49618,-27.93707],"type":"Point"}
}