{
  "type": "Feature",
  "properties": {
    "gn:admin1_code":"2",
    "gn:admin2_code":"DC29",
    "gn:admin3_code":"KZN292",
    "gn:asciiname":"New Guelderland",
    "gn:country_code":"ZA",
    "gn:dem":63,
    "gn:feature_class":"P",
    "gn:feature_code":"PPL",
    "gn:name":"New Guelderland",
    "gn:population":0,
    "gn:timezone":"Africa/Johannesburg",
    "iso:country":"ZA",
    "name:afr_x_preferred":[
        "Nieu-Guelderland"
    ],
    "wof:lang_x_official":[
        "eng"
    ],
    "wof:lang_x_spoken":[
        "eng",
        "zul",
        "xho",
        "afr",
        "nso",
        "tsn",
        "sot",
        "tso",
        "ssw",
        "ven",
        "nbl"
    ],
    "wof:name":"New Guelderland",
    "wof:placetype":"locality"
},
  "geometry": {"coordinates":[31.32942,-29.32459],"type":"Point"}
}