{
  "type": "Feature",
  "properties": {
    "gn:admin1_code":"2",
    "gn:admin2_code":"DC21",
    "gn:admin3_code":"KZN213",
    "gn:asciiname":"Hazeldene",
    "gn:country_code":"ZA",
    "gn:dem":272,
    "gn:feature_class":"P",
    "gn:feature_code":"PPL",
    "gn:name":"Hazeldene",
    "gn:population":0,
    "gn:timezone":"Africa/Johannesburg",
    "iso:country":"ZA",
    "wof:lang_x_official":[
        "eng"
    ],
    "wof:lang_x_spoken":[
        "eng",
        "zul",
        "xho",
        "afr",
        "nso",
        "tsn",
        "sot",
        "tso",
        "ssw",
        "ven",
        "nbl"
    ],
    "wof:name":"Hazeldene",
    "wof:placetype":"locality"
},
  "geometry": {"coordinates":[30.52934,-30.5082],"type":"Point"}
}