{
  "type": "Feature",
  "properties": {
    "gn:admin1_code":"9",
    "gn:admin2_code":"DC35",
    "gn:admin3_code":"LIM352",
    "gn:asciiname":"Ga-Mankgodi",
    "gn:country_code":"ZA",
    "gn:dem":1053,
    "gn:feature_class":"P",
    "gn:feature_code":"PPL",
    "gn:name":"Ga-Mankgodi",
    "gn:population":0,
    "gn:timezone":"Africa/Johannesburg",
    "iso:country":"ZA",
    "wof:name":"Ga-Mankgodi",
    "wof:placetype":"locality"
},
  "geometry": {"coordinates":[29.00807,-23.45023],"type":"Point"}
}