{
  "type": "Feature",
  "properties": {
    "gn:admin1_code":"2.0",
    "gn:admin2_code":"DC43",
    "gn:admin3_code":"KZN433",
    "gn:asciiname":"Spitskop",
    "gn:country_code":"ZA",
    "gn:dem":1845,
    "gn:feature_class":"P",
    "gn:feature_code":"PPL",
    "gn:name":"Spitskop",
    "gn:population":0,
    "gn:timezone":"Africa/Johannesburg",
    "iso:country":"ZA",
    "wof:name":"Spitskop",
    "wof:placetype":"locality"
},
  "geometry": {"coordinates":[29.49776,-30.34006],"type":"Point"}
}