{
  "type": "Feature",
  "properties": {
    "gn:admin1_code":"5.0",
    "gn:admin2_code":"DC10",
    "gn:admin3_code":"EC108",
    "gn:asciiname":"Sandland",
    "gn:country_code":"ZA",
    "gn:dem":132,
    "gn:feature_class":"P",
    "gn:feature_code":"PPL",
    "gn:name":"Sandland",
    "gn:population":0,
    "gn:timezone":"Africa/Johannesburg",
    "iso:country":"ZA",
    "name:jav_x_preferred":[
        "Sandland"
    ],
    "name:msa_x_preferred":[
        "Sandland"
    ],
    "name:nor_x_preferred":[
        "Sandland"
    ],
    "wof:lang_x_official":[
        "eng"
    ],
    "wof:lang_x_spoken":[
        "eng",
        "zul",
        "xho",
        "afr",
        "nso",
        "tsn",
        "sot",
        "tso",
        "ssw",
        "ven",
        "nbl"
    ],
    "wof:name":"Sandland",
    "wof:placetype":"locality"
},
  "geometry": {"coordinates":[24.58872,-33.67503],"type":"Point"}
}