{
  "type": "Feature",
  "properties": {
    "gn:admin1_code":"5",
    "gn:admin2_code":"DC14",
    "gn:admin3_code":"EC141",
    "gn:asciiname":"Bowden",
    "gn:country_code":"ZA",
    "gn:dem":1898,
    "gn:feature_class":"P",
    "gn:feature_code":"PPL",
    "gn:name":"Bowden",
    "gn:population":0,
    "gn:timezone":"Africa/Johannesburg",
    "iso:country":"ZA",
    "wof:name":"Bowden",
    "wof:placetype":"locality"
},
  "geometry": {"coordinates":[28.21098,-30.74334],"type":"Point"}
}