{
  "type": "Feature",
  "properties": {
    "gn:admin1_code":"5",
    "gn:admin2_code":"DC14",
    "gn:admin3_code":"EC141",
    "gn:asciiname":"Bowden",
    "gn:country_code":"ZA",
    "gn:dem":1898,
    "gn:feature_class":"P",
    "gn:feature_code":"PPL",
    "gn:name":"Bowden",
    "gn:population":0,
    "gn:timezone":"Africa/Johannesburg",
    "iso:country":"ZA",
    "name:cat_x_preferred":[
        "Bowden"
    ],
    "name:ceb_x_preferred":[
        "Bowden"
    ],
    "name:deu_x_preferred":[
        "Bowden"
    ],
    "name:fra_x_preferred":[
        "Bowden"
    ],
    "name:ita_x_preferred":[
        "Bowden"
    ],
    "name:jpn_x_preferred":[
        "\u30dc\u30a6\u30c7\u30f3"
    ],
    "name:nld_x_preferred":[
        "Bowden"
    ],
    "name:pol_x_preferred":[
        "Bowden"
    ],
    "name:por_x_preferred":[
        "Bowden"
    ],
    "name:rus_x_preferred":[
        "\u0411\u043e\u0443\u0434\u0435\u043d"
    ],
    "name:swe_x_preferred":[
        "Bowden"
    ],
    "wof:lang_x_official":[
        "eng"
    ],
    "wof:lang_x_spoken":[
        "eng",
        "zul",
        "xho",
        "afr",
        "nso",
        "tsn",
        "sot",
        "tso",
        "ssw",
        "ven",
        "nbl"
    ],
    "wof:name":"Bowden",
    "wof:placetype":"locality"
},
  "geometry": {"coordinates":[28.21098,-30.74334],"type":"Point"}
}