{
  "type": "Feature",
  "properties": {
    "gn:admin1_code":"2",
    "gn:admin2_code":"DC43",
    "gn:admin3_code":"KZN431",
    "gn:asciiname":"eMfulumane",
    "gn:country_code":"ZA",
    "gn:dem":1629,
    "gn:feature_class":"P",
    "gn:feature_code":"PPL",
    "gn:name":"eMfulumane",
    "gn:population":0,
    "gn:timezone":"Africa/Johannesburg",
    "iso:country":"ZA",
    "wof:name":"eMfulumane",
    "wof:placetype":"locality"
},
  "geometry": {"coordinates":[29.5714,-29.9708],"type":"Point"}
}