{
  "type": "Feature",
  "properties": {
    "gn:admin1_code":"9",
    "gn:admin2_code":"DC36",
    "gn:admin3_code":"LIM362",
    "gn:asciiname":"KwaMadibaneng",
    "gn:country_code":"ZA",
    "gn:dem":849,
    "gn:feature_class":"P",
    "gn:feature_code":"PPL",
    "gn:name":"KwaMadibaneng",
    "gn:population":0,
    "gn:timezone":"Africa/Johannesburg",
    "iso:country":"ZA",
    "wof:name":"KwaMadibaneng",
    "wof:placetype":"locality"
},
  "geometry": {"coordinates":[27.98107000000001,-23.21906],"type":"Point"}
}