{
  "type": "Feature",
  "properties": {
    "gn:admin1_code":"10",
    "gn:asciiname":"Metsemantsi (3)",
    "gn:country_code":"ZA",
    "gn:dem":1147,
    "gn:feature_class":"P",
    "gn:feature_code":"PPL",
    "gn:name":"Metsemantsi (3)",
    "gn:population":0,
    "gn:timezone":"Africa/Johannesburg",
    "iso:country":"ZA",
    "wof:name":"Metsemantsi (3)",
    "wof:placetype":"locality"
},
  "geometry": {"coordinates":[23.16263,-26.94494000000001],"type":"Point"}
}