{
  "type": "Feature",
  "properties": {
    "gn:admin1_code":"5",
    "gn:admin2_code":"DC15",
    "gn:admin3_code":"EC156",
    "gn:asciiname":"Culunca",
    "gn:country_code":"ZA",
    "gn:dem":1004,
    "gn:feature_class":"P",
    "gn:feature_code":"PPL",
    "gn:name":"Culunca",
    "gn:population":0,
    "gn:timezone":"Africa/Johannesburg",
    "iso:country":"ZA",
    "name:und_x_variant":[
        "Lower Culunca",
        "Culunca"
    ],
    "wof:name":"Culunca",
    "wof:placetype":"locality"
},
  "geometry": {"coordinates":[28.72869,-31.14421],"type":"Point"}
}