{
  "type": "Feature",
  "properties": {
    "gn:admin1_code":"11",
    "gn:admin2_code":"DC4",
    "gn:admin3_code":"WC043",
    "gn:asciiname":"Herbertsdale",
    "gn:country_code":"ZA",
    "gn:dem":82,
    "gn:feature_class":"P",
    "gn:feature_code":"PPL",
    "gn:name":"Herbertsdale",
    "gn:population":0,
    "gn:timezone":"Africa/Johannesburg",
    "iso:country":"ZA",
    "name:afr_x_preferred":[
        "Herbertsdale"
    ],
    "name:est_x_preferred":[
        "Herbertsdale"
    ],
    "name:nld_x_preferred":[
        "Herbertsdale"
    ],
    "name:nso_x_preferred":[
        "Herbertsdale"
    ],
    "name:ron_x_preferred":[
        "Herbertsdale"
    ],
    "name:ukr_x_preferred":[
        "\u0413\u0435\u0440\u0431\u0435\u0440\u0446\u0434\u0430\u043b\u0435"
    ],
    "wof:name":"Herbertsdale",
    "wof:placetype":"locality"
},
  "geometry": {"coordinates":[21.76203,-34.01689],"type":"Point"}
}