{
  "type": "Feature",
  "properties": {
    "gn:admin1_code":"11",
    "gn:admin2_code":"DC4",
    "gn:admin3_code":"WC043",
    "gn:asciiname":"Herbertsdale",
    "gn:country_code":"ZA",
    "gn:dem":82,
    "gn:feature_class":"P",
    "gn:feature_code":"PPL",
    "gn:name":"Herbertsdale",
    "gn:population":0,
    "gn:timezone":"Africa/Johannesburg",
    "iso:country":"ZA",
    "wof:name":"Herbertsdale",
    "wof:placetype":"locality"
},
  "geometry": {"coordinates":[21.76203,-34.01689],"type":"Point"}
}