{
  "type": "Feature",
  "properties": {
    "gn:admin1_code":"9",
    "gn:admin2_code":"DC36",
    "gn:admin3_code":"LIM367",
    "gn:asciiname":"Ga-Mapela",
    "gn:country_code":"ZA",
    "gn:dem":1200,
    "gn:feature_class":"P",
    "gn:feature_code":"PPL",
    "gn:name":"Ga-Mapela",
    "gn:population":0,
    "gn:timezone":"Africa/Johannesburg",
    "iso:country":"ZA",
    "wof:name":"Ga-Mapela",
    "wof:placetype":"locality"
},
  "geometry": {"coordinates":[28.95641,-24.00555],"type":"Point"}
}