{
  "type": "Feature",
  "properties": {
    "gn:admin1_code":"5",
    "gn:admin2_code":"DC10",
    "gn:admin3_code":"EC105",
    "gn:asciiname":"Kleinemonde",
    "gn:country_code":"ZA",
    "gn:dem":141,
    "gn:feature_class":"P",
    "gn:feature_code":"PPL",
    "gn:name":"Kleinemonde",
    "gn:population":0,
    "gn:timezone":"Africa/Johannesburg",
    "iso:country":"ZA",
    "wof:name":"Kleinemonde",
    "wof:placetype":"locality"
},
  "geometry": {"coordinates":[26.91667,-33.51667],"type":"Point"}
}