{
  "type": "Feature",
  "properties": {
    "gn:admin1_code":"9",
    "gn:admin2_code":"DC34",
    "gn:admin3_code":"LIM343",
    "gn:asciiname":"Majika",
    "gn:country_code":"ZA",
    "gn:dem":454,
    "gn:feature_class":"P",
    "gn:feature_code":"PPL",
    "gn:name":"Majika",
    "gn:population":0,
    "gn:timezone":"Africa/Johannesburg",
    "iso:country":"ZA",
    "name:ind_x_preferred":[
        "Majika"
    ],
    "name:tgl_x_preferred":[
        "Majika"
    ],
    "wof:name":"Majika",
    "wof:placetype":"locality"
},
  "geometry": {"coordinates":[30.86667000000001,-22.81667],"type":"Point"}
}