{
  "type": "Feature",
  "properties": {
    "gn:admin1_code":"6",
    "gn:admin2_code":"DC48",
    "gn:admin3_code":"GT482",
    "gn:asciiname":"Droogheuwel",
    "gn:country_code":"ZA",
    "gn:dem":1735,
    "gn:feature_class":"P",
    "gn:feature_code":"PPL",
    "gn:name":"Droogheuwel",
    "gn:population":0,
    "gn:timezone":"Africa/Johannesburg",
    "iso:country":"ZA",
    "wof:name":"Droogheuwel",
    "wof:placetype":"locality"
},
  "geometry": {"coordinates":[27.65,-26.18333],"type":"Point"}
}