{
  "type": "Feature",
  "properties": {
    "gn:admin1_code":"5",
    "gn:admin2_code":"DC10",
    "gn:admin3_code":"EC108",
    "gn:asciiname":"Cambria",
    "gn:country_code":"ZA",
    "gn:dem":165,
    "gn:feature_class":"P",
    "gn:feature_code":"PPL",
    "gn:name":"Cambria",
    "gn:population":0,
    "gn:timezone":"Africa/Johannesburg",
    "iso:country":"ZA",
    "name:ara_x_preferred":[
        "\u0643\u0627\u0645\u0628\u0631\u064a\u0627"
    ],
    "name:bre_x_preferred":[
        "Cambria"
    ],
    "name:fra_x_preferred":[
        "Cambrie"
    ],
    "name:ita_x_preferred":[
        "Cambria"
    ],
    "name:kor_x_preferred":[
        "\uce84\ube0c\ub9ac\uc544"
    ],
    "name:msa_x_preferred":[
        "Cambria"
    ],
    "name:nno_x_preferred":[
        "Cambria"
    ],
    "name:nor_x_preferred":[
        "Cambria"
    ],
    "name:oci_x_preferred":[
        "Cambria"
    ],
    "name:rus_x_preferred":[
        "Cambria"
    ],
    "name:spa_x_preferred":[
        "Cambria"
    ],
    "wof:name":"Cambria",
    "wof:placetype":"locality"
},
  "geometry": {"coordinates":[24.56809,-33.66455],"type":"Point"}
}