{
  "type": "Feature",
  "properties": {
    "gn:admin1_code":"5",
    "gn:admin2_code":"DC10",
    "gn:admin3_code":"EC108",
    "gn:asciiname":"Cambria",
    "gn:country_code":"ZA",
    "gn:dem":165,
    "gn:feature_class":"P",
    "gn:feature_code":"PPL",
    "gn:name":"Cambria",
    "gn:population":0,
    "gn:timezone":"Africa/Johannesburg",
    "iso:country":"ZA",
    "wof:name":"Cambria",
    "wof:placetype":"locality"
},
  "geometry": {"coordinates":[24.56809,-33.66455],"type":"Point"}
}