{
  "type": "Feature",
  "properties": {
    "gn:admin1_code":"10",
    "gn:asciiname":"Metsemantsi",
    "gn:country_code":"ZA",
    "gn:dem":1142,
    "gn:feature_class":"P",
    "gn:feature_code":"PPL",
    "gn:name":"Metsemantsi",
    "gn:population":0,
    "gn:timezone":"Africa/Johannesburg",
    "iso:country":"ZA",
    "wof:name":"Metsemantsi",
    "wof:placetype":"locality"
},
  "geometry": {"coordinates":[23.2106,-27.00738],"type":"Point"}
}