{
  "type": "Feature",
  "properties": {
    "gn:admin1_code":"7",
    "gn:asciiname":"Kleinfontein",
    "gn:country_code":"ZA",
    "gn:dem":1256,
    "gn:feature_class":"P",
    "gn:feature_code":"PPL",
    "gn:name":"Kleinfontein",
    "gn:population":0,
    "gn:timezone":"Africa/Johannesburg",
    "iso:country":"ZA",
    "name:afr_x_preferred":[
        "Kleinfontein"
    ],
    "name:deu_x_preferred":[
        "Kleinfontein"
    ],
    "name:fra_x_preferred":[
        "Kleinfontein"
    ],
    "name:nld_x_preferred":[
        "Kleinfontein"
    ],
    "name:rus_x_preferred":[
        "\u041a\u043b\u0435\u0439\u043d\u0444\u043e\u043d\u0442\u0435\u0439\u043d"
    ],
    "name:swe_x_preferred":[
        "Kleinfontein"
    ],
    "wof:name":"Kleinfontein",
    "wof:placetype":"locality"
},
  "geometry": {"coordinates":[30.45,-24.73333],"type":"Point"}
}