{
  "type": "Feature",
  "properties": {
    "gn:admin1_code":"5",
    "gn:admin2_code":"DC14",
    "gn:admin3_code":"EC144",
    "gn:asciiname":"Groenvlei (1)",
    "gn:country_code":"ZA",
    "gn:dem":1480,
    "gn:feature_class":"P",
    "gn:feature_code":"PPL",
    "gn:name":"Groenvlei (1)",
    "gn:population":0,
    "gn:timezone":"Africa/Johannesburg",
    "iso:country":"ZA",
    "wof:name":"Groenvlei (1)",
    "wof:placetype":"locality"
},
  "geometry": {"coordinates":[26.40378,-31.02103],"type":"Point"}
}