{
  "type": "Feature",
  "properties": {
    "gn:admin1_code":"2",
    "gn:admin2_code":"ETH",
    "gn:admin3_code":"ETH",
    "gn:asciiname":"Adams College",
    "gn:country_code":"ZA",
    "gn:dem":171,
    "gn:feature_class":"P",
    "gn:feature_code":"PPL",
    "gn:name":"Adams College",
    "gn:population":0,
    "gn:timezone":"Africa/Johannesburg",
    "iso:country":"ZA",
    "name:und_x_variant":[
        "Adams Mission Station",
        "Adams Mission",
        "Adams M.S.",
        "Adams College"
    ],
    "wof:name":"Adams College",
    "wof:placetype":"locality"
},
  "geometry": {"coordinates":[30.81568,-30.03199],"type":"Point"}
}