{
  "type": "Feature",
  "properties": {
    "gn:admin1_code":"9",
    "gn:admin2_code":"DC47",
    "gn:admin3_code":"LIM474",
    "gn:asciiname":"Apel",
    "gn:country_code":"ZA",
    "gn:dem":768,
    "gn:feature_class":"P",
    "gn:feature_code":"PPLA3",
    "gn:name":"Apel",
    "gn:population":0,
    "gn:timezone":"Africa/Johannesburg",
    "iso:country":"ZA",
    "name:ces_x_preferred":[
        "Apel"
    ],
    "name:deu_x_preferred":[
        "Apel"
    ],
    "name:fra_x_preferred":[
        "Apel"
    ],
    "name:ita_x_preferred":[
        "Apel"
    ],
    "name:jpn_x_preferred":[
        "\u30a2\u30fc\u30da\u30eb"
    ],
    "name:lit_x_preferred":[
        "Apel"
    ],
    "name:nds_x_preferred":[
        "Apel"
    ],
    "name:nld_x_preferred":[
        "Apel"
    ],
    "name:pol_x_preferred":[
        "Apel"
    ],
    "name:por_x_preferred":[
        "Apel"
    ],
    "name:rus_x_preferred":[
        "\u0410\u043f\u0435\u043b\u044c"
    ],
    "name:spa_x_preferred":[
        "Apel"
    ],
    "wof:name":"Apel",
    "wof:placetype":"locality"
},
  "geometry": {"coordinates":[29.74991,-24.41445],"type":"Point"}
}