{
  "type": "Feature",
  "properties": {
    "gn:admin1_code":"9",
    "gn:admin2_code":"DC47",
    "gn:admin3_code":"LIM474",
    "gn:asciiname":"Apel",
    "gn:country_code":"ZA",
    "gn:dem":768,
    "gn:feature_class":"P",
    "gn:feature_code":"PPLA3",
    "gn:name":"Apel",
    "gn:population":0,
    "gn:timezone":"Africa/Johannesburg",
    "iso:country":"ZA",
    "wof:name":"Apel",
    "wof:placetype":"locality"
},
  "geometry": {"coordinates":[29.74991,-24.41445],"type":"Point"}
}