{
  "type": "Feature",
  "properties": {
    "gn:admin1_code":"3",
    "gn:admin2_code":"DC18",
    "gn:admin3_code":"FS182",
    "gn:asciiname":"Kameelpan",
    "gn:country_code":"ZA",
    "gn:dem":1199,
    "gn:feature_class":"P",
    "gn:feature_code":"PPL",
    "gn:name":"Kameelpan",
    "gn:population":0,
    "gn:timezone":"Africa/Johannesburg",
    "iso:country":"ZA",
    "wof:name":"Kameelpan",
    "wof:placetype":"locality"
},
  "geometry": {"coordinates":[24.96667,-28.85],"type":"Point"}
}