{
  "type": "Feature",
  "properties": {
    "iso:country":"ZA",
    "name:afr_x_preferred":[
        "Fourways"
    ],
    "name:eng_x_preferred":[
        "Fourways"
    ],
    "name:nso_x_preferred":[
        "Fourways"
    ],
    "qs:gn_adm0_cc":"ZA",
    "qs:gn_fcode":"PPL",
    "qs:gn_local":993800,
    "qs:gn_nam_loc":"Johannesburg, Johannesburg, City of Johannesburg, Gauteng, ZA",
    "qs:gn_namadm1":"06",
    "qs:gn_name":"Fourways",
    "qs:local_max":2766,
    "qs:local_sum":31655,
    "qs:localhoods":69,
    "qs:name":"Fourways",
    "qs:name_adm0":"South Africa",
    "qs:name_adm1":"Gauteng",
    "qs:name_adm2":"City of Johannesburg",
    "qs:name_lau":"Johannesburg",
    "qs:name_local":"Johannesburg",
    "qs:photo_max":613,
    "qs:photo_sum":2561,
    "qs:placetype":"Suburb",
    "qs:quad_count":83,
    "qs:woe_adm0":23424942,
    "qs:woe_adm1":2346981,
    "qs:woe_adm2":56189422,
    "qs:woe_lau":56189710,
    "qs:woe_local":1582504,
    "qs:woe_ver":"7.10.0",
    "wof:name":"Fourways",
    "wof:placetype":"neighbourhood"
},
  "geometry": {"coordinates":[28.006536,-26.023596],"type":"Point"}
}