{
  "type": "Feature",
  "properties": {
    "gn:country":"ZA",
    "gn:fcode":"ADM3",
    "gn:population":80141,
    "iso:country":"ZA",
    "name:afr_x_preferred":[
        "Lephalale"
    ],
    "name:ceb_x_preferred":[
        "Lephalale"
    ],
    "name:deu_x_preferred":[
        "Lephalale"
    ],
    "name:est_x_preferred":[
        "Lephalale"
    ],
    "name:fra_x_preferred":[
        "Lephalale"
    ],
    "name:ita_x_preferred":[
        "Lephalale"
    ],
    "name:nld_x_preferred":[
        "Lephalale"
    ],
    "name:nso_x_preferred":[
        "Lephalale"
    ],
    "name:pol_x_preferred":[
        "Lephalale"
    ],
    "name:ron_x_preferred":[
        "Lephalale"
    ],
    "name:rus_x_preferred":[
        "\u041b\u0435\u043f\u0445\u0430\u043b\u0430\u043b\u0435"
    ],
    "name:ven_x_preferred":[
        "Lephalale"
    ],
    "name:zho_x_preferred":[
        "\u840a\u5e15\u62c9\u840a"
    ],
    "qs_pg:aaroncc":"ZA",
    "qs_pg:gn_country":"ZA",
    "qs_pg:gn_fcode":"ADM3",
    "qs_pg:gn_pop":80141,
    "qs_pg:name":"Lephalale",
    "qs_pg:photos_9r":0,
    "qs_pg:photos_sr":0,
    "qs_pg:pop_sr":8,
    "qs_pg:qs_pg_placetype":"localadmin",
    "wof:name":"Lephalale",
    "wof:placetype":"localadmin",
    "wof:population":80141
},
  "geometry": {"coordinates":[27.79742,-23.67629],"type":"Point"}
}