{
  "type": "Feature",
  "properties": {
    "gn:country":"ZA",
    "gn:fcode":"PPLX",
    "gn:population":0,
    "iso:country":"ZA",
    "name:ces_x_preferred":[
        "Brighton Beach"
    ],
    "name:deu_x_preferred":[
        "Brighton Beach"
    ],
    "name:fas_x_preferred":[
        "\u0633\u0627\u062d\u0644 \u0628\u0631\u0627\u06cc\u062a\u0648\u0646"
    ],
    "name:fin_x_preferred":[
        "Brighton Beach"
    ],
    "name:fra_x_preferred":[
        "Brighton Beach"
    ],
    "name:heb_x_preferred":[
        "\u05d1\u05e8\u05d9\u05d9\u05d8\u05d5\u05df \u05d1\u05d9\u05e5'"
    ],
    "name:ind_x_preferred":[
        "Brighton Beach"
    ],
    "name:ita_x_preferred":[
        "Brighton Beach"
    ],
    "name:kat_x_preferred":[
        "\u10d1\u10e0\u10d0\u10d8\u10e2\u10dd\u10dc-\u10d1\u10d8\u10e9\u10d8"
    ],
    "name:pol_x_preferred":[
        "Brighton Beach"
    ],
    "name:por_x_preferred":[
        "Brighton Beach"
    ],
    "name:rus_x_preferred":[
        "\u0411\u0440\u0430\u0439\u0442\u043e\u043d-\u0411\u0438\u0447"
    ],
    "name:slk_x_preferred":[
        "Brighton Beach"
    ],
    "name:spa_x_preferred":[
        "Brighton Beach"
    ],
    "name:tur_x_preferred":[
        "Brighton Beach"
    ],
    "name:ukr_x_preferred":[
        "\u0411\u0440\u0430\u0439\u0442\u043e\u043d-\u0411\u0456\u0447"
    ],
    "name:xmf_x_preferred":[
        "\u10d1\u10e0\u10d0\u10d8\u10e2\u10dd\u10dc-\u10d1\u10d8\u10e9\u10d8"
    ],
    "name:yid_x_preferred":[
        "\u05d1\u05e8\u05d9\u05d9\u05d8\u05d0\u05df \u05d1\u05d9\u05d8\u05e9"
    ],
    "qs_pg:aaroncc":"ZA",
    "qs_pg:gn_country":"ZA",
    "qs_pg:gn_fcode":"PPLX",
    "qs_pg:gn_pop":0,
    "qs_pg:name":"Brighton Beach",
    "qs_pg:name_adm0":"South Africa",
    "qs_pg:name_adm1":"Kwazulu Natal",
    "qs_pg:photos":7,
    "qs_pg:photos_1k":1,
    "qs_pg:photos_9k":1,
    "qs_pg:photos_9r":1,
    "qs_pg:photos_all":7,
    "qs_pg:photos_sr":1,
    "qs_pg:pop_sr":0,
    "qs_pg:qs_pg_placetype":"neighbourhood",
    "qs_pg:qs_pg_placetype_gp":"Suburb",
    "qs_pg:woe_adm0":23424942,
    "woe:adm0_id":23424942,
    "woe:name_adm0":"South Africa",
    "woe:name_adm1":"Kwazulu Natal",
    "woe:placetype":"Suburb",
    "wof:name":"Brighton Beach",
    "wof:placetype":"neighbourhood"
},
  "geometry": {"coordinates":[31.0009,-29.93957],"type":"Point"}
}