{
  "type": "Feature",
  "properties": {
    "gn:gn_country":"ZA",
    "gn:gn_fcode":"ADM3",
    "gn:gn_pop":46724,
    "gn:population":46724,
    "iso:country":"ZA",
    "qs_pg:aaroncc":"ZA",
    "qs_pg:gn_country":"ZA",
    "qs_pg:gn_fcode":"ADM3",
    "qs_pg:gn_pop":46724,
    "qs_pg:name":"Greater Kokstad",
    "qs_pg:photos_9r":0,
    "qs_pg:photos_sr":0,
    "qs_pg:pop_sr":7,
    "qs_pg:qs_pg_placetype":"localadmin",
    "wof:name":"Greater Kokstad",
    "wof:placetype":"localadmin",
    "wof:population":46724
},
  "geometry": {"coordinates":[29.334,-30.30095],"type":"Point"}
}