{
  "type": "Feature",
  "properties": {
    "gn:admin1_code":"5",
    "gn:admin2_code":"DC12",
    "gn:admin3_code":"EC122",
    "gn:asciiname":"Dlepu",
    "gn:country_code":"ZA",
    "gn:dem":556,
    "gn:feature_class":"P",
    "gn:feature_code":"PPL",
    "gn:name":"Dlepu",
    "gn:population":0,
    "gn:timezone":"Africa/Johannesburg",
    "iso:country":"ZA",
    "wof:name":"Dlepu",
    "wof:placetype":"locality"
},
  "geometry": {"coordinates":[28.03277000000001,-32.47948],"type":"Point"}
}