{
  "type": "Feature",
  "properties": {
    "gn:gn_country":"ZA",
    "gn:gn_fcode":"PPLA",
    "gn:gn_pop":123749,
    "gn:population":123749,
    "iso:country":"ZA",
    "name:afr_x_preferred":[
        "Pietersburg"
    ],
    "name:afr_x_variant":[
        "Polokwane"
    ],
    "name:amh_x_preferred":[
        "\u1356\u120e\u12ad\u12cb\u1294"
    ],
    "name:ara_x_preferred":[
        "\u0628\u0648\u0644\u0648\u0643\u0648\u0627\u0646"
    ],
    "name:bel_x_preferred":[
        "\u0413\u043e\u0440\u0430\u0434 \u041f\u0430\u043b\u0430\u043a\u0432\u0430\u043d\u044d"
    ],
    "name:bul_x_preferred":[
        "\u041f\u043e\u043b\u043e\u043a\u0432\u0430\u043d\u0435"
    ],
    "name:deu_x_preferred":[
        "Polokwane"
    ],
    "name:ell_x_preferred":[
        "\u03a0\u03bf\u03bb\u03bf\u03ba\u03bf\u03c5\u03ac\u03bd\u03b5"
    ],
    "name:eng_x_preferred":[
        "Polokwane"
    ],
    "name:fas_x_preferred":[
        "\u067e\u0648\u0644\u0648\u06a9\u0648\u06cc\u0646"
    ],
    "name:fin_x_preferred":[
        "Polokwane"
    ],
    "name:fra_x_historical":[
        "Pietersburg"
    ],
    "name:fra_x_preferred":[
        "Pietersburg"
    ],
    "name:fra_x_variant":[
        "Polokwane"
    ],
    "name:heb_x_preferred":[
        "\u05e4\u05d5\u05dc\u05d5\u05e7\u05d5\u05d5\u05d0\u05e0\u05d4"
    ],
    "name:hin_x_preferred":[
        "\u092a\u094b\u0932\u0915\u094d\u0935\u093e\u0928\u0940"
    ],
    "name:jpn_x_preferred":[
        "\u30dd\u30ed\u30af\u30ef\u30cd"
    ],
    "name:kor_x_preferred":[
        "\ud3f4\ub85c\ucf70\ub124"
    ],
    "name:lat_x_preferred":[
        "Petriburgum"
    ],
    "name:lav_x_preferred":[
        "Polokvane"
    ],
    "name:lit_x_preferred":[
        "Polokvan\u0117"
    ],
    "name:mar_x_preferred":[
        "\u092a\u094b\u0932\u094b\u0915\u094d\u0935\u093e\u0928\u0947"
    ],
    "name:mkd_x_preferred":[
        "\u041f\u043e\u043b\u043e\u043a\u0432\u0430\u043d\u0435"
    ],
    "name:nld_x_preferred":[
        "Polokwane"
    ],
    "name:pnb_x_preferred":[
        "\u067e\u0648\u0644\u0648\u06a9\u0648\u06cc\u0646"
    ],
    "name:rus_x_preferred":[
        "\u041f\u043e\u043b\u043e\u043a\u0432\u0430\u043d\u0435"
    ],
    "name:srp_x_preferred":[
        "\u041f\u043e\u043b\u043e\u043a\u0432\u0430\u043d\u0435"
    ],
    "name:tha_x_preferred":[
        "\u0e42\u0e1e\u0e42\u0e25\u0e40\u0e04\u0e27\u0e19"
    ],
    "name:ukr_x_preferred":[
        "\u041f\u043e\u043b\u043e\u043a\u0432\u0430\u043d\u0435"
    ],
    "name:unk_x_variant":[
        "Pietersburg"
    ],
    "name:urd_x_preferred":[
        "\u067e\u0648\u0644\u0648\u06a9\u0648\u0627\u0646\u06d2"
    ],
    "name:vep_x_preferred":[
        "Polokvane"
    ],
    "name:zho_x_preferred":[
        "\u6ce2\u7f85\u514b\u74e6\u5c3c"
    ],
    "qs_pg:aaroncc":"ZA",
    "qs_pg:gn_country":"ZA",
    "qs_pg:gn_fcode":"PPLA",
    "qs_pg:gn_pop":123749,
    "qs_pg:name":"Polokwane",
    "qs_pg:photos_9r":0,
    "qs_pg:photos_sr":0,
    "qs_pg:pop_sr":10,
    "qs_pg:qs_pg_placetype":"locality",
    "wof:name":"Polokwane",
    "wof:placetype":"locality",
    "wof:population":123749
},
  "geometry": {"coordinates":[29.46885,-23.90448],"type":"Point"}
}