{
  "type": "Feature",
  "properties": {
    "gn:admin1_code":"8.0",
    "gn:admin2_code":"DC6",
    "gn:admin3_code":"NC064",
    "gn:asciiname":"Kamieskroon",
    "gn:country_code":"ZA",
    "gn:dem":762,
    "gn:feature_class":"P",
    "gn:feature_code":"PPL",
    "gn:name":"Kamieskroon",
    "gn:population":0,
    "gn:timezone":"Africa/Johannesburg",
    "iso:country":"ZA",
    "name:afr_x_preferred":[
        "Kamieskroon"
    ],
    "name:est_x_preferred":[
        "Kamieskroon"
    ],
    "name:nld_x_preferred":[
        "Kamieskroon"
    ],
    "name:nso_x_preferred":[
        "Kamieskroon"
    ],
    "name:ron_x_preferred":[
        "Kamieskroon"
    ],
    "wof:name":"Kamieskroon",
    "wof:placetype":"locality"
},
  "geometry": {"coordinates":[17.93385,-30.20937],"type":"Point"}
}