{
  "type": "Feature",
  "properties": {
    "gn:admin1_code":"7",
    "gn:admin2_code":"DC32",
    "gn:admin3_code":"MP322",
    "gn:asciiname":"Gatehouse",
    "gn:country_code":"ZA",
    "gn:dem":965,
    "gn:feature_class":"P",
    "gn:feature_code":"PPL",
    "gn:name":"Gatehouse",
    "gn:population":0,
    "gn:timezone":"Africa/Johannesburg",
    "iso:country":"ZA",
    "name:deu_x_preferred":[
        "Torhaus"
    ],
    "name:eus_x_preferred":[
        "Ate gotortu"
    ],
    "name:fra_x_preferred":[
        "Porterie"
    ],
    "name:gle_x_preferred":[
        "Teach geata"
    ],
    "name:jpn_x_preferred":[
        "\u30b2\u30fc\u30c8\u30cf\u30a6\u30b9"
    ],
    "name:slv_x_preferred":[
        "Vhodno poslopje"
    ],
    "name:tha_x_preferred":[
        "\u0e40\u0e23\u0e37\u0e2d\u0e19\u0e40\u0e1d\u0e49\u0e32\u0e1b\u0e23\u0e30\u0e15\u0e39"
    ],
    "wof:name":"Gatehouse",
    "wof:placetype":"locality"
},
  "geometry": {"coordinates":[31.06667,-25.23333],"type":"Point"}
}