{
  "type": "Feature",
  "properties": {
    "gn:admin1_code":"7",
    "gn:admin2_code":"DC32",
    "gn:admin3_code":"MP322",
    "gn:asciiname":"Gatehouse",
    "gn:country_code":"ZA",
    "gn:dem":965,
    "gn:feature_class":"P",
    "gn:feature_code":"PPL",
    "gn:name":"Gatehouse",
    "gn:population":0,
    "gn:timezone":"Africa/Johannesburg",
    "iso:country":"ZA",
    "wof:name":"Gatehouse",
    "wof:placetype":"locality"
},
  "geometry": {"coordinates":[31.06667,-25.23333],"type":"Point"}
}