{
  "type": "Feature",
  "properties": {
    "gn:admin1_code":"8.0",
    "gn:admin2_code":"DC7",
    "gn:admin3_code":"NC077",
    "gn:asciiname":"Uitkoms",
    "gn:country_code":"ZA",
    "gn:dem":1019,
    "gn:feature_class":"P",
    "gn:feature_code":"PPL",
    "gn:name":"Uitkoms",
    "gn:population":0,
    "gn:timezone":"Africa/Johannesburg",
    "iso:country":"ZA",
    "name:afr_x_preferred":[
        "Uitkoms"
    ],
    "name:nso_x_preferred":[
        "Uitkoms"
    ],
    "wof:name":"Uitkoms",
    "wof:placetype":"locality"
},
  "geometry": {"coordinates":[22.05415,-29.95598],"type":"Point"}
}