{
  "type": "Feature",
  "properties": {
    "gn:admin1_code":"5",
    "gn:admin2_code":"DC12",
    "gn:admin3_code":"EC121",
    "gn:asciiname":"Mqele",
    "gn:country_code":"ZA",
    "gn:dem":478,
    "gn:feature_class":"P",
    "gn:feature_code":"PPL",
    "gn:name":"Mqele",
    "gn:population":0,
    "gn:timezone":"Africa/Johannesburg",
    "iso:country":"ZA",
    "name:und_x_variant":[
        "Mgele",
        "Mqele"
    ],
    "wof:name":"Mqele",
    "wof:placetype":"locality"
},
  "geometry": {"coordinates":[28.89457,-32.02142],"type":"Point"}
}