{
  "type": "Feature",
  "properties": {
    "gn:admin1_code":"2",
    "gn:admin2_code":"ETH",
    "gn:admin3_code":"ETH",
    "gn:asciiname":"Durban Point",
    "gn:country_code":"ZA",
    "gn:dem":11,
    "gn:feature_class":"P",
    "gn:feature_code":"PPLL",
    "gn:name":"Durban Point",
    "gn:population":0,
    "gn:timezone":"Africa/Johannesburg",
    "iso:country":"ZA",
    "wof:name":"Durban Point",
    "wof:placetype":"locality"
},
  "geometry": {"coordinates":[31.04719,-29.86941],"type":"Point"}
}