{
  "type": "Feature",
  "properties": {
    "gn:country":"ZA",
    "gn:fcode":"ADM3",
    "gn:population":20433,
    "iso:country":"ZA",
    "qs_pg:aaroncc":"ZA",
    "qs_pg:gn_country":"ZA",
    "qs_pg:gn_fcode":"ADM3",
    "qs_pg:gn_pop":20433,
    "qs_pg:name":"Magareng",
    "qs_pg:photos_9r":0,
    "qs_pg:photos_sr":0,
    "qs_pg:pop_sr":7,
    "qs_pg:qs_pg_placetype":"localadmin",
    "wof:lang_x_official":[
        "eng"
    ],
    "wof:lang_x_spoken":[
        "eng",
        "zul",
        "xho",
        "afr",
        "nso",
        "tsn",
        "sot",
        "tso",
        "ssw",
        "ven",
        "nbl"
    ],
    "wof:name":"Magareng",
    "wof:placetype":"localadmin",
    "wof:population":20433
},
  "geometry": {"coordinates":[24.78027,-28.16863],"type":"Point"}
}