{
  "type": "Feature",
  "properties": {
    "gn:admin1_code":"2",
    "gn:admin2_code":"DC24",
    "gn:admin3_code":"KZN244",
    "gn:asciiname":"Bassonsdrif",
    "gn:cc2":"ZA",
    "gn:country_code":"ZA",
    "gn:dem":645,
    "gn:feature_class":"P",
    "gn:feature_code":"PPL",
    "gn:name":"Bassonsdrif",
    "gn:population":0,
    "gn:timezone":"Africa/Johannesburg",
    "iso:country":"ZA",
    "name:und_x_variant":[
        "Bassonsdrift",
        "Bassonsdrif"
    ],
    "wof:name":"Bassonsdrif",
    "wof:placetype":"locality"
},
  "geometry": {"coordinates":[30.61667000000001,-28.75],"type":"Point"}
}