{
  "type": "Feature",
  "properties": {
    "gn:gn_country":"ZA",
    "gn:gn_fcode":"PPL",
    "gn:gn_pop":0,
    "iso:country":"ZA",
    "name:afr_x_preferred":[
        "Leipoldtville"
    ],
    "name:deu_x_preferred":[
        "Leipoldtville"
    ],
    "name:eng_x_preferred":[
        "Leipoldtville"
    ],
    "name:est_x_preferred":[
        "Leipoldtville"
    ],
    "name:nld_x_preferred":[
        "Leipoldtville"
    ],
    "name:nso_x_preferred":[
        "Leipoldtville"
    ],
    "name:unk_x_variant":[
        "Leipoldville"
    ],
    "qs_pg:aaroncc":"ZA",
    "qs_pg:gn_country":"ZA",
    "qs_pg:gn_fcode":"PPL",
    "qs_pg:gn_pop":0,
    "qs_pg:name":"Leipoldtville",
    "qs_pg:name_adm0":"South Africa",
    "qs_pg:name_adm1":"Western Cape",
    "qs_pg:photos_9r":0,
    "qs_pg:photos_sr":0,
    "qs_pg:pop_sr":0,
    "qs_pg:qs_pg_placetype":"locality",
    "qs_pg:qs_pg_placetype_gp":"Town",
    "qs_pg:woe_adm0":23424942,
    "woe:adm0_id":23424942,
    "woe:name_adm0":"South Africa",
    "woe:name_adm1":"Western Cape",
    "woe:placetype":"Town",
    "wof:name":"Leipoldtville",
    "wof:placetype":"locality"
},
  "geometry": {"coordinates":[18.48097,-32.22287],"type":"Point"}
}