{
  "type": "Feature",
  "properties": {
    "gn:admin1_code":"3",
    "gn:admin2_code":"MAN",
    "gn:admin3_code":"MAN",
    "gn:asciiname":"Moroto",
    "gn:country_code":"ZA",
    "gn:dem":1570,
    "gn:feature_class":"P",
    "gn:feature_code":"PPL",
    "gn:name":"Moroto",
    "gn:population":0,
    "gn:timezone":"Africa/Johannesburg",
    "iso:country":"ZA",
    "name:ceb_x_preferred":[
        "Moroto"
    ],
    "name:fra_x_preferred":[
        "Moroto"
    ],
    "wof:name":"Moroto",
    "wof:placetype":"locality"
},
  "geometry": {"coordinates":[26.98466,-29.10032],"type":"Point"}
}