{
  "type": "Feature",
  "properties": {
    "iso:country":"ZA",
    "name:eng_x_preferred":[
        "Prestbury"
    ],
    "name:pol_x_preferred":[
        "Prestbury"
    ],
    "qs:gn_adm0_cc":"ZA",
    "qs:gn_local":965301,
    "qs:local_max":51,
    "qs:local_sum":76,
    "qs:localhoods":3,
    "qs:name":"Prestbury",
    "qs:name_adm0":"South Africa",
    "qs:name_adm1":"Kwazulu Natal",
    "qs:name_adm2":"uMgungundlovu",
    "qs:name_lau":"The Msunduzi",
    "qs:name_local":"Pietermaritzburg",
    "qs:photo_max":4,
    "qs:photo_sum":5,
    "qs:placetype":"Suburb",
    "qs:quad_count":2,
    "qs:woe_adm0":23424942,
    "qs:woe_adm1":2346982,
    "qs:woe_adm2":56189434,
    "qs:woe_lau":56189494,
    "qs:woe_local":1586549,
    "qs:woe_ver":"7.10.0",
    "wd:wordcount":29,
    "wof:lang":[
        "eng"
    ],
    "wof:name":"Prestbury",
    "wof:placetype":"neighbourhood"
},
  "geometry": {"coordinates":[30.345886,-29.608327],"type":"Point"}
}