{
  "type": "Feature",
  "properties": {
    "gn:admin1_code":"5.0",
    "gn:admin2_code":"DC14",
    "gn:admin3_code":"EC143",
    "gn:asciiname":"Van de Merwes Fontein (2)",
    "gn:country_code":"ZA",
    "gn:dem":1632,
    "gn:feature_class":"P",
    "gn:feature_code":"PPL",
    "gn:name":"Van de Merwes Fontein (2)",
    "gn:population":0,
    "gn:timezone":"Africa/Johannesburg",
    "iso:country":"ZA",
    "wof:name":"Van de Merwes Fontein (2)",
    "wof:placetype":"locality"
},
  "geometry": {"coordinates":[26.94111,-31.23901],"type":"Point"}
}