{
  "type": "Feature",
  "properties": {
    "gn:admin1_code":"10.0",
    "gn:asciiname":"Tlapeng",
    "gn:country_code":"ZA",
    "gn:dem":1102,
    "gn:feature_class":"P",
    "gn:feature_code":"PPL",
    "gn:name":"Tlapeng",
    "gn:population":0,
    "gn:timezone":"Africa/Johannesburg",
    "iso:country":"ZA",
    "wof:name":"Tlapeng",
    "wof:placetype":"locality"
},
  "geometry": {"coordinates":[23.21365,-27.05986],"type":"Point"}
}