{
  "type": "Feature",
  "properties": {
    "gn:admin1_code":"5",
    "gn:admin2_code":"DC13",
    "gn:admin3_code":"EC135",
    "gn:asciiname":"Mazizini",
    "gn:country_code":"ZA",
    "gn:dem":972,
    "gn:feature_class":"P",
    "gn:feature_code":"PPL",
    "gn:name":"Mazizini",
    "gn:population":0,
    "gn:timezone":"Africa/Johannesburg",
    "iso:country":"ZA",
    "wof:name":"Mazizini",
    "wof:placetype":"locality"
},
  "geometry": {"coordinates":[27.75544,-31.9612],"type":"Point"}
}