{
  "type": "Feature",
  "properties": {
    "gn:admin1_code":"9",
    "gn:admin2_code":"DC47",
    "gn:admin3_code":"LIM473",
    "gn:asciiname":"Ga-Mokalapa",
    "gn:country_code":"ZA",
    "gn:dem":943,
    "gn:feature_class":"P",
    "gn:feature_code":"PPL",
    "gn:name":"Ga-Mokalapa",
    "gn:population":0,
    "gn:timezone":"Africa/Johannesburg",
    "iso:country":"ZA",
    "wof:name":"Ga-Mokalapa",
    "wof:placetype":"locality"
},
  "geometry": {"coordinates":[29.70236,-24.56521],"type":"Point"}
}