{
  "type": "Feature",
  "properties": {
    "gn:admin1_code":"10",
    "gn:asciiname":"Leeds",
    "gn:country_code":"ZA",
    "gn:dem":1053,
    "gn:feature_class":"P",
    "gn:feature_code":"PPL",
    "gn:name":"Leeds",
    "gn:population":0,
    "gn:timezone":"Africa/Johannesburg",
    "iso:country":"ZA",
    "wof:name":"Leeds",
    "wof:placetype":"locality"
},
  "geometry": {"coordinates":[23.19446,-26.46467],"type":"Point"}
}