{
  "type": "Feature",
  "properties": {
    "gn:admin1_code":"2",
    "gn:admin2_code":"DC29",
    "gn:admin3_code":"KZN294",
    "gn:asciiname":"Mtandeni",
    "gn:country_code":"ZA",
    "gn:dem":412,
    "gn:feature_class":"P",
    "gn:feature_code":"PPL",
    "gn:name":"Mtandeni",
    "gn:population":0,
    "gn:timezone":"Africa/Johannesburg",
    "iso:country":"ZA",
    "name:und_x_variant":[
        "Mtendeni",
        "Mtandeni"
    ],
    "wof:name":"Mtandeni",
    "wof:placetype":"locality"
},
  "geometry": {"coordinates":[31.06256,-29.26696],"type":"Point"}
}