{
  "type": "Feature",
  "properties": {
    "gn:admin1_code":"5",
    "gn:admin2_code":"DC12",
    "gn:admin3_code":"EC122",
    "gn:asciiname":"Gqunqe",
    "gn:cc2":"ZA",
    "gn:country_code":"ZA",
    "gn:dem":179,
    "gn:feature_class":"P",
    "gn:feature_code":"PPL",
    "gn:name":"Gqunqe",
    "gn:population":0,
    "gn:timezone":"Africa/Johannesburg",
    "iso:country":"ZA",
    "name:und_x_variant":[
        "Gqunge Trading Store",
        "Gqunge",
        "Gqunqe"
    ],
    "wof:lang_x_official":[
        "eng"
    ],
    "wof:lang_x_spoken":[
        "eng",
        "zul",
        "xho",
        "afr",
        "nso",
        "tsn",
        "sot",
        "tso",
        "ssw",
        "ven",
        "nbl"
    ],
    "wof:name":"Gqunqe",
    "wof:placetype":"locality"
},
  "geometry": {"coordinates":[28.55,-32.46667],"type":"Point"}
}