{
  "type": "Feature",
  "properties": {
    "gn:admin1_code":"3",
    "gn:admin2_code":"DC16",
    "gn:admin3_code":"FS162",
    "gn:asciiname":"Lyons Rose",
    "gn:country_code":"ZA",
    "gn:dem":1324,
    "gn:feature_class":"P",
    "gn:feature_code":"PPL",
    "gn:name":"Lyons Rose",
    "gn:population":0,
    "gn:timezone":"Africa/Johannesburg",
    "iso:country":"ZA",
    "wof:name":"Lyons Rose",
    "wof:placetype":"locality"
},
  "geometry": {"coordinates":[25.69216,-29.25491],"type":"Point"}
}