{
  "type": "Feature",
  "properties": {
    "gn:admin1_code":"9",
    "gn:admin2_code":"DC33",
    "gn:admin3_code":"LIM334",
    "gn:asciiname":"Leydsdorp",
    "gn:country_code":"ZA",
    "gn:dem":677,
    "gn:feature_class":"P",
    "gn:feature_code":"PPL",
    "gn:name":"Leydsdorp",
    "gn:population":0,
    "gn:timezone":"Africa/Johannesburg",
    "iso:country":"ZA",
    "wof:name":"Leydsdorp",
    "wof:placetype":"locality"
},
  "geometry": {"coordinates":[30.52055,-23.99544],"type":"Point"}
}