{
  "type": "Feature",
  "properties": {
    "gn:admin1_code":"5.0",
    "gn:admin2_code":"DC13",
    "gn:admin3_code":"EC138",
    "gn:asciiname":"The Glen",
    "gn:country_code":"ZA",
    "gn:dem":1438,
    "gn:feature_class":"P",
    "gn:feature_code":"PPL",
    "gn:name":"The Glen",
    "gn:population":0,
    "gn:timezone":"Africa/Johannesburg",
    "iso:country":"ZA",
    "wof:name":"The Glen",
    "wof:placetype":"locality"
},
  "geometry": {"coordinates":[27.79508,-31.45721],"type":"Point"}
}