{
  "type": "Feature",
  "properties": {
    "gn:country":"ZA",
    "gn:fcode":"PPLX",
    "gn:population":0,
    "iso:country":"ZA",
    "name:ara_x_preferred":[
        "\u0641\u064a\u0631\u063a\u0633\u0648\u0646"
    ],
    "name:cat_x_preferred":[
        "Ferguson"
    ],
    "name:ceb_x_preferred":[
        "Ferguson"
    ],
    "name:ces_x_preferred":[
        "Ferguson"
    ],
    "name:deu_x_preferred":[
        "Ferguson"
    ],
    "name:est_x_preferred":[
        "Ferguson"
    ],
    "name:fas_x_preferred":[
        "\u0641\u0631\u06af\u0648\u0633\u0646"
    ],
    "name:fin_x_preferred":[
        "Ferguson"
    ],
    "name:fra_x_preferred":[
        "Ferguson"
    ],
    "name:heb_x_preferred":[
        "\u05e4\u05e8\u05d2\u05d5\u05e1\u05d5\u05df"
    ],
    "name:ita_x_preferred":[
        "Ferguson"
    ],
    "name:jpn_x_preferred":[
        "\u30d5\u30a1\u30fc\u30ac\u30bd\u30f3"
    ],
    "name:kor_x_preferred":[
        "\ud37c\uac70\uc2a8"
    ],
    "name:nld_x_preferred":[
        "Ferguson"
    ],
    "name:pol_x_preferred":[
        "Ferguson"
    ],
    "name:por_x_preferred":[
        "Ferguson"
    ],
    "name:rus_x_preferred":[
        "\u0424\u0435\u0440\u0433\u044e\u0441\u043e\u043d"
    ],
    "name:spa_x_preferred":[
        "Ferguson"
    ],
    "name:swe_x_preferred":[
        "Ferguson"
    ],
    "name:ukr_x_preferred":[
        "\u0424\u0435\u0440\u0433\u044e\u0441\u043e\u043d"
    ],
    "name:vol_x_preferred":[
        "Ferguson"
    ],
    "name:zho_x_preferred":[
        "\u4f5b\u683c\u68ee"
    ],
    "qs_pg:aaroncc":"ZA",
    "qs_pg:gn_country":"ZA",
    "qs_pg:gn_fcode":"PPLX",
    "qs_pg:gn_pop":0,
    "qs_pg:name":"Ferguson",
    "qs_pg:name_adm0":"South Africa",
    "qs_pg:name_adm1":"Eastern Cape",
    "qs_pg:photos":1,
    "qs_pg:photos_1k":1,
    "qs_pg:photos_9k":1,
    "qs_pg:photos_9r":1,
    "qs_pg:photos_all":1,
    "qs_pg:photos_sr":1,
    "qs_pg:pop_sr":0,
    "qs_pg:qs_pg_placetype":"neighbourhood",
    "qs_pg:qs_pg_placetype_gp":"Suburb",
    "qs_pg:woe_adm0":23424942,
    "woe:adm0_id":23424942,
    "woe:name_adm0":"South Africa",
    "woe:name_adm1":"Eastern Cape",
    "woe:placetype":"Suburb",
    "wof:name":"Ferguson",
    "wof:placetype":"neighbourhood"
},
  "geometry": {"coordinates":[25.58333,-33.91667],"type":"Point"}
}