{
  "type": "Feature",
  "properties": {
    "iso:country":"ZA",
    "name:eng_x_preferred":[
        "Kanonnierspark"
    ],
    "qs:gn_adm0_cc":"ZA",
    "qs:gn_local":964349,
    "qs:local_max":42,
    "qs:local_sum":46,
    "qs:localhoods":2,
    "qs:name":"Kanonnierspark",
    "qs:name_adm0":"South Africa",
    "qs:name_adm1":"North-West",
    "qs:name_adm2":"Dr Kenneth Kaunda",
    "qs:name_lau":"Potchefstroom",
    "qs:name_local":"Potchefstroom",
    "qs:photo_max":10,
    "qs:photo_sum":42,
    "qs:placetype":"Suburb",
    "qs:quad_count":10,
    "qs:woe_adm0":23424942,
    "qs:woe_adm1":2346984,
    "qs:woe_adm2":56189440,
    "qs:woe_lau":56189657,
    "qs:woe_local":1586625,
    "qs:woe_ver":"7.10.0",
    "wof:lang":[
        "eng"
    ],
    "wof:name":"Kanonnierspark",
    "wof:placetype":"neighbourhood"
},
  "geometry": {"coordinates":[27.097125,-26.696779],"type":"Point"}
}