{
  "type": "Feature",
  "properties": {
    "gn:admin1_code":"5",
    "gn:admin2_code":"DC13",
    "gn:admin3_code":"EC133",
    "gn:asciiname":"Randfontein",
    "gn:country_code":"ZA",
    "gn:dem":1676,
    "gn:feature_class":"P",
    "gn:feature_code":"PPL",
    "gn:name":"Randfontein",
    "gn:population":0,
    "gn:timezone":"Africa/Johannesburg",
    "iso:country":"ZA",
    "name:afr_x_preferred":[
        "Randfontein"
    ],
    "name:ceb_x_preferred":[
        "Randfontein"
    ],
    "name:deu_x_preferred":[
        "Randfontein"
    ],
    "name:epo_x_preferred":[
        "Randfontein"
    ],
    "name:est_x_preferred":[
        "Randfontein"
    ],
    "name:fra_x_preferred":[
        "Randfontein"
    ],
    "name:ita_x_preferred":[
        "Randfontein"
    ],
    "name:mlg_x_preferred":[
        "Randfontein"
    ],
    "name:nso_x_preferred":[
        "Randfontein"
    ],
    "name:pol_x_preferred":[
        "Randfontein"
    ],
    "name:ron_x_preferred":[
        "Randfontein"
    ],
    "name:rus_x_preferred":[
        "\u0420\u0430\u043d\u0434\u0444\u043e\u043d\u0442\u0435\u0439\u043d"
    ],
    "name:sna_x_preferred":[
        "Randfontein"
    ],
    "name:spa_x_preferred":[
        "Randfontein"
    ],
    "name:zho_x_preferred":[
        "\u862d\u5fb7\u65b9\u5766"
    ],
    "wof:lang_x_official":[
        "eng"
    ],
    "wof:lang_x_spoken":[
        "eng",
        "zul",
        "xho",
        "afr",
        "nso",
        "tsn",
        "sot",
        "tso",
        "ssw",
        "ven",
        "nbl"
    ],
    "wof:name":"Randfontein",
    "wof:placetype":"locality"
},
  "geometry": {"coordinates":[26.5024,-31.2174],"type":"Point"}
}