{
  "type": "Feature",
  "properties": {
    "gn:admin1_code":"3.0",
    "gn:admin2_code":"DC16",
    "gn:admin3_code":"FS163",
    "gn:asciiname":"Sterkstroom",
    "gn:country_code":"ZA",
    "gn:dem":1419,
    "gn:feature_class":"P",
    "gn:feature_code":"PPL",
    "gn:name":"Sterkstroom",
    "gn:population":0,
    "gn:timezone":"Africa/Johannesburg",
    "iso:country":"ZA",
    "name:afr_x_preferred":[
        "Sterkstroom"
    ],
    "name:ceb_x_preferred":[
        "Sterkstroom"
    ],
    "name:deu_x_preferred":[
        "Sterkstroom"
    ],
    "name:est_x_preferred":[
        "Sterkstroom"
    ],
    "name:nld_x_preferred":[
        "Sterkstroom"
    ],
    "name:nso_x_preferred":[
        "Sterkstroom"
    ],
    "name:ron_x_preferred":[
        "Sterkstroom"
    ],
    "name:ven_x_preferred":[
        "Sterkstroom"
    ],
    "wof:name":"Sterkstroom",
    "wof:placetype":"locality"
},
  "geometry": {"coordinates":[26.94545,-30.5756],"type":"Point"}
}