{
  "type": "Feature",
  "properties": {
    "gn:admin1_code":"10",
    "gn:admin2_code":"DC37",
    "gn:admin3_code":"NW375",
    "gn:asciiname":"Matlhagame",
    "gn:country_code":"ZA",
    "gn:dem":1103,
    "gn:feature_class":"P",
    "gn:feature_code":"PPL",
    "gn:name":"Matlhagame",
    "gn:population":0,
    "gn:timezone":"Africa/Johannesburg",
    "iso:country":"ZA",
    "wof:name":"Matlhagame",
    "wof:placetype":"locality"
},
  "geometry": {"coordinates":[26.96667,-25.15],"type":"Point"}
}