{
  "type": "Feature",
  "properties": {
    "gn:admin1_code":"2",
    "gn:admin2_code":"DC26",
    "gn:admin3_code":"KZN265",
    "gn:asciiname":"KwaMandlakazi",
    "gn:country_code":"ZA",
    "gn:dem":663,
    "gn:feature_class":"P",
    "gn:feature_code":"PPLL",
    "gn:name":"KwaMandlakazi",
    "gn:population":0,
    "gn:timezone":"Africa/Johannesburg",
    "iso:country":"ZA",
    "wof:lang_x_official":[
        "eng"
    ],
    "wof:lang_x_spoken":[
        "eng",
        "zul",
        "xho",
        "afr",
        "nso",
        "tsn",
        "sot",
        "tso",
        "ssw",
        "ven",
        "nbl"
    ],
    "wof:name":"KwaMandlakazi",
    "wof:placetype":"locality"
},
  "geometry": {"coordinates":[31.71921,-28.02414],"type":"Point"}
}