{
  "type": "Feature",
  "properties": {
    "iso:country":"ZA",
    "name:eng_x_preferred":[
        "Generaal Kemp Heuwel"
    ],
    "name:unk_x_variant":[
        "Generaal Kemp Heuwel"
    ],
    "qs:gn_adm0_cc":"ZA",
    "qs:gn_local":964137,
    "qs:gn_nam_loc":"Tshwane, Pretoria, City of Tshwane, Gauteng, ZA",
    "qs:gn_namadm1":"06",
    "qs:local_max":848,
    "qs:local_sum":4611,
    "qs:localhoods":32,
    "qs:name":"Generaal Kemp Heuwel",
    "qs:name_adm0":"South Africa",
    "qs:name_adm1":"Gauteng",
    "qs:name_adm2":"City of Tshwane",
    "qs:name_lau":"Tshwane",
    "qs:name_local":"Pretoria",
    "qs:photo_max":183,
    "qs:photo_sum":239,
    "qs:placetype":"Suburb",
    "qs:quad_count":7,
    "qs:woe_adm0":23424942,
    "qs:woe_adm1":2346981,
    "qs:woe_adm2":56189409,
    "qs:woe_lau":56189696,
    "qs:woe_local":1586638,
    "qs:woe_ver":"7.10.0",
    "wof:lang":[
        "eng"
    ],
    "wof:name":"Generaal Kempheuwel",
    "wof:placetype":"neighbourhood"
},
  "geometry": {"coordinates":[28.158407,-25.787189],"type":"Point"}
}