{
  "type": "Feature",
  "properties": {
    "gn:admin1_code":"5",
    "gn:admin2_code":"DC14",
    "gn:admin3_code":"EC143",
    "gn:asciiname":"Croxteth",
    "gn:country_code":"ZA",
    "gn:dem":1542,
    "gn:feature_class":"P",
    "gn:feature_code":"PPL",
    "gn:name":"Croxteth",
    "gn:population":0,
    "gn:timezone":"Africa/Johannesburg",
    "iso:country":"ZA",
    "name:dan_x_preferred":[
        "Croxteth"
    ],
    "name:gle_x_preferred":[
        "Croxteth"
    ],
    "name:pol_x_preferred":[
        "Croxteth"
    ],
    "name:tur_x_preferred":[
        "Croxteth"
    ],
    "name:vie_x_preferred":[
        "Croxteth"
    ],
    "wof:name":"Croxteth",
    "wof:placetype":"locality"
},
  "geometry": {"coordinates":[26.82305,-30.95485],"type":"Point"}
}