{
  "type": "Feature",
  "properties": {
    "gn:admin1_code":"8.0",
    "gn:admin2_code":"DC6",
    "gn:admin3_code":"NC065",
    "gn:asciiname":"Voorspoed",
    "gn:country_code":"ZA",
    "gn:dem":858,
    "gn:feature_class":"P",
    "gn:feature_code":"PPL",
    "gn:name":"Voorspoed",
    "gn:population":0,
    "gn:timezone":"Africa/Johannesburg",
    "iso:country":"ZA",
    "wof:name":"Voorspoed",
    "wof:placetype":"locality"
},
  "geometry": {"coordinates":[21.22514,-29.71992],"type":"Point"}
}