{
  "type": "Feature",
  "properties": {
    "gn:admin1_code":"2",
    "gn:admin2_code":"DC43",
    "gn:admin3_code":"KZN433",
    "gn:asciiname":"Brechen",
    "gn:country_code":"ZA",
    "gn:dem":1760,
    "gn:feature_class":"P",
    "gn:feature_code":"PPL",
    "gn:name":"Brechen",
    "gn:population":0,
    "gn:timezone":"Africa/Johannesburg",
    "iso:country":"ZA",
    "name:und_x_variant":[
        "Brechan",
        "Brechen"
    ],
    "wof:name":"Brechen",
    "wof:placetype":"locality"
},
  "geometry": {"coordinates":[29.30686,-30.01776],"type":"Point"}
}