{
  "type": "Feature",
  "properties": {
    "gn:admin1_code":"2",
    "gn:admin2_code":"DC43",
    "gn:admin3_code":"KZN433",
    "gn:asciiname":"Brechen",
    "gn:country_code":"ZA",
    "gn:dem":1760,
    "gn:feature_class":"P",
    "gn:feature_code":"PPL",
    "gn:name":"Brechen",
    "gn:population":0,
    "gn:timezone":"Africa/Johannesburg",
    "iso:country":"ZA",
    "name:ceb_x_preferred":[
        "Brechen"
    ],
    "name:deu_x_preferred":[
        "Brechen"
    ],
    "name:epo_x_preferred":[
        "Brechen"
    ],
    "name:eus_x_preferred":[
        "Brechen"
    ],
    "name:fas_x_preferred":[
        "\u0628\u0631\u0627\u0634\u0646"
    ],
    "name:fra_x_preferred":[
        "Brechen"
    ],
    "name:hun_x_preferred":[
        "Brechen"
    ],
    "name:ita_x_preferred":[
        "Brechen"
    ],
    "name:kaz_x_preferred":[
        "\u0411\u0440\u0435\u0445\u0435\u043d"
    ],
    "name:kir_x_preferred":[
        "\u0411\u0440\u0435\u0445\u0435\u043d"
    ],
    "name:msa_x_preferred":[
        "Brechen"
    ],
    "name:nld_x_preferred":[
        "Brechen"
    ],
    "name:pol_x_preferred":[
        "Brechen"
    ],
    "name:por_x_preferred":[
        "Brechen"
    ],
    "name:ron_x_preferred":[
        "Brechen"
    ],
    "name:rus_x_preferred":[
        "\u0411\u0440\u0435\u0445\u0435\u043d"
    ],
    "name:spa_x_preferred":[
        "Brechen"
    ],
    "name:srp_x_preferred":[
        "\u0411\u0440\u0435\u0445\u0435\u043d"
    ],
    "name:ukr_x_preferred":[
        "\u0411\u0440\u0435\u0445\u0435\u043d"
    ],
    "name:und_x_variant":[
        "Brechan"
    ],
    "name:uzb_x_preferred":[
        "Brechen"
    ],
    "name:vol_x_preferred":[
        "Brechen"
    ],
    "name:war_x_preferred":[
        "Brechen"
    ],
    "name:zho_x_preferred":[
        "\u5e03\u96f7\u5174"
    ],
    "wof:lang_x_official":[
        "eng"
    ],
    "wof:lang_x_spoken":[
        "eng",
        "zul",
        "xho",
        "afr",
        "nso",
        "tsn",
        "sot",
        "tso",
        "ssw",
        "ven",
        "nbl"
    ],
    "wof:name":"Brechen",
    "wof:placetype":"locality"
},
  "geometry": {"coordinates":[29.30686,-30.01776],"type":"Point"}
}