{
  "type": "Feature",
  "properties": {
    "gn:admin1_code":"5",
    "gn:admin2_code":"DC13",
    "gn:admin3_code":"EC133",
    "gn:asciiname":"Derrington",
    "gn:country_code":"ZA",
    "gn:dem":1546,
    "gn:feature_class":"P",
    "gn:feature_code":"PPL",
    "gn:name":"Derrington",
    "gn:population":0,
    "gn:timezone":"Africa/Johannesburg",
    "iso:country":"ZA",
    "name:pol_x_preferred":[
        "Derrington"
    ],
    "name:spa_x_preferred":[
        "Derrington"
    ],
    "name:swe_x_preferred":[
        "Derrington"
    ],
    "wof:name":"Derrington",
    "wof:placetype":"locality"
},
  "geometry": {"coordinates":[26.35,-31.23333],"type":"Point"}
}