{
  "type": "Feature",
  "properties": {
    "gn:admin1_code":"10.0",
    "gn:admin2_code":"DC37",
    "gn:admin3_code":"NW373",
    "gn:asciiname":"Wevedeen",
    "gn:country_code":"ZA",
    "gn:dem":1040,
    "gn:feature_class":"P",
    "gn:feature_code":"PPL",
    "gn:name":"Wevedeen",
    "gn:population":0,
    "gn:timezone":"Africa/Johannesburg",
    "iso:country":"ZA",
    "name:und_x_variant":[
        "Wevedene",
        "Weverdene",
        "Wevedeen"
    ],
    "wof:name":"Wevedeen",
    "wof:placetype":"locality"
},
  "geometry": {"coordinates":[27.40733,-25.4692],"type":"Point"}
}