{
  "type": "Feature",
  "properties": {
    "gn:admin1_code":"3.0",
    "gn:admin2_code":"DC16",
    "gn:admin3_code":"FS162",
    "gn:asciiname":"Roorirantjies",
    "gn:country_code":"ZA",
    "gn:dem":1430,
    "gn:feature_class":"P",
    "gn:feature_code":"PPL",
    "gn:name":"Roorirantjies",
    "gn:population":0,
    "gn:timezone":"Africa/Johannesburg",
    "iso:country":"ZA",
    "wof:name":"Roorirantjies",
    "wof:placetype":"locality"
},
  "geometry": {"coordinates":[25.84767,-29.89613],"type":"Point"}
}