{
  "type": "Feature",
  "properties": {
    "gn:admin1_code":"11.0",
    "gn:admin2_code":"DC1",
    "gn:admin3_code":"WC013",
    "gn:asciiname":"Laaiplek",
    "gn:country_code":"ZA",
    "gn:dem":8,
    "gn:feature_class":"P",
    "gn:feature_code":"PPL",
    "gn:name":"Laaiplek",
    "gn:population":0,
    "gn:timezone":"Africa/Johannesburg",
    "iso:country":"ZA",
    "wof:name":"Laaiplek",
    "wof:placetype":"locality"
},
  "geometry": {"coordinates":[18.15593,-32.77369],"type":"Point"}
}