{
  "type": "Feature",
  "properties": {
    "gn:admin1_code":"5",
    "gn:admin2_code":"DC14",
    "gn:admin3_code":"EC141",
    "gn:asciiname":"Ku-Ngcengane",
    "gn:country_code":"ZA",
    "gn:dem":1295,
    "gn:feature_class":"P",
    "gn:feature_code":"PPL",
    "gn:name":"Ku-Ngcengane",
    "gn:population":0,
    "gn:timezone":"Africa/Johannesburg",
    "iso:country":"ZA",
    "wof:name":"Ku-Ngcengane",
    "wof:placetype":"locality"
},
  "geometry": {"coordinates":[28.38333,-31.31667],"type":"Point"}
}