{
  "type": "Feature",
  "properties": {
    "gn:admin1_code":"6",
    "gn:admin2_code":"JHB",
    "gn:admin3_code":"JHB",
    "gn:asciiname":"Chartwell",
    "gn:country_code":"ZA",
    "gn:dem":1358,
    "gn:feature_class":"P",
    "gn:feature_code":"PPL",
    "gn:name":"Chartwell",
    "gn:population":0,
    "gn:timezone":"Africa/Johannesburg",
    "iso:country":"ZA",
    "wof:name":"Chartwell",
    "wof:placetype":"locality"
},
  "geometry": {"coordinates":[27.96722,-25.97552],"type":"Point"}
}