{
  "type": "Feature",
  "properties": {
    "gn:admin1_code":"11.0",
    "gn:admin2_code":"DC2",
    "gn:admin3_code":"WC022",
    "gn:asciiname":"Groenfontein",
    "gn:country_code":"ZA",
    "gn:dem":1005,
    "gn:feature_class":"P",
    "gn:feature_code":"PPL",
    "gn:name":"Groenfontein",
    "gn:population":0,
    "gn:timezone":"Africa/Johannesburg",
    "iso:country":"ZA",
    "wof:name":"Groenfontein",
    "wof:placetype":"locality"
},
  "geometry": {"coordinates":[19.34776,-33.10849],"type":"Point"}
}