{
  "type": "Feature",
  "properties": {
    "iso:country":"ZA",
    "name:ceb_x_preferred":[
        "Groenvlei"
    ],
    "name:eng_x_preferred":[
        "Groenvlei"
    ],
    "qs:gn_local":0,
    "qs:local_max":142,
    "qs:local_sum":290,
    "qs:localhoods":6,
    "qs:name":"Groenvlei",
    "qs:name_adm0":"South Africa",
    "qs:name_adm1":"Western Cape",
    "qs:name_adm2":"Cape Winelands",
    "qs:name_lau":"Drakenstein",
    "qs:name_local":"Paarl",
    "qs:photo_max":28,
    "qs:photo_sum":40,
    "qs:placetype":"Suburb",
    "qs:quad_count":6,
    "qs:woe_adm0":23424942,
    "qs:woe_adm1":2346987,
    "qs:woe_adm2":56189424,
    "qs:woe_lau":56189688,
    "qs:woe_local":1586388,
    "qs:woe_ver":"7.10.0",
    "wd:wordcount":16,
    "wof:lang_x_official":[
        "eng"
    ],
    "wof:lang_x_spoken":[
        "eng",
        "zul",
        "xho",
        "afr",
        "nso",
        "tsn",
        "sot",
        "tso",
        "ssw",
        "ven",
        "nbl"
    ],
    "wof:name":"Groenvlei",
    "wof:placetype":"neighbourhood"
},
  "geometry": {"coordinates":[18.96262,-33.710662],"type":"Point"}
}