{
  "type": "Feature",
  "properties": {
    "gn:admin1_code":"5",
    "gn:admin2_code":"DC12",
    "gn:admin3_code":"EC126",
    "gn:asciiname":"Melton",
    "gn:country_code":"ZA",
    "gn:dem":83,
    "gn:feature_class":"P",
    "gn:feature_code":"PPL",
    "gn:name":"Melton",
    "gn:population":0,
    "gn:timezone":"Africa/Johannesburg",
    "iso:country":"ZA",
    "name:bar_x_preferred":[
        "Melton"
    ],
    "name:ceb_x_preferred":[
        "Melton"
    ],
    "name:ces_x_preferred":[
        "Melton"
    ],
    "name:deu_x_preferred":[
        "Melton"
    ],
    "name:fra_x_preferred":[
        "Melton"
    ],
    "name:mlg_x_preferred":[
        "Melton"
    ],
    "name:nld_x_preferred":[
        "Melton"
    ],
    "name:pol_x_preferred":[
        "Melton"
    ],
    "name:rus_x_preferred":[
        "\u041c\u0435\u043b\u0442\u043e\u043d"
    ],
    "name:spa_x_preferred":[
        "Melton"
    ],
    "name:swe_x_preferred":[
        "Melton"
    ],
    "wof:name":"Melton",
    "wof:placetype":"locality"
},
  "geometry": {"coordinates":[27.26766,-33.31573],"type":"Point"}
}