{
  "type": "Feature",
  "properties": {
    "gn:admin1_code":"5",
    "gn:admin2_code":"DC44",
    "gn:admin3_code":"EC441",
    "gn:asciiname":"Mvenyane",
    "gn:country_code":"ZA",
    "gn:dem":1370,
    "gn:feature_class":"P",
    "gn:feature_code":"PPL",
    "gn:name":"Mvenyane",
    "gn:population":0,
    "gn:timezone":"Africa/Johannesburg",
    "iso:country":"ZA",
    "wof:name":"Mvenyane",
    "wof:placetype":"locality"
},
  "geometry": {"coordinates":[29.02787,-30.54681],"type":"Point"}
}