{
  "type": "Feature",
  "properties": {
    "gn:admin1_code":"3",
    "gn:admin2_code":"DC16",
    "gn:admin3_code":"FS162",
    "gn:asciiname":"Kleinplaas",
    "gn:country_code":"ZA",
    "gn:dem":1433,
    "gn:feature_class":"P",
    "gn:feature_code":"PPL",
    "gn:name":"Kleinplaas",
    "gn:population":0,
    "gn:timezone":"Africa/Johannesburg",
    "iso:country":"ZA",
    "wof:name":"Kleinplaas",
    "wof:placetype":"locality"
},
  "geometry": {"coordinates":[25.83483,-29.91933],"type":"Point"}
}