{
  "type": "Feature",
  "properties": {
    "gn:admin1_code":"9",
    "gn:admin2_code":"DC35",
    "gn:admin3_code":"LIM351",
    "gn:asciiname":"Bobirwa",
    "gn:country_code":"ZA",
    "gn:dem":995,
    "gn:feature_class":"P",
    "gn:feature_code":"PPL",
    "gn:name":"Bobirwa",
    "gn:population":0,
    "gn:timezone":"Africa/Johannesburg",
    "iso:country":"ZA",
    "name:fra_x_preferred":[
        "Bobonong"
    ],
    "name:ita_x_preferred":[
        "Bobonong"
    ],
    "wof:name":"Bobirwa",
    "wof:placetype":"locality"
},
  "geometry": {"coordinates":[29.05323,-23.31774],"type":"Point"}
}