{
  "type": "Feature",
  "properties": {
    "gn:admin1_code":"10",
    "gn:admin2_code":"DC38",
    "gn:admin3_code":"NW385",
    "gn:asciiname":"Kwaggafontein",
    "gn:country_code":"ZA",
    "gn:dem":1358,
    "gn:feature_class":"P",
    "gn:feature_code":"PPL",
    "gn:name":"Kwaggafontein",
    "gn:population":0,
    "gn:timezone":"Africa/Johannesburg",
    "iso:country":"ZA",
    "name:afr_x_preferred":[
        "Kwaggafontein"
    ],
    "name:deu_x_preferred":[
        "EMpumalanga"
    ],
    "name:est_x_preferred":[
        "Kwaggafontein"
    ],
    "name:nso_x_preferred":[
        "Kwaggafontein"
    ],
    "wof:lang_x_official":[
        "eng"
    ],
    "wof:lang_x_spoken":[
        "eng",
        "zul",
        "xho",
        "afr",
        "nso",
        "tsn",
        "sot",
        "tso",
        "ssw",
        "ven",
        "nbl"
    ],
    "wof:name":"Kwaggafontein",
    "wof:placetype":"locality"
},
  "geometry": {"coordinates":[26.15822,-25.66174],"type":"Point"}
}