{
  "type": "Feature",
  "properties": {
    "gn:admin1_code":"3",
    "gn:admin2_code":"DC16",
    "gn:admin3_code":"FS162",
    "gn:asciiname":"Drukop",
    "gn:country_code":"ZA",
    "gn:dem":1590,
    "gn:feature_class":"P",
    "gn:feature_code":"PPL",
    "gn:name":"Drukop",
    "gn:population":0,
    "gn:timezone":"Africa/Johannesburg",
    "iso:country":"ZA",
    "wof:name":"Drukop",
    "wof:placetype":"locality"
},
  "geometry": {"coordinates":[26.33158,-29.77175],"type":"Point"}
}