{
  "type": "Feature",
  "properties": {
    "gn:admin1_code":"10",
    "gn:admin2_code":"DC37",
    "gn:admin3_code":"NW373",
    "gn:asciiname":"Rietfontein",
    "gn:country_code":"ZA",
    "gn:dem":1464,
    "gn:feature_class":"P",
    "gn:feature_code":"PPL",
    "gn:name":"Rietfontein",
    "gn:population":0,
    "gn:timezone":"Africa/Johannesburg",
    "iso:country":"ZA",
    "name:afr_x_preferred":[
        "Rietfontein"
    ],
    "name:bar_x_preferred":[
        "Rietfontein"
    ],
    "name:ceb_x_preferred":[
        "Rietfontein"
    ],
    "name:est_x_preferred":[
        "Rietfontein"
    ],
    "name:nld_x_preferred":[
        "Rietfontein"
    ],
    "wof:name":"Rietfontein",
    "wof:placetype":"locality"
},
  "geometry": {"coordinates":[27.46667,-25.78333],"type":"Point"}
}