{
  "type": "Feature",
  "properties": {
    "iso:country":"ZA",
    "name:deu_x_preferred":[
        "Adcock"
    ],
    "name:eng_x_preferred":[
        "Adcock"
    ],
    "name:fra_x_preferred":[
        "Adcock"
    ],
    "name:ita_x_preferred":[
        "Adcock"
    ],
    "name:rus_x_preferred":[
        "\u042d\u0434\u043a\u043e\u043a"
    ],
    "name:zho_min_nan_x_preferred":[
        "Adcock"
    ],
    "qs:gn_adm0_cc":"ZA",
    "qs:gn_fcode":"PPLX",
    "qs:gn_local":964420,
    "qs:gn_nam_loc":"Port Elizabeth, Eastern Cape, ZA",
    "qs:gn_namadm1":"05",
    "qs:gn_name":"Adcock",
    "qs:local_max":332,
    "qs:local_sum":1606,
    "qs:localhoods":11,
    "qs:name":"Adcock",
    "qs:name_adm0":"South Africa",
    "qs:name_adm1":"Eastern Cape",
    "qs:name_adm2":"Nelson Mandela Bay",
    "qs:name_lau":"Nelson Mandela Bay",
    "qs:name_local":"Port Elizabeth",
    "qs:photo_max":3,
    "qs:photo_sum":3,
    "qs:placetype":"Suburb",
    "qs:quad_count":1,
    "qs:woe_adm0":23424942,
    "qs:woe_adm1":2346979,
    "qs:woe_adm2":56189415,
    "qs:woe_lau":56189712,
    "qs:woe_local":1586614,
    "qs:woe_ver":"7.10.0",
    "wd:wordcount":160,
    "wof:lang_x_official":[
        "eng"
    ],
    "wof:lang_x_spoken":[
        "eng",
        "zul",
        "xho",
        "afr",
        "nso",
        "tsn",
        "sot",
        "tso",
        "ssw",
        "ven",
        "nbl"
    ],
    "wof:name":"Adcock",
    "wof:placetype":"neighbourhood"
},
  "geometry": {"coordinates":[25.567932,-33.931965],"type":"Point"}
}