{
  "type": "Feature",
  "properties": {
    "gn:admin1_code":"8",
    "gn:admin2_code":"DC8",
    "gn:admin3_code":"NC082",
    "gn:asciiname":"Currie's Camp",
    "gn:country_code":"ZA",
    "gn:dem":767,
    "gn:feature_class":"P",
    "gn:feature_code":"PPL",
    "gn:name":"Currie\u2019s Camp",
    "gn:population":0,
    "gn:timezone":"Africa/Johannesburg",
    "iso:country":"ZA",
    "wof:name":"Currie's Camp",
    "wof:placetype":"locality"
},
  "geometry": {"coordinates":[21.03944,-28.67552],"type":"Point"}
}