{
  "type": "Feature",
  "properties": {
    "gn:admin1_code":"5.0",
    "gn:admin2_code":"DC14",
    "gn:admin3_code":"EC143",
    "gn:asciiname":"Witbank (1)",
    "gn:country_code":"ZA",
    "gn:dem":1612,
    "gn:feature_class":"P",
    "gn:feature_code":"PPL",
    "gn:name":"Witbank (1)",
    "gn:population":0,
    "gn:timezone":"Africa/Johannesburg",
    "iso:country":"ZA",
    "wof:name":"Witbank (1)",
    "wof:placetype":"locality"
},
  "geometry": {"coordinates":[26.86258,-31.10436],"type":"Point"}
}