{
  "type": "Feature",
  "properties": {
    "gn:admin1_code":"8",
    "gn:admin2_code":"DC6",
    "gn:admin3_code":"NC065",
    "gn:asciiname":"Gannaholte",
    "gn:country_code":"ZA",
    "gn:dem":878,
    "gn:feature_class":"P",
    "gn:feature_code":"PPL",
    "gn:name":"Gannaholte",
    "gn:population":0,
    "gn:timezone":"Africa/Johannesburg",
    "iso:country":"ZA",
    "wof:name":"Gannaholte",
    "wof:placetype":"locality"
},
  "geometry": {"coordinates":[21.01259,-30.05221],"type":"Point"}
}