{
  "type": "Feature",
  "properties": {
    "gn:admin1_code":"7",
    "gn:asciiname":"Ohrigstad Settlement",
    "gn:country_code":"ZA",
    "gn:dem":1085,
    "gn:feature_class":"P",
    "gn:feature_code":"PPL",
    "gn:name":"Ohrigstad Settlement",
    "gn:population":0,
    "gn:timezone":"Africa/Johannesburg",
    "iso:country":"ZA",
    "name:und_x_variant":[
        "Ohrigstad Settement",
        "Ohrigstad Settlement"
    ],
    "wof:name":"Ohrigstad Settlement",
    "wof:placetype":"locality"
},
  "geometry": {"coordinates":[30.56194,-24.72024],"type":"Point"}
}