{
  "type": "Feature",
  "properties": {
    "gn:admin1_code":"10",
    "gn:admin2_code":"DC39",
    "gn:admin3_code":"NW393",
    "gn:asciiname":"Glaudina",
    "gn:country_code":"ZA",
    "gn:dem":1371,
    "gn:feature_class":"P",
    "gn:feature_code":"PPL",
    "gn:name":"Glaudina",
    "gn:population":0,
    "gn:timezone":"Africa/Johannesburg",
    "iso:country":"ZA",
    "name:und_x_variant":[
        "Claudina",
        "Claudine",
        "Glaudina"
    ],
    "wof:name":"Glaudina",
    "wof:placetype":"locality"
},
  "geometry": {"coordinates":[25.63026,-27.03679],"type":"Point"}
}