{
  "type": "Feature",
  "properties": {
    "gn:admin1_code":"2",
    "gn:admin2_code":"DC24",
    "gn:admin3_code":"KZN245",
    "gn:asciiname":"Oakover",
    "gn:country_code":"ZA",
    "gn:dem":1258,
    "gn:feature_class":"P",
    "gn:feature_code":"PPL",
    "gn:name":"Oakover",
    "gn:population":0,
    "gn:timezone":"Africa/Johannesburg",
    "iso:country":"ZA",
    "wof:name":"Oakover",
    "wof:placetype":"locality"
},
  "geometry": {"coordinates":[30.45,-29.08333],"type":"Point"}
}