{
  "type": "Feature",
  "properties": {
    "gn:admin1_code":"11.0",
    "gn:admin2_code":"DC2",
    "gn:admin3_code":"WC023",
    "gn:asciiname":"Hou Moed",
    "gn:country_code":"ZA",
    "gn:dem":241,
    "gn:feature_class":"P",
    "gn:feature_code":"PPL",
    "gn:name":"Hou Moed",
    "gn:population":0,
    "gn:timezone":"Africa/Johannesburg",
    "iso:country":"ZA",
    "wof:name":"Hou Moed",
    "wof:placetype":"locality"
},
  "geometry": {"coordinates":[19.05904,-33.8492],"type":"Point"}
}