{
  "type": "Feature",
  "properties": {
    "gn:admin1_code":"5.0",
    "gn:admin2_code":"DC44",
    "gn:admin3_code":"EC442",
    "gn:asciiname":"Mabomvu",
    "gn:country_code":"ZA",
    "gn:dem":1355,
    "gn:feature_class":"P",
    "gn:feature_code":"PPL",
    "gn:name":"Mabomvu",
    "gn:population":0,
    "gn:timezone":"Africa/Johannesburg",
    "iso:country":"ZA",
    "wof:name":"Mabomvu",
    "wof:placetype":"locality"
},
  "geometry": {"coordinates":[29.49381,-30.65489],"type":"Point"}
}