{
  "type": "Feature",
  "properties": {
    "gn:admin1_code":"8",
    "gn:admin2_code":"DC8",
    "gn:admin3_code":"NC084",
    "gn:asciiname":"Edenville",
    "gn:country_code":"ZA",
    "gn:dem":999,
    "gn:feature_class":"P",
    "gn:feature_code":"PPL",
    "gn:name":"Edenville",
    "gn:population":0,
    "gn:timezone":"Africa/Johannesburg",
    "iso:country":"ZA",
    "name:deu_x_preferred":[
        "Edenville"
    ],
    "name:hak_x_preferred":[
        "Edenville"
    ],
    "name:ita_x_preferred":[
        "Edenville"
    ],
    "wof:lang_x_official":[
        "eng"
    ],
    "wof:lang_x_spoken":[
        "eng",
        "zul",
        "xho",
        "afr",
        "nso",
        "tsn",
        "sot",
        "tso",
        "ssw",
        "ven",
        "nbl"
    ],
    "wof:name":"Edenville",
    "wof:placetype":"locality"
},
  "geometry": {"coordinates":[21.63966,-29.26076],"type":"Point"}
}