{
  "type": "Feature",
  "properties": {
    "gn:admin1_code":"9",
    "gn:admin2_code":"DC34",
    "gn:admin3_code":"LIM344",
    "gn:asciiname":"Gertrudsburg",
    "gn:country_code":"ZA",
    "gn:dem":921,
    "gn:feature_class":"P",
    "gn:feature_code":"PPL",
    "gn:name":"Gertrudsburg",
    "gn:population":0,
    "gn:timezone":"Africa/Johannesburg",
    "iso:country":"ZA",
    "wof:name":"Gertrudsburg",
    "wof:placetype":"locality"
},
  "geometry": {"coordinates":[29.8057,-23.11843],"type":"Point"}
}