{
  "type": "Feature",
  "properties": {
    "gn:admin1_code":"5",
    "gn:admin2_code":"DC13",
    "gn:admin3_code":"EC131",
    "gn:asciiname":"Groenkloof",
    "gn:country_code":"ZA",
    "gn:dem":1107,
    "gn:feature_class":"P",
    "gn:feature_code":"PPL",
    "gn:name":"Groenkloof",
    "gn:population":0,
    "gn:timezone":"Africa/Johannesburg",
    "iso:country":"ZA",
    "name:afr_x_preferred":[
        "Groenkloof"
    ],
    "name:ceb_x_preferred":[
        "Groenkloof"
    ],
    "name:fra_x_preferred":[
        "Groenkloof"
    ],
    "name:nld_x_preferred":[
        "Groenkloof"
    ],
    "wof:lang_x_official":[
        "eng"
    ],
    "wof:lang_x_spoken":[
        "eng",
        "zul",
        "xho",
        "afr",
        "nso",
        "tsn",
        "sot",
        "tso",
        "ssw",
        "ven",
        "nbl"
    ],
    "wof:name":"Groenkloof",
    "wof:placetype":"locality"
},
  "geometry": {"coordinates":[25.50906,-31.78089],"type":"Point"}
}