{
  "type": "Feature",
  "properties": {
    "gn:admin1_code":"5",
    "gn:admin2_code":"DC13",
    "gn:admin3_code":"EC131",
    "gn:asciiname":"Conway",
    "gn:country_code":"ZA",
    "gn:dem":1091,
    "gn:feature_class":"P",
    "gn:feature_code":"PPL",
    "gn:name":"Conway",
    "gn:population":0,
    "gn:timezone":"Africa/Johannesburg",
    "iso:country":"ZA",
    "name:ben_x_preferred":[
        "\u0995\u09a8\u0993\u09df\u09c7"
    ],
    "name:cat_x_preferred":[
        "Conway"
    ],
    "name:ceb_x_preferred":[
        "Conway"
    ],
    "name:ces_x_preferred":[
        "Conway"
    ],
    "name:deu_x_preferred":[
        "Conway"
    ],
    "name:ell_x_preferred":[
        "\u039a\u03cc\u03bd\u03b3\u03bf\u03c5\u03b5\u03ca"
    ],
    "name:fas_x_preferred":[
        "\u06a9\u0627\u0646\u0648\u06cc"
    ],
    "name:fin_x_preferred":[
        "Conway"
    ],
    "name:fra_x_preferred":[
        "Conway"
    ],
    "name:hin_x_preferred":[
        "\u0915\u0949\u0928\u0935\u0947"
    ],
    "name:hun_x_preferred":[
        "Conway"
    ],
    "name:ind_x_preferred":[
        "Conway"
    ],
    "name:ita_x_preferred":[
        "Conway"
    ],
    "name:jpn_x_preferred":[
        "\u30b3\u30f3\u30a6\u30a7\u30a4"
    ],
    "name:kor_x_preferred":[
        "\ucf58\uc6e8\uc774"
    ],
    "name:nld_x_preferred":[
        "Conway"
    ],
    "name:pol_x_preferred":[
        "Conway"
    ],
    "name:por_x_preferred":[
        "Conway"
    ],
    "name:rus_x_preferred":[
        "\u041a\u043e\u043d\u0443\u044d\u0439"
    ],
    "name:slv_x_preferred":[
        "Conway"
    ],
    "name:spa_x_preferred":[
        "Conway"
    ],
    "name:srp_x_preferred":[
        "\u041a\u043e\u043d\u0432\u0435\u0458"
    ],
    "name:swe_x_preferred":[
        "Conway"
    ],
    "name:ukr_x_preferred":[
        "\u041a\u043e\u043d\u0432\u0435\u0439"
    ],
    "name:urd_x_preferred":[
        "\u06a9\u0648\u0646\u0648\u06d2"
    ],
    "name:vol_x_preferred":[
        "Conway"
    ],
    "wof:lang_x_official":[
        "eng"
    ],
    "wof:lang_x_spoken":[
        "eng",
        "zul",
        "xho",
        "afr",
        "nso",
        "tsn",
        "sot",
        "tso",
        "ssw",
        "ven",
        "nbl"
    ],
    "wof:name":"Conway",
    "wof:placetype":"locality"
},
  "geometry": {"coordinates":[25.30232,-31.73384],"type":"Point"}
}