{
  "type": "Feature",
  "properties": {
    "gn:admin1_code":"2",
    "gn:admin2_code":"DC24",
    "gn:admin3_code":"KZN244",
    "gn:asciiname":"Pomeroy",
    "gn:country_code":"ZA",
    "gn:dem":1121,
    "gn:feature_class":"P",
    "gn:feature_code":"PPL",
    "gn:name":"Pomeroy",
    "gn:population":0,
    "gn:timezone":"Africa/Johannesburg",
    "iso:country":"ZA",
    "name:afr_x_preferred":[
        "Pomeroy"
    ],
    "name:nso_x_preferred":[
        "Pomeroy"
    ],
    "name:ron_x_preferred":[
        "Pomeroy"
    ],
    "wof:lang_x_official":[
        "eng"
    ],
    "wof:lang_x_spoken":[
        "eng",
        "zul",
        "xho",
        "afr",
        "nso",
        "tsn",
        "sot",
        "tso",
        "ssw",
        "ven",
        "nbl"
    ],
    "wof:name":"Pomeroy",
    "wof:placetype":"locality"
},
  "geometry": {"coordinates":[30.42502,-28.55292],"type":"Point"}
}