{
  "type": "Feature",
  "properties": {
    "iso:country":"ZA",
    "name:afr_x_preferred":[
        "Hlabisa"
    ],
    "name:ast_x_preferred":[
        "Hlabisa"
    ],
    "name:deu_x_preferred":[
        "Hlabisa"
    ],
    "name:eng_x_preferred":[
        "Hlabisa"
    ],
    "name:fra_x_preferred":[
        "Hlabisa"
    ],
    "name:jpn_x_preferred":[
        "\u30d5\u30e9\u30d3\u30b5"
    ],
    "name:nld_x_preferred":[
        "Hlabisa"
    ],
    "name:nso_x_preferred":[
        "Hlabisa"
    ],
    "name:zho_x_preferred":[
        "\u8d6b\u62c9\u6bd4\u85a9"
    ],
    "qs_pg:aaroncc":"ZA",
    "qs_pg:name":"Hlabisa",
    "qs_pg:name_adm0":"South Africa",
    "qs_pg:name_adm1":"Kwazulu Natal",
    "qs_pg:photos":7,
    "qs_pg:photos_1k":1,
    "qs_pg:photos_9k":1,
    "qs_pg:photos_9r":1,
    "qs_pg:photos_all":7,
    "qs_pg:photos_sr":1,
    "qs_pg:pop_sr":0,
    "qs_pg:qs_pg_placetype":"locality",
    "qs_pg:qs_pg_placetype_gp":"Town",
    "qs_pg:woe_adm0":23424942,
    "woe:adm0_id":23424942,
    "woe:name_adm0":"South Africa",
    "woe:name_adm1":"Kwazulu Natal",
    "woe:placetype":"Town",
    "wof:lang_x_official":[
        "eng"
    ],
    "wof:lang_x_spoken":[
        "eng",
        "zul",
        "xho",
        "afr",
        "nso",
        "tsn",
        "sot",
        "tso",
        "ssw",
        "ven",
        "nbl"
    ],
    "wof:name":"Hlabisa",
    "wof:placetype":"locality"
},
  "geometry": {"coordinates":[31.877174,-28.173566],"type":"Point"}
}