{
  "type": "Feature",
  "properties": {
    "iso:country":"ZA",
    "name:afr_x_preferred":[
        "Parktown"
    ],
    "name:bar_x_preferred":[
        "Parktown"
    ],
    "name:cat_x_preferred":[
        "Parktown"
    ],
    "name:deu_x_preferred":[
        "Parktown"
    ],
    "name:eng_x_preferred":[
        "Parktown"
    ],
    "name:fra_x_preferred":[
        "Parktown"
    ],
    "name:hye_x_preferred":[
        "\u0553\u0561\u0580\u0584\u0569\u0561\u0578\u0582\u0576"
    ],
    "name:nld_x_preferred":[
        "Parktown"
    ],
    "name:ron_x_preferred":[
        "Parktown"
    ],
    "name:rus_x_preferred":[
        "\u041f\u0430\u0440\u043a\u0442\u0430\u0443\u043d"
    ],
    "name:unk_x_variant":[
        "Parktown"
    ],
    "name:zho_x_preferred":[
        "\u5e15\u514b\u6566"
    ],
    "qs:gn_adm0_cc":"ZA",
    "qs:gn_fcode":"PPLX",
    "qs:gn_local":993800,
    "qs:gn_nam_loc":"Johannesburg, Johannesburg, City of Johannesburg, Gauteng, ZA",
    "qs:gn_namadm1":"06",
    "qs:gn_name":"Parktown",
    "qs:local_max":2766,
    "qs:local_sum":31655,
    "qs:localhoods":69,
    "qs:name":"Parktown",
    "qs:name_adm0":"South Africa",
    "qs:name_adm1":"Gauteng",
    "qs:name_adm2":"City of Johannesburg",
    "qs:name_lau":"Johannesburg",
    "qs:name_local":"Johannesburg",
    "qs:photo_max":3,
    "qs:photo_sum":13,
    "qs:placetype":"Suburb",
    "qs:quad_count":9,
    "qs:woe_adm0":23424942,
    "qs:woe_adm1":2346981,
    "qs:woe_adm2":56189422,
    "qs:woe_lau":56189710,
    "qs:woe_local":1582504,
    "qs:woe_ver":"7.10.0",
    "wd:wordcount":1010,
    "wof:lang":[
        "eng"
    ],
    "wof:name":"Parktown",
    "wof:placetype":"neighbourhood"
},
  "geometry": {"coordinates":[28.027567,-26.181637],"type":"Point"}
}