{
  "type": "Feature",
  "properties": {
    "gn:country":"ZA",
    "gn:fcode":"PPLX",
    "gn:population":0,
    "iso:country":"ZA",
    "name:bar_x_preferred":[
        "Chatsworth"
    ],
    "name:cat_x_preferred":[
        "Chatsworth"
    ],
    "name:ceb_x_preferred":[
        "Chatsworth"
    ],
    "name:ces_x_preferred":[
        "Chatsworth"
    ],
    "name:deu_x_preferred":[
        "Chatsworth"
    ],
    "name:fra_x_preferred":[
        "Chatsworth"
    ],
    "name:ita_x_preferred":[
        "Chatsworth"
    ],
    "name:nld_x_preferred":[
        "Chatsworth"
    ],
    "name:pol_x_preferred":[
        "Chatsworth"
    ],
    "name:srp_x_preferred":[
        "\u0427\u0430\u0442\u0441\u0432\u043e\u0440\u0442"
    ],
    "name:swe_x_preferred":[
        "Chatsworth"
    ],
    "name:ukr_x_preferred":[
        "\u0427\u0430\u0442\u0441\u0432\u043e\u0440\u0442"
    ],
    "name:und_x_variant":[
        "Chatsworth Indian Township"
    ],
    "name:vol_x_preferred":[
        "Chatsworth"
    ],
    "name:zho_x_preferred":[
        "\u67e5\u8328\u6c83\u601d"
    ],
    "qs_pg:aaroncc":"ZA",
    "qs_pg:gn_country":"ZA",
    "qs_pg:gn_fcode":"PPLX",
    "qs_pg:gn_pop":0,
    "qs_pg:name":"Chatsworth",
    "qs_pg:name_adm0":"South Africa",
    "qs_pg:name_adm1":"Kwazulu Natal",
    "qs_pg:photos":1,
    "qs_pg:photos_1k":1,
    "qs_pg:photos_9k":1,
    "qs_pg:photos_9r":1,
    "qs_pg:photos_all":1,
    "qs_pg:photos_sr":1,
    "qs_pg:pop_sr":0,
    "qs_pg:qs_pg_placetype":"neighbourhood",
    "qs_pg:qs_pg_placetype_gp":"Suburb",
    "qs_pg:woe_adm0":23424942,
    "woe:adm0_id":23424942,
    "woe:name_adm0":"South Africa",
    "woe:name_adm1":"Kwazulu Natal",
    "woe:placetype":"Suburb",
    "wof:lang_x_official":[
        "eng"
    ],
    "wof:lang_x_spoken":[
        "eng",
        "zul",
        "xho",
        "afr",
        "nso",
        "tsn",
        "sot",
        "tso",
        "ssw",
        "ven",
        "nbl"
    ],
    "wof:name":"Chatsworth",
    "wof:placetype":"neighbourhood"
},
  "geometry": {"coordinates":[30.8917,-29.91866],"type":"Point"}
}