{
  "type": "Feature",
  "properties": {
    "gn:admin1_code":"5",
    "gn:admin2_code":"DC44",
    "gn:admin3_code":"EC443",
    "gn:asciiname":"KuSiwisa Halt",
    "gn:country_code":"ZA",
    "gn:dem":993,
    "gn:feature_class":"P",
    "gn:feature_code":"PPL",
    "gn:name":"KuSiwisa Halt",
    "gn:population":0,
    "gn:timezone":"Africa/Johannesburg",
    "iso:country":"ZA",
    "wof:name":"KuSiwisa Halt",
    "wof:placetype":"locality"
},
  "geometry": {"coordinates":[29.7007,-30.85468],"type":"Point"}
}