{
  "type": "Feature",
  "properties": {
    "iso:country":"ZA",
    "name:eng_x_preferred":[
        "Krigeville"
    ],
    "qs:gn_local":0,
    "qs:local_max":1099,
    "qs:local_sum":3108,
    "qs:localhoods":9,
    "qs:name":"Krigeville",
    "qs:name_adm0":"South Africa",
    "qs:name_adm1":"Western Cape",
    "qs:name_adm2":"Cape Winelands",
    "qs:name_lau":"Stellenbosch",
    "qs:name_local":"Stellenbosch",
    "qs:photo_max":537,
    "qs:photo_sum":1099,
    "qs:placetype":"Suburb",
    "qs:quad_count":16,
    "qs:woe_adm0":23424942,
    "qs:woe_adm1":2346987,
    "qs:woe_adm2":56189424,
    "qs:woe_lau":56189563,
    "qs:woe_local":1587741,
    "qs:woe_ver":"7.10.0",
    "wof:lang":[
        "eng"
    ],
    "wof:name":"Krigeville",
    "wof:placetype":"neighbourhood"
},
  "geometry": {"coordinates":[18.860229,-33.944639],"type":"Point"}
}