{
  "type": "Feature",
  "properties": {
    "gn:admin1_code":"10",
    "gn:asciiname":"Albanie",
    "gn:country_code":"ZA",
    "gn:dem":1417,
    "gn:feature_class":"P",
    "gn:feature_code":"PPL",
    "gn:name":"Albanie",
    "gn:population":0,
    "gn:timezone":"Africa/Johannesburg",
    "iso:country":"ZA",
    "wof:name":"Albanie",
    "wof:placetype":"locality"
},
  "geometry": {"coordinates":[23.82945,-27.34428],"type":"Point"}
}