{
  "type": "Feature",
  "properties": {
    "gn:admin1_code":"5",
    "gn:admin2_code":"DC14",
    "gn:admin3_code":"EC141",
    "gn:asciiname":"Ngxazana",
    "gn:country_code":"ZA",
    "gn:dem":1512,
    "gn:feature_class":"P",
    "gn:feature_code":"PPL",
    "gn:name":"Ngxazana",
    "gn:population":0,
    "gn:timezone":"Africa/Johannesburg",
    "iso:country":"ZA",
    "wof:name":"Ngxazana",
    "wof:placetype":"locality"
},
  "geometry": {"coordinates":[28.52857,-30.58981],"type":"Point"}
}