{
  "type": "Feature",
  "properties": {
    "gn:admin1_code":"5",
    "gn:admin2_code":"DC13",
    "gn:admin3_code":"EC135",
    "gn:asciiname":"Lower Mtingwevu",
    "gn:country_code":"ZA",
    "gn:dem":1081,
    "gn:feature_class":"P",
    "gn:feature_code":"PPL",
    "gn:name":"Lower Mtingwevu",
    "gn:population":0,
    "gn:timezone":"Africa/Johannesburg",
    "iso:country":"ZA",
    "wof:name":"Lower Mtingwevu",
    "wof:placetype":"locality"
},
  "geometry": {"coordinates":[27.59668,-31.74045],"type":"Point"}
}