{
  "type": "Feature",
  "properties": {
    "gn:admin1_code":"10",
    "gn:asciiname":"Dilopye",
    "gn:country_code":"ZA",
    "gn:dem":1121,
    "gn:feature_class":"P",
    "gn:feature_code":"PPL",
    "gn:name":"Dilopye",
    "gn:population":0,
    "gn:timezone":"Africa/Johannesburg",
    "iso:country":"ZA",
    "wof:name":"Dilopye",
    "wof:placetype":"locality"
},
  "geometry": {"coordinates":[28.19318,-25.38364],"type":"Point"}
}