{
  "type": "Feature",
  "properties": {
    "gn:admin1_code":"8",
    "gn:admin2_code":"DC45",
    "gn:admin3_code":"NC451",
    "gn:asciiname":"Ga-Malelo",
    "gn:country_code":"ZA",
    "gn:dem":1110,
    "gn:feature_class":"P",
    "gn:feature_code":"PPL",
    "gn:name":"Ga-Malelo",
    "gn:population":0,
    "gn:timezone":"Africa/Johannesburg",
    "iso:country":"ZA",
    "name:und_x_variant":[
        "Gamolilo",
        "Gamalilo",
        "Ga-Malelo"
    ],
    "wof:lang_x_official":[
        "eng"
    ],
    "wof:lang_x_spoken":[
        "eng",
        "zul",
        "xho",
        "afr",
        "nso",
        "tsn",
        "sot",
        "tso",
        "ssw",
        "ven",
        "nbl"
    ],
    "wof:name":"Ga-Malelo",
    "wof:placetype":"locality"
},
  "geometry": {"coordinates":[23.07509,-26.99822],"type":"Point"}
}