{
  "type": "Feature",
  "properties": {
    "gn:admin1_code":"9",
    "gn:admin2_code":"DC47",
    "gn:admin3_code":"LIM473",
    "gn:asciiname":"Matshupe",
    "gn:country_code":"ZA",
    "gn:dem":1572,
    "gn:feature_class":"P",
    "gn:feature_code":"PPL",
    "gn:name":"Matshupe",
    "gn:population":0,
    "gn:timezone":"Africa/Johannesburg",
    "iso:country":"ZA",
    "wof:name":"Matshupe",
    "wof:placetype":"locality"
},
  "geometry": {"coordinates":[30.07499,-24.7766],"type":"Point"}
}