{
  "type": "Feature",
  "properties": {
    "gn:gn_country":"ZA",
    "gn:gn_fcode":"PPL",
    "gn:gn_pop":0,
    "iso:country":"ZA",
    "name:afr_x_preferred":[
        "McGregor"
    ],
    "name:dut_x_preferred":[
        "McGregor"
    ],
    "name:eng_x_preferred":[
        "McGregor"
    ],
    "name:ger_x_preferred":[
        "McGregor"
    ],
    "name:nso_x_preferred":[
        "McGregor"
    ],
    "name:rum_x_preferred":[
        "McGregor"
    ],
    "name:rus_x_preferred":[
        "\u041c\u0430\u043a\u0433\u0440\u0435\u0433\u043e\u0440"
    ],
    "qs_pg:aaroncc":"ZA",
    "qs_pg:gn_country":"ZA",
    "qs_pg:gn_fcode":"PPL",
    "qs_pg:gn_pop":0,
    "qs_pg:name":"McGregor",
    "qs_pg:name_adm0":"South Africa",
    "qs_pg:name_adm1":"Western Cape",
    "qs_pg:photos":149,
    "qs_pg:photos_1k":30,
    "qs_pg:photos_9k":1,
    "qs_pg:photos_9r":3,
    "qs_pg:photos_all":149,
    "qs_pg:photos_sr":3,
    "qs_pg:pop_sr":0,
    "qs_pg:qs_pg_placetype":"locality",
    "qs_pg:qs_pg_placetype_gp":"Town",
    "qs_pg:woe_adm0":23424942,
    "woe:adm0_id":23424942,
    "woe:name_adm0":"South Africa",
    "woe:name_adm1":"Western Cape",
    "woe:placetype":"Town",
    "wof:name":"McGregor",
    "wof:placetype":"locality"
},
  "geometry": {"coordinates":[19.82906,-33.94725],"type":"Point"}
}