{
  "type": "Feature",
  "properties": {
    "gn:admin1_code":"5",
    "gn:admin2_code":"DC15",
    "gn:admin3_code":"EC154",
    "gn:asciiname":"Nomadi",
    "gn:country_code":"ZA",
    "gn:dem":24,
    "gn:feature_class":"P",
    "gn:feature_code":"PPL",
    "gn:name":"Nomadi",
    "gn:population":0,
    "gn:timezone":"Africa/Johannesburg",
    "iso:country":"ZA",
    "name:deu_x_preferred":[
        "Nomadi"
    ],
    "name:fra_x_preferred":[
        "Nomadi"
    ],
    "name:ita_x_preferred":[
        "Nomadi"
    ],
    "name:lat_x_preferred":[
        "Nomadi"
    ],
    "name:spa_x_preferred":[
        "Nomadi"
    ],
    "name:sqi_x_preferred":[
        "Nomadi"
    ],
    "name:vec_x_preferred":[
        "Nomadi"
    ],
    "wof:lang_x_official":[
        "eng"
    ],
    "wof:lang_x_spoken":[
        "eng",
        "zul",
        "xho",
        "afr",
        "nso",
        "tsn",
        "sot",
        "tso",
        "ssw",
        "ven",
        "nbl"
    ],
    "wof:name":"Nomadi",
    "wof:placetype":"locality"
},
  "geometry": {"coordinates":[29.41667,-31.61667],"type":"Point"}
}