{
  "type": "Feature",
  "properties": {
    "gn:admin1_code":"2",
    "gn:admin2_code":"DC29",
    "gn:admin3_code":"KZN293",
    "gn:asciiname":"oGonothini",
    "gn:country_code":"ZA",
    "gn:dem":513,
    "gn:feature_class":"P",
    "gn:feature_code":"PPL",
    "gn:name":"oGonothini",
    "gn:population":0,
    "gn:timezone":"Africa/Johannesburg",
    "iso:country":"ZA",
    "wof:lang_x_official":[
        "eng"
    ],
    "wof:lang_x_spoken":[
        "eng",
        "zul",
        "xho",
        "afr",
        "nso",
        "tsn",
        "sot",
        "tso",
        "ssw",
        "ven",
        "nbl"
    ],
    "wof:name":"oGonothini",
    "wof:placetype":"locality"
},
  "geometry": {"coordinates":[30.95636,-29.44662],"type":"Point"}
}