{
  "type": "Feature",
  "properties": {
    "gn:admin1_code":"9",
    "gn:asciiname":"Maripi",
    "gn:country_code":"ZA",
    "gn:dem":494,
    "gn:feature_class":"P",
    "gn:feature_code":"PPL",
    "gn:name":"Maripi",
    "gn:population":0,
    "gn:timezone":"Africa/Johannesburg",
    "iso:country":"ZA",
    "wof:name":"Maripi",
    "wof:placetype":"locality"
},
  "geometry": {"coordinates":[31.18379,-24.72163],"type":"Point"}
}