{
  "type": "Feature",
  "properties": {
    "gn:admin1_code":"2",
    "gn:admin2_code":"DC27",
    "gn:admin3_code":"KZN274",
    "gn:asciiname":"Nagana",
    "gn:country_code":"ZA",
    "gn:dem":189,
    "gn:feature_class":"P",
    "gn:feature_code":"PPL",
    "gn:name":"Nagana",
    "gn:population":0,
    "gn:timezone":"Africa/Johannesburg",
    "iso:country":"ZA",
    "wof:name":"Nagana",
    "wof:placetype":"locality"
},
  "geometry": {"coordinates":[31.96667,-28.25],"type":"Point"}
}