{
  "type": "Feature",
  "properties": {
    "gn:admin1_code":"5",
    "gn:admin2_code":"DC13",
    "gn:admin3_code":"EC133",
    "gn:asciiname":"Hughenden",
    "gn:country_code":"ZA",
    "gn:dem":1557,
    "gn:feature_class":"P",
    "gn:feature_code":"PPL",
    "gn:name":"Hughenden",
    "gn:population":0,
    "gn:timezone":"Africa/Johannesburg",
    "iso:country":"ZA",
    "name:ara_x_preferred":[
        "\u0647\u064a\u063a\u064a\u0646\u062f\u064a\u0646"
    ],
    "name:ben_x_preferred":[
        "\u09b9\u09c1\u0998\u09c7\u09a8\u09cd\u09a1\u09c7\u09a8"
    ],
    "name:ceb_x_preferred":[
        "Hughenden"
    ],
    "name:ell_x_preferred":[
        "\u03a7\u03b9\u03bf\u03cd\u03c7\u03b5\u03bd\u03c4\u03b5\u03bd"
    ],
    "name:heb_x_preferred":[
        "\u05d4\u05d5\u05d2\u05e0\u05d3\u05df"
    ],
    "name:hin_x_preferred":[
        "\u0939\u0941\u0917\u0947\u0902\u0926\u0947\u0928"
    ],
    "name:hun_x_preferred":[
        "Hughenden"
    ],
    "name:ind_x_preferred":[
        "Hughenden"
    ],
    "name:ita_x_preferred":[
        "Hughenden"
    ],
    "name:kor_x_preferred":[
        "\ud734\uac90\ub374"
    ],
    "name:pol_x_preferred":[
        "Hughenden"
    ],
    "name:por_x_preferred":[
        "Hughenden"
    ],
    "name:spa_x_preferred":[
        "Hughenden"
    ],
    "name:swe_x_preferred":[
        "Hughenden"
    ],
    "name:tur_x_preferred":[
        "Hughenden"
    ],
    "name:urd_x_preferred":[
        "\u06c1\u06cc\u0648\u0627\u06cc\u0646\u0688\u06cc\u0646"
    ],
    "name:vie_x_preferred":[
        "Hughenden"
    ],
    "name:zho_cn_x_preferred":[
        "\u4f11\u6069\u767b"
    ],
    "name:zho_tw_x_preferred":[
        "\u4f11\u6839\u767b"
    ],
    "wof:lang_x_official":[
        "eng"
    ],
    "wof:lang_x_spoken":[
        "eng",
        "zul",
        "xho",
        "afr",
        "nso",
        "tsn",
        "sot",
        "tso",
        "ssw",
        "ven",
        "nbl"
    ],
    "wof:name":"Hughenden",
    "wof:placetype":"locality"
},
  "geometry": {"coordinates":[26.75976,-31.5973],"type":"Point"}
}