{
  "type": "Feature",
  "properties": {
    "gn:admin1_code":"5",
    "gn:admin2_code":"DC13",
    "gn:admin3_code":"EC133",
    "gn:asciiname":"Hughenden",
    "gn:country_code":"ZA",
    "gn:dem":1557,
    "gn:feature_class":"P",
    "gn:feature_code":"PPL",
    "gn:name":"Hughenden",
    "gn:population":0,
    "gn:timezone":"Africa/Johannesburg",
    "iso:country":"ZA",
    "name:ceb_x_preferred":[
        "Hughenden"
    ],
    "name:ita_x_preferred":[
        "Hughenden"
    ],
    "name:pol_x_preferred":[
        "Hughenden"
    ],
    "name:swe_x_preferred":[
        "Hughenden"
    ],
    "wof:name":"Hughenden",
    "wof:placetype":"locality"
},
  "geometry": {"coordinates":[26.75976,-31.5973],"type":"Point"}
}