{
  "type": "Feature",
  "properties": {
    "gn:admin1_code":"5",
    "gn:admin2_code":"DC12",
    "gn:admin3_code":"EC123",
    "gn:asciiname":"Pine Tops",
    "gn:country_code":"ZA",
    "gn:dem":177,
    "gn:feature_class":"P",
    "gn:feature_code":"PPL",
    "gn:name":"Pine Tops",
    "gn:population":0,
    "gn:timezone":"Africa/Johannesburg",
    "iso:country":"ZA",
    "wof:name":"Pine Tops",
    "wof:placetype":"locality"
},
  "geometry": {"coordinates":[28.20658,-32.73849000000001],"type":"Point"}
}