{
  "type": "Feature",
  "properties": {
    "gn:admin1_code":"5",
    "gn:admin2_code":"DC14",
    "gn:admin3_code":"EC143",
    "gn:asciiname":"Buffelsbadden",
    "gn:country_code":"ZA",
    "gn:dem":1333,
    "gn:feature_class":"P",
    "gn:feature_code":"PPL",
    "gn:name":"Buffelsbadden",
    "gn:population":0,
    "gn:timezone":"Africa/Johannesburg",
    "iso:country":"ZA",
    "wof:name":"Buffelsbadden",
    "wof:placetype":"locality"
},
  "geometry": {"coordinates":[26.71452,-30.7154],"type":"Point"}
}