{
  "type": "Feature",
  "properties": {
    "gn:admin1_code":"6.0",
    "gn:admin2_code":"JHB",
    "gn:admin3_code":"JHB",
    "gn:asciiname":"Southdale",
    "gn:country_code":"ZA",
    "gn:dem":1713,
    "gn:feature_class":"P",
    "gn:feature_code":"PPL",
    "gn:name":"Southdale",
    "gn:population":0,
    "gn:timezone":"Africa/Johannesburg",
    "iso:country":"ZA",
    "name:fra_x_preferred":[
        "Southdale"
    ],
    "wof:name":"Southdale",
    "wof:placetype":"locality"
},
  "geometry": {"coordinates":[28.02329000000001,-26.24031],"type":"Point"}
}