{
  "type": "Feature",
  "properties": {
    "gn:admin1_code":"5",
    "gn:admin2_code":"DC13",
    "gn:admin3_code":"EC136",
    "gn:asciiname":"Gubahoek",
    "gn:country_code":"ZA",
    "gn:dem":1273,
    "gn:feature_class":"P",
    "gn:feature_code":"PPL",
    "gn:name":"Gubahoek",
    "gn:population":0,
    "gn:timezone":"Africa/Johannesburg",
    "iso:country":"ZA",
    "wof:name":"Gubahoek",
    "wof:placetype":"locality"
},
  "geometry": {"coordinates":[27.30626,-31.51642],"type":"Point"}
}