{
  "type": "Feature",
  "properties": {
    "gn:admin1_code":"5",
    "gn:admin2_code":"DC13",
    "gn:admin3_code":"EC135",
    "gn:asciiname":"Bilaty",
    "gn:country_code":"ZA",
    "gn:dem":815,
    "gn:feature_class":"P",
    "gn:feature_code":"PPL",
    "gn:name":"Bilaty",
    "gn:population":0,
    "gn:timezone":"Africa/Johannesburg",
    "iso:country":"ZA",
    "name:und_x_variant":[
        "Bilatyi",
        "Bilaty"
    ],
    "wof:name":"Bilaty",
    "wof:placetype":"locality"
},
  "geometry": {"coordinates":[27.39817,-31.95581],"type":"Point"}
}