{
  "type": "Feature",
  "properties": {
    "gn:admin1_code":"9",
    "gn:admin2_code":"DC34",
    "gn:admin3_code":"LIM342",
    "gn:asciiname":"Pile",
    "gn:country_code":"ZA",
    "gn:dem":695,
    "gn:feature_class":"P",
    "gn:feature_code":"PPL",
    "gn:name":"Pile",
    "gn:population":0,
    "gn:timezone":"Africa/Johannesburg",
    "iso:country":"ZA",
    "name:ceb_x_preferred":[
        "Pile"
    ],
    "name:deu_x_preferred":[
        "Pile"
    ],
    "name:fra_x_preferred":[
        "Pile"
    ],
    "name:ita_x_preferred":[
        "Pile"
    ],
    "name:jpn_x_preferred":[
        "\u30d1\u30a4\u30eb"
    ],
    "name:swe_x_preferred":[
        "Pile"
    ],
    "wof:lang_x_official":[
        "eng"
    ],
    "wof:lang_x_spoken":[
        "eng",
        "zul",
        "xho",
        "afr",
        "nso",
        "tsn",
        "sot",
        "tso",
        "ssw",
        "ven",
        "nbl"
    ],
    "wof:name":"Pile",
    "wof:placetype":"locality"
},
  "geometry": {"coordinates":[30.47463,-22.76972],"type":"Point"}
}