{
  "type": "Feature",
  "properties": {
    "gn:admin1_code":"8",
    "gn:admin2_code":"DC8",
    "gn:admin3_code":"NC082",
    "gn:asciiname":"Neilersdrif",
    "gn:country_code":"ZA",
    "gn:dem":732,
    "gn:feature_class":"P",
    "gn:feature_code":"PPL",
    "gn:name":"Neilersdrif",
    "gn:population":0,
    "gn:timezone":"Africa/Johannesburg",
    "iso:country":"ZA",
    "name:und_x_variant":[
        "Neilersdrift",
        "Neilersdrif"
    ],
    "wof:lang_x_official":[
        "eng"
    ],
    "wof:lang_x_spoken":[
        "eng",
        "zul",
        "xho",
        "afr",
        "nso",
        "tsn",
        "sot",
        "tso",
        "ssw",
        "ven",
        "nbl"
    ],
    "wof:name":"Neilersdrif",
    "wof:placetype":"locality"
},
  "geometry": {"coordinates":[20.98537,-28.74493],"type":"Point"}
}