{
  "type": "Feature",
  "properties": {
    "gn:admin1_code":"5",
    "gn:admin2_code":"DC15",
    "gn:admin3_code":"EC156",
    "gn:asciiname":"Kwa-Dunjane",
    "gn:country_code":"ZA",
    "gn:dem":1077,
    "gn:feature_class":"P",
    "gn:feature_code":"PPL",
    "gn:name":"Kwa-Dunjane",
    "gn:population":0,
    "gn:timezone":"Africa/Johannesburg",
    "iso:country":"ZA",
    "wof:name":"Kwa-Dunjane",
    "wof:placetype":"locality"
},
  "geometry": {"coordinates":[28.79957000000001,-31.07767],"type":"Point"}
}