{
  "type": "Feature",
  "properties": {
    "gn:country":"ZA",
    "gn:fcode":"PPL",
    "gn:population":0,
    "iso:country":"ZA",
    "name:afr_x_preferred":[
        "Sedgefield"
    ],
    "name:ast_x_preferred":[
        "Sedgefield"
    ],
    "name:eng_x_preferred":[
        "Sedgefield"
    ],
    "name:hye_x_preferred":[
        "\u054d\u0565\u057b\u0586\u056b\u056c\u0564"
    ],
    "name:ita_x_preferred":[
        "Sedgefield"
    ],
    "name:jpn_x_preferred":[
        "\u30bb\u30c3\u30b8\u30d5\u30a3\u30fc\u30eb\u30c9"
    ],
    "name:nld_x_preferred":[
        "Segdefield"
    ],
    "name:nld_x_variant":[
        "Sedgefield"
    ],
    "name:nob_x_preferred":[
        "Sedgefield"
    ],
    "name:nso_x_preferred":[
        "Sedgefield"
    ],
    "name:pol_x_preferred":[
        "Sedgefield"
    ],
    "name:ron_x_preferred":[
        "Sedgefield"
    ],
    "name:ukr_x_preferred":[
        "\u041c\u0435\u0435\u0434\u0456\u043d\u0491\u0441\u0440\u0456\u0434\u0435"
    ],
    "name:urd_x_preferred":[
        "\u0633\u06cc\u062c \u0641\u06cc\u0644\u0688"
    ],
    "name:vol_x_preferred":[
        "Sedgefield"
    ],
    "name:zul_x_preferred":[
        "ISedgefield"
    ],
    "qs_pg:aaroncc":"ZA",
    "qs_pg:gn_country":"ZA",
    "qs_pg:gn_fcode":"PPL",
    "qs_pg:gn_pop":0,
    "qs_pg:name":"Sedgefield",
    "qs_pg:name_adm0":"South Africa",
    "qs_pg:name_adm1":"Western Cape",
    "qs_pg:photos":89,
    "qs_pg:photos_1k":18,
    "qs_pg:photos_9k":1,
    "qs_pg:photos_9r":3,
    "qs_pg:photos_all":89,
    "qs_pg:photos_sr":3,
    "qs_pg:pop_sr":0,
    "qs_pg:qs_pg_placetype":"locality",
    "qs_pg:qs_pg_placetype_gp":"Town",
    "qs_pg:woe_adm0":23424942,
    "woe:adm0_id":23424942,
    "woe:name_adm0":"South Africa",
    "woe:name_adm1":"Western Cape",
    "woe:placetype":"Town",
    "wof:lang_x_official":[
        "eng"
    ],
    "wof:lang_x_spoken":[
        "eng",
        "zul",
        "xho",
        "afr",
        "nso",
        "tsn",
        "sot",
        "tso",
        "ssw",
        "ven",
        "nbl"
    ],
    "wof:name":"Sedgefield",
    "wof:placetype":"locality"
},
  "geometry": {"coordinates":[22.8055,-34.0211],"type":"Point"}
}