{
  "type": "Feature",
  "properties": {
    "gn:admin1_code":"5",
    "gn:admin2_code":"DC14",
    "gn:admin3_code":"EC142",
    "gn:asciiname":"Blikana",
    "gn:country_code":"ZA",
    "gn:dem":1566,
    "gn:feature_class":"P",
    "gn:feature_code":"PPL",
    "gn:name":"Blikana",
    "gn:population":0,
    "gn:timezone":"Africa/Johannesburg",
    "iso:country":"ZA",
    "wof:name":"Blikana",
    "wof:placetype":"locality"
},
  "geometry": {"coordinates":[27.61667000000001,-30.56667],"type":"Point"}
}