{
  "type": "Feature",
  "properties": {
    "gn:admin1_code":"5.0",
    "gn:admin2_code":"DC12",
    "gn:admin3_code":"EC121",
    "gn:asciiname":"Talemofu",
    "gn:country_code":"ZA",
    "gn:dem":347,
    "gn:feature_class":"P",
    "gn:feature_code":"PPL",
    "gn:name":"Talemofu",
    "gn:population":0,
    "gn:timezone":"Africa/Johannesburg",
    "iso:country":"ZA",
    "wof:name":"Talemofu",
    "wof:placetype":"locality"
},
  "geometry": {"coordinates":[29.01534,-32.0157],"type":"Point"}
}