{
  "type": "Feature",
  "properties": {
    "gn:admin1_code":"2",
    "gn:admin2_code":"DC23",
    "gn:admin3_code":"KZN233",
    "gn:asciiname":"Fitty Park",
    "gn:country_code":"ZA",
    "gn:dem":1034,
    "gn:feature_class":"P",
    "gn:feature_code":"PPL",
    "gn:name":"Fitty Park",
    "gn:population":0,
    "gn:timezone":"Africa/Johannesburg",
    "iso:country":"ZA",
    "wof:name":"Fitty Park",
    "wof:placetype":"locality"
},
  "geometry": {"coordinates":[30.06561,-28.57196],"type":"Point"}
}