{
  "type": "Feature",
  "properties": {
    "gn:admin1_code":"5",
    "gn:admin2_code":"DC15",
    "gn:admin3_code":"EC153",
    "gn:asciiname":"Kwa-Magcude",
    "gn:country_code":"ZA",
    "gn:dem":918,
    "gn:feature_class":"P",
    "gn:feature_code":"PPL",
    "gn:name":"Kwa-Magcude",
    "gn:population":0,
    "gn:timezone":"Africa/Johannesburg",
    "iso:country":"ZA",
    "wof:name":"Kwa-Magcude",
    "wof:placetype":"locality"
},
  "geometry": {"coordinates":[29.33748,-31.25818],"type":"Point"}
}