{
  "type": "Feature",
  "properties": {
    "gn:admin1_code":"11.0",
    "gn:admin2_code":"DC3",
    "gn:admin3_code":"WC032",
    "gn:asciiname":"Kleinbaai",
    "gn:country_code":"ZA",
    "gn:dem":23,
    "gn:feature_class":"P",
    "gn:feature_code":"PPL",
    "gn:name":"Kleinbaai",
    "gn:population":0,
    "gn:timezone":"Africa/Johannesburg",
    "iso:country":"ZA",
    "wof:name":"Kleinbaai",
    "wof:placetype":"locality"
},
  "geometry": {"coordinates":[19.35065,-34.61561],"type":"Point"}
}