{
  "type": "Feature",
  "properties": {
    "gn:admin1_code":"5",
    "gn:admin2_code":"DC13",
    "gn:admin3_code":"EC138",
    "gn:asciiname":"Kerrera",
    "gn:country_code":"ZA",
    "gn:dem":1343,
    "gn:feature_class":"P",
    "gn:feature_code":"PPL",
    "gn:name":"Kerrera",
    "gn:population":0,
    "gn:timezone":"Africa/Johannesburg",
    "iso:country":"ZA",
    "name:bre_x_preferred":[
        "Cearrara"
    ],
    "name:cat_x_preferred":[
        "Kerrera"
    ],
    "name:ceb_x_preferred":[
        "Kerrera"
    ],
    "name:deu_x_preferred":[
        "Kerrera"
    ],
    "name:ell_x_preferred":[
        "\u039a\u03ad\u03c1\u03c1\u03b5\u03c1\u03b1"
    ],
    "name:fra_x_preferred":[
        "Kerrera"
    ],
    "name:gla_x_preferred":[
        "Cearrara"
    ],
    "name:gle_x_preferred":[
        "Cearrara"
    ],
    "name:hun_x_preferred":[
        "Kerrera"
    ],
    "name:ita_x_preferred":[
        "Kerrera"
    ],
    "name:nds_x_preferred":[
        "Kerrera"
    ],
    "name:nno_x_preferred":[
        "Kerrera"
    ],
    "name:nor_x_preferred":[
        "Kerrera"
    ],
    "name:rus_x_preferred":[
        "\u041a\u0435\u0440\u0440\u0435\u0440\u0430"
    ],
    "name:spa_x_preferred":[
        "Kerrera"
    ],
    "name:swe_x_preferred":[
        "Kerrera"
    ],
    "name:zho_x_preferred":[
        "\u51f1\u52d2\u62c9\u5cf6"
    ],
    "wof:name":"Kerrera",
    "wof:placetype":"locality"
},
  "geometry": {"coordinates":[27.59867,-31.34463],"type":"Point"}
}