{
  "type": "Feature",
  "properties": {
    "gn:country":"ZA",
    "gn:fcode":"ADM3",
    "gn:population":243242,
    "iso:country":"ZA",
    "name:afr_x_preferred":[
        "Umzimkhulu"
    ],
    "name:deu_x_preferred":[
        "Umzimkhulu"
    ],
    "name:est_x_preferred":[
        "Umzimkhulu"
    ],
    "name:nso_x_preferred":[
        "Umzimkhulu"
    ],
    "name:ron_x_preferred":[
        "Umzimkulu"
    ],
    "name:zho_x_preferred":[
        "\u70cf\u59c6\u6fdf\u59c6\u5eab\u76e7"
    ],
    "qs_pg:aaroncc":"ZA",
    "qs_pg:gn_country":"ZA",
    "qs_pg:gn_fcode":"ADM3",
    "qs_pg:gn_pop":243242,
    "qs_pg:name":"Umzimkhulu",
    "qs_pg:photos_9r":0,
    "qs_pg:photos_sr":0,
    "qs_pg:pop_sr":10,
    "qs_pg:qs_pg_placetype":"localadmin",
    "wof:lang_x_official":[
        "eng"
    ],
    "wof:lang_x_spoken":[
        "eng",
        "zul",
        "xho",
        "afr",
        "nso",
        "tsn",
        "sot",
        "tso",
        "ssw",
        "ven",
        "nbl"
    ],
    "wof:name":"Umzimkhulu",
    "wof:placetype":"localadmin",
    "wof:population":243242
},
  "geometry": {"coordinates":[29.73771,-30.29165],"type":"Point"}
}