{
  "type": "Feature",
  "properties": {
    "gn:gn_country":"ZA",
    "gn:gn_fcode":"PPL",
    "gn:gn_pop":68284,
    "gn:population":68284,
    "iso:country":"ZA",
    "name:afr_x_preferred":[
        "Saldanha"
    ],
    "name:ara_x_preferred":[
        "\u0633\u0627\u0644\u062f\u0627\u0646\u0647\u0627"
    ],
    "name:deu_x_preferred":[
        "Saldanha"
    ],
    "name:eng_x_preferred":[
        "Saldanha"
    ],
    "name:fra_x_preferred":[
        "Saldanha"
    ],
    "name:jpn_x_preferred":[
        "\u30b5\u30eb\u30c0\u30cb\u30e3\u30fb\u30d9\u30a4"
    ],
    "name:lat_x_preferred":[
        "Saldanha"
    ],
    "name:nld_x_preferred":[
        "Saldanha"
    ],
    "name:nso_x_preferred":[
        "Saldanha"
    ],
    "name:por_x_preferred":[
        "Saldanha"
    ],
    "name:ron_x_preferred":[
        "Saldanha"
    ],
    "name:rus_x_preferred":[
        "\u0421\u0430\u043b\u0434\u0430\u043d\u0430"
    ],
    "name:unk_x_variant":[
        "Hoedjesbaai"
    ],
    "qs_pg:aaroncc":"ZA",
    "qs_pg:gn_country":"ZA",
    "qs_pg:gn_fcode":"PPL",
    "qs_pg:gn_pop":68284,
    "qs_pg:name":"Saldanha",
    "qs_pg:name_adm0":"South Africa",
    "qs_pg:name_adm1":"Western Cape",
    "qs_pg:photos":48,
    "qs_pg:photos_1k":10,
    "qs_pg:photos_9k":1,
    "qs_pg:photos_9r":3,
    "qs_pg:photos_all":84,
    "qs_pg:photos_sr":2,
    "qs_pg:pop_sr":8,
    "qs_pg:qs_pg_placetype":"locality",
    "qs_pg:qs_pg_placetype_gp":"Town",
    "qs_pg:woe_adm0":23424942,
    "woe:adm0_id":23424942,
    "woe:name_adm0":"South Africa",
    "woe:name_adm1":"Western Cape",
    "woe:placetype":"Town",
    "wof:name":"Saldanha",
    "wof:placetype":"locality",
    "wof:population":68284
},
  "geometry": {"coordinates":[17.9442,-33.01167],"type":"Point"}
}