{
  "type": "Feature",
  "properties": {
    "gn:admin1_code":"6.0",
    "gn:admin2_code":"TSH",
    "gn:admin3_code":"TSH",
    "gn:asciiname":"Newlands",
    "gn:country_code":"ZA",
    "gn:dem":1459,
    "gn:feature_class":"P",
    "gn:feature_code":"PPL",
    "gn:name":"Newlands",
    "gn:population":0,
    "gn:timezone":"Africa/Johannesburg",
    "iso:country":"ZA",
    "name:bar_x_preferred":[
        "Newlands"
    ],
    "name:ceb_x_preferred":[
        "Newlands"
    ],
    "name:deu_x_preferred":[
        "Newlands"
    ],
    "name:fra_x_preferred":[
        "Newlands"
    ],
    "name:pol_x_preferred":[
        "Newlands"
    ],
    "name:rus_x_preferred":[
        "\u041d\u044c\u044e\u043b\u0435\u043d\u0434\u0441"
    ],
    "name:ukr_x_preferred":[
        "\u041d\u044c\u044e\u043b\u0435\u043d\u0434\u0441"
    ],
    "wof:lang_x_official":[
        "eng"
    ],
    "wof:lang_x_spoken":[
        "eng",
        "zul",
        "xho",
        "afr",
        "nso",
        "tsn",
        "sot",
        "tso",
        "ssw",
        "ven",
        "nbl"
    ],
    "wof:name":"Newlands",
    "wof:placetype":"locality"
},
  "geometry": {"coordinates":[28.26215,-25.79076],"type":"Point"}
}