{
  "type": "Feature",
  "properties": {
    "gn:admin1_code":"3",
    "gn:asciiname":"Orangia",
    "gn:country_code":"ZA",
    "gn:dem":1296,
    "gn:feature_class":"P",
    "gn:feature_code":"PPL",
    "gn:name":"Orangia",
    "gn:population":0,
    "gn:timezone":"Africa/Johannesburg",
    "iso:country":"ZA",
    "name:por_x_preferred":[
        "Orangia"
    ],
    "wof:name":"Orangia",
    "wof:placetype":"locality"
},
  "geometry": {"coordinates":[26.81667,-26.93333],"type":"Point"}
}