{
  "type": "Feature",
  "properties": {
    "gn:admin1_code":"3.0",
    "gn:admin2_code":"DC19",
    "gn:admin3_code":"FS196",
    "gn:asciiname":"The Willows",
    "gn:country_code":"ZA",
    "gn:dem":1481,
    "gn:feature_class":"P",
    "gn:feature_code":"PPL",
    "gn:name":"The Willows",
    "gn:population":0,
    "gn:timezone":"Africa/Johannesburg",
    "iso:country":"ZA",
    "name:ceb_x_preferred":[
        "The Willows"
    ],
    "name:deu_x_preferred":[
        "The Willows"
    ],
    "wof:name":"The Willows",
    "wof:placetype":"locality"
},
  "geometry": {"coordinates":[27.10726,-29.53551],"type":"Point"}
}