{
  "type": "Feature",
  "properties": {
    "gn:admin1_code":"5",
    "gn:admin2_code":"DC44",
    "gn:admin3_code":"EC443",
    "gn:asciiname":"Ndunge",
    "gn:country_code":"ZA",
    "gn:dem":818,
    "gn:feature_class":"P",
    "gn:feature_code":"PPL",
    "gn:name":"Ndunge",
    "gn:population":0,
    "gn:timezone":"Africa/Johannesburg",
    "iso:country":"ZA",
    "name:und_x_variant":[
        "Ndunges",
        "Ndunge"
    ],
    "wof:name":"Ndunge",
    "wof:placetype":"locality"
},
  "geometry": {"coordinates":[29.86789000000001,-30.82899],"type":"Point"}
}