{
  "type": "Feature",
  "properties": {
    "gn:admin1_code":"6",
    "gn:admin2_code":"DC42",
    "gn:admin3_code":"GT422",
    "gn:asciiname":"Balmoral",
    "gn:country_code":"ZA",
    "gn:dem":1538,
    "gn:feature_class":"P",
    "gn:feature_code":"PPL",
    "gn:name":"Balmoral",
    "gn:population":0,
    "gn:timezone":"Africa/Johannesburg",
    "iso:country":"ZA",
    "name:ceb_x_preferred":[
        "Balmoral"
    ],
    "name:deu_x_preferred":[
        "Balmoral"
    ],
    "name:fra_x_preferred":[
        "Balmoral"
    ],
    "name:ita_x_preferred":[
        "Balmoral"
    ],
    "name:mlg_x_preferred":[
        "Balmoral"
    ],
    "name:nds_x_preferred":[
        "Balmoral"
    ],
    "name:rus_x_preferred":[
        "\u0411\u0430\u043b\u043c\u043e\u0440\u0430\u043b"
    ],
    "name:swe_x_preferred":[
        "Balmoral"
    ],
    "wof:name":"Balmoral",
    "wof:placetype":"locality"
},
  "geometry": {"coordinates":[27.92467000000001,-26.50621],"type":"Point"}
}