{
  "type": "Feature",
  "properties": {
    "iso:country":"ZA",
    "name:eng_x_preferred":[
        "Amandelboom"
    ],
    "qs:gn_local":0,
    "qs:local_max":59,
    "qs:local_sum":59,
    "qs:localhoods":1,
    "qs:name":"Amandelboom",
    "qs:name_adm0":"South Africa",
    "qs:name_adm1":"Northern Cape",
    "qs:name_adm2":"Namakwa",
    "qs:name_lau":"Karoo Hoogland",
    "qs:name_local":"Williston",
    "qs:photo_max":34,
    "qs:photo_sum":59,
    "qs:placetype":"Suburb",
    "qs:quad_count":4,
    "qs:woe_adm0":23424942,
    "qs:woe_adm1":2346985,
    "qs:woe_adm2":56189407,
    "qs:woe_lau":56189550,
    "qs:woe_local":1588909,
    "qs:woe_ver":"7.10.0",
    "wof:lang":[
        "eng"
    ],
    "wof:name":"Amandelboom",
    "wof:placetype":"neighbourhood"
},
  "geometry": {"coordinates":[20.91741,-31.342506],"type":"Point"}
}