{
  "type": "Feature",
  "properties": {
    "gn:admin1_code":"8.0",
    "gn:admin2_code":"DC8",
    "gn:admin3_code":"NC085",
    "gn:asciiname":"Swartkoppies",
    "gn:country_code":"ZA",
    "gn:dem":1212,
    "gn:feature_class":"P",
    "gn:feature_code":"PPL",
    "gn:name":"Swartkoppies",
    "gn:population":0,
    "gn:timezone":"Africa/Johannesburg",
    "iso:country":"ZA",
    "wof:name":"Swartkoppies",
    "wof:placetype":"locality"
},
  "geometry": {"coordinates":[22.96667,-28.45],"type":"Point"}
}