{
  "type": "Feature",
  "properties": {
    "gn:admin1_code":"2",
    "gn:admin2_code":"DC22",
    "gn:admin3_code":"KZN222",
    "gn:asciiname":"Ashley",
    "gn:country_code":"ZA",
    "gn:dem":1103,
    "gn:feature_class":"P",
    "gn:feature_code":"PPL",
    "gn:name":"Ashley",
    "gn:population":0,
    "gn:timezone":"Africa/Johannesburg",
    "iso:country":"ZA",
    "name:ast_x_preferred":[
        "Ashley"
    ],
    "name:bel_x_preferred":[
        "\u042d\u0448\u043b\u0456"
    ],
    "name:bre_x_preferred":[
        "Ashley"
    ],
    "name:bul_x_preferred":[
        "\u0410\u0448\u043b\u0438"
    ],
    "name:cat_x_preferred":[
        "Ashley"
    ],
    "name:ceb_x_preferred":[
        "Ashley"
    ],
    "name:ces_x_preferred":[
        "Ashley"
    ],
    "name:deu_x_preferred":[
        "Ashley"
    ],
    "name:fin_x_preferred":[
        "Ashley"
    ],
    "name:fra_x_preferred":[
        "Ashley"
    ],
    "name:ita_x_preferred":[
        "Ashley"
    ],
    "name:jpn_x_preferred":[
        "\u30a2\u30b7\u30e5\u30ea\u30fc"
    ],
    "name:kor_x_preferred":[
        "\uc560\uc290\ub9ac"
    ],
    "name:nld_x_preferred":[
        "Ashley"
    ],
    "name:pol_x_preferred":[
        "Ashley"
    ],
    "name:por_x_preferred":[
        "Ashley"
    ],
    "name:rus_x_preferred":[
        "\u042d\u0448\u043b\u0438"
    ],
    "name:spa_x_preferred":[
        "Ashley"
    ],
    "name:srp_x_preferred":[
        "\u0415\u0448\u043b\u0438"
    ],
    "name:swe_x_preferred":[
        "Ashley"
    ],
    "name:ukr_x_preferred":[
        "\u0415\u0448\u043b\u0456"
    ],
    "name:vie_x_preferred":[
        "Ashley"
    ],
    "name:vol_x_preferred":[
        "Ashley"
    ],
    "wof:name":"Ashley",
    "wof:placetype":"locality"
},
  "geometry": {"coordinates":[30.11255,-29.55063],"type":"Point"}
}