{
  "type": "Feature",
  "properties": {
    "gn:admin1_code":"5",
    "gn:admin2_code":"DC12",
    "gn:admin3_code":"EC122",
    "gn:asciiname":"Centuli",
    "gn:country_code":"ZA",
    "gn:dem":409,
    "gn:feature_class":"P",
    "gn:feature_code":"PPL",
    "gn:name":"Centuli",
    "gn:population":0,
    "gn:timezone":"Africa/Johannesburg",
    "iso:country":"ZA",
    "name:und_x_variant":[
        "Centuti",
        "Centuli"
    ],
    "wof:name":"Centuli",
    "wof:placetype":"locality"
},
  "geometry": {"coordinates":[28.35402,-32.42746],"type":"Point"}
}