{
  "type": "Feature",
  "properties": {
    "gn:admin1_code":"8",
    "gn:admin2_code":"DC8",
    "gn:admin3_code":"NC083",
    "gn:asciiname":"Kurrees",
    "gn:country_code":"ZA",
    "gn:dem":909,
    "gn:feature_class":"P",
    "gn:feature_code":"PPL",
    "gn:name":"Kurrees",
    "gn:population":0,
    "gn:timezone":"Africa/Johannesburg",
    "iso:country":"ZA",
    "name:und_x_variant":[
        "Kurees",
        "Kurrees"
    ],
    "wof:name":"Kurrees",
    "wof:placetype":"locality"
},
  "geometry": {"coordinates":[21.19214,-28.16345],"type":"Point"}
}