{
  "type": "Feature",
  "properties": {
    "gn:admin1_code":"11",
    "gn:admin2_code":"DC2",
    "gn:admin3_code":"WC022",
    "gn:asciiname":"Voorsorg",
    "gn:country_code":"ZA",
    "gn:dem":954,
    "gn:feature_class":"P",
    "gn:feature_code":"PPL",
    "gn:name":"Voorsorg",
    "gn:population":0,
    "gn:timezone":"Africa/Johannesburg",
    "iso:country":"ZA",
    "wof:name":"Voorsorg",
    "wof:placetype":"locality"
},
  "geometry": {"coordinates":[19.3025,-32.90618],"type":"Point"}
}