{
  "type": "Feature",
  "properties": {
    "gn:admin1_code":"8.0",
    "gn:admin2_code":"DC7",
    "gn:admin3_code":"NC074",
    "gn:asciiname":"Van Wyksvlei",
    "gn:country_code":"ZA",
    "gn:dem":962,
    "gn:feature_class":"P",
    "gn:feature_code":"PPL",
    "gn:name":"Van Wyksvlei",
    "gn:population":1721,
    "gn:timezone":"Africa/Johannesburg",
    "iso:country":"ZA",
    "wof:name":"Van Wyksvlei",
    "wof:placetype":"locality",
    "wof:population":1721
},
  "geometry": {"coordinates":[21.82498,-30.35101],"type":"Point"}
}