{
  "type": "Feature",
  "properties": {
    "gn:admin1_code":"8.0",
    "gn:admin2_code":"DC7",
    "gn:admin3_code":"NC074",
    "gn:asciiname":"Van Wyksvlei",
    "gn:country_code":"ZA",
    "gn:dem":962,
    "gn:feature_class":"P",
    "gn:feature_code":"PPL",
    "gn:name":"Van Wyksvlei",
    "gn:population":1721,
    "gn:timezone":"Africa/Johannesburg",
    "iso:country":"ZA",
    "name:afr_x_preferred":[
        "Van Wyksvlei"
    ],
    "name:ara_x_preferred":[
        "\u0641\u0627\u0646\u0648\u064a\u0643\u0633\u0641\u0644\u064a"
    ],
    "name:est_x_preferred":[
        "Van Wyksvlei"
    ],
    "name:fas_x_preferred":[
        "\u0648\u0646\u0648\u06cc\u06a9\u0633\u0648\u0644\u06cc"
    ],
    "name:nld_x_preferred":[
        "Van Wyksvlei"
    ],
    "name:nso_x_preferred":[
        "Vanwyksvlei"
    ],
    "name:ron_x_preferred":[
        "Van Wyksvlei"
    ],
    "wof:lang_x_official":[
        "eng"
    ],
    "wof:lang_x_spoken":[
        "eng",
        "zul",
        "xho",
        "afr",
        "nso",
        "tsn",
        "sot",
        "tso",
        "ssw",
        "ven",
        "nbl"
    ],
    "wof:name":"Van Wyksvlei",
    "wof:placetype":"locality",
    "wof:population":1721
},
  "geometry": {"coordinates":[21.82498,-30.35101],"type":"Point"}
}