{
  "type": "Feature",
  "properties": {
    "gn:admin1_code":"10",
    "gn:asciiname":"Ditlharepaneng",
    "gn:country_code":"ZA",
    "gn:dem":1408,
    "gn:feature_class":"P",
    "gn:feature_code":"PPL",
    "gn:name":"Ditlharepaneng",
    "gn:population":0,
    "gn:timezone":"Africa/Johannesburg",
    "iso:country":"ZA",
    "wof:name":"Ditlharepaneng",
    "wof:placetype":"locality"
},
  "geometry": {"coordinates":[23.65789,-27.42986],"type":"Point"}
}