{
  "type": "Feature",
  "properties": {
    "iso:country":"ZA",
    "name:afr_x_preferred":[
        "Melkbosstrand"
    ],
    "name:eng_x_preferred":[
        "Melkbosstrand"
    ],
    "name:fra_x_preferred":[
        "Melkbosstrand"
    ],
    "name:jpn_x_preferred":[
        "\u30e1\u30eb\u30af\u30dc\u30b9\u30b9\u30c8\u30e9\u30f3\u30c8"
    ],
    "name:nld_x_preferred":[
        "Melkbosstrand"
    ],
    "name:nso_x_preferred":[
        "Melkbosstrand"
    ],
    "name:ron_x_preferred":[
        "Melkbosstrand"
    ],
    "name:und_x_variant":[
        "Melkboschstrand"
    ],
    "name:zho_x_preferred":[
        "\u6885\u723e\u514b\u535a\u65af\u7279\u862d"
    ],
    "qs:a0":"South Africa",
    "qs:a0_lc":"ZAF",
    "qs:a1":"*",
    "qs:a1r":"*",
    "qs:adm0":"South Africa",
    "qs:la_lc":"*",
    "qs:level":"locality",
    "qs:loc":"Melkbosstrand",
    "qs:pop":0,
    "qs:type":"Built-Up Area",
    "wd:wordcount":1293,
    "wof:lang_x_official":[
        "eng"
    ],
    "wof:lang_x_spoken":[
        "eng",
        "zul",
        "xho",
        "afr",
        "nso",
        "tsn",
        "sot",
        "tso",
        "ssw",
        "ven",
        "nbl"
    ],
    "wof:name":"Melkbosstrand",
    "wof:placetype":"neighbourhood"
},
  "geometry": {"coordinates":[18.44682,-33.694381],"type":"Point"}
}