{
  "type": "Feature",
  "properties": {
    "gn:admin1_code":"5",
    "gn:admin2_code":"DC13",
    "gn:admin3_code":"EC136",
    "gn:asciiname":"Guba",
    "gn:country_code":"ZA",
    "gn:dem":1264,
    "gn:feature_class":"P",
    "gn:feature_code":"PPL",
    "gn:name":"Guba",
    "gn:population":0,
    "gn:timezone":"Africa/Johannesburg",
    "iso:country":"ZA",
    "name:aze_x_preferred":[
        "Quba"
    ],
    "name:ceb_x_preferred":[
        "Guba"
    ],
    "name:deu_x_preferred":[
        "Guba"
    ],
    "name:rus_x_preferred":[
        "\u0413\u0443\u0431\u0430"
    ],
    "name:sun_x_preferred":[
        "Guba"
    ],
    "name:swe_x_preferred":[
        "Guba"
    ],
    "name:tat_x_preferred":[
        "\u0413\u0443\u0431\u0430"
    ],
    "name:ukr_x_preferred":[
        "\u0413\u0443\u0431\u0430"
    ],
    "wof:name":"Guba",
    "wof:placetype":"locality"
},
  "geometry": {"coordinates":[27.36658,-31.5628],"type":"Point"}
}