{
  "type": "Feature",
  "properties": {
    "gn:admin1_code":"5",
    "gn:admin2_code":"DC13",
    "gn:admin3_code":"EC136",
    "gn:asciiname":"Guba",
    "gn:country_code":"ZA",
    "gn:dem":1264,
    "gn:feature_class":"P",
    "gn:feature_code":"PPL",
    "gn:name":"Guba",
    "gn:population":0,
    "gn:timezone":"Africa/Johannesburg",
    "iso:country":"ZA",
    "wof:name":"Guba",
    "wof:placetype":"locality"
},
  "geometry": {"coordinates":[27.36658,-31.5628],"type":"Point"}
}