{
  "type": "Feature",
  "properties": {
    "gn:admin1_code":"9",
    "gn:admin2_code":"DC35",
    "gn:admin3_code":"LIM352",
    "gn:asciiname":"Knobel",
    "gn:country_code":"ZA",
    "gn:dem":1180,
    "gn:feature_class":"P",
    "gn:feature_code":"PPL",
    "gn:name":"Knobel",
    "gn:population":0,
    "gn:timezone":"Africa/Johannesburg",
    "iso:country":"ZA",
    "name:deu_x_preferred":[
        "Knobel"
    ],
    "name:nld_x_preferred":[
        "Knobel"
    ],
    "name:rus_x_preferred":[
        "\u041a\u043d\u043e\u0431\u0435\u043b\u044c"
    ],
    "name:ukr_x_preferred":[
        "\u041a\u043d\u043e\u0431\u0435\u043b\u044c"
    ],
    "wof:lang_x_official":[
        "eng"
    ],
    "wof:lang_x_spoken":[
        "eng",
        "zul",
        "xho",
        "afr",
        "nso",
        "tsn",
        "sot",
        "tso",
        "ssw",
        "ven",
        "nbl"
    ],
    "wof:name":"Knobel",
    "wof:placetype":"locality"
},
  "geometry": {"coordinates":[29.12169,-23.63426],"type":"Point"}
}