{
  "type": "Feature",
  "properties": {
    "gn:admin1_code":"9",
    "gn:admin2_code":"DC35",
    "gn:admin3_code":"LIM352",
    "gn:asciiname":"Knobel",
    "gn:country_code":"ZA",
    "gn:dem":1180,
    "gn:feature_class":"P",
    "gn:feature_code":"PPL",
    "gn:name":"Knobel",
    "gn:population":0,
    "gn:timezone":"Africa/Johannesburg",
    "iso:country":"ZA",
    "wof:name":"Knobel",
    "wof:placetype":"locality"
},
  "geometry": {"coordinates":[29.12169,-23.63426],"type":"Point"}
}