{
  "type": "Feature",
  "properties": {
    "gn:admin1_code":"9",
    "gn:admin2_code":"DC35",
    "gn:admin3_code":"LIM354",
    "gn:asciiname":"Leshoane",
    "gn:cc2":"ZA",
    "gn:country_code":"ZA",
    "gn:dem":1392,
    "gn:feature_class":"P",
    "gn:feature_code":"PPL",
    "gn:name":"Leshoane",
    "gn:population":0,
    "gn:timezone":"Africa/Johannesburg",
    "iso:country":"ZA",
    "name:und_x_variant":[
        "Leshwane",
        "Leshoane"
    ],
    "wof:lang_x_official":[
        "eng"
    ],
    "wof:lang_x_spoken":[
        "eng",
        "zul",
        "xho",
        "afr",
        "nso",
        "tsn",
        "sot",
        "tso",
        "ssw",
        "ven",
        "nbl"
    ],
    "wof:name":"Leshoane",
    "wof:placetype":"locality"
},
  "geometry": {"coordinates":[29.81667,-23.85],"type":"Point"}
}