{
  "type": "Feature",
  "properties": {
    "gn:admin1_code":"5",
    "gn:admin2_code":"DC13",
    "gn:admin3_code":"EC133",
    "gn:asciiname":"Moreson",
    "gn:country_code":"ZA",
    "gn:dem":1780,
    "gn:feature_class":"P",
    "gn:feature_code":"PPL",
    "gn:name":"M\u00f4reson",
    "gn:population":0,
    "gn:timezone":"Africa/Johannesburg",
    "iso:country":"ZA",
    "wof:name":"Moreson",
    "wof:placetype":"locality"
},
  "geometry": {"coordinates":[26.59389,-31.35541],"type":"Point"}
}