{
  "type": "Feature",
  "properties": {
    "gn:admin1_code":"6.0",
    "gn:admin2_code":"EKU",
    "gn:admin3_code":"EKU",
    "gn:asciiname":"Brackenhurst",
    "gn:country_code":"ZA",
    "gn:dem":1595,
    "gn:feature_class":"P",
    "gn:feature_code":"PPL",
    "gn:name":"Brackenhurst",
    "gn:population":0,
    "gn:timezone":"Africa/Johannesburg",
    "iso:country":"ZA",
    "wof:name":"Brackenhurst",
    "wof:placetype":"locality"
},
  "geometry": {"coordinates":[28.104,-26.31900000000001],"type":"Point"}
}