{
  "type": "Feature",
  "properties": {
    "gn:admin1_code":"9",
    "gn:admin2_code":"DC35",
    "gn:admin3_code":"LIM351",
    "gn:asciiname":"Dithabaneng",
    "gn:country_code":"ZA",
    "gn:dem":1061,
    "gn:feature_class":"P",
    "gn:feature_code":"PPL",
    "gn:name":"Dithabaneng",
    "gn:population":0,
    "gn:timezone":"Africa/Johannesburg",
    "iso:country":"ZA",
    "wof:name":"Dithabaneng",
    "wof:placetype":"locality"
},
  "geometry": {"coordinates":[28.91667,-23.13333],"type":"Point"}
}