{
  "type": "Feature",
  "properties": {
    "gn:admin1_code":"5",
    "gn:admin2_code":"DC15",
    "gn:admin3_code":"EC153",
    "gn:asciiname":"Cutweni",
    "gn:country_code":"ZA",
    "gn:dem":273,
    "gn:feature_class":"P",
    "gn:feature_code":"PPL",
    "gn:name":"Cutweni",
    "gn:population":0,
    "gn:timezone":"Africa/Johannesburg",
    "iso:country":"ZA",
    "name:und_x_variant":[
        "Cutini",
        "Cutweni"
    ],
    "wof:name":"Cutweni",
    "wof:placetype":"locality"
},
  "geometry": {"coordinates":[29.75518,-31.41007],"type":"Point"}
}