{
  "type": "Feature",
  "properties": {
    "gn:admin1_code":"2.0",
    "gn:admin2_code":"DC24",
    "gn:admin3_code":"KZN245",
    "gn:asciiname":"Umvoti Location",
    "gn:cc2":"ZA",
    "gn:country_code":"ZA",
    "gn:dem":503,
    "gn:feature_class":"P",
    "gn:feature_code":"PPLL",
    "gn:name":"Umvoti Location",
    "gn:population":0,
    "gn:timezone":"Africa/Johannesburg",
    "iso:country":"ZA",
    "name:und_x_variant":[
        "Mvoti Location",
        "Umvoti Location"
    ],
    "wof:name":"Umvoti Location",
    "wof:placetype":"locality"
},
  "geometry": {"coordinates":[30.91667,-29.25],"type":"Point"}
}