{
  "type": "Feature",
  "properties": {
    "gn:gn_country":"ZA",
    "gn:gn_fcode":"PPL",
    "gn:gn_pop":0,
    "iso:country":"ZA",
    "name:afr_x_preferred":[
        "Brenton-on-Sea"
    ],
    "name:dut_x_preferred":[
        "Brenton-on-Sea"
    ],
    "name:eng_x_preferred":[
        "Brenton-on-Sea"
    ],
    "name:nso_x_preferred":[
        "Brenton-on-Sea"
    ],
    "name:ukr_x_preferred":[
        "\u0411\u0440\u0435\u043d\u0442\u043e\u043d-\u043e\u043d-\u0421\u0456"
    ],
    "qs_pg:aaroncc":"ZA",
    "qs_pg:gn_country":"ZA",
    "qs_pg:gn_fcode":"PPL",
    "qs_pg:gn_pop":0,
    "qs_pg:name":"Brenton-on-Sea",
    "qs_pg:name_adm0":"South Africa",
    "qs_pg:name_adm1":"Western Cape",
    "qs_pg:photos":66,
    "qs_pg:photos_1k":13,
    "qs_pg:photos_9k":1,
    "qs_pg:photos_9r":2,
    "qs_pg:photos_all":66,
    "qs_pg:photos_sr":2,
    "qs_pg:pop_sr":0,
    "qs_pg:qs_pg_placetype":"locality",
    "qs_pg:qs_pg_placetype_gp":"Town",
    "qs_pg:woe_adm0":23424942,
    "woe:adm0_id":23424942,
    "woe:name_adm0":"South Africa",
    "woe:name_adm1":"Western Cape",
    "woe:placetype":"Town",
    "wof:name":"Brenton-on-Sea",
    "wof:placetype":"locality"
},
  "geometry": {"coordinates":[23.02726,-34.0725],"type":"Point"}
}