{
  "type": "Feature",
  "properties": {
    "gn:admin1_code":"5.0",
    "gn:admin2_code":"DC14",
    "gn:admin3_code":"EC144",
    "gn:asciiname":"Rosendal",
    "gn:country_code":"ZA",
    "gn:dem":1562,
    "gn:feature_class":"P",
    "gn:feature_code":"PPL",
    "gn:name":"Rosendal",
    "gn:population":0,
    "gn:timezone":"Africa/Johannesburg",
    "iso:country":"ZA",
    "name:ceb_x_preferred":[
        "Rosendal"
    ],
    "name:dan_x_preferred":[
        "Rosendal"
    ],
    "name:deu_x_preferred":[
        "Rosendal"
    ],
    "name:est_x_preferred":[
        "Rosendal"
    ],
    "name:nor_x_preferred":[
        "Rosendal"
    ],
    "name:pol_x_preferred":[
        "Rosendal"
    ],
    "name:swe_x_preferred":[
        "Rosendal"
    ],
    "wof:name":"Rosendal",
    "wof:placetype":"locality"
},
  "geometry": {"coordinates":[26.20871,-30.91911],"type":"Point"}
}