{
  "type": "Feature",
  "properties": {
    "iso:country":"ZA",
    "name:afr_x_preferred":[
        "Williston"
    ],
    "name:deu_x_preferred":[
        "Williston"
    ],
    "name:eng_x_preferred":[
        "Williston"
    ],
    "name:ita_x_preferred":[
        "Williston"
    ],
    "name:nld_x_preferred":[
        "Williston"
    ],
    "name:ron_x_preferred":[
        "Williston"
    ],
    "name:rus_x_preferred":[
        "\u0423\u0438\u043b\u043b\u0438\u0441\u0442\u043e\u043d"
    ],
    "name:zho_x_preferred":[
        "\u5a01\u5229\u65af\u9813"
    ],
    "qs_pg:aaroncc":"ZA",
    "qs_pg:name":"Williston",
    "qs_pg:name_adm0":"South Africa",
    "qs_pg:name_adm1":"Northern Cape",
    "qs_pg:photos":5,
    "qs_pg:photos_1k":1,
    "qs_pg:photos_9k":1,
    "qs_pg:photos_9r":2,
    "qs_pg:photos_all":63,
    "qs_pg:photos_sr":1,
    "qs_pg:pop_sr":0,
    "qs_pg:qs_pg_placetype":"locality",
    "qs_pg:qs_pg_placetype_gp":"Town",
    "qs_pg:woe_adm0":23424942,
    "woe:adm0_id":23424942,
    "woe:name_adm0":"South Africa",
    "woe:name_adm1":"Northern Cape",
    "woe:placetype":"Town",
    "wof:name":"Williston",
    "wof:placetype":"locality"
},
  "geometry": {"coordinates":[20.917968,-31.34045],"type":"Point"}
}