{
  "type": "Feature",
  "properties": {
    "gn:admin1_code":"9",
    "gn:admin2_code":"DC34",
    "gn:admin3_code":"LIM344",
    "gn:asciiname":"Ratombo",
    "gn:cc2":"ZA",
    "gn:country_code":"ZA",
    "gn:dem":835,
    "gn:feature_class":"P",
    "gn:feature_code":"PPL",
    "gn:name":"Ratombo",
    "gn:population":0,
    "gn:timezone":"Africa/Johannesburg",
    "iso:country":"ZA",
    "name:und_x_variant":[
        "Ratomba"
    ],
    "wof:name":"Ratombo",
    "wof:placetype":"locality"
},
  "geometry": {"coordinates":[30.16537000000001,-23.05928],"type":"Point"}
}