{
  "type": "Feature",
  "properties": {
    "gn:gn_country":"ZA",
    "gn:gn_fcode":"PPL",
    "gn:gn_pop":0,
    "iso:country":"ZA",
    "name:afr_x_preferred":[
        "Hondeklipbaai"
    ],
    "name:bul_x_preferred":[
        "\u0425\u043e\u043d\u0434\u0435\u043a\u043b\u0438\u043f\u0431\u0430\u0438"
    ],
    "name:ceb_x_preferred":[
        "Hondeklipbaai"
    ],
    "name:eng_x_preferred":[
        "Hondeklip Bay"
    ],
    "name:est_x_preferred":[
        "Hondeklipbaai"
    ],
    "name:fra_x_preferred":[
        "Hondeklipbaai"
    ],
    "name:nld_x_preferred":[
        "Hondeklipbaai"
    ],
    "name:nso_x_preferred":[
        "Hondeklipbaai"
    ],
    "name:ron_x_preferred":[
        "Hondeklipbaai"
    ],
    "name:unk_x_variant":[
        "Hondeklip Bay"
    ],
    "qs_pg:aaroncc":"ZA",
    "qs_pg:gn_country":"ZA",
    "qs_pg:gn_fcode":"PPL",
    "qs_pg:gn_pop":0,
    "qs_pg:name":"Hondeklipbaai",
    "qs_pg:name_adm0":"South Africa",
    "qs_pg:name_adm1":"Northern Cape",
    "qs_pg:photos":48,
    "qs_pg:photos_1k":10,
    "qs_pg:photos_9k":1,
    "qs_pg:photos_9r":2,
    "qs_pg:photos_all":48,
    "qs_pg:photos_sr":2,
    "qs_pg:pop_sr":5,
    "qs_pg:qs_pg_placetype":"locality",
    "qs_pg:qs_pg_placetype_gp":"Town",
    "qs_pg:woe_adm0":23424942,
    "woe:adm0_id":23424942,
    "woe:name_adm0":"South Africa",
    "woe:name_adm1":"Northern Cape",
    "woe:placetype":"Town",
    "wof:name":"Hondeklipbaai",
    "wof:placetype":"locality"
},
  "geometry": {"coordinates":[17.27733,-30.31774],"type":"Point"}
}