{
  "type": "Feature",
  "properties": {
    "gn:admin1_code":"7",
    "gn:admin2_code":"DC30",
    "gn:admin3_code":"MP307",
    "gn:asciiname":"Rolyna Estates",
    "gn:country_code":"ZA",
    "gn:dem":1591,
    "gn:feature_class":"P",
    "gn:feature_code":"PPL",
    "gn:name":"Rolyna Estates",
    "gn:population":0,
    "gn:timezone":"Africa/Johannesburg",
    "iso:country":"ZA",
    "wof:name":"Rolyna Estates",
    "wof:placetype":"locality"
},
  "geometry": {"coordinates":[28.92417,-26.27222],"type":"Point"}
}