{
  "type": "Feature",
  "properties": {
    "gn:admin1_code":"3",
    "gn:admin2_code":"DC16",
    "gn:admin3_code":"FS162",
    "gn:asciiname":"Brakfontein",
    "gn:country_code":"ZA",
    "gn:dem":1382,
    "gn:feature_class":"P",
    "gn:feature_code":"PPL",
    "gn:name":"Brakfontein",
    "gn:population":0,
    "gn:timezone":"Africa/Johannesburg",
    "iso:country":"ZA",
    "name:afr_x_preferred":[
        "Brakfontein"
    ],
    "name:est_x_preferred":[
        "Brakfontein"
    ],
    "name:nso_x_preferred":[
        "Brakfontein"
    ],
    "wof:name":"Brakfontein",
    "wof:placetype":"locality"
},
  "geometry": {"coordinates":[26.13525,-29.80104],"type":"Point"}
}