{
  "type": "Feature",
  "properties": {
    "gn:admin1_code":"11",
    "gn:admin2_code":"DC1",
    "gn:admin3_code":"WC011",
    "gn:asciiname":"Tahiti",
    "gn:country_code":"ZA",
    "gn:dem":18,
    "gn:feature_class":"P",
    "gn:feature_code":"PPL",
    "gn:name":"Tahiti",
    "gn:population":0,
    "gn:timezone":"Africa/Johannesburg",
    "iso:country":"ZA",
    "name:und_x_variant":[
        "Voorbeeld Nedersetting",
        "Tahiti"
    ],
    "wof:name":"Tahiti",
    "wof:placetype":"locality"
},
  "geometry": {"coordinates":[18.24398,-31.53758],"type":"Point"}
}