{
  "type": "Feature",
  "properties": {
    "gn:admin1_code":"9",
    "gn:admin2_code":"DC35",
    "gn:admin3_code":"LIM353",
    "gn:asciiname":"Mission",
    "gn:country_code":"ZA",
    "gn:dem":1071,
    "gn:feature_class":"P",
    "gn:feature_code":"PPL",
    "gn:name":"Mission",
    "gn:population":0,
    "gn:timezone":"Africa/Johannesburg",
    "iso:country":"ZA",
    "wof:name":"Mission",
    "wof:placetype":"locality"
},
  "geometry": {"coordinates":[29.37512000000001,-23.48446],"type":"Point"}
}