{
  "type": "Feature",
  "properties": {
    "gn:admin1_code":"10",
    "gn:admin2_code":"DC38",
    "gn:admin3_code":"NW382",
    "gn:asciiname":"Mokgalwane",
    "gn:country_code":"ZA",
    "gn:dem":1393,
    "gn:feature_class":"P",
    "gn:feature_code":"PPL",
    "gn:name":"Mokgalwane",
    "gn:population":0,
    "gn:timezone":"Africa/Johannesburg",
    "iso:country":"ZA",
    "wof:name":"Mokgalwane",
    "wof:placetype":"locality"
},
  "geometry": {"coordinates":[25.45639,-26.47325],"type":"Point"}
}