{
  "type": "Feature",
  "properties": {
    "gn:admin1_code":"11.0",
    "gn:admin2_code":"DC2",
    "gn:admin3_code":"WC022",
    "gn:asciiname":"Prince Alfred Hamlet",
    "gn:country_code":"ZA",
    "gn:dem":500,
    "gn:feature_class":"P",
    "gn:feature_code":"PPL",
    "gn:name":"Prince Alfred Hamlet",
    "gn:population":0,
    "gn:timezone":"Africa/Johannesburg",
    "iso:country":"ZA",
    "name:afr_x_preferred":[
        "Prince Alfred Hamlet"
    ],
    "name:est_x_preferred":[
        "Prince Alfred Hamlet"
    ],
    "name:fra_x_preferred":[
        "Prince Alfred Hamlet"
    ],
    "name:nld_x_preferred":[
        "Prince Alfred's Hamlet"
    ],
    "name:nso_x_preferred":[
        "Prince Alfred Hamlet"
    ],
    "name:ron_x_preferred":[
        "Prince Alfred"
    ],
    "name:rus_x_preferred":[
        "\u041f\u0440\u0438\u043d\u0441-\u0410\u043b\u044c\u0444\u0440\u0435\u0434-\u0425\u0430\u043c\u043b\u0435\u0442"
    ],
    "name:und_x_variant":[
        "Prince Alfreds Hamlet"
    ],
    "wof:lang_x_official":[
        "eng"
    ],
    "wof:lang_x_spoken":[
        "eng",
        "zul",
        "xho",
        "afr",
        "nso",
        "tsn",
        "sot",
        "tso",
        "ssw",
        "ven",
        "nbl"
    ],
    "wof:name":"Prince Alfred Hamlet",
    "wof:placetype":"locality"
},
  "geometry": {"coordinates":[19.32468,-33.30392],"type":"Point"}
}