{
  "type": "Feature",
  "properties": {
    "gn:admin1_code":"11.0",
    "gn:admin2_code":"DC2",
    "gn:admin3_code":"WC022",
    "gn:asciiname":"Prince Alfred Hamlet",
    "gn:country_code":"ZA",
    "gn:dem":500,
    "gn:feature_class":"P",
    "gn:feature_code":"PPL",
    "gn:name":"Prince Alfred Hamlet",
    "gn:population":0,
    "gn:timezone":"Africa/Johannesburg",
    "iso:country":"ZA",
    "name:und_x_variant":[
        "Prince Alfreds Hamlet",
        "Prince Alfred Hamlet"
    ],
    "wof:name":"Prince Alfred Hamlet",
    "wof:placetype":"locality"
},
  "geometry": {"coordinates":[19.32468,-33.30392],"type":"Point"}
}