{
  "type": "Feature",
  "properties": {
    "gn:admin1_code":"5",
    "gn:admin2_code":"DC12",
    "gn:admin3_code":"EC122",
    "gn:asciiname":"KuLotshazi",
    "gn:country_code":"ZA",
    "gn:dem":311,
    "gn:feature_class":"P",
    "gn:feature_code":"PPL",
    "gn:name":"KuLotshazi",
    "gn:population":0,
    "gn:timezone":"Africa/Johannesburg",
    "iso:country":"ZA",
    "wof:name":"KuLotshazi",
    "wof:placetype":"locality"
},
  "geometry": {"coordinates":[28.5349,-32.38379],"type":"Point"}
}