{
  "type": "Feature",
  "properties": {
    "gn:admin1_code":"5",
    "gn:admin2_code":"DC12",
    "gn:admin3_code":"EC124",
    "gn:asciiname":"Izeleni",
    "gn:country_code":"ZA",
    "gn:dem":529,
    "gn:feature_class":"P",
    "gn:feature_code":"PPLL",
    "gn:name":"Izeleni",
    "gn:population":0,
    "gn:timezone":"Africa/Johannesburg",
    "iso:country":"ZA",
    "wof:name":"Izeleni",
    "wof:placetype":"locality"
},
  "geometry": {"coordinates":[27.37743,-32.7443],"type":"Point"}
}