{
  "type": "Feature",
  "properties": {
    "gn:admin1_code":"5",
    "gn:admin2_code":"DC12",
    "gn:admin3_code":"EC123",
    "gn:asciiname":"Morganville",
    "gn:country_code":"ZA",
    "gn:dem":184,
    "gn:feature_class":"P",
    "gn:feature_code":"PPL",
    "gn:name":"Morganville",
    "gn:population":0,
    "gn:timezone":"Africa/Johannesburg",
    "iso:country":"ZA",
    "name:ceb_x_preferred":[
        "Morganville"
    ],
    "name:deu_x_preferred":[
        "Morganville"
    ],
    "name:ita_x_preferred":[
        "Morganville"
    ],
    "name:nld_x_preferred":[
        "Morganville"
    ],
    "name:pol_x_preferred":[
        "Morganville"
    ],
    "name:por_x_preferred":[
        "Morganville"
    ],
    "name:spa_x_preferred":[
        "Morganville"
    ],
    "name:srp_x_preferred":[
        "\u041c\u043e\u0440\u0433\u0430\u043d\u0432\u0438\u043b"
    ],
    "name:vol_x_preferred":[
        "Morganville"
    ],
    "wof:lang_x_official":[
        "eng"
    ],
    "wof:lang_x_spoken":[
        "eng",
        "zul",
        "xho",
        "afr",
        "nso",
        "tsn",
        "sot",
        "tso",
        "ssw",
        "ven",
        "nbl"
    ],
    "wof:name":"Morganville",
    "wof:placetype":"locality"
},
  "geometry": {"coordinates":[28.29743,-32.66609],"type":"Point"}
}