{
  "type": "Feature",
  "properties": {
    "gn:admin1_code":"11",
    "gn:admin2_code":"DC4",
    "gn:admin3_code":"WC044",
    "gn:asciiname":"Bergplaas",
    "gn:country_code":"ZA",
    "gn:dem":375,
    "gn:feature_class":"P",
    "gn:feature_code":"PPL",
    "gn:name":"Bergplaas",
    "gn:population":0,
    "gn:timezone":"Africa/Johannesburg",
    "iso:country":"ZA",
    "name:und_x_variant":[
        "Bergplaats",
        "Bergplaas"
    ],
    "wof:name":"Bergplaas",
    "wof:placetype":"locality"
},
  "geometry": {"coordinates":[22.67031,-33.89904],"type":"Point"}
}