{
  "type": "Feature",
  "properties": {
    "gn:gn_country":"ZA",
    "gn:gn_fcode":"PPL",
    "gn:gn_pop":2000,
    "gn:population":2000,
    "iso:country":"ZA",
    "name:ceb_x_preferred":[
        "Sunset Beach"
    ],
    "name:deu_x_preferred":[
        "Sunset Beach"
    ],
    "name:fra_x_preferred":[
        "Sunset Beach"
    ],
    "name:ita_x_preferred":[
        "Sunset Beach"
    ],
    "name:por_x_preferred":[
        "Sunset Beach"
    ],
    "name:srp_x_preferred":[
        "\u0421\u0430\u043d\u0441\u0435\u0442 \u0411\u0438\u0447"
    ],
    "name:swe_x_preferred":[
        "Sunset Beach"
    ],
    "name:vol_x_preferred":[
        "Sunset Beach"
    ],
    "qs_pg:aaroncc":"ZA",
    "qs_pg:gn_country":"ZA",
    "qs_pg:gn_fcode":"PPL",
    "qs_pg:gn_pop":2000,
    "qs_pg:name":"Sunset Beach",
    "qs_pg:photos_9r":0,
    "qs_pg:photos_sr":0,
    "qs_pg:pop_sr":3,
    "qs_pg:qs_pg_placetype":"locality",
    "wof:name":"Sunset Beach",
    "wof:placetype":"locality",
    "wof:population":2000
},
  "geometry": {"coordinates":[18.49231,-33.85395],"type":"Point"}
}