{
  "type": "Feature",
  "properties": {
    "gn:admin1_code":"9",
    "gn:admin2_code":"DC36",
    "gn:admin3_code":"LIM367",
    "gn:asciiname":"Ga-Masiane",
    "gn:country_code":"ZA",
    "gn:dem":988,
    "gn:feature_class":"P",
    "gn:feature_code":"PPL",
    "gn:name":"Ga-Masiane",
    "gn:population":0,
    "gn:timezone":"Africa/Johannesburg",
    "iso:country":"ZA",
    "wof:name":"Ga-Masiane",
    "wof:placetype":"locality"
},
  "geometry": {"coordinates":[28.82918,-23.57981],"type":"Point"}
}