{
  "type": "Feature",
  "properties": {
    "gn:admin1_code":"5",
    "gn:admin2_code":"DC15",
    "gn:admin3_code":"EC155",
    "gn:asciiname":"Mdumazulu",
    "gn:country_code":"ZA",
    "gn:dem":672,
    "gn:feature_class":"P",
    "gn:feature_code":"PPL",
    "gn:name":"Mdumazulu",
    "gn:population":0,
    "gn:timezone":"Africa/Johannesburg",
    "iso:country":"ZA",
    "name:und_x_variant":[
        "Mdamazulu",
        "Mdumazulu"
    ],
    "wof:name":"Mdumazulu",
    "wof:placetype":"locality"
},
  "geometry": {"coordinates":[29.13914,-31.6278],"type":"Point"}
}