{
  "type": "Feature",
  "properties": {
    "gn:admin1_code":"2",
    "gn:admin2_code":"DC28",
    "gn:admin3_code":"KZN284",
    "gn:asciiname":"Brooklyn",
    "gn:country_code":"ZA",
    "gn:dem":572,
    "gn:feature_class":"P",
    "gn:feature_code":"PPL",
    "gn:name":"Brooklyn",
    "gn:population":0,
    "gn:timezone":"Africa/Johannesburg",
    "iso:country":"ZA",
    "wof:name":"Brooklyn",
    "wof:placetype":"locality"
},
  "geometry": {"coordinates":[31.33101,-28.91902],"type":"Point"}
}