{
  "type": "Feature",
  "properties": {
    "gn:admin1_code":"5",
    "gn:admin2_code":"DC15",
    "gn:admin3_code":"EC156",
    "gn:asciiname":"Elujecweni",
    "gn:country_code":"ZA",
    "gn:dem":1032,
    "gn:feature_class":"P",
    "gn:feature_code":"PPL",
    "gn:name":"Elujecweni",
    "gn:population":0,
    "gn:timezone":"Africa/Johannesburg",
    "iso:country":"ZA",
    "wof:name":"Elujecweni",
    "wof:placetype":"locality"
},
  "geometry": {"coordinates":[28.58966,-31.26037],"type":"Point"}
}