{
  "type": "Feature",
  "properties": {
    "gn:admin1_code":"5.0",
    "gn:admin2_code":"DC44",
    "gn:admin3_code":"EC442",
    "gn:asciiname":"Zingcuka",
    "gn:country_code":"ZA",
    "gn:dem":1113,
    "gn:feature_class":"P",
    "gn:feature_code":"PPL",
    "gn:name":"Zingcuka",
    "gn:population":0,
    "gn:timezone":"Africa/Johannesburg",
    "iso:country":"ZA",
    "wof:name":"Zingcuka",
    "wof:placetype":"locality"
},
  "geometry": {"coordinates":[28.93445,-30.98375],"type":"Point"}
}