{
  "type": "Feature",
  "properties": {
    "gn:admin1_code":"10",
    "gn:admin2_code":"DC39",
    "gn:admin3_code":"NW397",
    "gn:asciiname":"Makarakong",
    "gn:country_code":"ZA",
    "gn:dem":1084,
    "gn:feature_class":"P",
    "gn:feature_code":"PPL",
    "gn:name":"Makarakong",
    "gn:population":0,
    "gn:timezone":"Africa/Johannesburg",
    "iso:country":"ZA",
    "wof:name":"Makarakong",
    "wof:placetype":"locality"
},
  "geometry": {"coordinates":[23.32353,-26.45364],"type":"Point"}
}