{
  "type": "Feature",
  "properties": {
    "gn:admin1_code":"11",
    "gn:admin2_code":"DC4",
    "gn:admin3_code":"WC044",
    "gn:asciiname":"Avontuur",
    "gn:country_code":"ZA",
    "gn:dem":876,
    "gn:feature_class":"P",
    "gn:feature_code":"PPL",
    "gn:name":"Avontuur",
    "gn:population":0,
    "gn:timezone":"Africa/Johannesburg",
    "iso:country":"ZA",
    "name:afr_x_preferred":[
        "Avontuur"
    ],
    "name:ceb_x_preferred":[
        "Avontuur"
    ],
    "name:est_x_preferred":[
        "Avontuur"
    ],
    "name:nld_x_preferred":[
        "Avontuur"
    ],
    "name:nso_x_preferred":[
        "Avontuur"
    ],
    "wof:lang_x_official":[
        "eng"
    ],
    "wof:lang_x_spoken":[
        "eng",
        "zul",
        "xho",
        "afr",
        "nso",
        "tsn",
        "sot",
        "tso",
        "ssw",
        "ven",
        "nbl"
    ],
    "wof:name":"Avontuur",
    "wof:placetype":"locality"
},
  "geometry": {"coordinates":[23.16948,-33.72823],"type":"Point"}
}