{
  "type": "Feature",
  "properties": {
    "gn:admin1_code":"11",
    "gn:admin2_code":"DC4",
    "gn:admin3_code":"WC045",
    "gn:asciiname":"Middelplaas",
    "gn:country_code":"ZA",
    "gn:dem":410,
    "gn:feature_class":"P",
    "gn:feature_code":"PPL",
    "gn:name":"Middelplaas",
    "gn:population":0,
    "gn:timezone":"Africa/Johannesburg",
    "iso:country":"ZA",
    "name:und_x_variant":[
        "Middelplaats",
        "Middelplaas"
    ],
    "wof:lang_x_official":[
        "eng"
    ],
    "wof:lang_x_spoken":[
        "eng",
        "zul",
        "xho",
        "afr",
        "nso",
        "tsn",
        "sot",
        "tso",
        "ssw",
        "ven",
        "nbl"
    ],
    "wof:name":"Middelplaas",
    "wof:placetype":"locality"
},
  "geometry": {"coordinates":[22.54874,-33.52386],"type":"Point"}
}