{
  "type": "Feature",
  "properties": {
    "gn:admin1_code":"10",
    "gn:admin2_code":"DC37",
    "gn:admin3_code":"NW374",
    "gn:asciiname":"Brakkloof",
    "gn:country_code":"ZA",
    "gn:dem":1109,
    "gn:feature_class":"P",
    "gn:feature_code":"PPL",
    "gn:name":"Brakkloof",
    "gn:population":0,
    "gn:timezone":"Africa/Johannesburg",
    "iso:country":"ZA",
    "wof:name":"Brakkloof",
    "wof:placetype":"locality"
},
  "geometry": {"coordinates":[26.82942,-25.47956],"type":"Point"}
}