{
  "type": "Feature",
  "properties": {
    "gn:admin1_code":"10",
    "gn:asciiname":"Mariba",
    "gn:country_code":"ZA",
    "gn:dem":1387,
    "gn:feature_class":"P",
    "gn:feature_code":"PPL",
    "gn:name":"Mariba",
    "gn:population":0,
    "gn:timezone":"Africa/Johannesburg",
    "iso:country":"ZA",
    "wof:name":"Mariba",
    "wof:placetype":"locality"
},
  "geometry": {"coordinates":[23.82583,-27.26218],"type":"Point"}
}