{
  "type": "Feature",
  "properties": {
    "gn:admin1_code":"10.0",
    "gn:admin2_code":"DC37",
    "gn:admin3_code":"NW373",
    "gn:asciiname":"Marikana",
    "gn:country_code":"ZA",
    "gn:dem":1170,
    "gn:feature_class":"P",
    "gn:feature_code":"PPL",
    "gn:name":"Marikana",
    "gn:population":0,
    "gn:timezone":"Africa/Johannesburg",
    "iso:country":"ZA",
    "name:afr_x_preferred":[
        "Marikana"
    ],
    "name:deu_x_preferred":[
        "Marikana"
    ],
    "name:ell_x_preferred":[
        "\u039c\u03b1\u03c1\u03b9\u03ba\u03ac\u03bd\u03b1"
    ],
    "name:est_x_preferred":[
        "Marikana"
    ],
    "name:fra_x_preferred":[
        "Marikana"
    ],
    "name:nld_x_preferred":[
        "Marikana"
    ],
    "name:nso_x_preferred":[
        "Marikana"
    ],
    "name:ron_x_preferred":[
        "Marikana"
    ],
    "name:spa_x_preferred":[
        "Marikana"
    ],
    "name:und_x_variant":[
        "Rooikoppies"
    ],
    "wof:lang_x_official":[
        "eng"
    ],
    "wof:lang_x_spoken":[
        "eng",
        "zul",
        "xho",
        "afr",
        "nso",
        "tsn",
        "sot",
        "tso",
        "ssw",
        "ven",
        "nbl"
    ],
    "wof:name":"Marikana",
    "wof:placetype":"locality"
},
  "geometry": {"coordinates":[27.47475,-25.699],"type":"Point"}
}