{
  "type": "Feature",
  "properties": {
    "gn:admin1_code":"10.0",
    "gn:admin2_code":"DC37",
    "gn:admin3_code":"NW373",
    "gn:asciiname":"Marikana",
    "gn:country_code":"ZA",
    "gn:dem":1170,
    "gn:feature_class":"P",
    "gn:feature_code":"PPL",
    "gn:name":"Marikana",
    "gn:population":0,
    "gn:timezone":"Africa/Johannesburg",
    "iso:country":"ZA",
    "name:und_x_variant":[
        "Rooikoppies"
    ],
    "wof:name":"Marikana",
    "wof:placetype":"locality"
},
  "geometry": {"coordinates":[27.47475,-25.699],"type":"Point"}
}