{
  "type": "Feature",
  "properties": {
    "gn:admin1_code":"9",
    "gn:admin2_code":"DC47",
    "gn:admin3_code":"LIM473",
    "gn:asciiname":"Mafatle",
    "gn:country_code":"ZA",
    "gn:dem":1407,
    "gn:feature_class":"P",
    "gn:feature_code":"PPL",
    "gn:name":"Mafatle",
    "gn:population":0,
    "gn:timezone":"Africa/Johannesburg",
    "iso:country":"ZA",
    "wof:name":"Mafatle",
    "wof:placetype":"locality"
},
  "geometry": {"coordinates":[29.73333,-24.78333],"type":"Point"}
}