{
  "type": "Feature",
  "properties": {
    "gn:admin1_code":"2",
    "gn:admin2_code":"DC27",
    "gn:admin3_code":"KZN271",
    "gn:asciiname":"Mangwenya",
    "gn:country_code":"ZA",
    "gn:dem":81,
    "gn:feature_class":"P",
    "gn:feature_code":"PPL",
    "gn:name":"Mangwenya",
    "gn:population":0,
    "gn:timezone":"Africa/Johannesburg",
    "iso:country":"ZA",
    "wof:name":"Mangwenya",
    "wof:placetype":"locality"
},
  "geometry": {"coordinates":[32.47215,-27.26442],"type":"Point"}
}