{
  "type": "Feature",
  "properties": {
    "gn:admin1_code":"5",
    "gn:admin2_code":"DC15",
    "gn:admin3_code":"EC153",
    "gn:asciiname":"Hillside",
    "gn:country_code":"ZA",
    "gn:dem":721,
    "gn:feature_class":"P",
    "gn:feature_code":"PPL",
    "gn:name":"Hillside",
    "gn:population":0,
    "gn:timezone":"Africa/Johannesburg",
    "iso:country":"ZA",
    "name:bar_x_preferred":[
        "Hillside"
    ],
    "name:ceb_x_preferred":[
        "Hillside"
    ],
    "name:cym_x_preferred":[
        "Hillside"
    ],
    "name:deu_x_preferred":[
        "Hillside"
    ],
    "name:ita_x_preferred":[
        "Hillside"
    ],
    "name:mlg_x_preferred":[
        "Hillside"
    ],
    "name:nld_x_preferred":[
        "Hillside"
    ],
    "name:pol_x_preferred":[
        "Hillside"
    ],
    "name:por_x_preferred":[
        "Hillside"
    ],
    "name:srp_x_preferred":[
        "\u0425\u0438\u043b\u0441\u0430\u0458\u0434"
    ],
    "name:swe_x_preferred":[
        "Hillside"
    ],
    "name:ukr_x_preferred":[
        "\u0413\u0456\u043b\u043b\u0441\u0430\u0439\u0434"
    ],
    "name:vol_x_preferred":[
        "Hillside"
    ],
    "wof:lang_x_official":[
        "eng"
    ],
    "wof:lang_x_spoken":[
        "eng",
        "zul",
        "xho",
        "afr",
        "nso",
        "tsn",
        "sot",
        "tso",
        "ssw",
        "ven",
        "nbl"
    ],
    "wof:name":"Hillside",
    "wof:placetype":"locality"
},
  "geometry": {"coordinates":[29.47704,-31.28022],"type":"Point"}
}