{
  "type": "Feature",
  "properties": {
    "gn:admin1_code":"10.0",
    "gn:admin2_code":"DC38",
    "gn:admin3_code":"NW384",
    "gn:asciiname":"Welverdiend",
    "gn:country_code":"ZA",
    "gn:dem":1418,
    "gn:feature_class":"P",
    "gn:feature_code":"PPL",
    "gn:name":"Welverdiend",
    "gn:population":0,
    "gn:timezone":"Africa/Johannesburg",
    "iso:country":"ZA",
    "wof:name":"Welverdiend",
    "wof:placetype":"locality"
},
  "geometry": {"coordinates":[25.75313,-26.04499],"type":"Point"}
}