{
  "type": "Feature",
  "properties": {
    "gn:admin1_code":"5",
    "gn:admin2_code":"DC13",
    "gn:admin3_code":"EC137",
    "gn:asciiname":"Bodini",
    "gn:country_code":"ZA",
    "gn:dem":879,
    "gn:feature_class":"P",
    "gn:feature_code":"PPL",
    "gn:name":"Bodini",
    "gn:population":0,
    "gn:timezone":"Africa/Johannesburg",
    "iso:country":"ZA",
    "name:deu_x_preferred":[
        "Bodini"
    ],
    "name:ita_x_preferred":[
        "Bodini"
    ],
    "wof:name":"Bodini",
    "wof:placetype":"locality"
},
  "geometry": {"coordinates":[27.91422,-31.78997],"type":"Point"}
}