{
  "type": "Feature",
  "properties": {
    "gn:admin1_code":"11.0",
    "gn:admin2_code":"DC1",
    "gn:admin3_code":"WC014",
    "gn:asciiname":"Donkergat",
    "gn:country_code":"ZA",
    "gn:dem":11,
    "gn:feature_class":"P",
    "gn:feature_code":"PPL",
    "gn:name":"Donkergat",
    "gn:population":0,
    "gn:timezone":"Africa/Johannesburg",
    "iso:country":"ZA",
    "wof:name":"Donkergat",
    "wof:placetype":"locality"
},
  "geometry": {"coordinates":[18.00075,-33.08227],"type":"Point"}
}