{
  "type": "Feature",
  "properties": {
    "gn:admin1_code":"5",
    "gn:admin2_code":"DC15",
    "gn:admin3_code":"EC157",
    "gn:asciiname":"Lubalekweni",
    "gn:country_code":"ZA",
    "gn:dem":725,
    "gn:feature_class":"P",
    "gn:feature_code":"PPL",
    "gn:name":"Lubalekweni",
    "gn:population":0,
    "gn:timezone":"Africa/Johannesburg",
    "iso:country":"ZA",
    "wof:name":"Lubalekweni",
    "wof:placetype":"locality"
},
  "geometry": {"coordinates":[28.73781,-31.85045],"type":"Point"}
}