{
  "type": "Feature",
  "properties": {
    "gn:admin1_code":"5",
    "gn:admin2_code":"NMA",
    "gn:admin3_code":"NMA",
    "gn:asciiname":"King Neptune",
    "gn:country_code":"ZA",
    "gn:dem":16,
    "gn:feature_class":"P",
    "gn:feature_code":"PPL",
    "gn:name":"King Neptune",
    "gn:population":0,
    "gn:timezone":"Africa/Johannesburg",
    "iso:country":"ZA",
    "wof:name":"King Neptune",
    "wof:placetype":"locality"
},
  "geometry": {"coordinates":[25.67869,-33.80575],"type":"Point"}
}