{
  "type": "Feature",
  "properties": {
    "gn:admin1_code":"6",
    "gn:asciiname":"Maanhaarrand",
    "gn:country_code":"ZA",
    "gn:dem":1447,
    "gn:feature_class":"P",
    "gn:feature_code":"PPL",
    "gn:name":"Maanhaarrand",
    "gn:population":0,
    "gn:timezone":"Africa/Johannesburg",
    "iso:country":"ZA",
    "wof:name":"Maanhaarrand",
    "wof:placetype":"locality"
},
  "geometry": {"coordinates":[27.45682,-25.91572],"type":"Point"}
}