{
  "type": "Feature",
  "properties": {
    "gn:admin1_code":"10.0",
    "gn:asciiname":"Tsaelengwe",
    "gn:cc2":"ZA",
    "gn:country_code":"ZA",
    "gn:dem":1408,
    "gn:feature_class":"P",
    "gn:feature_code":"PPL",
    "gn:name":"Tsaelengwe",
    "gn:population":0,
    "gn:timezone":"Africa/Johannesburg",
    "iso:country":"ZA",
    "name:und_x_variant":[
        "Tselaengwe",
        "Tsailingwe",
        "Tsaelengwe"
    ],
    "wof:name":"Tsaelengwe",
    "wof:placetype":"locality"
},
  "geometry": {"coordinates":[23.73333,-27.38333],"type":"Point"}
}