{
  "type": "Feature",
  "properties": {
    "gn:admin1_code":"2.0",
    "gn:admin2_code":"DC29",
    "gn:admin3_code":"KZN293",
    "gn:asciiname":"Umkhomazi",
    "gn:country_code":"ZA",
    "gn:dem":673,
    "gn:feature_class":"P",
    "gn:feature_code":"PPL",
    "gn:name":"Umkhomazi",
    "gn:population":0,
    "gn:timezone":"Africa/Johannesburg",
    "iso:country":"ZA",
    "wof:name":"Umkhomazi",
    "wof:placetype":"locality"
},
  "geometry": {"coordinates":[30.86246,-29.46904],"type":"Point"}
}