{
  "type": "Feature",
  "properties": {
    "gn:admin1_code":"2.0",
    "gn:admin2_code":"DC27",
    "gn:admin3_code":"KZN272",
    "gn:asciiname":"Lulwane",
    "gn:country_code":"ZA",
    "gn:dem":48,
    "gn:feature_class":"P",
    "gn:feature_code":"PPL",
    "gn:name":"Lulwane",
    "gn:population":0,
    "gn:timezone":"Africa/Johannesburg",
    "iso:country":"ZA",
    "wof:name":"Lulwane",
    "wof:placetype":"locality"
},
  "geometry": {"coordinates":[32.24493,-27.05545],"type":"Point"}
}