{
  "type": "Feature",
  "properties": {
    "gn:admin1_code":"5.0",
    "gn:admin2_code":"DC12",
    "gn:admin3_code":"EC126",
    "gn:asciiname":"Worthing",
    "gn:country_code":"ZA",
    "gn:dem":238,
    "gn:feature_class":"P",
    "gn:feature_code":"PPL",
    "gn:name":"Worthing",
    "gn:population":0,
    "gn:timezone":"Africa/Johannesburg",
    "iso:country":"ZA",
    "name:ast_x_preferred":[
        "Worthing"
    ],
    "name:azb_x_preferred":[
        "\u0648\u0648\u0631\u062a\u06cc\u0646\u0642"
    ],
    "name:bul_x_preferred":[
        "\u0423\u044a\u0440\u0434\u0438\u043d\u0433"
    ],
    "name:cat_x_preferred":[
        "Worthing"
    ],
    "name:ceb_x_preferred":[
        "Worthing"
    ],
    "name:cym_x_preferred":[
        "Worthing"
    ],
    "name:dan_x_preferred":[
        "Worthing"
    ],
    "name:deu_x_preferred":[
        "Worthing"
    ],
    "name:epo_x_preferred":[
        "Worthing"
    ],
    "name:fas_x_preferred":[
        "\u0648\u0648\u0631\u062a\u06cc\u0646\u06af"
    ],
    "name:fra_x_preferred":[
        "Worthing"
    ],
    "name:gle_x_preferred":[
        "Worthing"
    ],
    "name:hun_x_preferred":[
        "Worthing"
    ],
    "name:ita_x_preferred":[
        "Worthing"
    ],
    "name:jpn_x_preferred":[
        "\u30ef\u30fc\u30b8\u30f3\u30b0"
    ],
    "name:lit_x_preferred":[
        "Verdingas"
    ],
    "name:nld_x_preferred":[
        "Worthing"
    ],
    "name:nno_x_preferred":[
        "Worthing"
    ],
    "name:nor_x_preferred":[
        "Worthing"
    ],
    "name:pol_x_preferred":[
        "Worthing"
    ],
    "name:por_x_preferred":[
        "Worthing"
    ],
    "name:ron_x_preferred":[
        "Worthing"
    ],
    "name:rus_x_preferred":[
        "\u0423\u044d\u0440\u0442\u0438\u043d\u0433"
    ],
    "name:spa_x_preferred":[
        "Worthing"
    ],
    "name:srp_x_preferred":[
        "\u0412\u043e\u0440\u0442\u0438\u043d\u0433"
    ],
    "name:swe_x_preferred":[
        "Worthing"
    ],
    "name:tat_x_preferred":[
        "\u0412\u04e9\u0440\u0437\u0438\u04a3"
    ],
    "name:urd_x_preferred":[
        "\u0648\u0631\u062f\u0646\u06af"
    ],
    "name:vol_x_preferred":[
        "Worthing"
    ],
    "wof:name":"Worthing",
    "wof:placetype":"locality"
},
  "geometry": {"coordinates":[27.33333,-33.16667],"type":"Point"}
}