{
  "type": "Feature",
  "properties": {
    "gn:admin1_code":"11",
    "gn:admin2_code":"DC1",
    "gn:admin3_code":"WC012",
    "gn:asciiname":"Theerivier",
    "gn:country_code":"ZA",
    "gn:dem":276,
    "gn:feature_class":"P",
    "gn:feature_code":"PPL",
    "gn:name":"Theerivier",
    "gn:population":0,
    "gn:timezone":"Africa/Johannesburg",
    "iso:country":"ZA",
    "wof:name":"Theerivier",
    "wof:placetype":"locality"
},
  "geometry": {"coordinates":[19.08318,-32.80883],"type":"Point"}
}