{
  "type": "Feature",
  "properties": {
    "iso:country":"ZA",
    "name:deu_x_preferred":[
        "Meadowlands"
    ],
    "name:eng_x_preferred":[
        "Meadowlands"
    ],
    "name:fin_x_preferred":[
        "Meadowlands"
    ],
    "name:pol_x_preferred":[
        "Meadowlands"
    ],
    "name:rus_x_preferred":[
        "\u041c\u0435\u0434\u043e\u0443\u043b\u0435\u043d\u0434\u0441"
    ],
    "name:spa_x_preferred":[
        "Meadowlands"
    ],
    "name:srp_x_preferred":[
        "\u041c\u0435\u0434\u043e\u0443\u043b\u0430\u043d\u0434\u0441"
    ],
    "name:ukr_x_preferred":[
        "\u041c\u0435\u0434\u043e\u0432\u043b\u0435\u043d\u0434\u0441"
    ],
    "qs:gn_adm0_cc":"ZA",
    "qs:gn_local":993800,
    "qs:gn_nam_loc":"Johannesburg, Johannesburg, City of Johannesburg, Gauteng, ZA",
    "qs:gn_namadm1":"06",
    "qs:local_max":2766,
    "qs:local_sum":31655,
    "qs:localhoods":69,
    "qs:name":"Meadowlands",
    "qs:name_adm0":"South Africa",
    "qs:name_adm1":"Gauteng",
    "qs:name_adm2":"City of Johannesburg",
    "qs:name_lau":"Johannesburg",
    "qs:name_local":"Johannesburg",
    "qs:photo_max":130,
    "qs:photo_sum":624,
    "qs:placetype":"Suburb",
    "qs:quad_count":24,
    "qs:woe_adm0":23424942,
    "qs:woe_adm1":2346981,
    "qs:woe_adm2":56189422,
    "qs:woe_lau":56189710,
    "qs:woe_local":1582504,
    "qs:woe_ver":"7.10.0",
    "wof:lang":[
        "eng"
    ],
    "wof:name":"Meadowlands",
    "wof:placetype":"neighbourhood"
},
  "geometry": {"coordinates":[27.879812,-26.214959],"type":"Point"}
}