{
  "type": "Feature",
  "properties": {
    "gn:admin1_code":"5",
    "gn:admin2_code":"DC13",
    "gn:admin3_code":"EC133",
    "gn:asciiname":"Burnley",
    "gn:country_code":"ZA",
    "gn:dem":1758,
    "gn:feature_class":"P",
    "gn:feature_code":"PPL",
    "gn:name":"Burnley",
    "gn:population":0,
    "gn:timezone":"Africa/Johannesburg",
    "iso:country":"ZA",
    "name:ara_x_preferred":[
        "\u0628\u064a\u0631\u0646\u0644\u064a"
    ],
    "name:bul_x_preferred":[
        "\u0411\u044a\u0440\u043d\u043b\u0438"
    ],
    "name:cat_x_preferred":[
        "Burnley"
    ],
    "name:ceb_x_preferred":[
        "Burnley"
    ],
    "name:cym_x_preferred":[
        "Burnley"
    ],
    "name:dan_x_preferred":[
        "Burnley"
    ],
    "name:deu_x_preferred":[
        "Burnley"
    ],
    "name:ell_x_preferred":[
        "\u039c\u03c0\u03ad\u03c1\u03bd\u03bb\u03b9"
    ],
    "name:epo_x_preferred":[
        "Burnley"
    ],
    "name:eus_x_preferred":[
        "Burnley"
    ],
    "name:fas_x_preferred":[
        "\u0628\u0631\u0646\u0644\u06cc"
    ],
    "name:fin_x_preferred":[
        "Burnley"
    ],
    "name:fra_x_preferred":[
        "Burnley"
    ],
    "name:gle_x_preferred":[
        "Burnley"
    ],
    "name:glg_x_preferred":[
        "Burnley"
    ],
    "name:hak_x_preferred":[
        "Burnley"
    ],
    "name:heb_x_preferred":[
        "\u05d1\u05e8\u05e0\u05dc\u05d9"
    ],
    "name:ind_x_preferred":[
        "Burnley"
    ],
    "name:isl_x_preferred":[
        "Burnley"
    ],
    "name:ita_x_preferred":[
        "Burnley"
    ],
    "name:jpn_x_preferred":[
        "\u30d0\u30fc\u30f3\u30ea\u30fc"
    ],
    "name:lit_x_preferred":[
        "Bernlis"
    ],
    "name:nld_x_preferred":[
        "Burnley"
    ],
    "name:nno_x_preferred":[
        "Burnley"
    ],
    "name:nor_x_preferred":[
        "Burnley"
    ],
    "name:pol_x_preferred":[
        "Burnley"
    ],
    "name:por_x_preferred":[
        "Burnley"
    ],
    "name:ron_x_preferred":[
        "Burnley"
    ],
    "name:rus_x_preferred":[
        "\u0411\u0435\u0440\u043d\u043b\u0438"
    ],
    "name:sco_x_preferred":[
        "Burnley"
    ],
    "name:spa_x_preferred":[
        "Burnley"
    ],
    "name:srp_x_preferred":[
        "\u0411\u0435\u0440\u043d\u043b\u0438"
    ],
    "name:swe_x_preferred":[
        "Burnley"
    ],
    "name:szl_x_preferred":[
        "Burnley"
    ],
    "name:tat_x_preferred":[
        "\u0411\u04e9\u0440\u043d\u043b\u0438"
    ],
    "name:tur_x_preferred":[
        "Burnley"
    ],
    "name:ukr_x_preferred":[
        "\u0411\u0435\u0440\u043d\u043b\u0456"
    ],
    "name:vie_x_preferred":[
        "Burnley"
    ],
    "name:vol_x_preferred":[
        "Burnley"
    ],
    "name:zho_x_preferred":[
        "\u4f2f\u6069\u5229"
    ],
    "wof:lang_x_official":[
        "eng"
    ],
    "wof:lang_x_spoken":[
        "eng",
        "zul",
        "xho",
        "afr",
        "nso",
        "tsn",
        "sot",
        "tso",
        "ssw",
        "ven",
        "nbl"
    ],
    "wof:name":"Burnley",
    "wof:placetype":"locality"
},
  "geometry": {"coordinates":[26.33996,-31.54701],"type":"Point"}
}