{
  "type": "Feature",
  "properties": {
    "gn:admin1_code":"10",
    "gn:asciiname":"Kruissar",
    "gn:country_code":"ZA",
    "gn:dem":1374,
    "gn:feature_class":"P",
    "gn:feature_code":"PPL",
    "gn:name":"Kruissar",
    "gn:population":0,
    "gn:timezone":"Africa/Johannesburg",
    "iso:country":"ZA",
    "wof:name":"Kruissar",
    "wof:placetype":"locality"
},
  "geometry": {"coordinates":[23.82657,-27.2161],"type":"Point"}
}