{
  "type": "Feature",
  "properties": {
    "gn:admin1_code":"2",
    "gn:admin2_code":"DC29",
    "gn:admin3_code":"KZN291",
    "gn:asciiname":"Newark",
    "gn:country_code":"ZA",
    "gn:dem":91,
    "gn:feature_class":"P",
    "gn:feature_code":"PPL",
    "gn:name":"Newark",
    "gn:population":0,
    "gn:timezone":"Africa/Johannesburg",
    "iso:country":"ZA",
    "wof:name":"Newark",
    "wof:placetype":"locality"
},
  "geometry": {"coordinates":[31.40677,-29.19946],"type":"Point"}
}