{
  "type": "Feature",
  "properties": {
    "gn:admin1_code":"2",
    "gn:admin2_code":"DC29",
    "gn:admin3_code":"KZN291",
    "gn:asciiname":"Newark",
    "gn:country_code":"ZA",
    "gn:dem":91,
    "gn:feature_class":"P",
    "gn:feature_code":"PPL",
    "gn:name":"Newark",
    "gn:population":0,
    "gn:timezone":"Africa/Johannesburg",
    "iso:country":"ZA",
    "name:azb_x_preferred":[
        "\u0646\u06cc\u0648\u0622\u0631\u06a9"
    ],
    "name:bel_x_preferred":[
        "\u041d\u044c\u044e\u0430\u0440\u043a"
    ],
    "name:bre_x_preferred":[
        "Newark"
    ],
    "name:bul_x_preferred":[
        "\u041d\u044e\u0430\u0440\u043a"
    ],
    "name:cat_x_preferred":[
        "Newark"
    ],
    "name:ceb_x_preferred":[
        "Newark"
    ],
    "name:deu_x_preferred":[
        "Newark"
    ],
    "name:ell_x_preferred":[
        "\u039d\u03b9\u03bf\u03cd\u03b1\u03c1\u03ba"
    ],
    "name:est_x_preferred":[
        "Newark"
    ],
    "name:fas_x_preferred":[
        "\u0646\u06cc\u0648\u0622\u0631\u06a9"
    ],
    "name:fin_x_preferred":[
        "Newark"
    ],
    "name:fra_x_preferred":[
        "Newark"
    ],
    "name:glg_x_preferred":[
        "Newark"
    ],
    "name:hun_x_preferred":[
        "Newark"
    ],
    "name:ita_x_preferred":[
        "Newark"
    ],
    "name:jpn_x_preferred":[
        "\u30cb\u30e5\u30fc\u30a2\u30fc\u30af"
    ],
    "name:kor_x_preferred":[
        "\ub274\uc5b4\ud06c"
    ],
    "name:msa_x_preferred":[
        "Newark"
    ],
    "name:nld_x_preferred":[
        "Newark"
    ],
    "name:nor_x_preferred":[
        "Newark"
    ],
    "name:pol_x_preferred":[
        "Newark"
    ],
    "name:por_x_preferred":[
        "Newark"
    ],
    "name:rus_x_preferred":[
        "\u041d\u044c\u044e\u0430\u0440\u043a"
    ],
    "name:scn_x_preferred":[
        "Newark"
    ],
    "name:sco_x_preferred":[
        "Newark"
    ],
    "name:slk_x_preferred":[
        "Newark"
    ],
    "name:spa_x_preferred":[
        "Newark"
    ],
    "name:srp_x_preferred":[
        "\u040a\u0443\u0430\u0440\u043a"
    ],
    "name:swa_x_preferred":[
        "Newark"
    ],
    "name:swe_x_preferred":[
        "Newark"
    ],
    "name:tur_x_preferred":[
        "Newark"
    ],
    "name:ukr_x_preferred":[
        "\u041d\u044c\u044e\u0430\u0440\u043a"
    ],
    "name:urd_x_preferred":[
        "\u0646\u06cc\u0648\u0622\u0631\u06a9"
    ],
    "name:vol_x_preferred":[
        "Newark"
    ],
    "name:yor_x_preferred":[
        "Newark"
    ],
    "name:zho_x_preferred":[
        "\u7d10\u83ef\u514b"
    ],
    "wof:name":"Newark",
    "wof:placetype":"locality"
},
  "geometry": {"coordinates":[31.40677,-29.19946],"type":"Point"}
}