{
  "type": "Feature",
  "properties": {
    "gn:admin1_code":"8",
    "gn:admin2_code":"DC7",
    "gn:admin3_code":"NC074",
    "gn:asciiname":"Karringmelkskolk",
    "gn:country_code":"ZA",
    "gn:dem":1003,
    "gn:feature_class":"P",
    "gn:feature_code":"PPL",
    "gn:name":"Karringmelkskolk",
    "gn:population":0,
    "gn:timezone":"Africa/Johannesburg",
    "iso:country":"ZA",
    "wof:name":"Karringmelkskolk",
    "wof:placetype":"locality"
},
  "geometry": {"coordinates":[21.56264,-30.57091],"type":"Point"}
}