{
  "type": "Feature",
  "properties": {
    "gn:admin1_code":"8.0",
    "gn:admin2_code":"DC45",
    "gn:admin3_code":"NC451",
    "gn:asciiname":"Sutton",
    "gn:country_code":"ZA",
    "gn:dem":1083,
    "gn:feature_class":"P",
    "gn:feature_code":"PPL",
    "gn:name":"Sutton",
    "gn:population":0,
    "gn:timezone":"Africa/Johannesburg",
    "iso:country":"ZA",
    "wof:name":"Sutton",
    "wof:placetype":"locality"
},
  "geometry": {"coordinates":[22.82384,-27.43193],"type":"Point"}
}