{
  "type": "Feature",
  "properties": {
    "gn:admin1_code":"8.0",
    "gn:admin2_code":"DC45",
    "gn:admin3_code":"NC451",
    "gn:asciiname":"Sutton",
    "gn:country_code":"ZA",
    "gn:dem":1083,
    "gn:feature_class":"P",
    "gn:feature_code":"PPL",
    "gn:name":"Sutton",
    "gn:population":0,
    "gn:timezone":"Africa/Johannesburg",
    "iso:country":"ZA",
    "name:ang_x_preferred":[
        "S\u016b\u00fetun"
    ],
    "name:ben_x_preferred":[
        "\u09b8\u09c1\u099f\u09a8"
    ],
    "name:cat_x_preferred":[
        "Sutton"
    ],
    "name:ceb_x_preferred":[
        "Sutton"
    ],
    "name:cym_x_preferred":[
        "Sutton"
    ],
    "name:dan_x_preferred":[
        "Sutton"
    ],
    "name:deu_x_preferred":[
        "Sutton"
    ],
    "name:ell_x_preferred":[
        "\u03a3\u03ac\u03c4\u03bf\u03bd"
    ],
    "name:fin_x_preferred":[
        "Sutton"
    ],
    "name:fra_x_preferred":[
        "Sutton"
    ],
    "name:heb_x_preferred":[
        "\u05e1\u05d0\u05d8\u05d5\u05df"
    ],
    "name:ind_x_preferred":[
        "Sutton"
    ],
    "name:ita_x_preferred":[
        "Sutton"
    ],
    "name:jpn_x_preferred":[
        "\u30b5\u30c3\u30c8\u30f3"
    ],
    "name:lit_x_preferred":[
        "Satonas"
    ],
    "name:nld_x_preferred":[
        "Sutton"
    ],
    "name:pol_x_preferred":[
        "Sutton"
    ],
    "name:por_x_preferred":[
        "Sutton"
    ],
    "name:rus_x_preferred":[
        "\u0421\u0430\u0442\u0442\u043e\u043d"
    ],
    "name:sco_x_preferred":[
        "Sutton"
    ],
    "name:spa_x_preferred":[
        "Sutton"
    ],
    "name:srp_x_preferred":[
        "\u0421\u0430\u0442\u043e\u043d"
    ],
    "name:swe_x_preferred":[
        "Sutton"
    ],
    "name:ukr_x_preferred":[
        "\u0421\u0430\u0442\u0442\u043e\u043d"
    ],
    "name:vie_x_preferred":[
        "Sutton"
    ],
    "name:vol_x_preferred":[
        "Sutton"
    ],
    "wof:lang_x_official":[
        "eng"
    ],
    "wof:lang_x_spoken":[
        "eng",
        "zul",
        "xho",
        "afr",
        "nso",
        "tsn",
        "sot",
        "tso",
        "ssw",
        "ven",
        "nbl"
    ],
    "wof:name":"Sutton",
    "wof:placetype":"locality"
},
  "geometry": {"coordinates":[22.82384,-27.43193],"type":"Point"}
}