{
  "type": "Feature",
  "properties": {
    "gn:admin1_code":"8.0",
    "gn:admin2_code":"DC8",
    "gn:admin3_code":"NC084",
    "gn:asciiname":"Tarka se Kop",
    "gn:country_code":"ZA",
    "gn:dem":1016,
    "gn:feature_class":"P",
    "gn:feature_code":"PPL",
    "gn:name":"Tarka se Kop",
    "gn:population":0,
    "gn:timezone":"Africa/Johannesburg",
    "iso:country":"ZA",
    "wof:name":"Tarka se Kop",
    "wof:placetype":"locality"
},
  "geometry": {"coordinates":[21.67904,-29.62547],"type":"Point"}
}