{
  "type": "Feature",
  "properties": {
    "iso:country":"ZA",
    "qs_pg:aaroncc":"ZA",
    "qs_pg:name":"Lindhaven",
    "qs_pg:name_adm0":"South Africa",
    "qs_pg:name_adm1":"Gauteng",
    "qs_pg:photos":2,
    "qs_pg:photos_1k":1,
    "qs_pg:photos_9k":1,
    "qs_pg:photos_9r":1,
    "qs_pg:photos_all":2,
    "qs_pg:photos_sr":1,
    "qs_pg:pop_sr":0,
    "qs_pg:qs_pg_placetype":"neighbourhood",
    "qs_pg:qs_pg_placetype_gp":"Suburb",
    "qs_pg:woe_adm0":23424942,
    "woe:adm0_id":23424942,
    "woe:name_adm0":"South Africa",
    "woe:name_adm1":"Gauteng",
    "woe:placetype":"Suburb",
    "wof:lang_x_official":[
        "eng"
    ],
    "wof:lang_x_spoken":[
        "eng",
        "zul",
        "xho",
        "afr",
        "nso",
        "tsn",
        "sot",
        "tso",
        "ssw",
        "ven",
        "nbl"
    ],
    "wof:name":"Lindhaven",
    "wof:placetype":"neighbourhood"
},
  "geometry": {"coordinates":[27.87137,-26.134172],"type":"Point"}
}