{
  "type": "Feature",
  "properties": {
    "gn:admin1_code":"11.0",
    "gn:admin2_code":"DC1",
    "gn:admin3_code":"WC015",
    "gn:asciiname":"Kalbaskraal",
    "gn:country_code":"ZA",
    "gn:dem":75,
    "gn:feature_class":"P",
    "gn:feature_code":"PPL",
    "gn:name":"Kalbaskraal",
    "gn:population":0,
    "gn:timezone":"Africa/Johannesburg",
    "iso:country":"ZA",
    "name:und_x_variant":[
        "Kalabaskraal",
        "Kalbaskraal"
    ],
    "wof:name":"Kalbaskraal",
    "wof:placetype":"locality"
},
  "geometry": {"coordinates":[18.64887,-33.57315999999999],"type":"Point"}
}