{
  "type": "Feature",
  "properties": {
    "gn:admin1_code":"9.0",
    "gn:admin2_code":"DC36",
    "gn:admin3_code":"LIM362",
    "gn:asciiname":"Woudend",
    "gn:country_code":"ZA",
    "gn:dem":803,
    "gn:feature_class":"P",
    "gn:feature_code":"PPL",
    "gn:name":"Woudend",
    "gn:population":0,
    "gn:timezone":"Africa/Johannesburg",
    "iso:country":"ZA",
    "wof:name":"Woudend",
    "wof:placetype":"locality"
},
  "geometry": {"coordinates":[27.73945,-23.30066],"type":"Point"}
}