{
  "type": "Feature",
  "properties": {
    "gn:admin1_code":"5",
    "gn:admin2_code":"DC14",
    "gn:admin3_code":"EC144",
    "gn:asciiname":"Glenridge",
    "gn:country_code":"ZA",
    "gn:dem":1355,
    "gn:feature_class":"P",
    "gn:feature_code":"PPL",
    "gn:name":"Glenridge",
    "gn:population":0,
    "gn:timezone":"Africa/Johannesburg",
    "iso:country":"ZA",
    "wof:name":"Glenridge",
    "wof:placetype":"locality"
},
  "geometry": {"coordinates":[26.20143,-30.67191],"type":"Point"}
}