{
  "type": "Feature",
  "properties": {
    "gn:admin1_code":"5",
    "gn:admin2_code":"DC13",
    "gn:admin3_code":"EC137",
    "gn:asciiname":"Elabafazi",
    "gn:country_code":"ZA",
    "gn:dem":885,
    "gn:feature_class":"P",
    "gn:feature_code":"PPL",
    "gn:name":"Elabafazi",
    "gn:population":0,
    "gn:timezone":"Africa/Johannesburg",
    "iso:country":"ZA",
    "wof:name":"Elabafazi",
    "wof:placetype":"locality"
},
  "geometry": {"coordinates":[28.18977000000001,-31.53185],"type":"Point"}
}