{
  "type": "Feature",
  "properties": {
    "gn:admin1_code":"8.0",
    "gn:admin2_code":"DC7",
    "gn:admin3_code":"NC078",
    "gn:asciiname":"Rooidam",
    "gn:country_code":"ZA",
    "gn:dem":998,
    "gn:feature_class":"P",
    "gn:feature_code":"PPL",
    "gn:name":"Rooidam",
    "gn:population":0,
    "gn:timezone":"Africa/Johannesburg",
    "iso:country":"ZA",
    "wof:name":"Rooidam",
    "wof:placetype":"locality"
},
  "geometry": {"coordinates":[22.34853,-29.12161],"type":"Point"}
}