{
  "type": "Feature",
  "properties": {
    "gn:admin1_code":"7",
    "gn:admin2_code":"DC30",
    "gn:admin3_code":"MP305",
    "gn:asciiname":"Padgesvlei",
    "gn:country_code":"ZA",
    "gn:dem":1615,
    "gn:feature_class":"P",
    "gn:feature_code":"PPL",
    "gn:name":"Padgesvlei",
    "gn:population":0,
    "gn:timezone":"Africa/Johannesburg",
    "iso:country":"ZA",
    "wof:name":"Padgesvlei",
    "wof:placetype":"locality"
},
  "geometry": {"coordinates":[29.36667000000001,-26.78333],"type":"Point"}
}