{
  "type": "Feature",
  "properties": {
    "gn:admin1_code":"5",
    "gn:admin2_code":"DC13",
    "gn:admin3_code":"EC137",
    "gn:asciiname":"Mjanyana",
    "gn:country_code":"ZA",
    "gn:dem":783,
    "gn:feature_class":"P",
    "gn:feature_code":"PPL",
    "gn:name":"Mjanyana",
    "gn:population":0,
    "gn:timezone":"Africa/Johannesburg",
    "iso:country":"ZA",
    "name:und_x_variant":[
        "Emjanyana",
        "Mjanyama",
        "Mjanyana"
    ],
    "wof:name":"Mjanyana",
    "wof:placetype":"locality"
},
  "geometry": {"coordinates":[28.10055,-31.83775],"type":"Point"}
}