{
  "type": "Feature",
  "properties": {
    "gn:admin1_code":"7",
    "gn:admin2_code":"DC30",
    "gn:admin3_code":"MP304",
    "gn:asciiname":"Klipplaatdrift",
    "gn:country_code":"ZA",
    "gn:dem":1646,
    "gn:feature_class":"P",
    "gn:feature_code":"PPL",
    "gn:name":"Klipplaatdrift",
    "gn:population":0,
    "gn:timezone":"Africa/Johannesburg",
    "iso:country":"ZA",
    "wof:name":"Klipplaatdrift",
    "wof:placetype":"locality"
},
  "geometry": {"coordinates":[29.87489,-26.93766],"type":"Point"}
}