{
  "type": "Feature",
  "properties": {
    "gn:admin1_code":"5",
    "gn:admin2_code":"DC12",
    "gn:admin3_code":"EC123",
    "gn:asciiname":"Kwenxura",
    "gn:country_code":"ZA",
    "gn:dem":189,
    "gn:feature_class":"P",
    "gn:feature_code":"PPL",
    "gn:name":"Kwenxura",
    "gn:population":0,
    "gn:timezone":"Africa/Johannesburg",
    "iso:country":"ZA",
    "name:und_x_variant":[
        "Kwenxuha",
        "Kwenxura"
    ],
    "wof:name":"Kwenxura",
    "wof:placetype":"locality"
},
  "geometry": {"coordinates":[28.1092,-32.71734],"type":"Point"}
}