{
  "type": "Feature",
  "properties": {
    "gn:admin1_code":"9",
    "gn:admin2_code":"DC36",
    "gn:admin3_code":"LIM362",
    "gn:asciiname":"Marnitz",
    "gn:country_code":"ZA",
    "gn:dem":942,
    "gn:feature_class":"P",
    "gn:feature_code":"PPL",
    "gn:name":"Marnitz",
    "gn:population":0,
    "gn:timezone":"Africa/Johannesburg",
    "iso:country":"ZA",
    "name:und_x_variant":[
        "Manitz Kraal",
        "Marnitz"
    ],
    "wof:name":"Marnitz",
    "wof:placetype":"locality"
},
  "geometry": {"coordinates":[28.21071,-23.16296],"type":"Point"}
}