{
  "type": "Feature",
  "properties": {
    "gn:admin1_code":"9",
    "gn:admin2_code":"DC36",
    "gn:admin3_code":"LIM362",
    "gn:asciiname":"Marnitz",
    "gn:country_code":"ZA",
    "gn:dem":942,
    "gn:feature_class":"P",
    "gn:feature_code":"PPL",
    "gn:name":"Marnitz",
    "gn:population":0,
    "gn:timezone":"Africa/Johannesburg",
    "iso:country":"ZA",
    "name:ceb_x_preferred":[
        "Marnitz"
    ],
    "name:deu_x_preferred":[
        "Marnitz"
    ],
    "name:epo_x_preferred":[
        "Marnitz"
    ],
    "name:fas_x_preferred":[
        "\u0645\u0627\u0631\u0646\u06cc\u062a\u0633"
    ],
    "name:fra_x_preferred":[
        "Marnitz"
    ],
    "name:hun_x_preferred":[
        "Marnitz"
    ],
    "name:ita_x_preferred":[
        "Marnitz"
    ],
    "name:kaz_x_preferred":[
        "\u041c\u0430\u0440\u043d\u0438\u0446"
    ],
    "name:kir_x_preferred":[
        "\u041c\u0430\u0440\u043d\u0438\u0446"
    ],
    "name:mkd_x_preferred":[
        "\u041c\u0430\u0440\u043d\u0438\u0446"
    ],
    "name:msa_x_preferred":[
        "Marnitz"
    ],
    "name:nld_x_preferred":[
        "Marnitz"
    ],
    "name:pol_x_preferred":[
        "Marnitz"
    ],
    "name:por_x_preferred":[
        "Marnitz"
    ],
    "name:ron_x_preferred":[
        "Marnitz"
    ],
    "name:rus_x_preferred":[
        "\u041c\u0430\u0440\u043d\u0438\u0446"
    ],
    "name:spa_x_preferred":[
        "Marnitz"
    ],
    "name:srp_x_preferred":[
        "\u041c\u0430\u0440\u043d\u0438\u0446"
    ],
    "name:swe_x_preferred":[
        "Marnitz"
    ],
    "name:tgl_x_preferred":[
        "Marnitz"
    ],
    "name:ukr_x_preferred":[
        "\u041c\u0430\u0440\u043d\u0456\u0446"
    ],
    "name:und_x_variant":[
        "Manitz Kraal"
    ],
    "name:uzb_x_preferred":[
        "Marnitz"
    ],
    "name:vie_x_preferred":[
        "Marnitz"
    ],
    "name:vol_x_preferred":[
        "Marnitz"
    ],
    "name:war_x_preferred":[
        "Marnitz"
    ],
    "name:zho_x_preferred":[
        "\u9a6c\u5c14\u5c3c\u8328"
    ],
    "wof:lang_x_official":[
        "eng"
    ],
    "wof:lang_x_spoken":[
        "eng",
        "zul",
        "xho",
        "afr",
        "nso",
        "tsn",
        "sot",
        "tso",
        "ssw",
        "ven",
        "nbl"
    ],
    "wof:name":"Marnitz",
    "wof:placetype":"locality"
},
  "geometry": {"coordinates":[28.21071,-23.16296],"type":"Point"}
}