{
  "type": "Feature",
  "properties": {
    "gn:admin1_code":"11.0",
    "gn:asciiname":"Victoria Bay",
    "gn:country_code":"ZA",
    "gn:dem":22,
    "gn:feature_class":"P",
    "gn:feature_code":"PPL",
    "gn:name":"Victoria Bay",
    "gn:population":0,
    "gn:timezone":"Africa/Johannesburg",
    "iso:country":"ZA",
    "name:afr_x_preferred":[
        "Victoriabaai"
    ],
    "name:nld_x_preferred":[
        "Victoriabaai"
    ],
    "wof:name":"Victoria Bay",
    "wof:placetype":"locality"
},
  "geometry": {"coordinates":[22.55287,-34.00486],"type":"Point"}
}