{
  "type": "Feature",
  "properties": {
    "gn:admin1_code":"3",
    "gn:admin2_code":"DC16",
    "gn:admin3_code":"FS163",
    "gn:asciiname":"Excelsior",
    "gn:country_code":"ZA",
    "gn:dem":1489,
    "gn:feature_class":"P",
    "gn:feature_code":"PPL",
    "gn:name":"Excelsior",
    "gn:population":0,
    "gn:timezone":"Africa/Johannesburg",
    "iso:country":"ZA",
    "name:bar_x_preferred":[
        "Excelsior"
    ],
    "name:ceb_x_preferred":[
        "Excelsior"
    ],
    "name:ces_x_preferred":[
        "Excelsior"
    ],
    "name:deu_x_preferred":[
        "Excelsior"
    ],
    "name:epo_x_preferred":[
        "Ekscelsior"
    ],
    "name:eus_x_preferred":[
        "Excelsior"
    ],
    "name:fin_x_preferred":[
        "Excelsior"
    ],
    "name:fra_x_preferred":[
        "Excelsior"
    ],
    "name:ita_x_preferred":[
        "Excelsior"
    ],
    "name:jpn_x_preferred":[
        "\u30a8\u30af\u30bb\u30eb\u30b7\u30aa\u30fc\u30eb"
    ],
    "name:nld_x_preferred":[
        "Excelsior"
    ],
    "name:pol_x_preferred":[
        "Excelsior"
    ],
    "name:ron_x_preferred":[
        "Excelsior"
    ],
    "name:rus_x_preferred":[
        "Excelsior"
    ],
    "name:slk_x_preferred":[
        "Excelsior"
    ],
    "name:spa_x_preferred":[
        "Excelsior"
    ],
    "name:swe_x_preferred":[
        "Excelsior"
    ],
    "name:ukr_x_preferred":[
        "\u0415\u043a\u0441\u0435\u043b\u0441\u0456\u043e\u0440"
    ],
    "name:vol_x_preferred":[
        "Excelsior"
    ],
    "wof:lang_x_official":[
        "eng"
    ],
    "wof:lang_x_spoken":[
        "eng",
        "zul",
        "xho",
        "afr",
        "nso",
        "tsn",
        "sot",
        "tso",
        "ssw",
        "ven",
        "nbl"
    ],
    "wof:name":"Excelsior",
    "wof:placetype":"locality"
},
  "geometry": {"coordinates":[26.9532,-30.531],"type":"Point"}
}