{
  "type": "Feature",
  "properties": {
    "gn:admin1_code":"3",
    "gn:admin2_code":"DC16",
    "gn:admin3_code":"FS164",
    "gn:asciiname":"Collingham",
    "gn:country_code":"ZA",
    "gn:dem":1563,
    "gn:feature_class":"P",
    "gn:feature_code":"PPL",
    "gn:name":"Collingham",
    "gn:population":0,
    "gn:timezone":"Africa/Johannesburg",
    "iso:country":"ZA",
    "name:ceb_x_preferred":[
        "Collingham"
    ],
    "name:fra_x_preferred":[
        "Collingham"
    ],
    "name:nld_x_preferred":[
        "Collingham"
    ],
    "name:pol_x_preferred":[
        "Collingham"
    ],
    "wof:name":"Collingham",
    "wof:placetype":"locality"
},
  "geometry": {"coordinates":[26.75,-29.65],"type":"Point"}
}