{
  "type": "Feature",
  "properties": {
    "gn:admin1_code":"10",
    "gn:admin2_code":"DC40",
    "gn:admin3_code":"NW402",
    "gn:asciiname":"Haaskraal",
    "gn:country_code":"ZA",
    "gn:dem":1350,
    "gn:feature_class":"P",
    "gn:feature_code":"PPL",
    "gn:name":"Haaskraal",
    "gn:population":0,
    "gn:timezone":"Africa/Johannesburg",
    "iso:country":"ZA",
    "wof:name":"Haaskraal",
    "wof:placetype":"locality"
},
  "geometry": {"coordinates":[27.03481,-26.76804000000001],"type":"Point"}
}