{
  "type": "Feature",
  "properties": {
    "gn:admin1_code":"8",
    "gn:admin2_code":"DC7",
    "gn:admin3_code":"NC077",
    "gn:asciiname":"Marydale",
    "gn:country_code":"ZA",
    "gn:dem":982,
    "gn:feature_class":"P",
    "gn:feature_code":"PPL",
    "gn:name":"Marydale",
    "gn:population":0,
    "gn:timezone":"Africa/Johannesburg",
    "iso:country":"ZA",
    "name:afr_x_preferred":[
        "Marydale"
    ],
    "name:deu_x_preferred":[
        "Marydale"
    ],
    "name:est_x_preferred":[
        "Marydale"
    ],
    "name:nld_x_preferred":[
        "Marydale"
    ],
    "name:nso_x_preferred":[
        "Marydale"
    ],
    "name:ron_x_preferred":[
        "Marydale"
    ],
    "wof:name":"Marydale",
    "wof:placetype":"locality"
},
  "geometry": {"coordinates":[22.10654,-29.40739],"type":"Point"}
}