{
  "type": "Feature",
  "properties": {
    "gn:admin1_code":"2",
    "gn:admin2_code":"DC28",
    "gn:admin3_code":"KZN286",
    "gn:asciiname":"Fort Louis",
    "gn:country_code":"ZA",
    "gn:dem":1192,
    "gn:feature_class":"P",
    "gn:feature_code":"PPL",
    "gn:name":"Fort Louis",
    "gn:population":0,
    "gn:timezone":"Africa/Johannesburg",
    "iso:country":"ZA",
    "name:deu_x_preferred":[
        "Fort Louis"
    ],
    "name:fra_x_preferred":[
        "Fort Louis"
    ],
    "wof:name":"Fort Louis",
    "wof:placetype":"locality"
},
  "geometry": {"coordinates":[30.95342,-28.41186],"type":"Point"}
}