{
  "type": "Feature",
  "properties": {
    "gn:admin1_code":"2",
    "gn:admin2_code":"DC28",
    "gn:admin3_code":"KZN281",
    "gn:asciiname":"Aboyne",
    "gn:country_code":"ZA",
    "gn:dem":38,
    "gn:feature_class":"P",
    "gn:feature_code":"PPL",
    "gn:name":"Aboyne",
    "gn:population":0,
    "gn:timezone":"Africa/Johannesburg",
    "iso:country":"ZA",
    "name:ceb_x_preferred":[
        "Aboyne"
    ],
    "name:cym_x_preferred":[
        "Aboyne"
    ],
    "name:deu_x_preferred":[
        "Aboyne"
    ],
    "name:eus_x_preferred":[
        "Aboyne"
    ],
    "name:fas_x_preferred":[
        "\u0627\u0628\u06cc\u0648\u0646"
    ],
    "name:fra_x_preferred":[
        "Aboyne"
    ],
    "name:gla_x_preferred":[
        "Ab\u00e8idh"
    ],
    "name:gle_x_preferred":[
        "Ab\u00e9idh"
    ],
    "name:ita_x_preferred":[
        "Aboyne"
    ],
    "name:nno_x_preferred":[
        "Aboyne"
    ],
    "name:nor_x_preferred":[
        "Aboyne"
    ],
    "name:pol_x_preferred":[
        "Aboyne"
    ],
    "name:sco_x_preferred":[
        "Abyne"
    ],
    "name:spa_x_preferred":[
        "Aboyne"
    ],
    "name:swe_x_preferred":[
        "Aboyne"
    ],
    "wof:name":"Aboyne",
    "wof:placetype":"locality"
},
  "geometry": {"coordinates":[32.03333,-28.66667],"type":"Point"}
}