{
  "type": "Feature",
  "properties": {
    "gn:admin1_code":"2",
    "gn:admin2_code":"DC28",
    "gn:admin3_code":"KZN281",
    "gn:asciiname":"Aboyne",
    "gn:country_code":"ZA",
    "gn:dem":38,
    "gn:feature_class":"P",
    "gn:feature_code":"PPL",
    "gn:name":"Aboyne",
    "gn:population":0,
    "gn:timezone":"Africa/Johannesburg",
    "iso:country":"ZA",
    "wof:name":"Aboyne",
    "wof:placetype":"locality"
},
  "geometry": {"coordinates":[32.03333,-28.66667],"type":"Point"}
}