{
  "type": "Feature",
  "properties": {
    "gn:country":"ZA",
    "iso:country":"ZA",
    "qs_pg:aaroncc":"ZA",
    "qs_pg:gn_country":"ZA",
    "qs_pg:name":"Meer en See",
    "qs_pg:name_adm0":"South Africa",
    "qs_pg:name_adm1":"Kwazulu Natal",
    "qs_pg:photos":78,
    "qs_pg:photos_1k":16,
    "qs_pg:photos_9k":1,
    "qs_pg:photos_9r":3,
    "qs_pg:photos_all":78,
    "qs_pg:photos_sr":3,
    "qs_pg:pop_sr":0,
    "qs_pg:qs_pg_placetype":"locality",
    "qs_pg:qs_pg_placetype_gp":"Town",
    "qs_pg:woe_adm0":23424942,
    "woe:adm0_id":23424942,
    "woe:name_adm0":"South Africa",
    "woe:name_adm1":"Kwazulu Natal",
    "woe:placetype":"Town",
    "wof:name":"Meer en See",
    "wof:placetype":"locality"
},
  "geometry": {"coordinates":[32.0986385,-28.791638],"type":"Point"}
}