{
  "type": "Feature",
  "properties": {
    "gn:admin1_code":"8",
    "gn:admin2_code":"DC7",
    "gn:admin3_code":"NC074",
    "gn:asciiname":"Droogeboom",
    "gn:country_code":"ZA",
    "gn:dem":1317,
    "gn:feature_class":"P",
    "gn:feature_code":"PPL",
    "gn:name":"Droogeboom",
    "gn:population":0,
    "gn:timezone":"Africa/Johannesburg",
    "iso:country":"ZA",
    "wof:name":"Droogeboom",
    "wof:placetype":"locality"
},
  "geometry": {"coordinates":[21.68333,-30.91667],"type":"Point"}
}