{
  "type": "Feature",
  "properties": {
    "gn:country":"ZA",
    "gn:fcode":"ADM3",
    "gn:population":175372,
    "iso:country":"ZA",
    "qs_pg:aaroncc":"ZA",
    "qs_pg:gn_country":"ZA",
    "qs_pg:gn_fcode":"ADM3",
    "qs_pg:gn_pop":175372,
    "qs_pg:name":"uMlalazi",
    "qs_pg:photos_9r":0,
    "qs_pg:photos_sr":0,
    "qs_pg:pop_sr":9,
    "qs_pg:qs_pg_placetype":"localadmin",
    "wof:name":"uMlalazi",
    "wof:placetype":"localadmin",
    "wof:population":175372
},
  "geometry": {"coordinates":[31.4449,-28.90486],"type":"Point"}
}