{
  "type": "Feature",
  "properties": {
    "gn:admin1_code":"5",
    "gn:admin2_code":"DC10",
    "gn:admin3_code":"EC108",
    "gn:asciiname":"De Mistkraal",
    "gn:country_code":"ZA",
    "gn:dem":86,
    "gn:feature_class":"P",
    "gn:feature_code":"PPL",
    "gn:name":"De Mistkraal",
    "gn:population":0,
    "gn:timezone":"Africa/Johannesburg",
    "iso:country":"ZA",
    "name:und_x_variant":[
        "Mistkraal",
        "Miskraal",
        "De Mistkraal"
    ],
    "wof:name":"De Mistkraal",
    "wof:placetype":"locality"
},
  "geometry": {"coordinates":[24.7101,-33.74278],"type":"Point"}
}