{
  "type": "Feature",
  "properties": {
    "gn:admin1_code":"11.0",
    "gn:admin2_code":"CPT",
    "gn:admin3_code":"CPT",
    "gn:asciiname":"Steelwater",
    "gn:country_code":"ZA",
    "gn:dem":76,
    "gn:feature_class":"P",
    "gn:feature_code":"PPL",
    "gn:name":"Steelwater",
    "gn:population":0,
    "gn:timezone":"Africa/Johannesburg",
    "iso:country":"ZA",
    "wof:name":"Steelwater",
    "wof:placetype":"locality"
},
  "geometry": {"coordinates":[18.58848,-33.69935],"type":"Point"}
}