{
  "type": "Feature",
  "properties": {
    "gn:admin1_code":"9.0",
    "gn:admin2_code":"DC36",
    "gn:admin3_code":"LIM365",
    "gn:asciiname":"Tweetstroom",
    "gn:country_code":"ZA",
    "gn:dem":1201,
    "gn:feature_class":"P",
    "gn:feature_code":"PPL",
    "gn:name":"Tweetstroom",
    "gn:population":0,
    "gn:timezone":"Africa/Johannesburg",
    "iso:country":"ZA",
    "wof:name":"Tweetstroom",
    "wof:placetype":"locality"
},
  "geometry": {"coordinates":[28.10779,-24.42628],"type":"Point"}
}