{
  "type": "Feature",
  "properties": {
    "gn:admin1_code":"7.0",
    "gn:admin2_code":"DC32",
    "gn:admin3_code":"MP322",
    "gn:asciiname":"Nyongane",
    "gn:country_code":"ZA",
    "gn:dem":518,
    "gn:feature_class":"P",
    "gn:feature_code":"PPL",
    "gn:name":"Nyongane",
    "gn:population":0,
    "gn:timezone":"Africa/Johannesburg",
    "iso:country":"ZA",
    "wof:name":"Nyongane",
    "wof:placetype":"locality"
},
  "geometry": {"coordinates":[31.1907,-25.05264],"type":"Point"}
}