{
  "type": "Feature",
  "properties": {
    "gn:admin1_code":"5",
    "gn:admin2_code":"DC13",
    "gn:admin3_code":"EC137",
    "gn:asciiname":"KuDidi",
    "gn:country_code":"ZA",
    "gn:dem":757,
    "gn:feature_class":"P",
    "gn:feature_code":"PPL",
    "gn:name":"KuDidi",
    "gn:population":0,
    "gn:timezone":"Africa/Johannesburg",
    "iso:country":"ZA",
    "name:und_x_variant":[
        "Didi",
        "KuDidi"
    ],
    "wof:name":"KuDidi",
    "wof:placetype":"locality"
},
  "geometry": {"coordinates":[28.28578,-31.7074],"type":"Point"}
}