{
  "type": "Feature",
  "properties": {
    "gn:admin1_code":"5",
    "gn:admin2_code":"DC14",
    "gn:admin3_code":"EC141",
    "gn:asciiname":"Philipsrust",
    "gn:country_code":"ZA",
    "gn:dem":2001,
    "gn:feature_class":"P",
    "gn:feature_code":"PPL",
    "gn:name":"Philipsrust",
    "gn:population":0,
    "gn:timezone":"Africa/Johannesburg",
    "iso:country":"ZA",
    "wof:name":"Philipsrust",
    "wof:placetype":"locality"
},
  "geometry": {"coordinates":[28.22214,-30.71179],"type":"Point"}
}