{
  "type": "Feature",
  "properties": {
    "gn:admin1_code":"5.0",
    "gn:admin2_code":"NMA",
    "gn:admin3_code":"NMA",
    "gn:asciiname":"The Springs",
    "gn:country_code":"ZA",
    "gn:dem":175,
    "gn:feature_class":"P",
    "gn:feature_code":"PPL",
    "gn:name":"The Springs",
    "gn:population":0,
    "gn:timezone":"Africa/Johannesburg",
    "iso:country":"ZA",
    "wof:name":"The Springs",
    "wof:placetype":"locality"
},
  "geometry": {"coordinates":[25.43658,-33.70207],"type":"Point"}
}