{
  "type": "Feature",
  "properties": {
    "gn:admin1_code":"5",
    "gn:admin2_code":"DC44",
    "gn:admin3_code":"EC441",
    "gn:asciiname":"Mateleng",
    "gn:country_code":"ZA",
    "gn:dem":1627,
    "gn:feature_class":"P",
    "gn:feature_code":"PPL",
    "gn:name":"Mateleng",
    "gn:population":0,
    "gn:timezone":"Africa/Johannesburg",
    "iso:country":"ZA",
    "wof:name":"Mateleng",
    "wof:placetype":"locality"
},
  "geometry": {"coordinates":[28.42554,-30.34865],"type":"Point"}
}