{
  "type": "Feature",
  "properties": {
    "gn:admin1_code":"2",
    "gn:admin2_code":"DC24",
    "gn:admin3_code":"KZN244",
    "gn:asciiname":"Mount Saint Bernard",
    "gn:country_code":"ZA",
    "gn:dem":759,
    "gn:feature_class":"P",
    "gn:feature_code":"PPL",
    "gn:name":"Mount Saint Bernard",
    "gn:population":0,
    "gn:timezone":"Africa/Johannesburg",
    "iso:country":"ZA",
    "wof:name":"Mount Saint Bernard",
    "wof:placetype":"locality"
},
  "geometry": {"coordinates":[30.38173,-28.91284000000001],"type":"Point"}
}