{
  "type": "Feature",
  "properties": {
    "gn:country":"ZA",
    "gn:fcode":"PPLA3",
    "gn:population":17946,
    "iso:country":"ZA",
    "name:afr_x_preferred":[
        "Warrenton"
    ],
    "name:ast_x_preferred":[
        "Warrenton"
    ],
    "name:ceb_x_preferred":[
        "Warrenton"
    ],
    "name:dan_x_preferred":[
        "Warrenton"
    ],
    "name:deu_x_preferred":[
        "Warrenton"
    ],
    "name:eng_x_preferred":[
        "Warrenton"
    ],
    "name:est_x_preferred":[
        "Warrenton"
    ],
    "name:ita_x_preferred":[
        "Warrenton"
    ],
    "name:jpn_x_preferred":[
        "\u30a6\u30a9\u30ec\u30f3\u30c8\u30f3"
    ],
    "name:nld_x_preferred":[
        "Warrenton"
    ],
    "name:nso_x_preferred":[
        "Warrenton"
    ],
    "name:pol_x_preferred":[
        "Warrenton"
    ],
    "name:ron_x_preferred":[
        "Warrenton"
    ],
    "name:zho_x_preferred":[
        "\u6c83\u502b\u9813"
    ],
    "name:zul_x_preferred":[
        "IWarrenton"
    ],
    "qs_pg:aaroncc":"ZA",
    "qs_pg:gn_country":"ZA",
    "qs_pg:gn_fcode":"PPLA3",
    "qs_pg:gn_pop":17946,
    "qs_pg:name":"Warrenton",
    "qs_pg:photos_9r":0,
    "qs_pg:photos_sr":0,
    "qs_pg:pop_sr":6,
    "qs_pg:qs_pg_placetype":"locality",
    "wof:lang_x_official":[
        "eng"
    ],
    "wof:lang_x_spoken":[
        "eng",
        "zul",
        "xho",
        "afr",
        "nso",
        "tsn",
        "sot",
        "tso",
        "ssw",
        "ven",
        "nbl"
    ],
    "wof:name":"Warrenton",
    "wof:placetype":"locality",
    "wof:population":17946
},
  "geometry": {"coordinates":[24.84753,-28.11396],"type":"Point"}
}