{
  "type": "Feature",
  "properties": {
    "gn:admin1_code":"9",
    "gn:admin2_code":"DC35",
    "gn:admin3_code":"LIM351",
    "gn:asciiname":"Motshitong",
    "gn:country_code":"ZA",
    "gn:dem":935,
    "gn:feature_class":"P",
    "gn:feature_code":"PPL",
    "gn:name":"Motshitong",
    "gn:population":0,
    "gn:timezone":"Africa/Johannesburg",
    "iso:country":"ZA",
    "wof:name":"Motshitong",
    "wof:placetype":"locality"
},
  "geometry": {"coordinates":[28.95134,-23.01057],"type":"Point"}
}