{
  "type": "Feature",
  "properties": {
    "gn:admin1_code":"7",
    "gn:admin2_code":"DC32",
    "gn:admin3_code":"MP322",
    "gn:asciiname":"Barretts",
    "gn:country_code":"ZA",
    "gn:dem":1333,
    "gn:feature_class":"P",
    "gn:feature_code":"PPL",
    "gn:name":"Barretts",
    "gn:population":0,
    "gn:timezone":"Africa/Johannesburg",
    "iso:country":"ZA",
    "wof:name":"Barretts",
    "wof:placetype":"locality"
},
  "geometry": {"coordinates":[30.73333,-25.55],"type":"Point"}
}