{
  "type": "Feature",
  "properties": {
    "gn:admin1_code":"9",
    "gn:admin2_code":"DC33",
    "gn:admin3_code":"LIM333",
    "gn:asciiname":"Makhwibiding",
    "gn:country_code":"ZA",
    "gn:dem":668,
    "gn:feature_class":"P",
    "gn:feature_code":"PPL",
    "gn:name":"Makhwibiding",
    "gn:population":0,
    "gn:timezone":"Africa/Johannesburg",
    "iso:country":"ZA",
    "wof:name":"Makhwibiding",
    "wof:placetype":"locality"
},
  "geometry": {"coordinates":[30.2675,-24.02565],"type":"Point"}
}