{
  "type": "Feature",
  "properties": {
    "gn:admin1_code":"7",
    "gn:admin2_code":"DC32",
    "gn:admin3_code":"MP321",
    "gn:asciiname":"Doornkop",
    "gn:country_code":"ZA",
    "gn:dem":1541,
    "gn:feature_class":"P",
    "gn:feature_code":"PPL",
    "gn:name":"Doornkop",
    "gn:population":0,
    "gn:timezone":"Africa/Johannesburg",
    "iso:country":"ZA",
    "name:ceb_x_preferred":[
        "Doornkop"
    ],
    "name:tur_x_preferred":[
        "Doornkop"
    ],
    "wof:name":"Doornkop",
    "wof:placetype":"locality"
},
  "geometry": {"coordinates":[30.46902,-25.18696],"type":"Point"}
}