{
  "type": "Feature",
  "properties": {
    "gn:admin1_code":"10",
    "gn:admin2_code":"DC37",
    "gn:admin3_code":"NW372",
    "gn:asciiname":"Kwarriekraal",
    "gn:country_code":"ZA",
    "gn:dem":1051,
    "gn:feature_class":"P",
    "gn:feature_code":"PPL",
    "gn:name":"Kwarriekraal",
    "gn:population":0,
    "gn:timezone":"Africa/Johannesburg",
    "iso:country":"ZA",
    "wof:name":"Kwarriekraal",
    "wof:placetype":"locality"
},
  "geometry": {"coordinates":[27.64132,-25.05343],"type":"Point"}
}