{
  "type": "Feature",
  "properties": {
    "gn:admin1_code":"3.0",
    "gn:admin2_code":"DC16",
    "gn:admin3_code":"FS164",
    "gn:asciiname":"Vaalbank (2)",
    "gn:country_code":"ZA",
    "gn:dem":1554,
    "gn:feature_class":"P",
    "gn:feature_code":"PPL",
    "gn:name":"Vaalbank (2)",
    "gn:population":0,
    "gn:timezone":"Africa/Johannesburg",
    "iso:country":"ZA",
    "wof:name":"Vaalbank (2)",
    "wof:placetype":"locality"
},
  "geometry": {"coordinates":[26.56112000000001,-29.62192000000001],"type":"Point"}
}