{
  "type": "Feature",
  "properties": {
    "gn:admin1_code":"3.0",
    "gn:admin2_code":"DC16",
    "gn:admin3_code":"FS164",
    "gn:asciiname":"Vaalbank (2)",
    "gn:country_code":"ZA",
    "gn:dem":1554,
    "gn:feature_class":"P",
    "gn:feature_code":"PPL",
    "gn:name":"Vaalbank (2)",
    "gn:population":0,
    "gn:timezone":"Africa/Johannesburg",
    "iso:country":"ZA",
    "wof:lang_x_official":[
        "eng"
    ],
    "wof:lang_x_spoken":[
        "eng",
        "zul",
        "xho",
        "afr",
        "nso",
        "tsn",
        "sot",
        "tso",
        "ssw",
        "ven",
        "nbl"
    ],
    "wof:name":"Vaalbank (2)",
    "wof:placetype":"locality"
},
  "geometry": {"coordinates":[26.56112,-29.62192],"type":"Point"}
}