{
  "type": "Feature",
  "properties": {
    "gn:admin1_code":"5",
    "gn:admin2_code":"DC13",
    "gn:admin3_code":"EC132",
    "gn:asciiname":"Elandsberg",
    "gn:country_code":"ZA",
    "gn:dem":1275,
    "gn:feature_class":"P",
    "gn:feature_code":"PPL",
    "gn:name":"Elandsberg",
    "gn:population":0,
    "gn:timezone":"Africa/Johannesburg",
    "iso:country":"ZA",
    "wof:name":"Elandsberg",
    "wof:placetype":"locality"
},
  "geometry": {"coordinates":[25.68141,-31.88524],"type":"Point"}
}