{
  "type": "Feature",
  "properties": {
    "gn:admin1_code":"3.0",
    "gn:admin2_code":"DC19",
    "gn:admin3_code":"FS195",
    "gn:asciiname":"Waterbult",
    "gn:country_code":"ZA",
    "gn:dem":1994,
    "gn:feature_class":"P",
    "gn:feature_code":"PPL",
    "gn:name":"Waterbult",
    "gn:population":0,
    "gn:timezone":"Africa/Johannesburg",
    "iso:country":"ZA",
    "wof:name":"Waterbult",
    "wof:placetype":"locality"
},
  "geometry": {"coordinates":[29.45,-27.78333],"type":"Point"}
}