{
  "type": "Feature",
  "properties": {
    "gn:admin1_code":"8",
    "gn:admin2_code":"DC8",
    "gn:admin3_code":"NC083",
    "gn:asciiname":"Lambrechtsdrif",
    "gn:country_code":"ZA",
    "gn:dem":836,
    "gn:feature_class":"P",
    "gn:feature_code":"PPL",
    "gn:name":"Lambrechtsdrif",
    "gn:population":0,
    "gn:timezone":"Africa/Johannesburg",
    "iso:country":"ZA",
    "name:und_x_variant":[
        "Lambrechts Drift",
        "Lambrechtsdrif"
    ],
    "wof:name":"Lambrechtsdrif",
    "wof:placetype":"locality"
},
  "geometry": {"coordinates":[21.69442,-28.4967],"type":"Point"}
}