{
  "type": "Feature",
  "properties": {
    "gn:admin1_code":"5",
    "gn:admin2_code":"DC14",
    "gn:admin3_code":"EC144",
    "gn:asciiname":"Pleisterkraal",
    "gn:country_code":"ZA",
    "gn:dem":1399,
    "gn:feature_class":"P",
    "gn:feature_code":"PPL",
    "gn:name":"Pleisterkraal",
    "gn:population":0,
    "gn:timezone":"Africa/Johannesburg",
    "iso:country":"ZA",
    "wof:name":"Pleisterkraal",
    "wof:placetype":"locality"
},
  "geometry": {"coordinates":[26.02969,-30.95418],"type":"Point"}
}