{
  "type": "Feature",
  "properties": {
    "gn:admin1_code":"2",
    "gn:admin2_code":"DC43",
    "gn:admin3_code":"KZN434",
    "gn:asciiname":"Joubertstroom",
    "gn:country_code":"ZA",
    "gn:dem":414,
    "gn:feature_class":"P",
    "gn:feature_code":"PPL",
    "gn:name":"Joubertstroom",
    "gn:population":0,
    "gn:timezone":"Africa/Johannesburg",
    "iso:country":"ZA",
    "wof:name":"Joubertstroom",
    "wof:placetype":"locality"
},
  "geometry": {"coordinates":[30.15,-29.98333],"type":"Point"}
}