{
  "type": "Feature",
  "properties": {
    "gn:admin1_code":"10",
    "gn:asciiname":"Kgomohute",
    "gn:country_code":"ZA",
    "gn:dem":1239,
    "gn:feature_class":"P",
    "gn:feature_code":"PPL",
    "gn:name":"Kgomohute",
    "gn:population":0,
    "gn:timezone":"Africa/Johannesburg",
    "iso:country":"ZA",
    "wof:name":"Kgomohute",
    "wof:placetype":"locality"
},
  "geometry": {"coordinates":[23.52446,-27.14721],"type":"Point"}
}