{
  "type": "Feature",
  "properties": {
    "iso:country":"ZA",
    "name:ceb_x_preferred":[
        "Morningside"
    ],
    "name:deu_x_preferred":[
        "Morningside"
    ],
    "name:eng_x_preferred":[
        "Morningside"
    ],
    "name:fra_x_preferred":[
        "Morningside"
    ],
    "name:ita_x_preferred":[
        "Morningside"
    ],
    "name:mlg_x_preferred":[
        "Morningside"
    ],
    "name:pol_x_preferred":[
        "Morningside"
    ],
    "name:spa_x_preferred":[
        "Morningside"
    ],
    "name:srp_x_preferred":[
        "\u041c\u043e\u0440\u043d\u0438\u043d\u0433\u0441\u0430\u0458\u0434"
    ],
    "name:swe_x_preferred":[
        "Morningside"
    ],
    "name:ukr_x_preferred":[
        "\u041c\u043e\u0440\u043d\u0456\u043d\u0433\u0441\u0430\u0439\u0434"
    ],
    "name:unk_x_variant":[
        "Morningside"
    ],
    "qs:gn_adm0_cc":"ZA",
    "qs:gn_fcode":"PPLX",
    "qs:gn_local":993800,
    "qs:gn_nam_loc":"Johannesburg, Johannesburg, City of Johannesburg, Gauteng, ZA",
    "qs:gn_namadm1":"06",
    "qs:gn_name":"Morningside",
    "qs:local_max":2766,
    "qs:local_sum":31655,
    "qs:localhoods":69,
    "qs:name":"Morningside",
    "qs:name_adm0":"South Africa",
    "qs:name_adm1":"Gauteng",
    "qs:name_adm2":"City of Johannesburg",
    "qs:name_lau":"Johannesburg",
    "qs:name_local":"Johannesburg",
    "qs:photo_max":8,
    "qs:photo_sum":33,
    "qs:placetype":"Suburb",
    "qs:quad_count":12,
    "qs:woe_adm0":23424942,
    "qs:woe_adm1":2346981,
    "qs:woe_adm2":56189422,
    "qs:woe_lau":56189710,
    "qs:woe_local":1582504,
    "qs:woe_ver":"7.10.0",
    "wof:lang":[
        "eng"
    ],
    "wof:name":"Morningside",
    "wof:placetype":"neighbourhood"
},
  "geometry": {"coordinates":[28.057345,-26.080475],"type":"Point"}
}