{
  "type": "Feature",
  "properties": {
    "gn:admin1_code":"6.0",
    "gn:admin2_code":"JHB",
    "gn:admin3_code":"JHB",
    "gn:asciiname":"Van Wyksrus",
    "gn:country_code":"ZA",
    "gn:dem":1558,
    "gn:feature_class":"P",
    "gn:feature_code":"PPL",
    "gn:name":"Van Wyksrus",
    "gn:population":0,
    "gn:timezone":"Africa/Johannesburg",
    "iso:country":"ZA",
    "name:und_x_variant":[
        "Van Wyksrust",
        "Van Wyksrus"
    ],
    "wof:name":"Van Wyksrus",
    "wof:placetype":"locality"
},
  "geometry": {"coordinates":[27.8797,-26.32517],"type":"Point"}
}