{
  "type": "Feature",
  "properties": {
    "gn:admin1_code":"5",
    "gn:admin2_code":"BUF",
    "gn:admin3_code":"BUF",
    "gn:asciiname":"Fort Murray",
    "gn:country_code":"ZA",
    "gn:dem":371,
    "gn:feature_class":"P",
    "gn:feature_code":"PPL",
    "gn:name":"Fort Murray",
    "gn:population":0,
    "gn:timezone":"Africa/Johannesburg",
    "iso:country":"ZA",
    "wof:name":"Fort Murray",
    "wof:placetype":"locality"
},
  "geometry": {"coordinates":[27.48842,-32.94088],"type":"Point"}
}