{
  "type": "Feature",
  "properties": {
    "gn:admin1_code":"5",
    "gn:admin2_code":"DC14",
    "gn:admin3_code":"EC143",
    "gn:asciiname":"Milner",
    "gn:country_code":"ZA",
    "gn:dem":1573,
    "gn:feature_class":"P",
    "gn:feature_code":"PPL",
    "gn:name":"Milner",
    "gn:population":0,
    "gn:timezone":"Africa/Johannesburg",
    "iso:country":"ZA",
    "name:deu_x_preferred":[
        "Milner"
    ],
    "name:fin_x_preferred":[
        "Milner"
    ],
    "name:fra_x_preferred":[
        "Milner"
    ],
    "name:heb_x_preferred":[
        "\u05de\u05d9\u05dc\u05e0\u05e8"
    ],
    "name:hun_x_preferred":[
        "Milner"
    ],
    "name:ita_x_preferred":[
        "Milner"
    ],
    "name:jpn_x_preferred":[
        "\u30df\u30eb\u30ca\u30fc"
    ],
    "name:nds_x_preferred":[
        "Milner"
    ],
    "name:nld_x_preferred":[
        "Milner"
    ],
    "name:pol_x_preferred":[
        "Milner"
    ],
    "name:por_x_preferred":[
        "Milner"
    ],
    "name:rus_x_preferred":[
        "\u041c\u0438\u043b\u044c\u043d\u0435\u0440"
    ],
    "name:swe_x_preferred":[
        "Milner"
    ],
    "name:tur_x_preferred":[
        "Milner"
    ],
    "wof:lang_x_official":[
        "eng"
    ],
    "wof:lang_x_spoken":[
        "eng",
        "zul",
        "xho",
        "afr",
        "nso",
        "tsn",
        "sot",
        "tso",
        "ssw",
        "ven",
        "nbl"
    ],
    "wof:name":"Milner",
    "wof:placetype":"locality"
},
  "geometry": {"coordinates":[26.98644,-31.22821],"type":"Point"}
}