{
  "type": "Feature",
  "properties": {
    "gn:admin1_code":"3.0",
    "gn:admin2_code":"DC16",
    "gn:admin3_code":"FS163",
    "gn:asciiname":"Wildebeesfontein",
    "gn:country_code":"ZA",
    "gn:dem":1547,
    "gn:feature_class":"P",
    "gn:feature_code":"PPL",
    "gn:name":"Wildebeesfontein",
    "gn:population":0,
    "gn:timezone":"Africa/Johannesburg",
    "iso:country":"ZA",
    "wof:name":"Wildebeesfontein",
    "wof:placetype":"locality"
},
  "geometry": {"coordinates":[26.41138,-29.74154],"type":"Point"}
}