{
  "type": "Feature",
  "properties": {
    "gn:admin1_code":"7",
    "gn:admin2_code":"DC30",
    "gn:admin3_code":"MP305",
    "gn:asciiname":"Nooitgedacht",
    "gn:country_code":"ZA",
    "gn:dem":1629,
    "gn:feature_class":"P",
    "gn:feature_code":"PPL",
    "gn:name":"Nooitgedacht",
    "gn:population":0,
    "gn:timezone":"Africa/Johannesburg",
    "iso:country":"ZA",
    "name:ceb_x_preferred":[
        "Nooitgedacht"
    ],
    "name:fra_x_preferred":[
        "Nooitgedacht"
    ],
    "name:nld_x_preferred":[
        "Nooitgedacht"
    ],
    "wof:lang_x_official":[
        "eng"
    ],
    "wof:lang_x_spoken":[
        "eng",
        "zul",
        "xho",
        "afr",
        "nso",
        "tsn",
        "sot",
        "tso",
        "ssw",
        "ven",
        "nbl"
    ],
    "wof:name":"Nooitgedacht",
    "wof:placetype":"locality"
},
  "geometry": {"coordinates":[29.78311,-26.75004],"type":"Point"}
}