{
  "type": "Feature",
  "properties": {
    "gn:admin1_code":"7.0",
    "gn:admin2_code":"DC31",
    "gn:admin3_code":"MP314",
    "gn:asciiname":"Schoemanskloof",
    "gn:country_code":"ZA",
    "gn:dem":1298,
    "gn:feature_class":"P",
    "gn:feature_code":"PPL",
    "gn:name":"Schoemanskloof",
    "gn:population":0,
    "gn:timezone":"Africa/Johannesburg",
    "iso:country":"ZA",
    "wof:name":"Schoemanskloof",
    "wof:placetype":"locality"
},
  "geometry": {"coordinates":[30.41667,-25.45],"type":"Point"}
}