{
  "type": "Feature",
  "properties": {
    "gn:admin1_code":"7",
    "gn:admin2_code":"DC31",
    "gn:admin3_code":"MP312",
    "gn:asciiname":"Balmoral",
    "gn:country_code":"ZA",
    "gn:dem":1455,
    "gn:feature_class":"P",
    "gn:feature_code":"PPL",
    "gn:name":"Balmoral",
    "gn:population":0,
    "gn:timezone":"Africa/Johannesburg",
    "iso:country":"ZA",
    "wof:name":"Balmoral",
    "wof:placetype":"locality"
},
  "geometry": {"coordinates":[28.97551,-25.8612],"type":"Point"}
}