{
  "type": "Feature",
  "properties": {
    "gn:admin1_code":"5",
    "gn:admin2_code":"DC15",
    "gn:admin3_code":"EC157",
    "gn:asciiname":"Lands End",
    "gn:country_code":"ZA",
    "gn:dem":849,
    "gn:feature_class":"P",
    "gn:feature_code":"PPL",
    "gn:name":"Lands End",
    "gn:population":0,
    "gn:timezone":"Africa/Johannesburg",
    "iso:country":"ZA",
    "name:ben_x_preferred":[
        "\u09b2\u09cd\u09af\u09be\u09a8\u09cd\u09a1\u09b8 \u098f\u09a8\u09cd\u09a1"
    ],
    "name:ell_x_preferred":[
        "\u039b\u03b1\u03bd\u03c4\u03c2 \u0388\u03bd\u03c4"
    ],
    "name:hin_x_preferred":[
        "\u0932\u0948\u0902\u0921\u094d\u0938 \u090f\u0902\u0921"
    ],
    "name:hun_x_preferred":[
        "Lands End"
    ],
    "name:ind_x_preferred":[
        "Lands End"
    ],
    "name:kor_x_preferred":[
        "\ub79c\uc988 \uc5d4\ub4dc"
    ],
    "name:tur_x_preferred":[
        "Lands End"
    ],
    "name:urd_x_preferred":[
        "\u0644\u06cc\u0646\u0688\u0632 \u0627\u06cc\u0646\u0688"
    ],
    "name:vie_x_preferred":[
        "M\u0169i Lands End"
    ],
    "wof:lang_x_official":[
        "eng"
    ],
    "wof:lang_x_spoken":[
        "eng",
        "zul",
        "xho",
        "afr",
        "nso",
        "tsn",
        "sot",
        "tso",
        "ssw",
        "ven",
        "nbl"
    ],
    "wof:name":"Lands End",
    "wof:placetype":"locality"
},
  "geometry": {"coordinates":[28.62045,-31.57601],"type":"Point"}
}