{
  "type": "Feature",
  "properties": {
    "gn:admin1_code":"11.0",
    "gn:admin2_code":"DC1",
    "gn:admin3_code":"WC012",
    "gn:asciiname":"Sandberg",
    "gn:country_code":"ZA",
    "gn:dem":97,
    "gn:feature_class":"P",
    "gn:feature_code":"PPL",
    "gn:name":"Sandberg",
    "gn:population":0,
    "gn:timezone":"Africa/Johannesburg",
    "iso:country":"ZA",
    "wof:name":"Sandberg",
    "wof:placetype":"locality"
},
  "geometry": {"coordinates":[18.56707,-32.29173],"type":"Point"}
}