{
  "type": "Feature",
  "properties": {
    "gn:admin1_code":"11.0",
    "gn:admin2_code":"DC1",
    "gn:admin3_code":"WC012",
    "gn:asciiname":"Sandberg",
    "gn:country_code":"ZA",
    "gn:dem":97,
    "gn:feature_class":"P",
    "gn:feature_code":"PPL",
    "gn:name":"Sandberg",
    "gn:population":0,
    "gn:timezone":"Africa/Johannesburg",
    "iso:country":"ZA",
    "name:ara_x_preferred":[
        "\u062c\u0627\u0643\u0633\u0648\u0646"
    ],
    "name:ceb_x_preferred":[
        "Sandberg"
    ],
    "name:deu_x_preferred":[
        "Sandberg"
    ],
    "name:fra_x_preferred":[
        "Sandberg"
    ],
    "name:heb_x_preferred":[
        "\u05d6\u05e0\u05d3\u05d1\u05e8\u05d2"
    ],
    "name:jpn_x_preferred":[
        "\u30b5\u30f3\u30c9\u30d9\u30ea"
    ],
    "name:kor_x_preferred":[
        "\uc0cc\ub4dc\ubc84\uadf8"
    ],
    "name:nld_x_preferred":[
        "Sandberg"
    ],
    "name:pol_x_preferred":[
        "Sandberg"
    ],
    "name:slk_x_preferred":[
        "Sandberg"
    ],
    "name:swe_x_preferred":[
        "Sandberg"
    ],
    "name:vol_x_preferred":[
        "Sandberg"
    ],
    "wof:name":"Sandberg",
    "wof:placetype":"locality"
},
  "geometry": {"coordinates":[18.56707,-32.29173],"type":"Point"}
}