{
  "type": "Feature",
  "properties": {
    "gn:admin1_code":"7",
    "gn:admin2_code":"DC32",
    "gn:admin3_code":"MP322",
    "gn:asciiname":"Kaapsehoop",
    "gn:country_code":"ZA",
    "gn:dem":1634,
    "gn:feature_class":"P",
    "gn:feature_code":"PPL",
    "gn:name":"Kaapsehoop",
    "gn:population":0,
    "gn:timezone":"Africa/Johannesburg",
    "iso:country":"ZA",
    "name:und_x_variant":[
        "Kaapschehoop",
        "Kaapsehoop"
    ],
    "wof:name":"Kaapsehoop",
    "wof:placetype":"locality"
},
  "geometry": {"coordinates":[30.76762,-25.59045],"type":"Point"}
}