{
  "type": "Feature",
  "properties": {
    "gn:admin1_code":"5",
    "gn:admin2_code":"DC13",
    "gn:admin3_code":"EC132",
    "gn:asciiname":"Heilbron",
    "gn:country_code":"ZA",
    "gn:dem":1477,
    "gn:feature_class":"P",
    "gn:feature_code":"PPL",
    "gn:name":"Heilbron",
    "gn:population":0,
    "gn:timezone":"Africa/Johannesburg",
    "iso:country":"ZA",
    "name:afr_x_preferred":[
        "Heilbron"
    ],
    "name:ceb_x_preferred":[
        "Heilbron"
    ],
    "name:deu_x_preferred":[
        "Heilbron"
    ],
    "name:est_x_preferred":[
        "Heilbron"
    ],
    "name:mlg_x_preferred":[
        "Heilbron"
    ],
    "name:nld_x_preferred":[
        "Heilbron"
    ],
    "name:nso_x_preferred":[
        "Heilbron"
    ],
    "name:pol_x_preferred":[
        "Heilbron"
    ],
    "name:ron_x_preferred":[
        "Heilbron"
    ],
    "name:sot_x_preferred":[
        "Heilbron"
    ],
    "name:spa_x_preferred":[
        "Heilbron"
    ],
    "wof:name":"Heilbron",
    "wof:placetype":"locality"
},
  "geometry": {"coordinates":[26.06337000000001,-31.69522000000001],"type":"Point"}
}