{
  "type": "Feature",
  "properties": {
    "gn:admin1_code":"2",
    "gn:admin2_code":"DC21",
    "gn:admin3_code":"KZN216",
    "gn:asciiname":"Portobello",
    "gn:country_code":"ZA",
    "gn:dem":33,
    "gn:feature_class":"P",
    "gn:feature_code":"PPL",
    "gn:name":"Portobello",
    "gn:population":0,
    "gn:timezone":"Africa/Johannesburg",
    "iso:country":"ZA",
    "name:ceb_x_preferred":[
        "Portobello"
    ],
    "name:deu_x_preferred":[
        "Portobello"
    ],
    "name:eus_x_preferred":[
        "Portobello"
    ],
    "name:fra_x_preferred":[
        "Portobello"
    ],
    "name:heb_x_preferred":[
        "\u05e4\u05d5\u05e8\u05d8\u05d5\u05d1\u05dc\u05d5"
    ],
    "name:ita_x_preferred":[
        "Portobello"
    ],
    "name:nld_x_preferred":[
        "Portobello"
    ],
    "name:por_x_preferred":[
        "Portobello"
    ],
    "name:spa_x_preferred":[
        "Portobello"
    ],
    "name:swe_x_preferred":[
        "Portobello"
    ],
    "wof:lang_x_official":[
        "eng"
    ],
    "wof:lang_x_spoken":[
        "eng",
        "zul",
        "xho",
        "afr",
        "nso",
        "tsn",
        "sot",
        "tso",
        "ssw",
        "ven",
        "nbl"
    ],
    "wof:name":"Portobello",
    "wof:placetype":"locality"
},
  "geometry": {"coordinates":[30.26533,-30.99824],"type":"Point"}
}