{
  "type": "Feature",
  "properties": {
    "gn:admin1_code":"10.0",
    "gn:admin2_code":"DC38",
    "gn:admin3_code":"NW382",
    "gn:asciiname":"Vaalplaats",
    "gn:country_code":"ZA",
    "gn:dem":1377,
    "gn:feature_class":"P",
    "gn:feature_code":"PPL",
    "gn:name":"Vaalplaats",
    "gn:population":0,
    "gn:timezone":"Africa/Johannesburg",
    "iso:country":"ZA",
    "wof:name":"Vaalplaats",
    "wof:placetype":"locality"
},
  "geometry": {"coordinates":[25.65648,-26.32022000000001],"type":"Point"}
}