{
  "type": "Feature",
  "properties": {
    "gn:admin1_code":"5",
    "gn:admin2_code":"DC44",
    "gn:admin3_code":"EC443",
    "gn:asciiname":"Fort Donald",
    "gn:country_code":"ZA",
    "gn:dem":1435,
    "gn:feature_class":"P",
    "gn:feature_code":"PPL",
    "gn:name":"Fort Donald",
    "gn:population":0,
    "gn:timezone":"Africa/Johannesburg",
    "iso:country":"ZA",
    "wof:name":"Fort Donald",
    "wof:placetype":"locality"
},
  "geometry": {"coordinates":[29.55713,-30.75673],"type":"Point"}
}