{
  "type": "Feature",
  "properties": {
    "iso:country":"ZA",
    "name:afr_x_preferred":[
        "Sandton"
    ],
    "name:ara_x_preferred":[
        "\u0633\u0627\u0646\u062f\u062a\u0648\u0646"
    ],
    "name:ceb_x_preferred":[
        "Sandton"
    ],
    "name:dan_x_preferred":[
        "Sandton"
    ],
    "name:deu_x_preferred":[
        "Sandton"
    ],
    "name:eng_x_preferred":[
        "Sandton"
    ],
    "name:fra_x_preferred":[
        "Sandton"
    ],
    "name:ind_x_preferred":[
        "Sandton"
    ],
    "name:jpn_x_preferred":[
        "\u30b5\u30f3\u30c8\u30f3"
    ],
    "name:nld_x_preferred":[
        "Sandton"
    ],
    "name:nso_x_preferred":[
        "Sandton"
    ],
    "name:pol_x_preferred":[
        "Sandton"
    ],
    "name:ron_x_preferred":[
        "Sandton"
    ],
    "name:spa_x_preferred":[
        "Sandton"
    ],
    "name:urd_x_preferred":[
        "\u0633\u0627\u0646\u062f\u062a\u0648\u0646"
    ],
    "name:xho_x_preferred":[
        "Sandton"
    ],
    "name:zul_x_preferred":[
        "Sandton"
    ],
    "wof:lang_x_official":[
        "eng"
    ],
    "wof:lang_x_spoken":[
        "eng",
        "zul",
        "xho",
        "afr",
        "nso",
        "tsn",
        "sot",
        "tso",
        "ssw",
        "ven",
        "nbl"
    ],
    "wof:name":"Sandton",
    "wof:placetype":"neighbourhood"
},
  "geometry": {"coordinates":[28.047632,-26.095643],"type":"Point"}
}