{
  "type": "Feature",
  "properties": {
    "iso:country":"ZA",
    "name:ara_x_preferred":[
        "\u0633\u0627\u0646\u062f\u062a\u0648\u0646"
    ],
    "name:eng_x_preferred":[
        "Sandton"
    ],
    "name:jpn_x_preferred":[
        "\u30b5\u30f3\u30c8\u30f3"
    ],
    "wof:lang":[
        "eng"
    ],
    "wof:name":"Sandton",
    "wof:placetype":"neighbourhood"
},
  "geometry": {"coordinates":[28.047632,-26.095643],"type":"Point"}
}