{
  "type": "Feature",
  "properties": {
    "gn:admin1_code":"6",
    "gn:admin2_code":"DC42",
    "gn:admin3_code":"GT422",
    "gn:asciiname":"Ironside",
    "gn:country_code":"ZA",
    "gn:dem":1541,
    "gn:feature_class":"P",
    "gn:feature_code":"PPL",
    "gn:name":"Ironside",
    "gn:population":0,
    "gn:timezone":"Africa/Johannesburg",
    "iso:country":"ZA",
    "name:deu_x_preferred":[
        "Ironside"
    ],
    "name:fin_x_preferred":[
        "Ironside"
    ],
    "name:fra_x_preferred":[
        "Ironside"
    ],
    "name:jpn_x_preferred":[
        "\u30a2\u30a4\u30a2\u30f3\u30b5\u30a4\u30c9"
    ],
    "name:rus_x_preferred":[
        "\u0410\u0439\u0440\u043e\u043d\u0441\u0430\u0439\u0434"
    ],
    "name:spa_x_preferred":[
        "Ironside"
    ],
    "name:swe_x_preferred":[
        "Ironside"
    ],
    "wof:name":"Ironside",
    "wof:placetype":"locality"
},
  "geometry": {"coordinates":[27.9127,-26.50949],"type":"Point"}
}