{
  "type": "Feature",
  "properties": {
    "gn:admin1_code":"8.0",
    "gn:admin2_code":"DC6",
    "gn:admin3_code":"NC061",
    "gn:asciiname":"Doringrivier",
    "gn:country_code":"ZA",
    "gn:dem":583,
    "gn:feature_class":"P",
    "gn:feature_code":"PPL",
    "gn:name":"Doringrivier",
    "gn:population":0,
    "gn:timezone":"Africa/Johannesburg",
    "iso:country":"ZA",
    "wof:name":"Doringrivier",
    "wof:placetype":"locality"
},
  "geometry": {"coordinates":[17.3676,-28.99693],"type":"Point"}
}