{
  "type": "Feature",
  "properties": {
    "gn:admin1_code":"11.0",
    "gn:admin2_code":"DC3",
    "gn:admin3_code":"WC032",
    "gn:asciiname":"Die Dam",
    "gn:country_code":"ZA",
    "gn:dem":11,
    "gn:feature_class":"P",
    "gn:feature_code":"PPL",
    "gn:name":"Die Dam",
    "gn:population":0,
    "gn:timezone":"Africa/Johannesburg",
    "iso:country":"ZA",
    "wof:name":"Die Dam",
    "wof:placetype":"locality"
},
  "geometry": {"coordinates":[19.68052,-34.77067],"type":"Point"}
}