{
  "type": "Feature",
  "properties": {
    "gn:admin1_code":"8.0",
    "gn:admin2_code":"DC8",
    "gn:admin3_code":"NC084",
    "gn:asciiname":"Witkoppies (1)",
    "gn:country_code":"ZA",
    "gn:dem":944,
    "gn:feature_class":"P",
    "gn:feature_code":"PPL",
    "gn:name":"Witkoppies (1)",
    "gn:population":0,
    "gn:timezone":"Africa/Johannesburg",
    "iso:country":"ZA",
    "wof:lang_x_official":[
        "eng"
    ],
    "wof:lang_x_spoken":[
        "eng",
        "zul",
        "xho",
        "afr",
        "nso",
        "tsn",
        "sot",
        "tso",
        "ssw",
        "ven",
        "nbl"
    ],
    "wof:name":"Witkoppies (1)",
    "wof:placetype":"locality"
},
  "geometry": {"coordinates":[21.40554,-29.59992],"type":"Point"}
}