{
  "type": "Feature",
  "properties": {
    "gn:admin1_code":"6.0",
    "gn:admin2_code":"JHB",
    "gn:admin3_code":"JHB",
    "gn:asciiname":"Dunkeld West",
    "gn:country_code":"ZA",
    "gn:dem":1634,
    "gn:feature_class":"P",
    "gn:feature_code":"PPL",
    "gn:name":"Dunkeld West",
    "gn:population":0,
    "gn:timezone":"Africa/Johannesburg",
    "iso:country":"ZA",
    "name:afr_x_preferred":[
        "Dunkeld-Wes"
    ],
    "wof:lang_x_official":[
        "eng"
    ],
    "wof:lang_x_spoken":[
        "eng",
        "zul",
        "xho",
        "afr",
        "nso",
        "tsn",
        "sot",
        "tso",
        "ssw",
        "ven",
        "nbl"
    ],
    "wof:name":"Dunkeld West",
    "wof:placetype":"neighbourhood"
},
  "geometry": {"coordinates":[28.03445,-26.13276],"type":"Point"}
}