{
  "type": "Feature",
  "properties": {
    "gn:admin1_code":"3",
    "gn:admin2_code":"DC19",
    "gn:admin3_code":"FS192",
    "gn:asciiname":"Letselaskraal",
    "gn:country_code":"ZA",
    "gn:dem":1818,
    "gn:feature_class":"P",
    "gn:feature_code":"PPL",
    "gn:name":"Letselaskraal",
    "gn:population":0,
    "gn:timezone":"Africa/Johannesburg",
    "iso:country":"ZA",
    "wof:name":"Letselaskraal",
    "wof:placetype":"locality"
},
  "geometry": {"coordinates":[28.31667,-28.55],"type":"Point"}
}