{
  "type": "Feature",
  "properties": {
    "gn:admin1_code":"5.0",
    "gn:admin2_code":"DC14",
    "gn:admin3_code":"EC142",
    "gn:asciiname":"Skisazana",
    "gn:country_code":"ZA",
    "gn:dem":1531,
    "gn:feature_class":"P",
    "gn:feature_code":"PPL",
    "gn:name":"Skisazana",
    "gn:population":0,
    "gn:timezone":"Africa/Johannesburg",
    "iso:country":"ZA",
    "wof:name":"Skisazana",
    "wof:placetype":"locality"
},
  "geometry": {"coordinates":[27.22598,-30.52244],"type":"Point"}
}