{
  "type": "Feature",
  "properties": {
    "gn:admin1_code":"5",
    "gn:admin2_code":"DC12",
    "gn:admin3_code":"EC127",
    "gn:asciiname":"Healdton Fingo",
    "gn:country_code":"ZA",
    "gn:dem":767,
    "gn:feature_class":"P",
    "gn:feature_code":"PPLL",
    "gn:name":"Healdton Fingo",
    "gn:population":0,
    "gn:timezone":"Africa/Johannesburg",
    "iso:country":"ZA",
    "wof:name":"Healdton Fingo",
    "wof:placetype":"locality"
},
  "geometry": {"coordinates":[26.66667,-32.73333],"type":"Point"}
}