{
  "type": "Feature",
  "properties": {
    "gn:admin1_code":"9",
    "gn:admin2_code":"DC34",
    "gn:admin3_code":"LIM343",
    "gn:asciiname":"Khalavha",
    "gn:country_code":"ZA",
    "gn:dem":1032,
    "gn:feature_class":"P",
    "gn:feature_code":"PPL",
    "gn:name":"Khalavha",
    "gn:population":0,
    "gn:timezone":"Africa/Johannesburg",
    "iso:country":"ZA",
    "wof:name":"Khalavha",
    "wof:placetype":"locality"
},
  "geometry": {"coordinates":[30.29652,-22.92325],"type":"Point"}
}