{
  "type": "Feature",
  "properties": {
    "gn:admin1_code":"3",
    "gn:admin2_code":"DC19",
    "gn:admin3_code":"FS193",
    "gn:asciiname":"Goede Hoop",
    "gn:country_code":"ZA",
    "gn:dem":1665,
    "gn:feature_class":"P",
    "gn:feature_code":"PPL",
    "gn:name":"Goede Hoop",
    "gn:population":0,
    "gn:timezone":"Africa/Johannesburg",
    "iso:country":"ZA",
    "wof:name":"Goede Hoop",
    "wof:placetype":"locality"
},
  "geometry": {"coordinates":[28.51667,-27.76667],"type":"Point"}
}