{
  "type": "Feature",
  "properties": {
    "gn:country":"ZA",
    "gn:fcode":"FRMT",
    "gn:population":35,
    "iso:country":"ZA",
    "qs_pg:aaroncc":"ZA",
    "qs_pg:gn_country":"ZA",
    "qs_pg:gn_fcode":"FRMT",
    "qs_pg:gn_pop":35,
    "qs_pg:name":"Vadersgawe (God's Gift)",
    "qs_pg:photos_9r":0,
    "qs_pg:photos_sr":0,
    "qs_pg:pop_sr":1,
    "qs_pg:qs_pg_placetype":"locality",
    "wof:lang_x_official":[
        "eng"
    ],
    "wof:lang_x_spoken":[
        "eng",
        "zul",
        "xho",
        "afr",
        "nso",
        "tsn",
        "sot",
        "tso",
        "ssw",
        "ven",
        "nbl"
    ],
    "wof:name":"Vadersgawe (God's Gift)",
    "wof:placetype":"locality",
    "wof:population":35
},
  "geometry": {"coordinates":[19.38333,-33.38333],"type":"Point"}
}