{
  "type": "Feature",
  "properties": {
    "gn:admin1_code":"5",
    "gn:admin2_code":"DC13",
    "gn:admin3_code":"EC132",
    "gn:asciiname":"Bonaparte",
    "gn:country_code":"ZA",
    "gn:dem":1182,
    "gn:feature_class":"P",
    "gn:feature_code":"PPL",
    "gn:name":"Bonaparte",
    "gn:population":0,
    "gn:timezone":"Africa/Johannesburg",
    "iso:country":"ZA",
    "name:cat_x_preferred":[
        "Bonaparte"
    ],
    "name:ceb_x_preferred":[
        "Bonaparte"
    ],
    "name:deu_x_preferred":[
        "Bonaparte"
    ],
    "name:fra_x_preferred":[
        "Bonaparte"
    ],
    "name:ita_x_preferred":[
        "Bonaparte"
    ],
    "name:kor_x_preferred":[
        "\ubcf4\ub098\ud30c\ub974\ud2b8"
    ],
    "name:lav_x_preferred":[
        "Bonaparts"
    ],
    "name:nld_x_preferred":[
        "Bonaparte"
    ],
    "name:nor_x_preferred":[
        "Bonaparte"
    ],
    "name:pol_x_preferred":[
        "Bonaparte"
    ],
    "name:por_x_preferred":[
        "Bonaparte"
    ],
    "name:spa_x_preferred":[
        "Bonaparte"
    ],
    "name:swe_x_preferred":[
        "Bonaparte"
    ],
    "wof:name":"Bonaparte",
    "wof:placetype":"locality"
},
  "geometry": {"coordinates":[26.6485,-31.89043],"type":"Point"}
}