{
  "type": "Feature",
  "properties": {
    "gn:admin1_code":"5",
    "gn:admin2_code":"DC13",
    "gn:admin3_code":"EC132",
    "gn:asciiname":"Bonaparte",
    "gn:country_code":"ZA",
    "gn:dem":1182,
    "gn:feature_class":"P",
    "gn:feature_code":"PPL",
    "gn:name":"Bonaparte",
    "gn:population":0,
    "gn:timezone":"Africa/Johannesburg",
    "iso:country":"ZA",
    "wof:name":"Bonaparte",
    "wof:placetype":"locality"
},
  "geometry": {"coordinates":[26.6485,-31.89043],"type":"Point"}
}