{
  "type": "Feature",
  "properties": {
    "gn:admin1_code":"8.0",
    "gn:admin2_code":"DC6",
    "gn:admin3_code":"NC061",
    "gn:asciiname":"Sanddrif",
    "gn:country_code":"ZA",
    "gn:dem":24,
    "gn:feature_class":"P",
    "gn:feature_code":"PPL",
    "gn:name":"Sanddrif",
    "gn:population":0,
    "gn:timezone":"Africa/Johannesburg",
    "iso:country":"ZA",
    "wof:name":"Sanddrif",
    "wof:placetype":"locality"
},
  "geometry": {"coordinates":[16.77722,-28.42722],"type":"Point"}
}