{
  "type": "Feature",
  "properties": {
    "gn:admin1_code":"9",
    "gn:admin2_code":"DC47",
    "gn:admin3_code":"LIM475",
    "gn:asciiname":"Maphopha",
    "gn:country_code":"ZA",
    "gn:dem":1138,
    "gn:feature_class":"P",
    "gn:feature_code":"PPL",
    "gn:name":"Maphopha",
    "gn:population":0,
    "gn:timezone":"Africa/Johannesburg",
    "iso:country":"ZA",
    "wof:name":"Maphopha",
    "wof:placetype":"locality"
},
  "geometry": {"coordinates":[29.91329,-24.86727],"type":"Point"}
}