{
  "type": "Feature",
  "properties": {
    "gn:admin1_code":"5",
    "gn:admin2_code":"DC13",
    "gn:admin3_code":"EC135",
    "gn:asciiname":"Bolotwa",
    "gn:country_code":"ZA",
    "gn:dem":927,
    "gn:feature_class":"P",
    "gn:feature_code":"PPL",
    "gn:name":"Bolotwa",
    "gn:population":0,
    "gn:timezone":"Africa/Johannesburg",
    "iso:country":"ZA",
    "name:afr_x_preferred":[
        "Bolotwa"
    ],
    "name:est_x_preferred":[
        "Bolotwa"
    ],
    "name:nso_x_preferred":[
        "Bolotwa"
    ],
    "wof:name":"Bolotwa",
    "wof:placetype":"locality"
},
  "geometry": {"coordinates":[27.19129,-31.98666],"type":"Point"}
}