{
  "type": "Feature",
  "properties": {
    "gn:admin1_code":"11.0",
    "gn:admin2_code":"DC3",
    "gn:admin3_code":"WC033",
    "gn:asciiname":"Aasfontein",
    "gn:country_code":"ZA",
    "gn:dem":14,
    "gn:feature_class":"P",
    "gn:feature_code":"PPL",
    "gn:name":"Aasfontein",
    "gn:population":0,
    "gn:timezone":"Africa/Johannesburg",
    "iso:country":"ZA",
    "wof:name":"Aasfontein",
    "wof:placetype":"locality"
},
  "geometry": {"coordinates":[19.85612,-34.7654],"type":"Point"}
}