{
  "type": "Feature",
  "properties": {
    "gn:admin1_code":"5",
    "gn:admin2_code":"DC14",
    "gn:admin3_code":"EC144",
    "gn:asciiname":"Berea",
    "gn:country_code":"ZA",
    "gn:dem":1386,
    "gn:feature_class":"P",
    "gn:feature_code":"PPL",
    "gn:name":"Berea",
    "gn:population":0,
    "gn:timezone":"Africa/Johannesburg",
    "iso:country":"ZA",
    "name:afr_x_preferred":[
        "Berea"
    ],
    "name:cat_x_preferred":[
        "Beroea"
    ],
    "name:ceb_x_preferred":[
        "Berea"
    ],
    "name:deu_x_preferred":[
        "Berea"
    ],
    "name:fin_x_preferred":[
        "Beroia"
    ],
    "name:fra_x_preferred":[
        "Berea"
    ],
    "name:ita_x_preferred":[
        "Beroia"
    ],
    "name:lat_x_preferred":[
        "Beroea"
    ],
    "name:nld_x_preferred":[
        "Berea"
    ],
    "name:pol_x_preferred":[
        "Berea"
    ],
    "name:por_x_preferred":[
        "Berea"
    ],
    "name:rus_x_preferred":[
        "\u0411\u0435\u0440\u0435\u044f"
    ],
    "name:spa_x_preferred":[
        "Berea"
    ],
    "name:srp_x_preferred":[
        "\u0411\u0435\u0440\u0438\u0458\u0430"
    ],
    "name:swe_x_preferred":[
        "Berea"
    ],
    "name:ukr_x_preferred":[
        "\u0411\u0435\u0440\u0456\u044f"
    ],
    "name:vol_x_preferred":[
        "Berea"
    ],
    "wof:lang_x_official":[
        "eng"
    ],
    "wof:lang_x_spoken":[
        "eng",
        "zul",
        "xho",
        "afr",
        "nso",
        "tsn",
        "sot",
        "tso",
        "ssw",
        "ven",
        "nbl"
    ],
    "wof:name":"Berea",
    "wof:placetype":"locality"
},
  "geometry": {"coordinates":[26.37693,-30.93745],"type":"Point"}
}