{
  "type": "Feature",
  "properties": {
    "gn:admin1_code":"5",
    "gn:admin2_code":"DC10",
    "gn:admin3_code":"EC104",
    "gn:asciiname":"Alicedale",
    "gn:country_code":"ZA",
    "gn:dem":313,
    "gn:feature_class":"P",
    "gn:feature_code":"PPL",
    "gn:name":"Alicedale",
    "gn:population":0,
    "gn:timezone":"Africa/Johannesburg",
    "iso:country":"ZA",
    "name:afr_x_preferred":[
        "Alicedale"
    ],
    "name:est_x_preferred":[
        "Alicedale"
    ],
    "name:fas_x_preferred":[
        "\u0627\u0644\u06cc\u0633\u062f\u0627\u0644"
    ],
    "name:nso_x_preferred":[
        "Alicedale"
    ],
    "name:ron_x_preferred":[
        "Alicedale"
    ],
    "name:sot_x_preferred":[
        "Alicedale"
    ],
    "name:tsn_x_preferred":[
        "Alicedale"
    ],
    "wof:name":"Alicedale",
    "wof:placetype":"locality"
},
  "geometry": {"coordinates":[26.09139,-33.31905],"type":"Point"}
}