{
  "type": "Feature",
  "properties": {
    "gn:admin1_code":"6.0",
    "gn:admin2_code":"TSH",
    "gn:admin3_code":"TSH",
    "gn:asciiname":"Winterveldt",
    "gn:country_code":"ZA",
    "gn:dem":1129,
    "gn:feature_class":"P",
    "gn:feature_code":"PPL",
    "gn:name":"Winterveldt",
    "gn:population":0,
    "gn:timezone":"Africa/Johannesburg",
    "iso:country":"ZA",
    "wof:name":"Winterveldt",
    "wof:placetype":"locality"
},
  "geometry": {"coordinates":[28.00793,-25.41461],"type":"Point"}
}