{
  "type": "Feature",
  "properties": {
    "gn:admin1_code":"5",
    "gn:admin2_code":"DC14",
    "gn:admin3_code":"EC144",
    "gn:asciiname":"Hoogstede",
    "gn:country_code":"ZA",
    "gn:dem":1426,
    "gn:feature_class":"P",
    "gn:feature_code":"PPL",
    "gn:name":"Hoogstede",
    "gn:population":0,
    "gn:timezone":"Africa/Johannesburg",
    "iso:country":"ZA",
    "wof:name":"Hoogstede",
    "wof:placetype":"locality"
},
  "geometry": {"coordinates":[26.21595,-30.7602],"type":"Point"}
}