{
  "type": "Feature",
  "properties": {
    "gn:admin1_code":"10",
    "gn:asciiname":"Mmatoro",
    "gn:country_code":"ZA",
    "gn:dem":1076,
    "gn:feature_class":"P",
    "gn:feature_code":"PPL",
    "gn:name":"Mmatoro",
    "gn:population":0,
    "gn:timezone":"Africa/Johannesburg",
    "iso:country":"ZA",
    "wof:name":"Mmatoro",
    "wof:placetype":"locality"
},
  "geometry": {"coordinates":[23.16292,-27.05356],"type":"Point"}
}