{
  "type": "Feature",
  "properties": {
    "gn:admin1_code":"9",
    "gn:admin2_code":"DC34",
    "gn:admin3_code":"LIM344",
    "gn:asciiname":"Chiefs Kraal",
    "gn:country_code":"ZA",
    "gn:dem":789,
    "gn:feature_class":"P",
    "gn:feature_code":"PPL",
    "gn:name":"Chiefs Kraal",
    "gn:population":0,
    "gn:timezone":"Africa/Johannesburg",
    "iso:country":"ZA",
    "wof:name":"Chiefs Kraal",
    "wof:placetype":"locality"
},
  "geometry": {"coordinates":[30.15,-22.88333],"type":"Point"}
}