{
  "type": "Feature",
  "properties": {
    "gn:admin1_code":"5",
    "gn:admin2_code":"DC13",
    "gn:admin3_code":"EC134",
    "gn:asciiname":"KwaManzikraka",
    "gn:country_code":"ZA",
    "gn:dem":1180,
    "gn:feature_class":"P",
    "gn:feature_code":"PPL",
    "gn:name":"KwaManzikraka",
    "gn:population":0,
    "gn:timezone":"Africa/Johannesburg",
    "iso:country":"ZA",
    "wof:name":"KwaManzikraka",
    "wof:placetype":"locality"
},
  "geometry": {"coordinates":[26.71081,-32.1217],"type":"Point"}
}