{
  "type": "Feature",
  "properties": {
    "gn:admin1_code":"5",
    "gn:admin2_code":"DC12",
    "gn:admin3_code":"EC126",
    "gn:asciiname":"KwaJaji",
    "gn:country_code":"ZA",
    "gn:dem":164,
    "gn:feature_class":"P",
    "gn:feature_code":"PPL",
    "gn:name":"KwaJaji",
    "gn:population":0,
    "gn:timezone":"Africa/Johannesburg",
    "iso:country":"ZA",
    "wof:name":"KwaJaji",
    "wof:placetype":"locality"
},
  "geometry": {"coordinates":[27.13273,-33.37869],"type":"Point"}
}