{
  "type": "Feature",
  "properties": {
    "gn:admin1_code":"5",
    "gn:admin2_code":"DC15",
    "gn:admin3_code":"EC156",
    "gn:asciiname":"Mbombo",
    "gn:country_code":"ZA",
    "gn:dem":949,
    "gn:feature_class":"P",
    "gn:feature_code":"PPL",
    "gn:name":"Mbombo",
    "gn:population":0,
    "gn:timezone":"Africa/Johannesburg",
    "iso:country":"ZA",
    "name:cat_x_preferred":[
        "Bumba"
    ],
    "name:fra_x_preferred":[
        "Bumba"
    ],
    "name:ind_x_preferred":[
        "Mbombo"
    ],
    "name:ita_x_preferred":[
        "Bumba"
    ],
    "name:pol_x_preferred":[
        "Bumba"
    ],
    "name:por_x_preferred":[
        "Mbombo"
    ],
    "name:slv_x_preferred":[
        "Bumba"
    ],
    "name:swe_x_preferred":[
        "Mbombo"
    ],
    "wof:lang_x_official":[
        "eng"
    ],
    "wof:lang_x_spoken":[
        "eng",
        "zul",
        "xho",
        "afr",
        "nso",
        "tsn",
        "sot",
        "tso",
        "ssw",
        "ven",
        "nbl"
    ],
    "wof:name":"Mbombo",
    "wof:placetype":"locality"
},
  "geometry": {"coordinates":[29.07769,-31.16008],"type":"Point"}
}