{
  "type": "Feature",
  "properties": {
    "gn:admin1_code":"8",
    "gn:admin2_code":"DC7",
    "gn:admin3_code":"NC077",
    "gn:asciiname":"Klein Gelukpan (2)",
    "gn:country_code":"ZA",
    "gn:dem":1066,
    "gn:feature_class":"P",
    "gn:feature_code":"PPL",
    "gn:name":"Klein Gelukpan (2)",
    "gn:population":0,
    "gn:timezone":"Africa/Johannesburg",
    "iso:country":"ZA",
    "wof:name":"Klein Gelukpan (2)",
    "wof:placetype":"locality"
},
  "geometry": {"coordinates":[21.95479,-29.70926],"type":"Point"}
}