{
  "type": "Feature",
  "properties": {
    "gn:admin1_code":"7",
    "gn:asciiname":"Kuilsrivier",
    "gn:country_code":"ZA",
    "gn:dem":986,
    "gn:feature_class":"P",
    "gn:feature_code":"PPL",
    "gn:name":"Kuilsrivier",
    "gn:population":0,
    "gn:timezone":"Africa/Johannesburg",
    "iso:country":"ZA",
    "wof:name":"Kuilsrivier",
    "wof:placetype":"locality"
},
  "geometry": {"coordinates":[29.15,-25.15],"type":"Point"}
}