{
  "type": "Feature",
  "properties": {
    "gn:admin1_code":"11.0",
    "gn:asciiname":"Kalkoond",
    "gn:country_code":"ZA",
    "gn:dem":39,
    "gn:feature_class":"P",
    "gn:feature_code":"PPL",
    "gn:name":"Kalkoond",
    "gn:population":0,
    "gn:timezone":"Africa/Johannesburg",
    "iso:country":"ZA",
    "wof:name":"Kalkoond",
    "wof:placetype":"locality"
},
  "geometry": {"coordinates":[18.45,-33.78333],"type":"Point"}
}