{
  "type": "Feature",
  "properties": {
    "gn:admin1_code":"8",
    "gn:admin2_code":"DC7",
    "gn:admin3_code":"NC074",
    "gn:asciiname":"Request",
    "gn:country_code":"ZA",
    "gn:dem":1154,
    "gn:feature_class":"P",
    "gn:feature_code":"PPL",
    "gn:name":"Request",
    "gn:population":0,
    "gn:timezone":"Africa/Johannesburg",
    "iso:country":"ZA",
    "name:deu_x_preferred":[
        "Request"
    ],
    "name:hin_x_preferred":[
        "\u0905\u0928\u0941\u0930\u094b\u0927"
    ],
    "name:jpn_x_preferred":[
        "\u30ea\u30af\u30a8\u30b9\u30c8"
    ],
    "name:kor_x_preferred":[
        "\ub9ac\ud018\uc2a4\ud2b8"
    ],
    "wof:lang_x_official":[
        "eng"
    ],
    "wof:lang_x_spoken":[
        "eng",
        "zul",
        "xho",
        "afr",
        "nso",
        "tsn",
        "sot",
        "tso",
        "ssw",
        "ven",
        "nbl"
    ],
    "wof:name":"Request",
    "wof:placetype":"locality"
},
  "geometry": {"coordinates":[22.46667,-30.55],"type":"Point"}
}