{
  "type": "Feature",
  "properties": {
    "gn:admin1_code":"5.0",
    "gn:admin2_code":"DC15",
    "gn:admin3_code":"EC156",
    "gn:asciiname":"Sulenkama",
    "gn:country_code":"ZA",
    "gn:dem":1225,
    "gn:feature_class":"P",
    "gn:feature_code":"PPL",
    "gn:name":"Sulenkama",
    "gn:population":0,
    "gn:timezone":"Africa/Johannesburg",
    "iso:country":"ZA",
    "wof:name":"Sulenkama",
    "wof:placetype":"locality"
},
  "geometry": {"coordinates":[28.68606,-31.01787],"type":"Point"}
}