{
  "type": "Feature",
  "properties": {
    "gn:admin1_code":"11.0",
    "gn:admin2_code":"DC4",
    "gn:admin3_code":"WC044",
    "gn:asciiname":"Saasveld",
    "gn:country_code":"ZA",
    "gn:dem":183,
    "gn:feature_class":"P",
    "gn:feature_code":"PPL",
    "gn:name":"Saasveld",
    "gn:population":0,
    "gn:timezone":"Africa/Johannesburg",
    "iso:country":"ZA",
    "name:afr_x_preferred":[
        "Saasveld"
    ],
    "name:ceb_x_preferred":[
        "Saasveld"
    ],
    "name:fas_x_preferred":[
        "\u0633\u0627\u0633\u200c\u0641\u0644\u062f"
    ],
    "name:fra_x_preferred":[
        "Saasveld"
    ],
    "name:nld_x_preferred":[
        "Saasveld"
    ],
    "name:por_x_preferred":[
        "Saasveld"
    ],
    "name:und_x_variant":[
        "Saarsveld Forestry School"
    ],
    "name:urd_x_preferred":[
        "\u0633\u0627\u0633\u0648\u06cc\u0644\u0688"
    ],
    "wof:name":"Saasveld",
    "wof:placetype":"locality"
},
  "geometry": {"coordinates":[22.54308,-33.96597],"type":"Point"}
}