{
  "type": "Feature",
  "properties": {
    "gn:admin1_code":"3",
    "gn:admin2_code":"MAN",
    "gn:admin3_code":"MAN",
    "gn:asciiname":"Die Vlatke",
    "gn:country_code":"ZA",
    "gn:dem":1306,
    "gn:feature_class":"P",
    "gn:feature_code":"PPL",
    "gn:name":"Die Vlatke",
    "gn:population":0,
    "gn:timezone":"Africa/Johannesburg",
    "iso:country":"ZA",
    "wof:name":"Die Vlatke",
    "wof:placetype":"locality"
},
  "geometry": {"coordinates":[25.93677000000001,-29.07525],"type":"Point"}
}