{
  "type": "Feature",
  "properties": {
    "gn:admin1_code":"5",
    "gn:admin2_code":"DC15",
    "gn:admin3_code":"EC155",
    "gn:asciiname":"Ncambedlana",
    "gn:country_code":"ZA",
    "gn:dem":686,
    "gn:feature_class":"P",
    "gn:feature_code":"PPL",
    "gn:name":"Ncambedlana",
    "gn:population":0,
    "gn:timezone":"Africa/Johannesburg",
    "iso:country":"ZA",
    "wof:name":"Ncambedlana",
    "wof:placetype":"locality"
},
  "geometry": {"coordinates":[28.98089,-31.70797],"type":"Point"}
}