{
  "type": "Feature",
  "properties": {
    "gn:admin1_code":"8",
    "gn:admin2_code":"DC45",
    "gn:admin3_code":"NC453",
    "gn:asciiname":"Dagbreek",
    "gn:country_code":"ZA",
    "gn:dem":1112,
    "gn:feature_class":"P",
    "gn:feature_code":"PPL",
    "gn:name":"Dagbreek",
    "gn:population":0,
    "gn:timezone":"Africa/Johannesburg",
    "iso:country":"ZA",
    "wof:name":"Dagbreek",
    "wof:placetype":"locality"
},
  "geometry": {"coordinates":[22.87789,-27.6006],"type":"Point"}
}