{
  "type": "Feature",
  "properties": {
    "gn:admin1_code":"5",
    "gn:admin2_code":"DC15",
    "gn:admin3_code":"EC156",
    "gn:asciiname":"Ngqubusini",
    "gn:country_code":"ZA",
    "gn:dem":833,
    "gn:feature_class":"P",
    "gn:feature_code":"PPL",
    "gn:name":"Ngqubusini",
    "gn:population":0,
    "gn:timezone":"Africa/Johannesburg",
    "iso:country":"ZA",
    "name:und_x_variant":[
        "Ngubinsa",
        "Ngqubusini"
    ],
    "wof:name":"Ngqubusini",
    "wof:placetype":"locality"
},
  "geometry": {"coordinates":[28.96401,-31.2702],"type":"Point"}
}