{
  "type": "Feature",
  "properties": {
    "gn:admin1_code":"7",
    "gn:admin2_code":"DC32",
    "gn:admin3_code":"MP321",
    "gn:asciiname":"Ga-Sekubu",
    "gn:country_code":"ZA",
    "gn:dem":1627,
    "gn:feature_class":"P",
    "gn:feature_code":"PPL",
    "gn:name":"Ga-Sekubu",
    "gn:population":0,
    "gn:timezone":"Africa/Johannesburg",
    "iso:country":"ZA",
    "wof:name":"Ga-Sekubu",
    "wof:placetype":"locality"
},
  "geometry": {"coordinates":[30.76118,-24.92536],"type":"Point"}
}