{
  "type": "Feature",
  "properties": {
    "gn:admin1_code":"5",
    "gn:admin2_code":"BUF",
    "gn:admin3_code":"BUF",
    "gn:asciiname":"Dongwe",
    "gn:country_code":"ZA",
    "gn:dem":335,
    "gn:feature_class":"P",
    "gn:feature_code":"PPLL",
    "gn:name":"Dongwe",
    "gn:population":0,
    "gn:timezone":"Africa/Johannesburg",
    "iso:country":"ZA",
    "name:ara_x_preferred":[
        "\u062f\u0648\u0646\u063a\u0648\u064a"
    ],
    "name:ben_x_preferred":[
        "\u09a6\u0999\u09cd\u0997\u09cb\u09df\u09c7"
    ],
    "name:deu_x_preferred":[
        "Dongwe"
    ],
    "name:ell_x_preferred":[
        "\u039d\u03c4\u03cc\u03bd\u03b3\u03ba\u03b2\u03b5"
    ],
    "name:fas_x_preferred":[
        "\u062f\u0648\u0646\u06af\u0648\u0647"
    ],
    "name:fra_x_preferred":[
        "Dongwe"
    ],
    "name:heb_x_preferred":[
        "\u05d3\u05d5\u05e0\u05d2\u05d5\u05d5\u05d4"
    ],
    "name:hin_x_preferred":[
        "\u0921\u094b\u0902\u0917\u0935\u0947"
    ],
    "name:hun_x_preferred":[
        "Dongwe"
    ],
    "name:ind_x_preferred":[
        "Dongwe"
    ],
    "name:ita_x_preferred":[
        "Dongwe"
    ],
    "name:jpn_x_preferred":[
        "\u30c9\u30f3\u30b0\u30a6\u30a7\u5ddd"
    ],
    "name:kor_x_preferred":[
        "\ub3d9\uc6e8"
    ],
    "name:nld_x_preferred":[
        "Dongwe"
    ],
    "name:pol_x_preferred":[
        "Dongwe"
    ],
    "name:por_x_preferred":[
        "Dongwe"
    ],
    "name:rus_x_preferred":[
        "\u0440\u0435\u043a\u0430 \u0414\u043e\u043d\u0433\u0443"
    ],
    "name:spa_x_preferred":[
        "Dongwe"
    ],
    "name:swe_x_preferred":[
        "Dongwe"
    ],
    "name:tur_x_preferred":[
        "Dongwe"
    ],
    "name:ukr_x_preferred":[
        "\u0414\u043e\u043d\u0433\u0432\u0435"
    ],
    "name:urd_x_preferred":[
        "\u0688\u0627\u0646\u06af\u0648\u06d2"
    ],
    "name:vie_x_preferred":[
        "S\u00f4ng Dongwe"
    ],
    "name:zho_cn_x_preferred":[
        "\u677e\u5a01\u6cb3"
    ],
    "name:zho_tw_x_preferred":[
        "\u6771\u5a01\u6cb3"
    ],
    "wof:lang_x_official":[
        "eng"
    ],
    "wof:lang_x_spoken":[
        "eng",
        "zul",
        "xho",
        "afr",
        "nso",
        "tsn",
        "sot",
        "tso",
        "ssw",
        "ven",
        "nbl"
    ],
    "wof:name":"Dongwe",
    "wof:placetype":"locality"
},
  "geometry": {"coordinates":[27.56181,-32.93977],"type":"Point"}
}