{
  "type": "Feature",
  "properties": {
    "gn:admin1_code":"5",
    "gn:admin2_code":"BUF",
    "gn:admin3_code":"BUF",
    "gn:asciiname":"Dongwe",
    "gn:country_code":"ZA",
    "gn:dem":335,
    "gn:feature_class":"P",
    "gn:feature_code":"PPLL",
    "gn:name":"Dongwe",
    "gn:population":0,
    "gn:timezone":"Africa/Johannesburg",
    "iso:country":"ZA",
    "wof:name":"Dongwe",
    "wof:placetype":"locality"
},
  "geometry": {"coordinates":[27.56181,-32.93977],"type":"Point"}
}