{
  "type": "Feature",
  "properties": {
    "gn:admin1_code":"5",
    "gn:admin2_code":"DC12",
    "gn:admin3_code":"EC126",
    "gn:asciiname":"KwaMhlekwa",
    "gn:country_code":"ZA",
    "gn:dem":193,
    "gn:feature_class":"P",
    "gn:feature_code":"PPL",
    "gn:name":"KwaMhlekwa",
    "gn:population":0,
    "gn:timezone":"Africa/Johannesburg",
    "iso:country":"ZA",
    "name:und_x_variant":[
        "Mhlekwa",
        "KwaMhlekwa"
    ],
    "wof:name":"KwaMhlekwa",
    "wof:placetype":"locality"
},
  "geometry": {"coordinates":[27.12122,-33.30507],"type":"Point"}
}