{
  "type": "Feature",
  "properties": {
    "gn:admin1_code":"2",
    "gn:admin2_code":"DC22",
    "gn:admin3_code":"KZN221",
    "gn:asciiname":"Krommedraai",
    "gn:country_code":"ZA",
    "gn:dem":760,
    "gn:feature_class":"P",
    "gn:feature_code":"PPL",
    "gn:name":"Krommedraai",
    "gn:population":0,
    "gn:timezone":"Africa/Johannesburg",
    "iso:country":"ZA",
    "wof:name":"Krommedraai",
    "wof:placetype":"locality"
},
  "geometry": {"coordinates":[30.49987,-29.39463],"type":"Point"}
}