{
  "type": "Feature",
  "properties": {
    "gn:admin1_code":"5.0",
    "gn:admin2_code":"DC44",
    "gn:admin3_code":"EC444",
    "gn:asciiname":"Taleni",
    "gn:country_code":"ZA",
    "gn:dem":1086,
    "gn:feature_class":"P",
    "gn:feature_code":"PPL",
    "gn:name":"Taleni",
    "gn:population":0,
    "gn:timezone":"Africa/Johannesburg",
    "iso:country":"ZA",
    "wof:name":"Taleni",
    "wof:placetype":"locality"
},
  "geometry": {"coordinates":[29.19814,-30.99993],"type":"Point"}
}