{
  "type": "Feature",
  "properties": {
    "gn:admin1_code":"7.0",
    "gn:admin2_code":"DC31",
    "gn:admin3_code":"MP312",
    "gn:asciiname":"Rooibloem",
    "gn:country_code":"ZA",
    "gn:dem":1584,
    "gn:feature_class":"P",
    "gn:feature_code":"PPL",
    "gn:name":"Rooibloem",
    "gn:population":0,
    "gn:timezone":"Africa/Johannesburg",
    "iso:country":"ZA",
    "wof:name":"Rooibloem",
    "wof:placetype":"locality"
},
  "geometry": {"coordinates":[29.22315,-26.23135],"type":"Point"}
}