{
  "type": "Feature",
  "properties": {
    "gn:admin1_code":"6",
    "gn:asciiname":"Richmond",
    "gn:country_code":"ZA",
    "gn:dem":1440,
    "gn:feature_class":"P",
    "gn:feature_code":"PPL",
    "gn:name":"Richmond",
    "gn:population":0,
    "gn:timezone":"Africa/Johannesburg",
    "iso:country":"ZA",
    "wof:name":"Richmond",
    "wof:placetype":"locality"
},
  "geometry": {"coordinates":[27.9374,-26.69372000000001],"type":"Point"}
}