{
  "type": "Feature",
  "properties": {
    "gn:admin1_code":"10",
    "gn:asciiname":"Ga-Tatisi",
    "gn:country_code":"ZA",
    "gn:dem":1276,
    "gn:feature_class":"P",
    "gn:feature_code":"PPL",
    "gn:name":"Ga-Tatisi",
    "gn:population":0,
    "gn:timezone":"Africa/Johannesburg",
    "iso:country":"ZA",
    "wof:name":"Ga-Tatisi",
    "wof:placetype":"locality"
},
  "geometry": {"coordinates":[23.9081,-27.02992],"type":"Point"}
}