{
  "type": "Feature",
  "properties": {
    "gn:admin1_code":"9",
    "gn:admin2_code":"DC47",
    "gn:admin3_code":"LIM475",
    "gn:asciiname":"Rietfontein",
    "gn:country_code":"ZA",
    "gn:dem":1144,
    "gn:feature_class":"P",
    "gn:feature_code":"PPL",
    "gn:name":"Rietfontein",
    "gn:population":0,
    "gn:timezone":"Africa/Johannesburg",
    "iso:country":"ZA",
    "wof:name":"Rietfontein",
    "wof:placetype":"locality"
},
  "geometry": {"coordinates":[30.55,-24.61667000000001],"type":"Point"}
}