{
  "type": "Feature",
  "properties": {
    "gn:admin1_code":"9",
    "gn:admin2_code":"DC47",
    "gn:admin3_code":"LIM475",
    "gn:asciiname":"Rietfontein",
    "gn:country_code":"ZA",
    "gn:dem":1144,
    "gn:feature_class":"P",
    "gn:feature_code":"PPL",
    "gn:name":"Rietfontein",
    "gn:population":0,
    "gn:timezone":"Africa/Johannesburg",
    "iso:country":"ZA",
    "name:afr_x_preferred":[
        "Rietfontein"
    ],
    "name:bar_x_preferred":[
        "Rietfontein"
    ],
    "name:ceb_x_preferred":[
        "Rietfontein"
    ],
    "name:est_x_preferred":[
        "Rietfontein"
    ],
    "name:nld_x_preferred":[
        "Rietfontein"
    ],
    "wof:lang_x_official":[
        "eng"
    ],
    "wof:lang_x_spoken":[
        "eng",
        "zul",
        "xho",
        "afr",
        "nso",
        "tsn",
        "sot",
        "tso",
        "ssw",
        "ven",
        "nbl"
    ],
    "wof:name":"Rietfontein",
    "wof:placetype":"locality"
},
  "geometry": {"coordinates":[30.55,-24.61667],"type":"Point"}
}