{
  "type": "Feature",
  "properties": {
    "gn:admin1_code":"7.0",
    "gn:admin2_code":"DC32",
    "gn:admin3_code":"MP325",
    "gn:asciiname":"Rooiboklaagte",
    "gn:country_code":"ZA",
    "gn:dem":636,
    "gn:feature_class":"P",
    "gn:feature_code":"PPL",
    "gn:name":"Rooiboklaagte",
    "gn:population":0,
    "gn:timezone":"Africa/Johannesburg",
    "iso:country":"ZA",
    "name:afr_x_preferred":[
        "Rooiboklaagte"
    ],
    "name:nso_x_preferred":[
        "Rooiboklaagte"
    ],
    "wof:name":"Rooiboklaagte",
    "wof:placetype":"locality"
},
  "geometry": {"coordinates":[31.05886,-24.66173],"type":"Point"}
}