{
  "type": "Feature",
  "properties": {
    "gn:admin1_code":"10",
    "gn:admin2_code":"DC37",
    "gn:admin3_code":"NW373",
    "gn:asciiname":"Boschfroek",
    "gn:country_code":"ZA",
    "gn:dem":1163,
    "gn:feature_class":"P",
    "gn:feature_code":"PPL",
    "gn:name":"Boschfroek",
    "gn:population":0,
    "gn:timezone":"Africa/Johannesburg",
    "iso:country":"ZA",
    "wof:name":"Boschfroek",
    "wof:placetype":"locality"
},
  "geometry": {"coordinates":[27.08333,-25.48333],"type":"Point"}
}