{
  "type": "Feature",
  "properties": {
    "iso:country":"ZA",
    "name:eng_x_preferred":[
        "Central Business District"
    ],
    "name:eng_x_variant":[
        "Central Business District"
    ],
    "name:por_x_preferred":[
        "CBD"
    ],
    "qs:gn_adm0_cc":"ZA",
    "qs:gn_local":993800,
    "qs:gn_nam_loc":"Johannesburg, Johannesburg, City of Johannesburg, Gauteng, ZA",
    "qs:gn_namadm1":"06",
    "qs:local_max":2766,
    "qs:local_sum":31655,
    "qs:localhoods":69,
    "qs:name":"Central Business District",
    "qs:name_adm0":"South Africa",
    "qs:name_adm1":"Gauteng",
    "qs:name_adm2":"City of Johannesburg",
    "qs:name_lau":"Johannesburg",
    "qs:name_local":"Johannesburg",
    "qs:photo_max":131,
    "qs:photo_sum":542,
    "qs:placetype":"Suburb",
    "qs:quad_count":24,
    "qs:woe_adm0":23424942,
    "qs:woe_adm1":2346981,
    "qs:woe_adm2":56189422,
    "qs:woe_lau":56189710,
    "qs:woe_local":1582504,
    "qs:woe_ver":"7.10.0",
    "wd:wordcount":148,
    "wof:lang_x_official":[
        "eng"
    ],
    "wof:lang_x_spoken":[
        "eng",
        "zul",
        "xho",
        "afr",
        "nso",
        "tsn",
        "sot",
        "tso",
        "ssw",
        "ven",
        "nbl"
    ],
    "wof:name":"CBD",
    "wof:placetype":"neighbourhood"
},
  "geometry": {"coordinates":[28.045003,-26.205816],"type":"Point"}
}