{
  "type": "Feature",
  "properties": {
    "gn:admin1_code":"3",
    "gn:admin2_code":"DC16",
    "gn:admin3_code":"FS163",
    "gn:asciiname":"Bothasrus",
    "gn:country_code":"ZA",
    "gn:dem":1598,
    "gn:feature_class":"P",
    "gn:feature_code":"PPL",
    "gn:name":"Bothasrus",
    "gn:population":0,
    "gn:timezone":"Africa/Johannesburg",
    "iso:country":"ZA",
    "wof:name":"Bothasrus",
    "wof:placetype":"locality"
},
  "geometry": {"coordinates":[26.57506,-29.6702],"type":"Point"}
}