{
  "type": "Feature",
  "properties": {
    "gn:admin1_code":"2",
    "gn:admin2_code":"DC43",
    "gn:admin3_code":"KZN431",
    "gn:asciiname":"Oaklands",
    "gn:country_code":"ZA",
    "gn:dem":1195,
    "gn:feature_class":"P",
    "gn:feature_code":"PPL",
    "gn:name":"Oaklands",
    "gn:population":0,
    "gn:timezone":"Africa/Johannesburg",
    "iso:country":"ZA",
    "name:deu_x_preferred":[
        "Oaklands"
    ],
    "name:swe_x_preferred":[
        "Oaklands"
    ],
    "wof:lang_x_official":[
        "eng"
    ],
    "wof:lang_x_spoken":[
        "eng",
        "zul",
        "xho",
        "afr",
        "nso",
        "tsn",
        "sot",
        "tso",
        "ssw",
        "ven",
        "nbl"
    ],
    "wof:name":"Oaklands",
    "wof:placetype":"locality"
},
  "geometry": {"coordinates":[29.9548,-29.8898],"type":"Point"}
}