{
  "type": "Feature",
  "properties": {
    "gn:admin1_code":"6.0",
    "gn:admin2_code":"JHB",
    "gn:admin3_code":"JHB",
    "gn:asciiname":"Gleneagles",
    "gn:country_code":"ZA",
    "gn:dem":1674,
    "gn:feature_class":"P",
    "gn:feature_code":"PPL",
    "gn:name":"Gleneagles",
    "gn:population":0,
    "gn:timezone":"Africa/Johannesburg",
    "iso:country":"ZA",
    "wof:name":"Gleneagles",
    "wof:placetype":"locality"
},
  "geometry": {"coordinates":[28.0481,-26.26971],"type":"Point"}
}