{
  "type": "Feature",
  "properties": {
    "iso:country":"ZA",
    "qs_pg:aaroncc":"ZA",
    "qs_pg:name":"Wedela",
    "qs_pg:name_adm0":"South Africa",
    "qs_pg:name_adm1":"North-West",
    "qs_pg:photos":6,
    "qs_pg:photos_1k":1,
    "qs_pg:photos_9k":1,
    "qs_pg:photos_9r":1,
    "qs_pg:photos_all":6,
    "qs_pg:photos_sr":1,
    "qs_pg:pop_sr":0,
    "qs_pg:qs_pg_placetype":"locality",
    "qs_pg:qs_pg_placetype_gp":"Town",
    "qs_pg:woe_adm0":23424942,
    "woe:adm0_id":23424942,
    "woe:name_adm0":"South Africa",
    "woe:name_adm1":"North-West",
    "woe:placetype":"Town",
    "wof:name":"Wedela",
    "wof:placetype":"locality"
},
  "geometry": {"coordinates":[27.4305,-26.4525],"type":"Point"}
}