{
  "type": "Feature",
  "properties": {
    "gn:admin1_code":"6",
    "gn:admin2_code":"JHB",
    "gn:admin3_code":"JHB",
    "gn:asciiname":"Moroka",
    "gn:country_code":"ZA",
    "gn:dem":1599,
    "gn:feature_class":"P",
    "gn:feature_code":"PPL",
    "gn:name":"Moroka",
    "gn:population":0,
    "gn:timezone":"Africa/Johannesburg",
    "iso:country":"ZA",
    "name:und_x_variant":[
        "Orlando",
        "Moroka"
    ],
    "wof:name":"Moroka",
    "wof:placetype":"locality"
},
  "geometry": {"coordinates":[27.87682,-26.25942],"type":"Point"}
}