{
  "type": "Feature",
  "properties": {
    "gn:admin1_code":"5",
    "gn:admin2_code":"DC14",
    "gn:admin3_code":"EC142",
    "gn:asciiname":"Mdlokovane",
    "gn:country_code":"ZA",
    "gn:dem":1443,
    "gn:feature_class":"P",
    "gn:feature_code":"PPL",
    "gn:name":"Mdlokovane",
    "gn:population":0,
    "gn:timezone":"Africa/Johannesburg",
    "iso:country":"ZA",
    "wof:name":"Mdlokovane",
    "wof:placetype":"locality"
},
  "geometry": {"coordinates":[27.02855,-30.55391],"type":"Point"}
}