{
  "type": "Feature",
  "properties": {
    "gn:admin1_code":"11",
    "gn:admin2_code":"CPT",
    "gn:admin3_code":"CPT",
    "gn:asciiname":"Sunnycroft",
    "gn:country_code":"ZA",
    "gn:dem":21,
    "gn:feature_class":"P",
    "gn:feature_code":"PPL",
    "gn:name":"Sunnycroft",
    "gn:population":0,
    "gn:timezone":"Africa/Johannesburg",
    "iso:country":"ZA",
    "wof:name":"Sunnycroft",
    "wof:placetype":"locality"
},
  "geometry": {"coordinates":[18.38333,-34.13333],"type":"Point"}
}