{
  "type": "Feature",
  "properties": {
    "gn:admin1_code":"9",
    "gn:admin2_code":"DC36",
    "gn:admin3_code":"LIM366",
    "gn:asciiname":"Moheme",
    "gn:country_code":"ZA",
    "gn:dem":1172,
    "gn:feature_class":"P",
    "gn:feature_code":"PPL",
    "gn:name":"Moheme",
    "gn:population":0,
    "gn:timezone":"Africa/Johannesburg",
    "iso:country":"ZA",
    "wof:name":"Moheme",
    "wof:placetype":"locality"
},
  "geometry": {"coordinates":[28.11444,-24.86955],"type":"Point"}
}