{
  "type": "Feature",
  "properties": {
    "gn:admin1_code":"7.0",
    "gn:admin2_code":"DC31",
    "gn:admin3_code":"MP313",
    "gn:asciiname":"Schoonoord",
    "gn:country_code":"ZA",
    "gn:dem":1651,
    "gn:feature_class":"P",
    "gn:feature_code":"PPL",
    "gn:name":"Schoonoord",
    "gn:population":0,
    "gn:timezone":"Africa/Johannesburg",
    "iso:country":"ZA",
    "name:ceb_x_preferred":[
        "Schoonoord"
    ],
    "name:nld_x_preferred":[
        "Schoonoord"
    ],
    "wof:lang_x_official":[
        "eng"
    ],
    "wof:lang_x_spoken":[
        "eng",
        "zul",
        "xho",
        "afr",
        "nso",
        "tsn",
        "sot",
        "tso",
        "ssw",
        "ven",
        "nbl"
    ],
    "wof:name":"Schoonoord",
    "wof:placetype":"locality"
},
  "geometry": {"coordinates":[29.76521,-26.00169],"type":"Point"}
}