{
  "type": "Feature",
  "properties": {
    "gn:admin1_code":"3",
    "gn:admin2_code":"MAN",
    "gn:admin3_code":"MAN",
    "gn:asciiname":"Hope Valley",
    "gn:country_code":"ZA",
    "gn:dem":1393,
    "gn:feature_class":"P",
    "gn:feature_code":"PPL",
    "gn:name":"Hope Valley",
    "gn:population":0,
    "gn:timezone":"Africa/Johannesburg",
    "iso:country":"ZA",
    "name:bar_x_preferred":[
        "Hope Valley"
    ],
    "name:ceb_x_preferred":[
        "Hope Valley"
    ],
    "name:deu_x_preferred":[
        "Hope Valley"
    ],
    "name:mlg_x_preferred":[
        "Hope Valley"
    ],
    "name:swe_x_preferred":[
        "Hope Valley"
    ],
    "wof:name":"Hope Valley",
    "wof:placetype":"locality"
},
  "geometry": {"coordinates":[26.16384,-29.21601],"type":"Point"}
}