{
  "type": "Feature",
  "properties": {
    "gn:admin1_code":"10.0",
    "gn:admin2_code":"DC39",
    "gn:admin3_code":"NW397",
    "gn:asciiname":"Water-fouche",
    "gn:country_code":"ZA",
    "gn:dem":1116,
    "gn:feature_class":"P",
    "gn:feature_code":"PPL",
    "gn:name":"Water-fouch\u00e9",
    "gn:population":0,
    "gn:timezone":"Africa/Johannesburg",
    "iso:country":"ZA",
    "wof:name":"Water-fouche",
    "wof:placetype":"locality"
},
  "geometry": {"coordinates":[23.49557,-26.43268],"type":"Point"}
}