{
  "type": "Feature",
  "properties": {
    "gn:admin1_code":"3",
    "gn:admin2_code":"DC16",
    "gn:admin3_code":"FS163",
    "gn:asciiname":"Montagu",
    "gn:country_code":"ZA",
    "gn:dem":1512,
    "gn:feature_class":"P",
    "gn:feature_code":"PPL",
    "gn:name":"Montagu",
    "gn:population":0,
    "gn:timezone":"Africa/Johannesburg",
    "iso:country":"ZA",
    "name:deu_x_preferred":[
        "Montagu"
    ],
    "name:fra_x_preferred":[
        "Montagu"
    ],
    "name:heb_x_preferred":[
        "\u05de\u05d5\u05e0\u05d8\u05d2\u05d9\u05d5"
    ],
    "name:ita_x_preferred":[
        "Montagu"
    ],
    "name:jpn_x_preferred":[
        "\u30e2\u30f3\u30bf\u30ae\u30e5\u30fc"
    ],
    "name:nld_x_preferred":[
        "Montagu"
    ],
    "name:ron_x_preferred":[
        "Montagu"
    ],
    "wof:name":"Montagu",
    "wof:placetype":"locality"
},
  "geometry": {"coordinates":[26.39347,-30.15475],"type":"Point"}
}