{
  "type": "Feature",
  "properties": {
    "gn:gn_country":"ZA",
    "gn:gn_fcode":"ADM3",
    "gn:gn_pop":343468,
    "gn:population":343468,
    "iso:country":"ZA",
    "qs_pg:aaroncc":"ZA",
    "qs_pg:gn_country":"ZA",
    "qs_pg:gn_fcode":"ADM3",
    "qs_pg:gn_pop":343468,
    "qs_pg:name":"Greater Tubatse",
    "qs_pg:photos_9r":0,
    "qs_pg:photos_sr":0,
    "qs_pg:pop_sr":10,
    "qs_pg:qs_pg_placetype":"localadmin",
    "wof:name":"Greater Tubatse",
    "wof:placetype":"localadmin",
    "wof:population":343468
},
  "geometry": {"coordinates":[30.30076,-24.64689],"type":"Point"}
}