{
  "type": "Feature",
  "properties": {
    "gn:admin1_code":"5.0",
    "gn:admin2_code":"DC14",
    "gn:admin3_code":"EC141",
    "gn:asciiname":"Setabataba",
    "gn:country_code":"ZA",
    "gn:dem":1486,
    "gn:feature_class":"P",
    "gn:feature_code":"PPL",
    "gn:name":"Setabataba",
    "gn:population":0,
    "gn:timezone":"Africa/Johannesburg",
    "iso:country":"ZA",
    "wof:name":"Setabataba",
    "wof:placetype":"locality"
},
  "geometry": {"coordinates":[28.33513,-30.58918],"type":"Point"}
}