{
  "type": "Feature",
  "properties": {
    "gn:admin1_code":"9.0",
    "gn:admin2_code":"DC34",
    "gn:admin3_code":"LIM342",
    "gn:asciiname":"Sigonde",
    "gn:country_code":"ZA",
    "gn:dem":445,
    "gn:feature_class":"P",
    "gn:feature_code":"PPL",
    "gn:name":"Sigonde",
    "gn:population":0,
    "gn:timezone":"Africa/Johannesburg",
    "iso:country":"ZA",
    "wof:name":"Sigonde",
    "wof:placetype":"locality"
},
  "geometry": {"coordinates":[30.76667,-22.45],"type":"Point"}
}