{
  "type": "Feature",
  "properties": {
    "gn:admin1_code":"6",
    "gn:admin2_code":"EKU",
    "gn:admin3_code":"EKU",
    "gn:asciiname":"Laversburg",
    "gn:country_code":"ZA",
    "gn:dem":1588,
    "gn:feature_class":"P",
    "gn:feature_code":"PPL",
    "gn:name":"Laversburg",
    "gn:population":0,
    "gn:timezone":"Africa/Johannesburg",
    "iso:country":"ZA",
    "wof:name":"Laversburg",
    "wof:placetype":"locality"
},
  "geometry": {"coordinates":[28.49508,-26.42948],"type":"Point"}
}