{
  "type": "Feature",
  "properties": {
    "gn:admin1_code":"5.0",
    "gn:admin2_code":"DC15",
    "gn:admin3_code":"EC155",
    "gn:asciiname":"Zincukutwini",
    "gn:country_code":"ZA",
    "gn:dem":353,
    "gn:feature_class":"P",
    "gn:feature_code":"PPL",
    "gn:name":"Zincukutwini",
    "gn:population":0,
    "gn:timezone":"Africa/Johannesburg",
    "iso:country":"ZA",
    "wof:name":"Zincukutwini",
    "wof:placetype":"locality"
},
  "geometry": {"coordinates":[29.11688,-31.85889],"type":"Point"}
}