{
  "type": "Feature",
  "properties": {
    "gn:gn_fcode":"PPLA3",
    "gn:gn_pop":0,
    "iso:country":"ZA",
    "name:afr_x_preferred":[
        "Piketberg"
    ],
    "name:chi_x_preferred":[
        "\u76ae\u51f1\u7279\u8c9d\u8d6b"
    ],
    "name:dut_x_preferred":[
        "Piketberg"
    ],
    "name:eng_x_preferred":[
        "Piketberg"
    ],
    "name:fre_x_preferred":[
        "Piketberg"
    ],
    "name:ger_x_preferred":[
        "Piketberg"
    ],
    "name:ita_x_preferred":[
        "Piketberg"
    ],
    "name:nso_x_preferred":[
        "Piketberg"
    ],
    "name:rum_x_preferred":[
        "Piketberg"
    ],
    "name:rus_x_preferred":[
        "\u041f\u0438\u043a\u0435\u0442\u0431\u0435\u0440\u0445"
    ],
    "name:spa_x_preferred":[
        "Piketberg"
    ],
    "name:unk_x_variant":[
        "Piketburg"
    ],
    "qs_pg:aaroncc":"ZA",
    "qs_pg:gn_fcode":"PPLA3",
    "qs_pg:gn_pop":0,
    "qs_pg:name":"Piketberg",
    "qs_pg:name_adm0":"South Africa",
    "qs_pg:name_adm1":"Western Cape",
    "qs_pg:photos":56,
    "qs_pg:photos_1k":11,
    "qs_pg:photos_9k":1,
    "qs_pg:photos_9r":2,
    "qs_pg:photos_all":56,
    "qs_pg:photos_sr":2,
    "qs_pg:pop_sr":0,
    "qs_pg:qs_pg_placetype":"locality",
    "qs_pg:qs_pg_placetype_gp":"Town",
    "qs_pg:woe_adm0":23424942,
    "woe:adm0_id":23424942,
    "woe:name_adm0":"South Africa",
    "woe:name_adm1":"Western Cape",
    "woe:placetype":"Town",
    "wof:name":"Piketberg",
    "wof:placetype":"locality"
},
  "geometry": {"coordinates":[18.777694,-32.896308],"type":"Point"}
}