{
  "type": "Feature",
  "properties": {
    "gn:fcode":"PPLA3",
    "gn:population":0,
    "iso:country":"ZA",
    "name:afr_x_preferred":[
        "Piketberg"
    ],
    "name:ast_x_preferred":[
        "Piketberg"
    ],
    "name:ceb_x_preferred":[
        "Piketberg"
    ],
    "name:deu_x_preferred":[
        "Piketberg"
    ],
    "name:eng_x_preferred":[
        "Piketberg"
    ],
    "name:est_x_preferred":[
        "Piketberg"
    ],
    "name:fas_x_preferred":[
        "\u067e\u06cc\u06a9\u062a\u0628\u0631\u06af"
    ],
    "name:fra_x_preferred":[
        "Piketberg"
    ],
    "name:ita_x_preferred":[
        "Piketberg"
    ],
    "name:nld_x_preferred":[
        "Piketberg"
    ],
    "name:nso_x_preferred":[
        "Piketberg"
    ],
    "name:ron_x_preferred":[
        "Piketberg"
    ],
    "name:rus_x_preferred":[
        "\u041f\u0438\u043a\u0435\u0442\u0431\u0435\u0440\u0445"
    ],
    "name:spa_x_preferred":[
        "Piketberg"
    ],
    "name:und_x_variant":[
        "Piketburg"
    ],
    "name:zho_x_preferred":[
        "\u76ae\u51f1\u7279\u8c9d\u8d6b"
    ],
    "name:zul_x_preferred":[
        "IPiketberg"
    ],
    "qs_pg:aaroncc":"ZA",
    "qs_pg:gn_fcode":"PPLA3",
    "qs_pg:gn_pop":0,
    "qs_pg:name":"Piketberg",
    "qs_pg:name_adm0":"South Africa",
    "qs_pg:name_adm1":"Western Cape",
    "qs_pg:photos":56,
    "qs_pg:photos_1k":11,
    "qs_pg:photos_9k":1,
    "qs_pg:photos_9r":2,
    "qs_pg:photos_all":56,
    "qs_pg:photos_sr":2,
    "qs_pg:pop_sr":0,
    "qs_pg:qs_pg_placetype":"locality",
    "qs_pg:qs_pg_placetype_gp":"Town",
    "qs_pg:woe_adm0":23424942,
    "woe:adm0_id":23424942,
    "woe:name_adm0":"South Africa",
    "woe:name_adm1":"Western Cape",
    "woe:placetype":"Town",
    "wof:lang_x_official":[
        "eng"
    ],
    "wof:lang_x_spoken":[
        "eng",
        "zul",
        "xho",
        "afr",
        "nso",
        "tsn",
        "sot",
        "tso",
        "ssw",
        "ven",
        "nbl"
    ],
    "wof:name":"Piketberg",
    "wof:placetype":"locality"
},
  "geometry": {"coordinates":[18.777694,-32.896308],"type":"Point"}
}