{
  "type": "Feature",
  "properties": {
    "gn:admin1_code":"5",
    "gn:admin2_code":"DC44",
    "gn:admin3_code":"EC442",
    "gn:asciiname":"Dambisa",
    "gn:country_code":"ZA",
    "gn:dem":1051,
    "gn:feature_class":"P",
    "gn:feature_code":"PPL",
    "gn:name":"Dambisa",
    "gn:population":0,
    "gn:timezone":"Africa/Johannesburg",
    "iso:country":"ZA",
    "wof:name":"Dambisa",
    "wof:placetype":"locality"
},
  "geometry": {"coordinates":[29.01389,-30.86113],"type":"Point"}
}