{
  "type": "Feature",
  "properties": {
    "gn:admin1_code":"2",
    "gn:admin2_code":"DC26",
    "gn:admin3_code":"KZN266",
    "gn:asciiname":"Koningskroon",
    "gn:country_code":"ZA",
    "gn:dem":716,
    "gn:feature_class":"P",
    "gn:feature_code":"PPL",
    "gn:name":"Koningskroon",
    "gn:population":0,
    "gn:timezone":"Africa/Johannesburg",
    "iso:country":"ZA",
    "wof:name":"Koningskroon",
    "wof:placetype":"locality"
},
  "geometry": {"coordinates":[31.30555,-28.43347],"type":"Point"}
}