{
  "type": "Feature",
  "properties": {
    "gn:admin1_code":"3.0",
    "gn:admin2_code":"DC16",
    "gn:admin3_code":"FS162",
    "gn:asciiname":"Tweespruit",
    "gn:country_code":"ZA",
    "gn:dem":1389,
    "gn:feature_class":"P",
    "gn:feature_code":"PPL",
    "gn:name":"Tweespruit",
    "gn:population":0,
    "gn:timezone":"Africa/Johannesburg",
    "iso:country":"ZA",
    "name:afr_x_preferred":[
        "Tweespruit"
    ],
    "name:ceb_x_preferred":[
        "Tweespruit"
    ],
    "name:est_x_preferred":[
        "Tweespruit"
    ],
    "name:nld_x_preferred":[
        "Tweespruit"
    ],
    "name:nso_x_preferred":[
        "Tweespruit"
    ],
    "name:pol_x_preferred":[
        "Tweespruit"
    ],
    "name:ron_x_preferred":[
        "Tweespruit"
    ],
    "wof:lang_x_official":[
        "eng"
    ],
    "wof:lang_x_spoken":[
        "eng",
        "zul",
        "xho",
        "afr",
        "nso",
        "tsn",
        "sot",
        "tso",
        "ssw",
        "ven",
        "nbl"
    ],
    "wof:name":"Tweespruit",
    "wof:placetype":"locality"
},
  "geometry": {"coordinates":[26.16667,-29.76667],"type":"Point"}
}