{
  "type": "Feature",
  "properties": {
    "gn:admin1_code":"5.0",
    "gn:admin2_code":"DC44",
    "gn:admin3_code":"EC441",
    "gn:asciiname":"Saint Francis",
    "gn:country_code":"ZA",
    "gn:dem":1662,
    "gn:feature_class":"P",
    "gn:feature_code":"PPL",
    "gn:name":"Saint Francis",
    "gn:population":0,
    "gn:timezone":"Africa/Johannesburg",
    "iso:country":"ZA",
    "wof:name":"Saint Francis",
    "wof:placetype":"locality"
},
  "geometry": {"coordinates":[28.41235,-30.39118],"type":"Point"}
}