{
  "type": "Feature",
  "properties": {
    "gn:admin1_code":"5",
    "gn:admin2_code":"DC15",
    "gn:admin3_code":"EC156",
    "gn:asciiname":"Ncalukeni",
    "gn:country_code":"ZA",
    "gn:dem":993,
    "gn:feature_class":"P",
    "gn:feature_code":"PPL",
    "gn:name":"Ncalukeni",
    "gn:population":0,
    "gn:timezone":"Africa/Johannesburg",
    "iso:country":"ZA",
    "wof:name":"Ncalukeni",
    "wof:placetype":"locality"
},
  "geometry": {"coordinates":[28.86112,-31.19274],"type":"Point"}
}