{
  "type": "Feature",
  "properties": {
    "gn:admin1_code":"5.0",
    "gn:admin2_code":"DC10",
    "gn:admin3_code":"EC109",
    "gn:asciiname":"Sanddrif",
    "gn:country_code":"ZA",
    "gn:dem":239,
    "gn:feature_class":"P",
    "gn:feature_code":"PPL",
    "gn:name":"Sanddrif",
    "gn:population":0,
    "gn:timezone":"Africa/Johannesburg",
    "iso:country":"ZA",
    "name:afr_x_preferred":[
        "Sanddrif"
    ],
    "name:est_x_preferred":[
        "Sanddrif"
    ],
    "name:nld_x_preferred":[
        "Sanddrif"
    ],
    "name:nso_x_preferred":[
        "Sanddrif"
    ],
    "wof:lang_x_official":[
        "eng"
    ],
    "wof:lang_x_spoken":[
        "eng",
        "zul",
        "xho",
        "afr",
        "nso",
        "tsn",
        "sot",
        "tso",
        "ssw",
        "ven",
        "nbl"
    ],
    "wof:name":"Sanddrif",
    "wof:placetype":"locality"
},
  "geometry": {"coordinates":[23.99581,-33.98298],"type":"Point"}
}