{
  "type": "Feature",
  "properties": {
    "gn:admin1_code":"5",
    "gn:admin2_code":"DC15",
    "gn:admin3_code":"EC156",
    "gn:asciiname":"Killarney",
    "gn:country_code":"ZA",
    "gn:dem":963,
    "gn:feature_class":"P",
    "gn:feature_code":"PPL",
    "gn:name":"Killarney",
    "gn:population":0,
    "gn:timezone":"Africa/Johannesburg",
    "iso:country":"ZA",
    "name:afr_x_preferred":[
        "Killarney"
    ],
    "name:bar_x_preferred":[
        "Killarney"
    ],
    "name:bel_x_preferred":[
        "\u041a\u0456\u043b\u0430\u0440\u043d\u0456"
    ],
    "name:bre_x_preferred":[
        "Cill Airne"
    ],
    "name:bul_x_preferred":[
        "\u041a\u0438\u043b\u0430\u0440\u043d\u0438"
    ],
    "name:cat_x_preferred":[
        "Killarney"
    ],
    "name:ceb_x_preferred":[
        "Cill Airne"
    ],
    "name:dan_x_preferred":[
        "Killarney"
    ],
    "name:deu_x_preferred":[
        "Killarney"
    ],
    "name:epo_x_preferred":[
        "Cill Airne"
    ],
    "name:est_x_preferred":[
        "Killarney"
    ],
    "name:eus_x_preferred":[
        "Killarney"
    ],
    "name:fas_x_preferred":[
        "\u06a9\u06cc\u0644\u0627\u0631\u0646\u06cc"
    ],
    "name:fra_x_preferred":[
        "Killarney"
    ],
    "name:gle_x_preferred":[
        "Cill Airne"
    ],
    "name:glg_x_preferred":[
        "Killarney"
    ],
    "name:glv_x_preferred":[
        "Keeill Airney"
    ],
    "name:hye_x_preferred":[
        "\u053f\u056b\u056c\u056c\u0561\u0580\u0576\u056b"
    ],
    "name:ind_x_preferred":[
        "Killarney"
    ],
    "name:ita_x_preferred":[
        "Killarney"
    ],
    "name:jpn_x_preferred":[
        "\u30ad\u30e9\u30fc\u30cb\u30fc"
    ],
    "name:kor_x_preferred":[
        "\ud0ac\ub77c\ub2c8"
    ],
    "name:lit_x_preferred":[
        "Kilarnis"
    ],
    "name:nld_x_preferred":[
        "Killarney"
    ],
    "name:nor_x_preferred":[
        "Killarney"
    ],
    "name:pol_x_preferred":[
        "Killarney"
    ],
    "name:por_x_preferred":[
        "Killarney"
    ],
    "name:rus_x_preferred":[
        "\u041a\u0438\u043b\u043b\u0430\u0440\u043d\u0438"
    ],
    "name:sco_x_preferred":[
        "Killarney"
    ],
    "name:slv_x_preferred":[
        "Killarney"
    ],
    "name:spa_x_preferred":[
        "Killarney"
    ],
    "name:srp_x_preferred":[
        "\u041a\u0438\u043b\u0430\u0440\u043d\u0438"
    ],
    "name:swe_x_preferred":[
        "Killarney"
    ],
    "name:urd_x_preferred":[
        "\u06a9\u06cc\u0644\u0627\u0631\u0646\u06cc"
    ],
    "name:zho_x_preferred":[
        "\u57fa\u62c9\u5c3c"
    ],
    "wof:name":"Killarney",
    "wof:placetype":"locality"
},
  "geometry": {"coordinates":[29.0496,-31.13288],"type":"Point"}
}