{
  "type": "Feature",
  "properties": {
    "gn:admin1_code":"7",
    "gn:admin2_code":"DC32",
    "gn:admin3_code":"MP325",
    "gn:asciiname":"Oakley",
    "gn:country_code":"ZA",
    "gn:dem":552,
    "gn:feature_class":"P",
    "gn:feature_code":"PPL",
    "gn:name":"Oakley",
    "gn:population":0,
    "gn:timezone":"Africa/Johannesburg",
    "iso:country":"ZA",
    "wof:name":"Oakley",
    "wof:placetype":"locality"
},
  "geometry": {"coordinates":[31.22888,-24.92682000000001],"type":"Point"}
}