{
  "type": "Feature",
  "properties": {
    "gn:admin1_code":"5",
    "gn:admin2_code":"DC13",
    "gn:admin3_code":"EC136",
    "gn:asciiname":"Ntshinindeni",
    "gn:country_code":"ZA",
    "gn:dem":1439,
    "gn:feature_class":"P",
    "gn:feature_code":"PPL",
    "gn:name":"Ntshinindeni",
    "gn:population":0,
    "gn:timezone":"Africa/Johannesburg",
    "iso:country":"ZA",
    "wof:name":"Ntshinindeni",
    "wof:placetype":"locality"
},
  "geometry": {"coordinates":[26.90777000000001,-31.66988],"type":"Point"}
}