{
  "type": "Feature",
  "properties": {
    "gn:gn_country":"ZA",
    "gn:gn_fcode":"PPL",
    "gn:gn_pop":0,
    "iso:country":"ZA",
    "qs_pg:aaroncc":"ZA",
    "qs_pg:gn_country":"ZA",
    "qs_pg:gn_fcode":"PPL",
    "qs_pg:gn_pop":0,
    "qs_pg:name":"Nuwedorp",
    "qs_pg:name_adm0":"South Africa",
    "qs_pg:name_adm1":"Western Cape",
    "qs_pg:photos":39,
    "qs_pg:photos_1k":8,
    "qs_pg:photos_9k":1,
    "qs_pg:photos_9r":2,
    "qs_pg:photos_all":39,
    "qs_pg:photos_sr":2,
    "qs_pg:pop_sr":0,
    "qs_pg:qs_pg_placetype":"locality",
    "qs_pg:qs_pg_placetype_gp":"Town",
    "qs_pg:woe_adm0":23424942,
    "woe:adm0_id":23424942,
    "woe:name_adm0":"South Africa",
    "woe:name_adm1":"Western Cape",
    "woe:placetype":"Town",
    "wof:name":"Nuwedorp",
    "wof:placetype":"locality"
},
  "geometry": {"coordinates":[18.38846,-33.36581],"type":"Point"}
}