{
  "type": "Feature",
  "properties": {
    "gn:admin1_code":"10.0",
    "gn:asciiname":"Tsoe",
    "gn:country_code":"ZA",
    "gn:dem":1095,
    "gn:feature_class":"P",
    "gn:feature_code":"PPL",
    "gn:name":"Tsoe",
    "gn:population":0,
    "gn:timezone":"Africa/Johannesburg",
    "iso:country":"ZA",
    "wof:name":"Tsoe",
    "wof:placetype":"locality"
},
  "geometry": {"coordinates":[23.10656,-26.32703],"type":"Point"}
}