{
  "type": "Feature",
  "properties": {
    "gn:admin1_code":"9",
    "gn:asciiname":"Lefiso",
    "gn:country_code":"ZA",
    "gn:dem":1037,
    "gn:feature_class":"P",
    "gn:feature_code":"PPL",
    "gn:name":"Lefiso",
    "gn:population":0,
    "gn:timezone":"Africa/Johannesburg",
    "iso:country":"ZA",
    "wof:name":"Lefiso",
    "wof:placetype":"locality"
},
  "geometry": {"coordinates":[28.90065,-24.93405],"type":"Point"}
}