{
  "type": "Feature",
  "properties": {
    "gn:admin1_code":"5",
    "gn:admin2_code":"DC13",
    "gn:admin3_code":"EC138",
    "gn:asciiname":"Mtingwevu",
    "gn:country_code":"ZA",
    "gn:dem":1206,
    "gn:feature_class":"P",
    "gn:feature_code":"PPL",
    "gn:name":"Mtingwevu",
    "gn:population":0,
    "gn:timezone":"Africa/Johannesburg",
    "iso:country":"ZA",
    "wof:name":"Mtingwevu",
    "wof:placetype":"locality"
},
  "geometry": {"coordinates":[27.56271,-31.70499],"type":"Point"}
}